Workbook
Name _Toc225350871: '5.4.1.1-4 Atmos deposition'!$C$1
Name _Toc225350871: '5.5.1.1-2 Leaching and runoff'!$C$1
Name AgResidue_Equations_CropResidue.VEERG_6_1_1_1__1__NitrousOxideEmissionsFromCropResidues: _xlfn.LAMBDA(_xlpm.M_c,_xlpm.EF_Ni,_xlpm.C_N2O, _xlpm.M_c * _xlpm.EF_Ni * _xlpm.C_N2O * 10 ^ (-3))
Name AgResidue_Equations_CropResidue.VEERG_6_1_1_1__1__NitrousOxideEmissionsFromCropResidues_FunctionName: _xlfn.LAMBDA("VEERG_6_1_1_1__1__NitrousOxideEmissionsFromCropResidues")
Name AgResidue_Equations_CropResidue.VEERG_6_1_1_1__1__NitrousOxideEmissionsFromCropResidues_LatexEquation: _xlfn.LAMBDA("E=\sum\nolimits_c\left(M_{c}\times EF_{N}\right)\times C_{g,N2O}\times 10^{-3}")
Name AgResidue_Equations_CropResidue.VEERG_6_1_1_1__1__NitrousOxideEmissionsFromCropResidues_NIRReference: _xlfn.LAMBDA("")
Name AgResidue_Equations_CropResidue.VEERG_6_1_1_1__1__NitrousOxideEmissionsFromCropResidues_Source: _xlfn.LAMBDA("VEERG 2026: 6.1.1.1, Equation (1)")
Name AgResidue_Equations_CropResidue.VEERG_6_1_1_1__1__NitrousOxideEmissionsFromCropResidues_Title: _xlfn.LAMBDA("Nitrous oxide emissions from the return of crop residues across all crops c to the soil")
Name AgResidue_Equations_CropResidue.VEERG_6_1_1_1__1__NitrousOxideEmissionsFromCropResidues_Unit: _xlfn.LAMBDA("t N2O")
Name AgResidue_Equations_CropResidue.VEERG_6_1_1_1__1__NitrousOxideEmissionsFromCropResidues_Variable: _xlfn.LAMBDA("E")
Name AgResidue_Equations_CropResidue.VEERG_6_1_1_1__2__MassOfNitrogenInCropResidues_LatexEquation: _xlfn.LAMBDA("M_{c}=(P_{c}\times R_{AGc}\times(1-F_{c}-FFOD_{c})\times DM_{c}\times NC_{AGc})+(P_{c}\times R_{AGc}\times R_{BGc}\times DM_{c}\times NC_{BGc})")
Name AgResidue_Equations_CropResidue.VEERG_6_1_1_1__2__MassOfNitrogenInCropResidues_NIRReference: _xlfn.LAMBDA("")
Name AgResidue_Equations_CropResidue.VEERG_6_1_1_1__2__MassOfNitrogenInCropResidues_Source: _xlfn.LAMBDA("VEERG 2026: 6.1.1.1, Equation (2)")
Name AgResidue_Equations_CropResidue.VEERG_6_1_1_1__2__MassOfNitrogenInCropResidues_Title: _xlfn.LAMBDA("Mass of nitrogen in crop residues returned to the soil")
Name AgResidue_Equations_CropResidue.VEERG_6_1_1_1__2__MassOfNitrogenInCropResidues_Unit: _xlfn.LAMBDA("kg N")
Name AgResidue_Equations_CropResidue.VEERG_6_1_1_1__2__MassOfNitrogenInCropResidues_Variable: _xlfn.LAMBDA("M_c")
Name AgResidue_Equations_CropResidue.VEERG_6_1_1_2__1__FractionOfCropResidueRemovedBaled: _xlfn.LAMBDA(_xlpm.B,_xlpm.M_B,_xlpm.P_c,_xlpm.R_AGc, IFERROR((_xlpm.B * _xlpm.M_B) / (_xlpm.P_c * _xlpm.R_AGc), 0))
Name AgResidue_Equations_CropResidue.VEERG_6_1_1_2__1__FractionOfCropResidueRemovedBaled_LatexEquation: _xlfn.LAMBDA("FFOD_{c}=\frac{B\times M_{B}}{P_{c}\times R_{AG,c}}")
Name AgResidue_Equations_CropResidue.VEERG_6_1_1_2__1__FractionOfCropResidueRemovedBaled_NIRReference: _xlfn.LAMBDA("")
Name AgResidue_Equations_CropResidue.VEERG_6_1_1_2__1__FractionOfCropResidueRemovedBaled_Source: _xlfn.LAMBDA("VEERG 2026: 6.1.1.2, Equation (1)")
Name AgResidue_Equations_CropResidue.VEERG_6_1_1_2__1__FractionOfCropResidueRemovedBaled_Title: _xlfn.LAMBDA("Fraction of crop residue that is removed for crop c, calculated where residues are baled")
Name AgResidue_Equations_CropResidue.VEERG_6_1_1_2__1__FractionOfCropResidueRemovedBaled_Unit: _xlfn.LAMBDA("fraction")
Name AgResidue_Equations_CropResidue.VEERG_6_1_1_2__1__FractionOfCropResidueRemovedBaled_Variable: _xlfn.LAMBDA("FFOD_c")
Name AgResidue_Equations_CropResidue.VEERG_6_1_1_2__1__FractionOfCropResidueRemovedBaled_Variation: _xlfn.LAMBDA("")
Name AgResidue_Equations_FieldBurning.VEERG_6_4_1_1__1__MethaneEmissionsFromBurningOfCropResidues: _xlfn.LAMBDA(_xlpm.M_burnc,_xlpm.CC_c,_xlpm.EF_CH4,_xlpm.C_CH4, (_xlpm.M_burnc * _xlpm.CC_c) * _xlpm.EF_CH4 * _xlpm.C_CH4 * 10 ^ (-3))
Name AgResidue_Equations_FieldBurning.VEERG_6_4_1_1__1__MethaneEmissionsFromBurningOfCropResidues: _xlfn.LAMBDA(_xlpm.M_burnc,_xlpm.CC_c,_xlpm.EF_CH4,_xlpm.C_CH4, (_xlpm.M_burnc * _xlpm.CC_c) * _xlpm.EF_CH4 * _xlpm.C_CH4 * 10 ^ (-3))
Name AgResidue_Equations_FieldBurning.VEERG_6_4_1_1__1__MethaneEmissionsFromBurningOfCropResidues: _xlfn.LAMBDA(_xlpm.M_burnc,_xlpm.CC_c,_xlpm.EF_CH4,_xlpm.C_CH4, (_xlpm.M_burnc * _xlpm.CC_c) * _xlpm.EF_CH4 * _xlpm.C_CH4 * 10 ^ (-3))
Name AgResidue_Equations_FieldBurning.VEERG_6_4_1_1__1__MethaneEmissionsFromBurningOfCropResidues: _xlfn.LAMBDA(_xlpm.M_burnc,_xlpm.CC_c,_xlpm.EF_CH4,_xlpm.C_CH4, (_xlpm.M_burnc * _xlpm.CC_c) * _xlpm.EF_CH4 * _xlpm.C_CH4 * 10 ^ (-3))
Name AgResidue_Equations_FieldBurning.VEERG_6_4_1_1__1__MethaneEmissionsFromBurningOfCropResidues: _xlfn.LAMBDA(_xlpm.M_burnc,_xlpm.CC_c,_xlpm.EF_CH4,_xlpm.C_CH4, (_xlpm.M_burnc * _xlpm.CC_c) * _xlpm.EF_CH4 * _xlpm.C_CH4 * 10^(-3) )
Name AgResidue_Equations_FieldBurning.VEERG_6_4_1_1__1__MethaneEmissionsFromBurningOfCropResidues_FunctionName: _xlfn.LAMBDA("VEERG_6_4_1_1__1__MethaneEmissionsFromBurningOfCropResidues")
Name AgResidue_Equations_FieldBurning.VEERG_6_4_1_1__1__MethaneEmissionsFromBurningOfCropResidues_LatexEquation: _xlfn.LAMBDA("E_{CH4}=\sum\nolimits_c(M_{burn,c}\times CC_{c})\times EF_{CH4}\times C_{CH4}\times 10^{-3}")
Name AgResidue_Equations_FieldBurning.VEERG_6_4_1_1__1__MethaneEmissionsFromBurningOfCropResidues_LatexEquation: _xlfn.LAMBDA("E_{CH4}=\sum\nolimits_c(M_{burn,c}\times CC_{c})\times EF_{CH4}\times C_{CH4}\times 10^{-3}")
Name AgResidue_Equations_FieldBurning.VEERG_6_4_1_1__1__MethaneEmissionsFromBurningOfCropResidues_LatexEquation: _xlfn.LAMBDA("E_{CH4}=\sum\nolimits_c(M_{burn,c}\times CC_{c})\times EF_{CH4}\times C_{CH4}\times 10^{-3}")
Name AgResidue_Equations_FieldBurning.VEERG_6_4_1_1__1__MethaneEmissionsFromBurningOfCropResidues_LatexEquation: _xlfn.LAMBDA("E_{CH4}=\sum\nolimits_c(M_{burn,c}\times CC_{c})\times EF_{CH4}\times C_{CH4}\times 10^{-3}")
Name AgResidue_Equations_FieldBurning.VEERG_6_4_1_1__1__MethaneEmissionsFromBurningOfCropResidues_LatexEquation: _xlfn.LAMBDA("E_{CH4}=\sum\nolimits_c(M_{burn,c}\times CC_{c})\times EF_{CH4}\times C_{CH4}\times 10^{-3}")
Name AgResidue_Equations_FieldBurning.VEERG_6_4_1_1__1__MethaneEmissionsFromBurningOfCropResidues_NIRReference: _xlfn.LAMBDA("")
Name AgResidue_Equations_FieldBurning.VEERG_6_4_1_1__1__MethaneEmissionsFromBurningOfCropResidues_Source: _xlfn.LAMBDA("VEERG 2026: 6.4.1.1, Equation (1)")
Name AgResidue_Equations_FieldBurning.VEERG_6_4_1_1__1__MethaneEmissionsFromBurningOfCropResidues_Title: _xlfn.LAMBDA("Methane emissions from the burning of crop residues")
Name AgResidue_Equations_FieldBurning.VEERG_6_4_1_1__1__MethaneEmissionsFromBurningOfCropResidues_Unit: _xlfn.LAMBDA("t CH4")
Name AgResidue_Equations_FieldBurning.VEERG_6_4_1_1__1__MethaneEmissionsFromBurningOfCropResidues_Variable: _xlfn.LAMBDA("ECH4")
Name AgResidue_Equations_FieldBurning.VEERG_6_4_1_1__2__NitrousOxideEmissionsFromBurningOfCropResidues: _xlfn.LAMBDA(_xlpm.M_burnc,_xlpm.NC_AGc,_xlpm.EF_N2O,_xlpm.C_N2O, (_xlpm.M_burnc * _xlpm.NC_AGc) * _xlpm.EF_N2O * _xlpm.C_N2O * 10 ^ (-3))
Name AgResidue_Equations_FieldBurning.VEERG_6_4_1_1__2__NitrousOxideEmissionsFromBurningOfCropResidues: _xlfn.LAMBDA(_xlpm.M_burnc,_xlpm.NC_AGc,_xlpm.EF_N2O,_xlpm.C_N2O, (_xlpm.M_burnc * _xlpm.NC_AGc) * _xlpm.EF_N2O * _xlpm.C_N2O * 10 ^ (-3))
Name AgResidue_Equations_FieldBurning.VEERG_6_4_1_1__2__NitrousOxideEmissionsFromBurningOfCropResidues: _xlfn.LAMBDA(_xlpm.M_burnc,_xlpm.NC_AGc,_xlpm.EF_N2O,_xlpm.C_N2O, (_xlpm.M_burnc * _xlpm.NC_AGc) * _xlpm.EF_N2O * _xlpm.C_N2O * 10 ^ (-3))
Name AgResidue_Equations_FieldBurning.VEERG_6_4_1_1__2__NitrousOxideEmissionsFromBurningOfCropResidues: _xlfn.LAMBDA(_xlpm.M_burnc,_xlpm.NC_AGc,_xlpm.EF_N2O,_xlpm.C_N2O, (_xlpm.M_burnc * _xlpm.NC_AGc) * _xlpm.EF_N2O * _xlpm.C_N2O * 10 ^ (-3))
Name AgResidue_Equations_FieldBurning.VEERG_6_4_1_1__2__NitrousOxideEmissionsFromBurningOfCropResidues: _xlfn.LAMBDA(_xlpm.M_burnc,_xlpm.NC_AGc,_xlpm.EF_N2O,_xlpm.C_N2O, (_xlpm.M_burnc * _xlpm.NC_AGc) * _xlpm.EF_N2O * _xlpm.C_N2O * 10^(-3) )
Name AgResidue_Equations_FieldBurning.VEERG_6_4_1_1__2__NitrousOxideEmissionsFromBurningOfCropResidues_FunctionName: _xlfn.LAMBDA("VEERG_6_4_1_1__2__NitrousOxideEmissionsFromBurningOfCropResidues")
Name AgResidue_Equations_FieldBurning.VEERG_6_4_1_1__2__NitrousOxideEmissionsFromBurningOfCropResidues_LatexEquation: _xlfn.LAMBDA("E_{N2O}=\sum\nolimits_c(M_{burn,c}\times NC_{AGc})\times EF_{N2O}\times C_{N2O}\times 10^{-3}")
Name AgResidue_Equations_FieldBurning.VEERG_6_4_1_1__2__NitrousOxideEmissionsFromBurningOfCropResidues_LatexEquation: _xlfn.LAMBDA("E_{N2O}=\sum\nolimits_c(M_{burn,c}\times NC_{AGc})\times EF_{N2O}\times C_{N2O}\times 10^{-3}")
Name AgResidue_Equations_FieldBurning.VEERG_6_4_1_1__2__NitrousOxideEmissionsFromBurningOfCropResidues_LatexEquation: _xlfn.LAMBDA("E_{N2O}=\sum\nolimits_c(M_{burn,c}\times NC_{AGc})\times EF_{N2O}\times C_{N2O}\times 10^{-3}")
Name AgResidue_Equations_FieldBurning.VEERG_6_4_1_1__2__NitrousOxideEmissionsFromBurningOfCropResidues_LatexEquation: _xlfn.LAMBDA("E_{N2O}=\sum\nolimits_c(M_{burn,c}\times NC_{AGc})\times EF_{N2O}\times C_{N2O}\times 10^{-3}")
Name AgResidue_Equations_FieldBurning.VEERG_6_4_1_1__2__NitrousOxideEmissionsFromBurningOfCropResidues_LatexEquation: _xlfn.LAMBDA("E_{N2O}=\sum\nolimits_c(M_{burn,c}\times NC_{AGc})\times EF_{N2O}\times C_{N2O}\times 10^{-3}")
Name AgResidue_Equations_FieldBurning.VEERG_6_4_1_1__2__NitrousOxideEmissionsFromBurningOfCropResidues_NIRReference: _xlfn.LAMBDA("")
Name AgResidue_Equations_FieldBurning.VEERG_6_4_1_1__2__NitrousOxideEmissionsFromBurningOfCropResidues_Source: _xlfn.LAMBDA("VEERG 2026: 6.4.1.1, Equation (2)")
Name AgResidue_Equations_FieldBurning.VEERG_6_4_1_1__2__NitrousOxideEmissionsFromBurningOfCropResidues_Title: _xlfn.LAMBDA("Nitrous oxide emissions from the burning of crop residues")
Name AgResidue_Equations_FieldBurning.VEERG_6_4_1_1__2__NitrousOxideEmissionsFromBurningOfCropResidues_Unit: _xlfn.LAMBDA("t N2O")
Name AgResidue_Equations_FieldBurning.VEERG_6_4_1_1__2__NitrousOxideEmissionsFromBurningOfCropResidues_Variable: _xlfn.LAMBDA("EN2O")
Name AgResidue_Equations_FieldBurning.VEERG_6_4_1_1__3__MassOfCropResidueBurnt: _xlfn.LAMBDA(_xlpm.P_c,_xlpm.R_AGc,_xlpm.S_c,_xlpm.DM_c,_xlpm.Z_c,_xlpm.F_c, _xlpm.P_c * _xlpm.R_AGc * _xlpm.S_c * _xlpm.DM_c * _xlpm.Z_c * _xlpm.F_c)
Name AgResidue_Equations_FieldBurning.VEERG_6_4_1_1__3__MassOfCropResidueBurnt: _xlfn.LAMBDA(_xlpm.P_c,_xlpm.R_AGc,_xlpm.S_c,_xlpm.DM_c,_xlpm.Z_c,_xlpm.F_c, _xlpm.P_c * _xlpm.R_AGc * _xlpm.S_c * _xlpm.DM_c * _xlpm.Z_c * _xlpm.F_c)
Name AgResidue_Equations_FieldBurning.VEERG_6_4_1_1__3__MassOfCropResidueBurnt: _xlfn.LAMBDA(_xlpm.P_c,_xlpm.R_AGc,_xlpm.S_c,_xlpm.DM_c,_xlpm.Z_c,_xlpm.F_c, _xlpm.P_c * _xlpm.R_AGc * _xlpm.S_c * _xlpm.DM_c * _xlpm.Z_c * _xlpm.F_c)
Name AgResidue_Equations_FieldBurning.VEERG_6_4_1_1__3__MassOfCropResidueBurnt: _xlfn.LAMBDA(_xlpm.P_c,_xlpm.R_AGc,_xlpm.S_c,_xlpm.DM_c,_xlpm.Z_c,_xlpm.F_c, _xlpm.P_c * _xlpm.R_AGc * _xlpm.S_c * _xlpm.DM_c * _xlpm.Z_c * _xlpm.F_c)

Sheet Home
A1: #VALUE!
A3: =HYPERLINK("#'Home'!A1", "Home") -> Home
A4: =HYPERLINK("#'Results - Activity period'!A1", "Results - Activity period") -> Results - Activity period
A5: =HYPERLINK("#'Results - Product EI'!A1", "Results - Product Emissions Intensity") -> Results - Product Emissions Intensity
A8: INPUTS
A9: =HYPERLINK("#'Input - Enterprise'!A1", "Enterprise") -> Enterprise
A10: =HYPERLINK("#'Input - Site'!A1", "Site") -> Site
A11: =HYPERLINK("#'Input - Pasture Beef'!A1", "Pasture Beef") -> Pasture Beef
A12: =HYPERLINK("#'Input - Livestock sales'!A1", "Livestock sales") -> Livestock sales
A13: =HYPERLINK("#'Input - Beef cattle purchases'!A1", "Beef cattle purchases") -> Beef cattle purchases
A14: =HYPERLINK("#'Input - Pasture'!A1", "Pasture") -> Pasture
A15: =HYPERLINK("#'Input - Fert Prod System'!A1", "Fert Prod System") -> Fert Prod System
A16: =HYPERLINK("#'Input - Fertiliser'!A1", "Fertiliser") -> Fertiliser
A17: =HYPERLINK("#'Input - Fuel'!A1", "Fuel") -> Fuel
A18: =HYPERLINK("#'Input - Electricity'!A1", "Electricity") -> Electricity
A19: =HYPERLINK("#'Input - Common farm inputs'!A1", "Common farm inputs") -> Common farm inputs
A20: =HYPERLINK("#'Input - Crop pasture farm input'!A1", "Crop pasture farm input") -> Crop pasture farm input
A21: =HYPERLINK("#'Input - Livestock farm Inputs'!A1", "Livestock farm Inputs") -> Livestock farm Inputs
A22: =HYPERLINK("#'Input - Freight'!A1", "Freight") -> Freight
A23: =HYPERLINK("#'Input - Solid waste'!A1", "Solid waste") -> Solid waste
A24: =HYPERLINK("#'Input - Manure sent off-site'!A1", "Manure sent off-site") -> Manure sent off-site
A25: =HYPERLINK("#'Input - Data quality'!A1", "Data quality") -> Data quality
A28: CALCULATIONS
A29: =HYPERLINK("#'3.2.1.1-2 Enteric Methane'!A1", "3.2.1.1-2 Enteric Methane") -> 3.2.1.1-2 Enteric Methane
A30: =HYPERLINK("#'4.2.1.1-2 Methane'!A1", "4.2.1.1-2 Manure methane") -> 4.2.1.1-2 Manure methane
A31: =HYPERLINK("#'4.2.1.3-4 Soil direct N20'!A1", "4.2.1.3-4 Soil direct N2O") -> 4.2.1.3-4 Soil direct N2O
A32: =HYPERLINK("#'4.2.1.5-6 Soil Atmos Dep'!A1", "4.2.1.5-6 Soil atm. deposition") -> 4.2.1.5-6 Soil atm. deposition
A33: =HYPERLINK("#'4.2.1.7-8 Soil leach runoff'!A1", "4.2.1.7-8 Soil leach & runoff") -> 4.2.1.7-8 Soil leach & runoff
A34: =HYPERLINK("#'5.1.1.1-2 Inorganic fert N2O'!A1", "5.1.1.1-2 Inorganic fert N2O") -> 5.1.1.1-2 Inorganic fert N2O
A35: =HYPERLINK("#'5.1.1.3-4 Inorganic fert CO2'!A1", "5.1.1.3-4 Inorganic fert CO2") -> 5.1.1.3-4 Inorganic fert CO2
A36: =HYPERLINK("#'5.2.1.1-2 Organic Fert N2O'!A1", "5.2.1.1-2 Organic fert N2O") -> 5.2.1.1-2 Organic fert N2O
A37: =HYPERLINK("#'5.3.1.1-2 Lime CO2'!A1", "5.3.1.1-2 Lime CO2") -> 5.3.1.1-2 Lime CO2
A38: =HYPERLINK("#'5.4.1.1-4 Atmos deposition'!A1", "5.4.1.1-4 Atmos. deposition") -> 5.4.1.1-4 Atmos. deposition
A39: =HYPERLINK("#'5.5.1.1-2 Leaching and runoff'!A1", "5.5.1.1-2 Leaching & runoff") -> 5.5.1.1-2 Leaching & runoff
A40: =HYPERLINK("#'6.2.1.1-2 Pasture residue N2O'!A1", "6.2.1.1-2 Pasture residue N2O") -> 6.2.1.1-2 Pasture residue N2O
A41: =HYPERLINK("#'6.3.1.1-2 Leach runoff pasture'!A1", "6.3.1.1-2 Leach & runoff (pasture)") -> 6.3.1.1-2 Leach & runoff (pasture)
A42: =HYPERLINK("#'8.1.1.1-2 Transport fuel'!A1", "8.1.1.1-2 Transport fuel") -> 8.1.1.1-2 Transport fuel
A43: =HYPERLINK("#'8.2.1.1-2 Stationary fuel'!A1", "8.2.1.1-2 Stationary fuel") -> 8.2.1.1-2 Stationary fuel
A44: =HYPERLINK("#'10.1.1-2 Solid waste treatment'!A1", "10.1.1.1-2 Solid waste") -> 10.1.1.1-2 Solid waste
A45: =HYPERLINK("#'14.1.1-2 Purchased electricity'!A1", "14.1.1-2 Purchased electricity") -> 14.1.1-2 Purchased electricity
A46: =HYPERLINK("#'15 Scope 3'!A1", "15 Scope 3") -> 15 Scope 3
A47: =HYPERLINK("#'Calcs - Manure sent off-site'!A1", "Calcs - Manure sent off-site") -> Calcs - Manure sent off-site
A50: APPENDICES
A51: =HYPERLINK("#'Constants - Pasture Beef'!A1", "Constants - Pasture Beef") -> Constants - Pasture Beef
A52: =HYPERLINK("#'Constants - Ag Residue'!A1", "Constants - Ag residue") -> Constants - Ag residue
A53: =HYPERLINK("#'Constants - Common Livestock'!A1", "Constants - Common Livestock") -> Constants - Common Livestock
A54: =HYPERLINK("#'Constants - Electricity'!A1", "Constants - Electricity") -> Constants - Electricity
A55: =HYPERLINK("#'Constants - Fertiliser'!A1", "Constants - Fertiliser") -> Constants - Fertiliser
A56: =HYPERLINK("#'Constants - Fuel'!A1", "Constants - Fuel") -> Constants - Fuel
A57: =HYPERLINK("#'Constants - Scope 3'!A1", "Constants - Scope 3") -> Constants - Scope 3
A58: =HYPERLINK("#'Constants - Solid Waste'!A1", "Constants - Solid Waste") -> Constants - Solid Waste
A59: =HYPERLINK("#'Constants - Common'!A1", "Constants - Common") -> Constants - Common
A60: =HYPERLINK("#'Acknowledgements'!A1", "Acknowledgements") -> Acknowledgements

Sheet Results - Activity period
A1: #VALUE! | C1: Results - Activity period
A3: =HYPERLINK("#'Home'!A1", "Home") -> Home
A4: =HYPERLINK("#'Results - Activity period'!A1", "Results - Activity period") -> Results - Activity period | D4: ="Emissions breakdown for activities running between " & TEXT(X_Cell_Site_StartDate, "d mmmm yyyy") & " and " & TEXT(X_Cell_Site_EndDate, "d mmmm yyyy") -> Emissions breakdown for activities running between 0 January 1900 and 30 December 1900
A5: =HYPERLINK("#'Results - Product EI'!A1", "Results - Product Emissions Intensity") -> Results - Product Emissions Intensity
D6: Scope 1
A8: INPUTS | D8: Scope 1 source | E8: GHG emissions method 1 | F8: GHG emissions method 2 | G8: GHG Unit | H8: CO2-e emissions method 1 | I8: CO2-e emissions method 2
A9: =HYPERLINK("#'Input - Enterprise'!A1", "Enterprise") -> Enterprise | D9: 3.2.1.1-2 Enteric methane | E9: {=VEERG_3_2_1_1__1_TotalAnnualMethaneFromEntericFermentation_Result_Method1} -> #N/A | F9: {=VEERG_3_2_1_1__1_TotalAnnualMethaneFromEntericFermentation_Result_Method2} -> #N/A | G9: t CH4 | H9: {=Common_Equations.Common_ConvertCH4ToCO2e(E9,_xlfn.XLOOKUP("CH4", Table_GWPData[Gas],Table_GWPData[CO2-e factor]))} -> #N/A | I9: {=Common_Equations.Common_ConvertCH4ToCO2e(F9,_xlfn.XLOOKUP("CH4", Table_GWPData[Gas],Table_GWPData[CO2-e factor]))} -> #N/A | J9: t CO2e
A10: =HYPERLINK("#'Input - Site'!A1", "Site") -> Site | D10: 4.2.1.1-2 Manure methane | E10: {=VEERG_4_2_1_1__1_TotalAnnualMethaneProductionFromManureManagement_Result_Method1} -> #N/A | F10: {=VEERG_4_2_1_1__1_TotalAnnualMethaneProductionFromManureManagement_Result_Method2} -> #N/A | G10: t CH4 | H10: {=Common_Equations.Common_ConvertCH4ToCO2e(E10,_xlfn.XLOOKUP("CH4", Table_GWPData[Gas],Table_GWPData[CO2-e factor]))} -> #N/A | I10: {=Common_Equations.Common_ConvertCH4ToCO2e(F10,_xlfn.XLOOKUP("CH4", Table_GWPData[Gas],Table_GWPData[CO2-e factor]))} -> #N/A | J10: t CO2e
A11: =HYPERLINK("#'Input - Pasture Beef'!A1", "Pasture Beef") -> Pasture Beef | D11: 4.2.1.3-4 Soil direct N2O | E11: {=VEERG_4_2_1_3__1_DirectNitrousOxideEmissionsOnPasture_Result_Method1} -> #N/A | F11: {=VEERG_4_2_1_3__1_DirectNitrousOxideEmissionsOnPasture_Result_Method2} -> #N/A | G11: t N2O | H11: {=Common_Equations.Common_ConvertN2OToCO2e(E11,_xlfn.XLOOKUP("N2O", Table_GWPData[Gas],Table_GWPData[CO2-e factor]))} -> #N/A | I11: {=Common_Equations.Common_ConvertN2OToCO2e(F11,_xlfn.XLOOKUP("N2O", Table_GWPData[Gas],Table_GWPData[CO2-e factor]))} -> #N/A | J11: t CO2e
A12: =HYPERLINK("#'Input - Livestock sales'!A1", "Livestock sales") -> Livestock sales | D12: 4.2.1.5-6 Soil atmospheric deposition | E12: {=VEERG_4_2_1_5__1_AtmosphericDepositionEmissionsFromUrineAndDungOnPasture_Result_Method1} -> #N/A | F12: {=VEERG_4_2_1_5__1_AtmosphericDepositionEmissionsFromUrineAndDungOnPasture_Result_Method2} -> #N/A | G12: t N2O | H12: {=Common_Equations.Common_ConvertN2OToCO2e(E12,_xlfn.XLOOKUP("N2O", Table_GWPData[Gas],Table_GWPData[CO2-e factor]))} -> #N/A | I12: {=Common_Equations.Common_ConvertN2OToCO2e(F12,_xlfn.XLOOKUP("N2O", Table_GWPData[Gas],Table_GWPData[CO2-e factor]))} -> #N/A | J12: t CO2e
A13: =HYPERLINK("#'Input - Beef cattle purchases'!A1", "Beef cattle purchases") -> Beef cattle purchases | D13: 4.2.1.7-8 Soil leaching and runoff | E13: {=VEERG_4_2_1_7__1_LeachingAndRunoffEmissionsFromUrineAndDungOnPasture_Result_Method1} -> #N/A | F13: {=VEERG_4_2_1_7__1_LeachingAndRunoffEmissionsFromUrineAndDungOnPasture_Result_Method2} -> #N/A | G13: t N2O | H13: {=Common_Equations.Common_ConvertN2OToCO2e(E13,_xlfn.XLOOKUP("N2O", Table_GWPData[Gas],Table_GWPData[CO2-e factor]))} -> #N/A | I13: {=Common_Equations.Common_ConvertN2OToCO2e(F13,_xlfn.XLOOKUP("N2O", Table_GWPData[Gas],Table_GWPData[CO2-e factor]))} -> #N/A | J13: t CO2e
A14: =HYPERLINK("#'Input - Pasture'!A1", "Pasture") -> Pasture | D14: 5.1.1.1-2 Inorganic fert N2O | E14: {=VEERG_5_1_1_1__1_InorganicFertiliserApplicationN2OEmissions_Result_Method1} -> #N/A | F14: {=VEERG_5_1_1_1__1_InorganicFertiliserApplicationN2OEmissions_Result_Method2} -> #N/A | G14: t N2O | H14: {=Common_Equations.Common_ConvertN2OToCO2e(E14,_xlfn.XLOOKUP("N2O", Table_GWPData[Gas],Table_GWPData[CO2-e factor]))} -> #N/A | I14: {=Common_Equations.Common_ConvertN2OToCO2e(F14,_xlfn.XLOOKUP("N2O", Table_GWPData[Gas],Table_GWPData[CO2-e factor]))} -> #N/A | J14: t CO2e
A15: =HYPERLINK("#'Input - Fert Prod System'!A1", "Fert Prod System") -> Fert Prod System | D15: 5.1.1.3-4 Inorganic fert CO2 | E15: {=VEERG_5_1_1_3__1_InorganicFertiliserApplicationCO2Emissions_Result_Method1} -> 0 | F15: =E15 -> 0 | G15: t CO2 | H15: =E15 -> 0 | I15: =F15 -> 0 | J15: t CO2e
A16: =HYPERLINK("#'Input - Fertiliser'!A1", "Fertiliser") -> Fertiliser | D16: 5.2.1.1-2 Organic fert N2O | E16: {=VEERG_5_2_1_1__2_MassOfNitrogenInOrganicFertiliser_Result_Method1} -> 0 | F16: =E16 -> 0 | G16: t N2O | H16: {=Common_Equations.Common_ConvertN2OToCO2e(E16,_xlfn.XLOOKUP("N2O", Table_GWPData[Gas],Table_GWPData[CO2-e factor]))} -> 0 | I16: {=Common_Equations.Common_ConvertN2OToCO2e(F16,_xlfn.XLOOKUP("N2O", Table_GWPData[Gas],Table_GWPData[CO2-e factor]))} -> 0 | J16: t CO2e
A17: =HYPERLINK("#'Input - Fuel'!A1", "Fuel") -> Fuel | D17: 5.3.1.1-2 Lime CO2 | E17: {=VEERG_5_3_1_1__1_LimeApplicationCO2Emissions_Result_Method1} -> 0 | F17: =E17 -> 0 | G17: t CO2 | H17: =E17 -> 0 | I17: =F17 -> 0 | J17: t CO2e
A18: =HYPERLINK("#'Input - Electricity'!A1", "Electricity") -> Electricity | D18: 5.4.1.1-4 Atmos. deposition | E18: {=VEERG_5_4_1_3__1_OrganicFertiliserAtmosphericDepositionN2OEmissions_Result_Method1} -> #N/A | F18: =E18 -> #N/A | G18: t N2O | H18: {=Common_Equations.Common_ConvertN2OToCO2e(E18,_xlfn.XLOOKUP("N2O", Table_GWPData[Gas],Table_GWPData[CO2-e factor]))} -> #N/A | I18: {=Common_Equations.Common_ConvertN2OToCO2e(F18,_xlfn.XLOOKUP("N2O", Table_GWPData[Gas],Table_GWPData[CO2-e factor]))} -> #N/A | J18: t CO2e
A19: =HYPERLINK("#'Input - Common farm inputs'!A1", "Common farm inputs") -> Common farm inputs | D19: 5.5.1.1-2 Leaching & runoff | E19: {=VEERG_5_5_1_1__1_FertiliserLeachingAndRunoffN2OEmissions_result_Method1} -> 0 | F19: =E19 -> 0 | G19: t N2O | H19: {=Common_Equations.Common_ConvertN2OToCO2e(E19,_xlfn.XLOOKUP("N2O", Table_GWPData[Gas],Table_GWPData[CO2-e factor]))} -> 0 | I19: {=Common_Equations.Common_ConvertN2OToCO2e(F19,_xlfn.XLOOKUP("N2O", Table_GWPData[Gas],Table_GWPData[CO2-e factor]))} -> 0 | J19: t CO2e
A20: =HYPERLINK("#'Input - Crop pasture farm input'!A1", "Crop pasture farm input") -> Crop pasture farm input | D20: 6.2.1.1-2 Pasture residue N2O | E20: {=VEERG_6_2_1_1__1__NitrousOxideEmissionsFromPastureResidues_Result_Method1} -> 0 | F20: {=VEERG_6_2_1_1__1__NitrousOxideEmissionsFromPastureResidues_Result_Method2} -> #N/A | G20: t N2O | H20: {=Common_Equations.Common_ConvertN2OToCO2e(E20,_xlfn.XLOOKUP("N2O", Table_GWPData[Gas],Table_GWPData[CO2-e factor]))} -> 0 | I20: {=Common_Equations.Common_ConvertN2OToCO2e(F20,_xlfn.XLOOKUP("N2O", Table_GWPData[Gas],Table_GWPData[CO2-e factor]))} -> #N/A | J20: t CO2e
A21: =HYPERLINK("#'Input - Livestock farm Inputs'!A1", "Livestock farm Inputs") -> Livestock farm Inputs | D21: 6.3.1.1-2 Leach & runoff (pasture) | E21: {=VEERG_6_3_1_1__1__LeachingAndRunoffEmissionsCropAndPastureResidue_PastureOnly_Result_Method1} -> 0 | F21: {=VEERG_6_3_1_1__1__LeachingAndRunoffEmissionsCropAndPastureResidue_PastureOnly_Result_Method2} -> #N/A | G21: t N2O | H21: {=Common_Equations.Common_ConvertN2OToCO2e(E21,_xlfn.XLOOKUP("N2O", Table_GWPData[Gas],Table_GWPData[CO2-e factor]))} -> 0 | I21: {=Common_Equations.Common_ConvertN2OToCO2e(F21,_xlfn.XLOOKUP("N2O", Table_GWPData[Gas],Table_GWPData[CO2-e factor]))} -> #N/A | J21: t CO2e
A22: =HYPERLINK("#'Input - Freight'!A1", "Freight") -> Freight | D22: 8.1.1.1-2 Transport fuel CO2 | E22: {=VEERG_8_1_1_1__1_FuelCombustionTransport_Result_CO2} -> 0 | F22: =E22 -> 0 | G22: t CO2 | H22: =E22 -> 0 | I22: =F22 -> 0 | J22: t CO2e
A23: =HYPERLINK("#'Input - Solid waste'!A1", "Solid waste") -> Solid waste | D23: 8.1.1.1-2 Transport fuel CH4 | E23: {=VEERG_8_1_1_1__1_FuelCombustionTransport_Result_CH4} -> 0 | F23: =E23 -> 0 | G23: t CH4 | H23: {=Common_Equations.Common_ConvertCH4ToCO2e(E23,_xlfn.XLOOKUP("CH4", Table_GWPData[Gas],Table_GWPData[CO2-e factor]))} -> 0 | I23: {=Common_Equations.Common_ConvertCH4ToCO2e(F23,_xlfn.XLOOKUP("CH4", Table_GWPData[Gas],Table_GWPData[CO2-e factor]))} -> 0 | J23: t CO2e
A24: =HYPERLINK("#'Input - Manure sent off-site'!A1", "Manure sent off-site") -> Manure sent off-site | D24: 8.1.1.1-2 Transport fuel N2O | E24: {=VEERG_8_1_1_1__1_FuelCombustionTransport_Result_N2O} -> 0 | F24: =E24 -> 0 | G24: t N2O | H24: {=Common_Equations.Common_ConvertN2OToCO2e(E24,_xlfn.XLOOKUP("N2O", Table_GWPData[Gas],Table_GWPData[CO2-e factor]))} -> 0 | I24: {=Common_Equations.Common_ConvertN2OToCO2e(F24,_xlfn.XLOOKUP("N2O", Table_GWPData[Gas],Table_GWPData[CO2-e factor]))} -> 0 | J24: t CO2e
A25: =HYPERLINK("#'Input - Data quality'!A1", "Data quality") -> Data quality | D25: 8.2.1.1-2 Stationary fuel CO2 | E25: {=VEERG_8_2_1_1__1_FuelCombustionStationary_Result_CO2} -> 0 | F25: =E25 -> 0 | G25: t CO2 | H25: =E25 -> 0 | I25: =F25 -> 0 | J25: t CO2e
D26: 8.2.1.1-2 Stationary fuel CH4 | E26: {=VEERG_8_2_1_1__1_FuelCombustionStationary_Result_CH4} -> 0 | F26: =E26 -> 0 | G26: t CH4 | H26: {=Common_Equations.Common_ConvertCH4ToCO2e(E26,_xlfn.XLOOKUP("CH4", Table_GWPData[Gas],Table_GWPData[CO2-e factor]))} -> 0 | I26: {=Common_Equations.Common_ConvertCH4ToCO2e(F26,_xlfn.XLOOKUP("CH4", Table_GWPData[Gas],Table_GWPData[CO2-e factor]))} -> 0 | J26: t CO2e
D27: 8.2.1.1-2 Stationary fuel N2O | E27: {=VEERG_8_2_1_1__1_FuelCombustionStationary_Result_N2O} -> 0 | F27: =E27 -> 0 | G27: t N2O | H27: {=Common_Equations.Common_ConvertN2OToCO2e(E27,_xlfn.XLOOKUP("N2O", Table_GWPData[Gas],Table_GWPData[CO2-e factor]))} -> 0 | I27: {=Common_Equations.Common_ConvertN2OToCO2e(F27,_xlfn.XLOOKUP("N2O", Table_GWPData[Gas],Table_GWPData[CO2-e factor]))} -> 0 | J27: t CO2e
A28: CALCULATIONS | D28: Total scope 1 | H28: =SUM(H9:H27) -> #N/A | I28: =SUM(I9:I27) -> #N/A | J28: t CO2e
A29: =HYPERLINK("#'3.2.1.1-2 Enteric Methane'!A1", "3.2.1.1-2 Enteric Methane") -> 3.2.1.1-2 Enteric Methane
A30: =HYPERLINK("#'4.2.1.1-2 Methane'!A1", "4.2.1.1-2 Manure methane") -> 4.2.1.1-2 Manure methane
A31: =HYPERLINK("#'4.2.1.3-4 Soil direct N20'!A1", "4.2.1.3-4 Soil direct N2O") -> 4.2.1.3-4 Soil direct N2O | D31: Scope 2
A32: =HYPERLINK("#'4.2.1.5-6 Soil Atmos Dep'!A1", "4.2.1.5-6 Soil atm. deposition") -> 4.2.1.5-6 Soil atm. deposition
A33: =HYPERLINK("#'4.2.1.7-8 Soil leach runoff'!A1", "4.2.1.7-8 Soil leach & runoff") -> 4.2.1.7-8 Soil leach & runoff | D33: Scope 2 source | E33: GHG emissions method 1 | F33: GHG emissions method 2 | G33: GHG Unit | H33: CO2-e emissions method 1 | I33: CO2-e emissions method 2
A34: =HYPERLINK("#'5.1.1.1-2 Inorganic fert N2O'!A1", "5.1.1.1-2 Inorganic fert N2O") -> 5.1.1.1-2 Inorganic fert N2O | D34: {="14.1.1-2 Purchased electricity " & IF(X_Cell_Electricity_CalculationMethod="Location-based (simpler)", "(Location-based)", "(Market-based)")} -> 14.1.1-2 Purchased electricity (Market-based) | E34: {=IF(X_Cell_Electricity_CalculationMethod="Location-based (simpler)", VEERG_14_1_1__1_LocationBasedScopeElectricityEmissions_Result_Method1, VEERG_14_1_2__1_MarketBasedScopeElectricityEmissionsVariation_Result_Method1)} -> 0 | F34: =E34 -> 0 | G34: t CO2e | H34: =E34 -> 0 | I34: =F34 -> 0 | J34: t CO2e
A35: =HYPERLINK("#'5.1.1.3-4 Inorganic fert CO2'!A1", "5.1.1.3-4 Inorganic fert CO2") -> 5.1.1.3-4 Inorganic fert CO2 | D35: Total scope 2 | H35: =SUM(H34:H34) -> 0 | I35: =SUM(I34:I34) -> 0 | J35: t CO2e
A36: =HYPERLINK("#'5.2.1.1-2 Organic Fert N2O'!A1", "5.2.1.1-2 Organic fert N2O") -> 5.2.1.1-2 Organic fert N2O
A37: =HYPERLINK("#'5.3.1.1-2 Lime CO2'!A1", "5.3.1.1-2 Lime CO2") -> 5.3.1.1-2 Lime CO2
A38: =HYPERLINK("#'5.4.1.1-4 Atmos deposition'!A1", "5.4.1.1-4 Atmos. deposition") -> 5.4.1.1-4 Atmos. deposition | D38: Scope 3
A39: =HYPERLINK("#'5.5.1.1-2 Leaching and runoff'!A1", "5.5.1.1-2 Leaching & runoff") -> 5.5.1.1-2 Leaching & runoff | D39: Scope 3 source | E39: GHG emissions method 1 | F39: GHG emissions method 2 | G39: GHG Unit | H39: CO2-e emissions method 1 | I39: CO2-e emissions method 2
A40: =HYPERLINK("#'6.2.1.1-2 Pasture residue N2O'!A1", "6.2.1.1-2 Pasture residue N2O") -> 6.2.1.1-2 Pasture residue N2O | D40: 15.1.1.1 Purchased livestock | E40: {=VEERG_15_1_1_1__1_EmissionsFromPurchasedLivestock_Result_Method1} -> 0 | F40: {=VEERG_15_1_1_1__1_EmissionsFromPurchasedLivestock_Result_Method2} -> 0 | G40: t CO2e | H40: =E40 -> 0 | I40: =F40 -> 0 | J40: t CO2e
A41: =HYPERLINK("#'6.3.1.1-2 Leach runoff pasture'!A1", "6.3.1.1-2 Leach & runoff (pasture)") -> 6.3.1.1-2 Leach & runoff (pasture) | D41: 15.2.1.1 Purchased feed | E41: {=VEERG_15_2_1_1__1_EmissionsFromPurchasedFeed_Result_Method1} -> 0 | F41: {=VEERG_15_2_1_1__1_EmissionsFromPurchasedFeed_Result_Method2} -> 0 | G41: t CO2e | H41: =E41 -> 0 | I41: =F41 -> 0 | J41: t CO2e
A42: =HYPERLINK("#'8.1.1.1-2 Transport fuel'!A1", "8.1.1.1-2 Transport fuel") -> 8.1.1.1-2 Transport fuel | D42: 15.3.1.1 Mineral supplements | E42: {=VEERG_15_3_1_1__1_EmissionsFromPurchasedMineralSupplements_Result_Method1} -> 0 | F42: {=VEERG_15_3_1_1__1_EmissionsFromPurchasedMineralSupplements_Result_Method2} -> 0 | G42: t CO2e | H42: =E42 -> 0 | I42: =F42 -> 0 | J42: t CO2e
A43: =HYPERLINK("#'8.2.1.1-2 Stationary fuel'!A1", "8.2.1.1-2 Stationary fuel") -> 8.2.1.1-2 Stationary fuel | D43: 15.4.1.1 Fertiliser | E43: {=VEERG_15_4_1_1__2_EmissionsFromPurchasedFertiliserComponentsVariation_Result_Method1} -> 0 | F43: {=VEERG_15_4_1_1__2_EmissionsFromPurchasedFertiliserComponentsVariation_Result_Method2} -> 0 | G43: t CO2e | H43: =E43 -> 0 | I43: =F43 -> 0 | J43: t CO2e
A44: =HYPERLINK("#'10.1.1-2 Solid waste treatment'!A1", "10.1.1.1-2 Solid waste") -> 10.1.1.1-2 Solid waste | D44: 15.5.1.1 Agrichemicals | E44: {=VEERG_15_5_1_1__1_EmissionsFromPurchasedAgrichemicals_Result_Method1} -> 0 | F44: {=VEERG_15_5_1_1__1_EmissionsFromPurchasedAgrichemicals_Result_Method2} -> 0 | G44: t CO2e | H44: =E44 -> 0 | I44: =F44 -> 0 | J44: t CO2e
A45: =HYPERLINK("#'14.1.1-2 Purchased electricity'!A1", "14.1.1-2 Purchased electricity") -> 14.1.1-2 Purchased electricity | D45: 15.6.1.1 Lime | E45: {=VEERG_15_6_1_1__1_EmissionsFromPurchasedLime_Result_Method1} -> 0 | F45: {=VEERG_15_6_1_1__1_EmissionsFromPurchasedLime_Result_Method2} -> 0 | G45: t CO2e | H45: =E45 -> 0 | I45: =F45 -> 0 | J45: t CO2e
A46: =HYPERLINK("#'15 Scope 3'!A1", "15 Scope 3") -> 15 Scope 3 | D46: 15.7.1.1 Services and contractor operations | E46: {=VEERG_15_7_1_1__1_EmissionsFromPurchasedServices_Result_Method1} -> No data | F46: {=VEERG_15_7_1_1__1_EmissionsFromPurchasedServices_Result_Method2} -> 0 | G46: t CO2e | H46: =E46 -> No data | I46: =F46 -> 0 | J46: t CO2e
A47: =HYPERLINK("#'Calcs - Manure sent off-site'!A1", "Calcs - Manure sent off-site") -> Calcs - Manure sent off-site | D47: 15.10.1.1 Other: Cleaning chemicals | E47: {=VEERG_15_10_1_1__1_OtherPurchasedGoodsAndServices_CleaningChemicals_Result_Method1} -> 0 | F47: {=VEERG_15_10_1_1__1_OtherPurchasedGoodsAndServices_CleaningChemicals_Result_Method2} -> 0 | G47: t CO2e | H47: =E47 -> 0 | I47: =F47 -> 0 | J47: t CO2e
D48: 15.10.1.1 Other: Pharmacy chemicals | E48: {=VEERG_15_10_1_1__1_OtherPurchasedGoodsAndServices_PharmacyChemicals_Result_Method1} -> 0 | F48: {=VEERG_15_10_1_1__1_OtherPurchasedGoodsAndServices_PharmacyChemicals_Result_Method2} -> 0 | G48: t CO2e | H48: =E48 -> 0 | I48: =F48 -> 0 | J48: t CO2e
D49: 15.10.1.1 Other: Miscellaneous | E49: {=VEERG_15_10_1_1__1_OtherPurchasedGoodsAndServices_Misc_Result_Method1} -> 0 | F49: {=VEERG_15_10_1_1__1_OtherPurchasedGoodsAndServices_Misc_Result_Method2} -> 0 | G49: t CO2e | H49: =E49 -> 0 | I49: =F49 -> 0 | J49: t CO2e
A50: APPENDICES | D50: 15.10.1.1 Other: Uncategorised | E50: {=VEERG_15_10_1_1__1_OtherPurchasedGoodsAndServices_Uncategorised_Result_Method1} -> No data | F50: {=VEERG_15_10_1_1__1_OtherPurchasedGoodsAndServices_Uncategorised_Result_Method2} -> 0 | G50: t CO2e | H50: =E50 -> No data | I50: =F50 -> 0 | J50: t CO2e
A51: =HYPERLINK("#'Constants - Pasture Beef'!A1", "Constants - Pasture Beef") -> Constants - Pasture Beef | D51: 15.11.1.1 Fuel | E51: {=VEERG_15_11_1_1__1_TotalUpstreamEmissionsFromFuel_Result} -> 0 | F51: =E51 -> 0 | G51: t CO2e | H51: =E51 -> 0 | I51: =F51 -> 0 | J51: t CO2e
A52: =HYPERLINK("#'Constants - Ag Residue'!A1", "Constants - Ag residue") -> Constants - Ag residue | D52: {="15.12.1.1 Purchased electricity " & IF(X_Cell_Electricity_CalculationMethod="Location-based (simpler)", "(Location-based)", "(Market-based)")} -> 15.12.1.1 Purchased electricity (Market-based) | E52: {=IF(X_Cell_Electricity_CalculationMethod="Location-based (simpler)", VEERG_15_12_1_1__1_UpstreamPurchasedElectricityLocationBased_Result, VEERG_15_12_1_1__1_UpstreamPurchasedElectricityMarketBased_Result)} -> #NAME? | F52: =E52 -> #NAME? | G52: t CO2e | H52: =E52 -> #NAME? | I52: =F52 -> #NAME? | J52: t CO2e
A53: =HYPERLINK("#'Constants - Common Livestock'!A1", "Constants - Common Livestock") -> Constants - Common Livestock | D53: 15.14.1.1 Incoming freight | E53: {=VEERG_15_14_1_1__1_EmbeddedEmissionsFromUpstreamFreight_Incoming_Result_Method1} -> No data | F53: {=VEERG_15_14_1_1__1_EmbeddedEmissionsFromUpstreamFreight_Incoming_Result_Method2} -> 0 | G53: t CO2e | H53: =E53 -> No data | I53: =F53 -> 0 | J53: t CO2e
A54: =HYPERLINK("#'Constants - Electricity'!A1", "Constants - Electricity") -> Constants - Electricity | D54: 15.13.1.1 Waste sent to treatment facility | E54: {=VEERG_10_1_1_1__1_EmissionsFromWasteManagement_Scope3_Result_Method1} -> 0 | F54: =E54 -> 0 | G54: t CO2e | H54: =E54 -> 0 | I54: =F54 -> 0 | J54: t CO2e
A55: =HYPERLINK("#'Constants - Fertiliser'!A1", "Constants - Fertiliser") -> Constants - Fertiliser | D55: 15.14.1.1 Outgoing freight | E55: {=VEERG_15_14_1_1__1_EmbeddedEmissionsFromUpstreamFreight_Outgoing_Result_Method1} -> No data | F55: {=VEERG_15_14_1_1__1_EmbeddedEmissionsFromUpstreamFreight_Outgoing_Result_Method2} -> 0 | G55: t CO2e | H55: =E55 -> No data | I55: =F55 -> 0 | J55: t CO2e
A56: =HYPERLINK("#'Constants - Fuel'!A1", "Constants - Fuel") -> Constants - Fuel | D56: Total scope 3 | H56: =SUM(H40:H55) -> #NAME? | I56: =SUM(I40:I55) -> #NAME? | J56: t CO2e
A57: =HYPERLINK("#'Constants - Scope 3'!A1", "Constants - Scope 3") -> Constants - Scope 3
A58: =HYPERLINK("#'Constants - Solid Waste'!A1", "Constants - Solid Waste") -> Constants - Solid Waste
A59: =HYPERLINK("#'Constants - Common'!A1", "Constants - Common") -> Constants - Common | D59: ="Carbon removals from plantings for the activity period " & TEXT(X_Cell_Site_StartDate, "d mmmm yyyy") & " and " & TEXT(X_Cell_Site_EndDate, "d mmmm yyyy") -> Carbon removals from plantings for the activity period 0 January 1900 and 30 December 1900
A60: =HYPERLINK("#'Acknowledgements'!A1", "Acknowledgements") -> Acknowledgements
D61: Total removals | E61: =SUM(Table_Input_Enterprise_PlantingRemovals[Removal allocated to this enterprise]) -> 0 | F61: t CO2
D64: ="Net emissions for the activity period " & TEXT(X_Cell_Site_StartDate, "d mmmm yyyy") & " and " & TEXT(X_Cell_Site_EndDate, "d mmmm yyyy") -> Net emissions for the activity period 0 January 1900 and 30 December 1900
E66: Method 1 | F66: Method 2
D67: Total emissions excluding removals | E67: =Result_Enterprise_Scope1_Method1+Result_Enterprise_Scope2_Method1+Result_Enterprise_Scope3_Method1 -> #N/A | F67: =Result_Enterprise_Scope1_Method2+Result_Enterprise_Scope2_Method2+Result_Enterprise_Scope3_Method2 -> #N/A | G67: t CO2-e
D68: Total net emissions | E68: =Result_Enterprise_Scope1_Method1-Result_Enterprise_Removals -> #N/A | F68: =Result_Enterprise_Scope1_Method2-Result_Enterprise_Removals -> #N/A | G68: t CO2-e

Sheet Results - Product EI
C1: Results - Product emissions intensity
A3: =HYPERLINK("#'Home'!A1", "Home") -> Home
A4: =HYPERLINK("#'Results - Activity period'!A1", "Results - Activity period") -> Results - Activity period
A5: =HYPERLINK("#'Results - Product EI'!A1", "Results - Product Emissions Intensity") -> Results - Product Emissions Intensity
A8: INPUTS
A9: =HYPERLINK("#'Input - Enterprise'!A1", "Enterprise") -> Enterprise
A10: =HYPERLINK("#'Input - Site'!A1", "Site") -> Site
A11: =HYPERLINK("#'Input - Pasture Beef'!A1", "Pasture Beef") -> Pasture Beef
A12: =HYPERLINK("#'Input - Livestock sales'!A1", "Livestock sales") -> Livestock sales
A13: =HYPERLINK("#'Input - Beef cattle purchases'!A1", "Beef cattle purchases") -> Beef cattle purchases
A14: =HYPERLINK("#'Input - Pasture'!A1", "Pasture") -> Pasture
A15: =HYPERLINK("#'Input - Fert Prod System'!A1", "Fert Prod System") -> Fert Prod System
A16: =HYPERLINK("#'Input - Fertiliser'!A1", "Fertiliser") -> Fertiliser
A17: =HYPERLINK("#'Input - Fuel'!A1", "Fuel") -> Fuel
A18: =HYPERLINK("#'Input - Electricity'!A1", "Electricity") -> Electricity
A19: =HYPERLINK("#'Input - Common farm inputs'!A1", "Common farm inputs") -> Common farm inputs
A20: =HYPERLINK("#'Input - Crop pasture farm input'!A1", "Crop pasture farm input") -> Crop pasture farm input
A21: =HYPERLINK("#'Input - Livestock farm Inputs'!A1", "Livestock farm Inputs") -> Livestock farm Inputs
A22: =HYPERLINK("#'Input - Freight'!A1", "Freight") -> Freight
A23: =HYPERLINK("#'Input - Solid waste'!A1", "Solid waste") -> Solid waste
A24: =HYPERLINK("#'Input - Manure sent off-site'!A1", "Manure sent off-site") -> Manure sent off-site
A25: =HYPERLINK("#'Input - Data quality'!A1", "Data quality") -> Data quality
A28: CALCULATIONS
A29: =HYPERLINK("#'3.2.1.1-2 Enteric Methane'!A1", "3.2.1.1-2 Enteric Methane") -> 3.2.1.1-2 Enteric Methane
A30: =HYPERLINK("#'4.2.1.1-2 Methane'!A1", "4.2.1.1-2 Manure methane") -> 4.2.1.1-2 Manure methane
A31: =HYPERLINK("#'4.2.1.3-4 Soil direct N20'!A1", "4.2.1.3-4 Soil direct N2O") -> 4.2.1.3-4 Soil direct N2O
A32: =HYPERLINK("#'4.2.1.5-6 Soil Atmos Dep'!A1", "4.2.1.5-6 Soil atm. deposition") -> 4.2.1.5-6 Soil atm. deposition | D32: ="Emissions for whole production cycle running between " & TEXT(X_Cell_Enterprise_ProductionTimeframeStart, "d mmmm yyyy") & " and " & TEXT(X_Cell_Enterprise_ProductionTimeframeEnd, "d mmmm yyyy") -> Emissions for whole production cycle running between 0 January 1900 and 0 January 1900
A33: =HYPERLINK("#'4.2.1.7-8 Soil leach runoff'!A1", "4.2.1.7-8 Soil leach & runoff") -> 4.2.1.7-8 Soil leach & runoff
A34: =HYPERLINK("#'5.1.1.1-2 Inorganic fert N2O'!A1", "5.1.1.1-2 Inorganic fert N2O") -> 5.1.1.1-2 Inorganic fert N2O
A35: =HYPERLINK("#'5.1.1.3-4 Inorganic fert CO2'!A1", "5.1.1.3-4 Inorganic fert CO2") -> 5.1.1.3-4 Inorganic fert CO2 | E35: Method 1 | F35: Method 2
A36: =HYPERLINK("#'5.2.1.1-2 Organic Fert N2O'!A1", "5.2.1.1-2 Organic fert N2O") -> 5.2.1.1-2 Organic fert N2O | D36: Emissions for production cycle excluding removals | E36: =Result_EmissionsForWholeProductionCycle_Method1 -> 0 | F36: =Result_EmissionsForWholeProductionCycle_Method2 -> 0 | G36: t CO2e
A37: =HYPERLINK("#'5.3.1.1-2 Lime CO2'!A1", "5.3.1.1-2 Lime CO2") -> 5.3.1.1-2 Lime CO2 | D37: Net emissions for production cycle | E37: =Result_EmissionsForWholeProductionCycle_Method1-Result_CarbonRemovalsFromPlantings -> 0 | F37: =Result_EmissionsForWholeProductionCycle_Method2-Result_CarbonRemovalsFromPlantings -> 0 | G37: t CO2e
A38: =HYPERLINK("#'5.4.1.1-4 Atmos deposition'!A1", "5.4.1.1-4 Atmos. deposition") -> 5.4.1.1-4 Atmos. deposition
A39: =HYPERLINK("#'5.5.1.1-2 Leaching and runoff'!A1", "5.5.1.1-2 Leaching & runoff") -> 5.5.1.1-2 Leaching & runoff
A40: =HYPERLINK("#'6.2.1.1-2 Pasture residue N2O'!A1", "6.2.1.1-2 Pasture residue N2O") -> 6.2.1.1-2 Pasture residue N2O | D40: ="Product emissions intensity for whole production cycle running between " & TEXT(X_Cell_Enterprise_ProductionTimeframeStart, "d mmmm yyyy") & " and " & TEXT(X_Cell_Enterprise_ProductionTimeframeEnd, "d mmmm yyyy") -> Product emissions intensity for whole production cycle running between 0 January 1900 and 0 January 1900
A41: =HYPERLINK("#'6.3.1.1-2 Leach runoff pasture'!A1", "6.3.1.1-2 Leach & runoff (pasture)") -> 6.3.1.1-2 Leach & runoff (pasture)
A42: =HYPERLINK("#'8.1.1.1-2 Transport fuel'!A1", "8.1.1.1-2 Transport fuel") -> 8.1.1.1-2 Transport fuel | D42: Product emissions - Mass
A43: =HYPERLINK("#'8.2.1.1-2 Stationary fuel'!A1", "8.2.1.1-2 Stationary fuel") -> 8.2.1.1-2 Stationary fuel | D43: Product | E43: Product type | F43: Amount in tonnes (Method 1) | G43: Amount in tonnes (Method 2) | H43: Mass emissions assignment (Method 1) | I43: Mass emissions assignment (Method 2) | J43: Emissions intensity (Method 1) | K43: Emissions intensity (Method 2) | L43: Unit
A44: =HYPERLINK("#'10.1.1-2 Solid waste treatment'!A1", "10.1.1.1-2 Solid waste") -> 10.1.1.1-2 Solid waste | D44: Liveweight sold - excluding removals | E44: Main product | F44: =X_Cell_Enterprise_LiveweightSold -> 0 | G44: =X_Cell_Enterprise_LiveweightSold -> 0 | H44: =F44/(F44+F46) -> #DIV/0! | I44: =G44/(G44+G46) -> #DIV/0! | J44: =(Result_EmissionsForWholeProductionCycle_Method1/F44)*H44 -> #DIV/0! | K44: =(Result_EmissionsForWholeProductionCycle_Method2/G44)*I44 -> #DIV/0! | L44: t co2e/t liveweight sold
A45: =HYPERLINK("#'14.1.1-2 Purchased electricity'!A1", "14.1.1-2 Purchased electricity") -> 14.1.1-2 Purchased electricity | D45: Liveweight sold - net emissions | E45: Main product | F45: =F44 -> 0 | G45: =G44 -> 0 | H45: =H44 -> #DIV/0! | I45: =I44 -> #DIV/0! | J45: =(Result_NetEmissions_Method1/F45)*H45 -> #DIV/0! | K45: =(Result_NetEmissions_Method2/G45)*I45 -> #DIV/0! | L45: t co2e/t liveweight sold
A46: =HYPERLINK("#'15 Scope 3'!A1", "15 Scope 3") -> 15 Scope 3 | D46: Manure sold - excluding removals | E46: Co-product | F46: =X_Cell_Enteprise_ManureProduced_Method1*X_Cell_Enteprise_PercentManureSold -> 0 | G46: =X_Cell_Enteprise_ManureProduced_Method2*X_Cell_Enteprise_PercentManureSold -> 0 | H46: =F46/(F44+F46) -> #DIV/0! | I46: =G46/(G44+G46) -> #DIV/0! | J46: =(Result_EmissionsForWholeProductionCycle_Method1/F46)*H46 -> #DIV/0! | K46: =(Result_EmissionsForWholeProductionCycle_Method2/G46)*I46 -> #DIV/0! | L46: t co2e/t manure
A47: =HYPERLINK("#'Calcs - Manure sent off-site'!A1", "Calcs - Manure sent off-site") -> Calcs - Manure sent off-site | D47: Manure sold - net emissions | E47: Co-product | F47: =F46 -> 0 | G47: =G46 -> 0 | H47: =H46 -> #DIV/0! | I47: =I46 -> #DIV/0! | J47: =(Result_NetEmissions_Method1/F47)*H47 -> #DIV/0! | K47: =(Result_NetEmissions_Method2/G47)*I47 -> #DIV/0! | L47: t co2e/t manure
D48: Manure used as fertiliser on own farm | E48: Residual product | F48: =X_Cell_Enteprise_ManureProduced_Method1*X_Cell_Enteprise_PercentManureAppliedAsFertiliserOwnFarm -> 0 | G48: =X_Cell_Enteprise_ManureProduced_Method2*X_Cell_Enteprise_PercentManureAppliedAsFertiliserOwnFarm -> 0 | H48: N/A | I48: N/A | J48: N/A | K48: N/A
A50: APPENDICES | D50: Product emissions - Economic
A51: =HYPERLINK("#'Constants - Pasture Beef'!A1", "Constants - Pasture Beef") -> Constants - Pasture Beef | D51: Product | E51: Product type | F51: Amount in tonnes (Method 1) | G51: Amount in tonnes (Method 2) | H51: Economic emissions assignment | J51: Emissions intensity (Method 1) | K51: Emissions intensity (Method 2) | L51: Unit
A52: =HYPERLINK("#'Constants - Ag Residue'!A1", "Constants - Ag residue") -> Constants - Ag residue | D52: Liveweight sold - excluding removals | E52: Main product | F52: =F44 -> 0 | G52: =G44 -> 0 | H52: =X_Cell_Enteprise_PercentIncomeFromLiveweight -> 0 | J52: =(Result_EmissionsForWholeProductionCycle_Method1/F52)*H52 -> #DIV/0! | K52: =(Result_EmissionsForWholeProductionCycle_Method2/G52)*H52 -> #DIV/0! | L52: t co2e/t liveweight sold
A53: =HYPERLINK("#'Constants - Common Livestock'!A1", "Constants - Common Livestock") -> Constants - Common Livestock | D53: Liveweight sold - net emissions | E53: Main product | F53: =F45 -> 0 | G53: =G45 -> 0 | H53: =H52 -> 0 | J53: =(Result_NetEmissions_Method1/F53)*H53 -> #DIV/0! | K53: =(Result_NetEmissions_Method2/G53)*H53 -> #DIV/0! | L53: t co2e/t liveweight sold
A54: =HYPERLINK("#'Constants - Electricity'!A1", "Constants - Electricity") -> Constants - Electricity | D54: Manure sold - excluding removals | E54: Co-product | F54: =F46 -> 0 | G54: =G46 -> 0 | H54: =X_Cell_Enteprise_PercentIncomeFromManure -> 0 | J54: =(Result_EmissionsForWholeProductionCycle_Method1/F54)*H54 -> #DIV/0! | K54: =(Result_EmissionsForWholeProductionCycle_Method2/G54)*H54 -> #DIV/0! | L54: t co2e/t manure
A55: =HYPERLINK("#'Constants - Fertiliser'!A1", "Constants - Fertiliser") -> Constants - Fertiliser | D55: Manure sold - net emissions | E55: Co-product | F55: =F47 -> 0 | G55: =G47 -> 0 | H55: =H54 -> 0 | J55: =(Result_NetEmissions_Method1/F55)*H55 -> #DIV/0! | K55: =(Result_NetEmissions_Method2/G55)*H55 -> #DIV/0! | L55: t co2e/t manure
A56: =HYPERLINK("#'Constants - Fuel'!A1", "Constants - Fuel") -> Constants - Fuel | D56: Manure used as fertiliser on own farm | E56: Residual product | F56: =F48 -> 0 | G56: =G48 -> 0 | H56: N/A | J56: N/A | K56: N/A
A57: =HYPERLINK("#'Constants - Scope 3'!A1", "Constants - Scope 3") -> Constants - Scope 3
A58: =HYPERLINK("#'Constants - Solid Waste'!A1", "Constants - Solid Waste") -> Constants - Solid Waste | D58: Emissions per tonne liveweight grown
A59: =HYPERLINK("#'Constants - Common'!A1", "Constants - Common") -> Constants - Common | D59: Product | E59: Product type | F59: Amount in tonnes (Method 1) | G59: Amount in tonnes (Method 2) | J59: Emissions intensity (Method 1) | K59: Emissions intensity (Method 2) | L59: Unit
A60: =HYPERLINK("#'Acknowledgements'!A1", "Acknowledgements") -> Acknowledgements | D60: Liveweight grown - Method 1 | E60: N/A | F60: =X_Cell_Enteprise_LiveweightGrown_Method1 -> 0 | G60: =X_Cell_Enteprise_LiveweightGrown_Method2 -> 0 | J60: =Result_NetEmissions_Method1/F60 -> #DIV/0! | K60: =Result_NetEmissions_Method1/G60 -> #DIV/0! | L60: t co2e/t liveweight grown

Sheet Input - Enterprise
A1: #VALUE! | C1: Input - Enterprise
A3: =HYPERLINK("#'Home'!A1", "Home") -> Home
A4: =HYPERLINK("#'Results - Activity period'!A1", "Results - Activity period") -> Results - Activity period
A5: =HYPERLINK("#'Results - Product EI'!A1", "Results - Product Emissions Intensity") -> Results - Product Emissions Intensity | D5: Your business
D7: Farm name
A8: INPUTS | D8: Reporting entity name
A9: =HYPERLINK("#'Input - Enterprise'!A1", "Enterprise") -> Enterprise
A10: =HYPERLINK("#'Input - Site'!A1", "Site") -> Site | D10: 💡An 'Emissions accounting period' is a 12 month period where the business can report on the emissions, and is typically the same as the business' financial accounting period.
A11: =HYPERLINK("#'Input - Pasture Beef'!A1", "Pasture Beef") -> Pasture Beef
A12: =HYPERLINK("#'Input - Livestock sales'!A1", "Livestock sales") -> Livestock sales | D12: Emissions calculation period start date | F12: ← DD/MM/YYYY or DD Month YYYY
A13: =HYPERLINK("#'Input - Beef cattle purchases'!A1", "Beef cattle purchases") -> Beef cattle purchases | D13: Emissions calculation period end date | E13: =DATE(YEAR(E12)+1,MONTH(E12),DAY(E12))-1 -> 365 | F13: ← Automatically calculated, 12 months after start date
A14: =HYPERLINK("#'Input - Pasture'!A1", "Pasture") -> Pasture
A15: =HYPERLINK("#'Input - Fert Prod System'!A1", "Fert Prod System") -> Fert Prod System
A16: =HYPERLINK("#'Input - Fertiliser'!A1", "Fertiliser") -> Fertiliser | D16: Production
A17: =HYPERLINK("#'Input - Fuel'!A1", "Fuel") -> Fuel
A18: =HYPERLINK("#'Input - Electricity'!A1", "Electricity") -> Electricity | D18: Production timeframe start | F18: ← DD/MM/YYYY or DD Month YYYY
A19: =HYPERLINK("#'Input - Common farm inputs'!A1", "Common farm inputs") -> Common farm inputs | D19: Production timeframe end | F19: ← DD/MM/YYYY or DD Month YYYY
A20: =HYPERLINK("#'Input - Crop pasture farm input'!A1", "Crop pasture farm input") -> Crop pasture farm input | D20: Production timeframe length | E20: =DATEDIF(E18,E19+1,"m") -> 0 | F20: Months
A21: =HYPERLINK("#'Input - Livestock farm Inputs'!A1", "Livestock farm Inputs") -> Livestock farm Inputs
A22: =HYPERLINK("#'Input - Freight'!A1", "Freight") -> Freight | D22: Liveweight sold | E22: =SUM(Table_Input_LivestockSales[Total liveweight sold])*10^-3 -> 0 | G22: tonnes
A23: =HYPERLINK("#'Input - Solid waste'!A1", "Solid waste") -> Solid waste | D23: Liveweight grown - method 1 | E23: =SUM(Enterprise_PastureBeef_InputFunctions.multiplyCorrespondingCells([0]!X_Table_PastureBeef_Head_Method1, [0]!X_Table_PastureBeef_Duration_Method1, [0]!X_Table_PastureBeef_LiveweightGain_Method1))*10^-3 -> 0 | G23: tonnes
A24: =HYPERLINK("#'Input - Manure sent off-site'!A1", "Manure sent off-site") -> Manure sent off-site | D24: Liveweight grown - method 2 | E24: =SUM(Enterprise_PastureBeef_InputFunctions.multiplyCorrespondingCells([0]!X_Table_PastureBeef_Head_Method2, [0]!X_Table_PastureBeef_Duration_Method2, [0]!X_Table_PastureBeef_LiveweightGain_Method2))*10^-3 -> 0 | G24: tonnes
A25: =HYPERLINK("#'Input - Data quality'!A1", "Data quality") -> Data quality | D25: Manure produced - method 1 | E25: =SUM(Enterprise_PastureBeef_InputFunctions.multiplyCorrespondingCells([0]!X_Table_PastureBeef_Head_Method1, [0]!X_Table_PastureBeef_Duration_Method1, [0]!M1_Table_VS_j_k_l))*10^-3 -> 0 | G25: tonnes
D26: Manure produced - method 2 | E26: =SUM(Enterprise_PastureBeef_InputFunctions.multiplyCorrespondingCells([0]!X_Table_PastureBeef_Head_Method2, [0]!X_Table_PastureBeef_Duration_Method2, M2_Table_VS_j_k_l))*10^-3 -> 0 | G26: tonnes
D27: Percent manure sold | G27: percent
A28: CALCULATIONS | D28: Percent manure applied as fertiliser on own farm | G28: percent
A29: =HYPERLINK("#'3.2.1.1-2 Enteric Methane'!A1", "3.2.1.1-2 Enteric Methane") -> 3.2.1.1-2 Enteric Methane | D29: Percent manure applied to soil with no purpose (as waste) | E29: =100%-E27-E28 -> 1 | G29: percent
A30: =HYPERLINK("#'4.2.1.1-2 Methane'!A1", "4.2.1.1-2 Manure methane") -> 4.2.1.1-2 Manure methane
A31: =HYPERLINK("#'4.2.1.3-4 Soil direct N20'!A1", "4.2.1.3-4 Soil direct N2O") -> 4.2.1.3-4 Soil direct N2O | D31: Percentage of income from liveweight sold | G31: percent
A32: =HYPERLINK("#'4.2.1.5-6 Soil Atmos Dep'!A1", "4.2.1.5-6 Soil atm. deposition") -> 4.2.1.5-6 Soil atm. deposition | D32: Percentage of income from manure sold | G32: percent
A33: =HYPERLINK("#'4.2.1.7-8 Soil leach runoff'!A1", "4.2.1.7-8 Soil leach & runoff") -> 4.2.1.7-8 Soil leach & runoff
A34: =HYPERLINK("#'5.1.1.1-2 Inorganic fert N2O'!A1", "5.1.1.1-2 Inorganic fert N2O") -> 5.1.1.1-2 Inorganic fert N2O
A35: =HYPERLINK("#'5.1.1.3-4 Inorganic fert CO2'!A1", "5.1.1.3-4 Inorganic fert CO2") -> 5.1.1.3-4 Inorganic fert CO2
A36: =HYPERLINK("#'5.2.1.1-2 Organic Fert N2O'!A1", "5.2.1.1-2 Organic fert N2O") -> 5.2.1.1-2 Organic fert N2O
A37: =HYPERLINK("#'5.3.1.1-2 Lime CO2'!A1", "5.3.1.1-2 Lime CO2") -> 5.3.1.1-2 Lime CO2 | D37: Carbon removals
A38: =HYPERLINK("#'5.4.1.1-4 Atmos deposition'!A1", "5.4.1.1-4 Atmos. deposition") -> 5.4.1.1-4 Atmos. deposition
A39: =HYPERLINK("#'5.5.1.1-2 Leaching and runoff'!A1", "5.5.1.1-2 Leaching & runoff") -> 5.5.1.1-2 Leaching & runoff
A40: =HYPERLINK("#'6.2.1.1-2 Pasture residue N2O'!A1", "6.2.1.1-2 Pasture residue N2O") -> 6.2.1.1-2 Pasture residue N2O | D40: ="Carbon captured from " & TEXT(X_Cell_Site_StartDate, "d mmmm yyyy") & " to " & TEXT(X_Cell_Site_EndDate, "d, mmmm, yyyy") & " from environmental plantings" -> Carbon captured from 0 January 1900 to 30, December, 1900 from environmental plantings
A41: =HYPERLINK("#'6.3.1.1-2 Leach runoff pasture'!A1", "6.3.1.1-2 Leach & runoff (pasture)") -> 6.3.1.1-2 Leach & runoff (pasture)
A42: =HYPERLINK("#'8.1.1.1-2 Transport fuel'!A1", "8.1.1.1-2 Transport fuel") -> 8.1.1.1-2 Transport fuel | D42: Planting name | E42: Total removed CO2 | F42: Percent allocated to this enterprise | G42: Removal allocated to this enterprise
A43: =HYPERLINK("#'8.2.1.1-2 Stationary fuel'!A1", "8.2.1.1-2 Stationary fuel") -> 8.2.1.1-2 Stationary fuel | G43: =Table_Input_Enterprise_PlantingRemovals[[#This Row],[Total removed CO2]]*Table_Input_Enterprise_PlantingRemovals[[#This Row],[Percent allocated to this enterprise]] -> 0
A44: =HYPERLINK("#'10.1.1-2 Solid waste treatment'!A1", "10.1.1.1-2 Solid waste") -> 10.1.1.1-2 Solid waste
A45: =HYPERLINK("#'14.1.1-2 Purchased electricity'!A1", "14.1.1-2 Purchased electricity") -> 14.1.1-2 Purchased electricity
A46: =HYPERLINK("#'15 Scope 3'!A1", "15 Scope 3") -> 15 Scope 3
A47: =HYPERLINK("#'Calcs - Manure sent off-site'!A1", "Calcs - Manure sent off-site") -> Calcs - Manure sent off-site | D47: Production cycle emissions and removals
D49: ="Gross emissions from other activity periods in the production timeframe " & TEXT(X_Cell_Enterprise_ProductionTimeframeStart, "d mmmm yyyy") & " to " & TEXT(X_Cell_Enterprise_ProductionTimeframeEnd, "d mmmm yyyy") -> Gross emissions from other activity periods in the production timeframe 0 January 1900 to 0 January 1900
A50: APPENDICES
A51: =HYPERLINK("#'Constants - Pasture Beef'!A1", "Constants - Pasture Beef") -> Constants - Pasture Beef | D51: {="There are " & Common_InputFunctions.getOverlappingReportingCycles(X_Cell_Enterprise_ProductionTimeframeStart,X_Cell_Enterprise_ProductionTimeframeEnd,X_Cell_Site_StartDate) & " emissions calculation periods that need to be completed before total product emissions can be determined."} -> #NUM!
A52: =HYPERLINK("#'Constants - Ag Residue'!A1", "Constants - Ag residue") -> Constants - Ag residue | D52: Enter the method 1 and 2 CO2e emissions (excluding removals) from previous emissions calculation periods if applicable.
A53: =HYPERLINK("#'Constants - Common Livestock'!A1", "Constants - Common Livestock") -> Constants - Common Livestock
A54: =HYPERLINK("#'Constants - Electricity'!A1", "Constants - Electricity") -> Constants - Electricity | D54: Emissions calculation cycle | E54: CO2-e emissions method 1 | F54: CO2-e emissions method 2
A55: =HYPERLINK("#'Constants - Fertiliser'!A1", "Constants - Fertiliser") -> Constants - Fertiliser | D55: {=Common_InputFunctions.getOverlappingReportingPeriods(X_Cell_Enterprise_ProductionTimeframeStart,X_Cell_Enterprise_ProductionTimeframeEnd,X_Cell_Site_StartDate)} -> #NUM! | E55: =IF(ISBLANK($D55), 0, IF(ISNUMBER(SEARCH("reporting", $D55)), Result_Enterprise_Scope1_Method1, "Enter value")) -> Enter value | F55: =IF(ISBLANK($D55), 0, IF(ISNUMBER(SEARCH("reporting", $D55)), Result_Enterprise_Scope1_Method2, "Enter value")) -> Enter value | G55: t CO2e
A56: =HYPERLINK("#'Constants - Fuel'!A1", "Constants - Fuel") -> Constants - Fuel | E56: =IF(ISBLANK($D56), 0, IF(ISNUMBER(SEARCH("reporting", $D56)), Result_Enterprise_Scope1_Method1, "Enter value")) -> 0 | F56: =IF(ISBLANK($D56), 0, IF(ISNUMBER(SEARCH("reporting", $D56)), Result_Enterprise_Scope1_Method2, "Enter value")) -> 0 | G56: t CO2e
A57: =HYPERLINK("#'Constants - Scope 3'!A1", "Constants - Scope 3") -> Constants - Scope 3 | E57: =IF(ISBLANK($D57), 0, IF(ISNUMBER(SEARCH("reporting", $D57)), Result_Enterprise_Scope1_Method1, "Enter value")) -> 0 | F57: =IF(ISBLANK($D57), 0, IF(ISNUMBER(SEARCH("reporting", $D57)), Result_Enterprise_Scope1_Method2, "Enter value")) -> 0 | G57: t CO2e
A58: =HYPERLINK("#'Constants - Solid Waste'!A1", "Constants - Solid Waste") -> Constants - Solid Waste | E58: =IF(ISBLANK($D58), 0, IF(ISNUMBER(SEARCH("reporting", $D58)), Result_Enterprise_Scope1_Method1, "Enter value")) -> 0 | F58: =IF(ISBLANK($D58), 0, IF(ISNUMBER(SEARCH("reporting", $D58)), Result_Enterprise_Scope1_Method2, "Enter value")) -> 0 | G58: t CO2e
A59: =HYPERLINK("#'Constants - Common'!A1", "Constants - Common") -> Constants - Common | E59: =IF(ISBLANK($D59), 0, IF(ISNUMBER(SEARCH("reporting", $D59)), Result_Enterprise_Scope1_Method1, "Enter value")) -> 0 | F59: =IF(ISBLANK($D59), 0, IF(ISNUMBER(SEARCH("reporting", $D59)), Result_Enterprise_Scope1_Method2, "Enter value")) -> 0 | G59: t CO2e
A60: =HYPERLINK("#'Acknowledgements'!A1", "Acknowledgements") -> Acknowledgements | D60: Total emissions for production cycle | E60: =SUM(E55:E59) -> 0 | F60: =SUM(F55:F59) -> 0 | G60: t CO2e
D65: ="Carbon removals from environmental plantings for whole production cycle running between " & TEXT(X_Cell_Enterprise_ProductionTimeframeStart, "d mmmm yyyy") & " and " & TEXT(X_Cell_Enterprise_ProductionTimeframeEnd, "d mmmm yyyy") -> Carbon removals from environmental plantings for whole production cycle running between 0 January 1900 and 0 January 1900
D67: Emissions calculation cycle | E67: CO2 removed attributed to this enterprise
D68: {=Common_InputFunctions.getOverlappingReportingPeriods(X_Cell_Enterprise_ProductionTimeframeStart,X_Cell_Enterprise_ProductionTimeframeEnd,X_Cell_Site_StartDate)} -> #NUM! | E68: =IF(ISBLANK($D68), 0, IF(ISNUMBER(SEARCH("reporting", $D68)), SUM(Table_Input_Enterprise_PlantingRemovals[Removal allocated to this enterprise]), "Enter value")) -> Enter value | F68: t CO2
E69: =IF(ISBLANK($D69), 0, IF(ISNUMBER(SEARCH("reporting", $D69)), SUM(Table_Input_Enterprise_PlantingRemovals[Removal allocated to this enterprise]), "Enter value")) -> 0 | F69: t CO2
E70: =IF(ISBLANK($D70), 0, IF(ISNUMBER(SEARCH("reporting", $D70)), SUM(Table_Input_Enterprise_PlantingRemovals[Removal allocated to this enterprise]), "Enter value")) -> 0 | F70: t CO2
E71: =IF(ISBLANK($D71), 0, IF(ISNUMBER(SEARCH("reporting", $D71)), SUM(Table_Input_Enterprise_PlantingRemovals[Removal allocated to this enterprise]), "Enter value")) -> 0 | F71: t CO2
E72: =IF(ISBLANK($D72), 0, IF(ISNUMBER(SEARCH("reporting", $D72)), SUM(Table_Input_Enterprise_PlantingRemovals[Removal allocated to this enterprise]), "Enter value")) -> 0 | F72: t CO2
D73: Total carbon removals for production cycle | E73: =SUM(E68:E72) -> 0 | F73: t CO2

Sheet Input - Site
A1: #VALUE! | C1: Input - Site
A3: =HYPERLINK("#'Home'!A1", "Home") -> Home
A4: =HYPERLINK("#'Results - Activity period'!A1", "Results - Activity period") -> Results - Activity period
A5: =HYPERLINK("#'Results - Product EI'!A1", "Results - Product Emissions Intensity") -> Results - Product Emissions Intensity | D5: Location and climate
D7: Location information is used to reference some region and climate-specific emission factors
A8: INPUTS | D8: Tip: Use the web-based GAF Location Helper tool to easily get region and climate information. You will need an internet connection to use the GAF Location Helper.
A9: =HYPERLINK("#'Input - Enterprise'!A1", "Enterprise") -> Enterprise
A10: =HYPERLINK("#'Input - Site'!A1", "Site") -> Site | D10: State | F10: ← Please select
A11: =HYPERLINK("#'Input - Pasture Beef'!A1", "Pasture Beef") -> Pasture Beef | D11: Region (ABS Statistical area level 4) if state is WA | F11: ← Please select
A12: =HYPERLINK("#'Input - Livestock sales'!A1", "Livestock sales") -> Livestock sales | D12: Leaching zone | F12: ← Please select
A13: =HYPERLINK("#'Input - Beef cattle purchases'!A1", "Beef cattle purchases") -> Beef cattle purchases | D13: Elevation | F13: Meters
A14: =HYPERLINK("#'Input - Pasture'!A1", "Pasture") -> Pasture | D14: Average temperature for reporting period | F14: Degrees celsius
A15: =HYPERLINK("#'Input - Fert Prod System'!A1", "Fert Prod System") -> Fert Prod System | D15: Total rainfall for reporting period | F15: Millimetres
A16: =HYPERLINK("#'Input - Fertiliser'!A1", "Fertiliser") -> Fertiliser | D16: Potential evapotranspiration for reporting period | F16: Millimetres
A17: =HYPERLINK("#'Input - Fuel'!A1", "Fuel") -> Fuel | D17: Number of frost days for reporting period | F17: Days
A18: =HYPERLINK("#'Input - Electricity'!A1", "Electricity") -> Electricity | D18: MAP:PET ratio | E18: =E15/E16 -> #DIV/0!
A19: =HYPERLINK("#'Input - Common farm inputs'!A1", "Common farm inputs") -> Common farm inputs | D19: Rainfall zone | E19: =Common_InputFunctions.Utility_LookupItemFromMinMax(E15,Table_SourceData_RainfallZones[Min rainfall],Table_SourceData_RainfallZones[Max rainfall],Table_SourceData_RainfallZones[Rainfall Zone]) -> Low rainfall
A20: =HYPERLINK("#'Input - Crop pasture farm input'!A1", "Crop pasture farm input") -> Crop pasture farm input | D20: Climate zone | E20: =Common_InputFunctions.Utility_GetClimateZone(E14,E15,E17,E13,E18,Table_SourceData_ClimateZones[Min temp],Table_SourceData_ClimateZones[Max temp],Table_SourceData_ClimateZones[Min rainfall],Table_SourceData_ClimateZones[Max rainfall],Table_SourceData_ClimateZones[Min frost days],Table_SourceData_ClimateZones[Max frost days],Table_SourceData_ClimateZones[Min elevation],Table_SourceData_ClimateZones[Max elevation],Table_SourceData_ClimateZones[Min MAP:PET],Table_SourceData_ClimateZones[Max MAP:PET],Table_SourceData_ClimateZones[Climate zone]) -> #DIV/0!
A21: =HYPERLINK("#'Input - Livestock farm Inputs'!A1", "Livestock farm Inputs") -> Livestock farm Inputs | D21: Wet or dry climate zone | E21: =Common_InputFunctions.Utility_LookupValueInTable($E$20,Table_SourceData_WetDryZones[Climate zone],Table_SourceData_WetDryZones[Wet or Dry Zone]) -> #DIV/0!
A22: =HYPERLINK("#'Input - Freight'!A1", "Freight") -> Freight | D22: Temperature zone | E22: =Common_InputFunctions.Utility_LookupItemFromMinMax(E14,Table_SourceData_TemperatureZones[Min MAT],Table_SourceData_TemperatureZones[Max MAT],Table_SourceData_TemperatureZones[Temperature Zone]) -> Cool
A23: =HYPERLINK("#'Input - Solid waste'!A1", "Solid waste") -> Solid waste
A24: =HYPERLINK("#'Input - Manure sent off-site'!A1", "Manure sent off-site") -> Manure sent off-site
A25: =HYPERLINK("#'Input - Data quality'!A1", "Data quality") -> Data quality
A28: CALCULATIONS
A29: =HYPERLINK("#'3.2.1.1-2 Enteric Methane'!A1", "3.2.1.1-2 Enteric Methane") -> 3.2.1.1-2 Enteric Methane
A30: =HYPERLINK("#'4.2.1.1-2 Methane'!A1", "4.2.1.1-2 Manure methane") -> 4.2.1.1-2 Manure methane
A31: =HYPERLINK("#'4.2.1.3-4 Soil direct N20'!A1", "4.2.1.3-4 Soil direct N2O") -> 4.2.1.3-4 Soil direct N2O
A32: =HYPERLINK("#'4.2.1.5-6 Soil Atmos Dep'!A1", "4.2.1.5-6 Soil atm. deposition") -> 4.2.1.5-6 Soil atm. deposition
A33: =HYPERLINK("#'4.2.1.7-8 Soil leach runoff'!A1", "4.2.1.7-8 Soil leach & runoff") -> 4.2.1.7-8 Soil leach & runoff
A34: =HYPERLINK("#'5.1.1.1-2 Inorganic fert N2O'!A1", "5.1.1.1-2 Inorganic fert N2O") -> 5.1.1.1-2 Inorganic fert N2O
A35: =HYPERLINK("#'5.1.1.3-4 Inorganic fert CO2'!A1", "5.1.1.3-4 Inorganic fert CO2") -> 5.1.1.3-4 Inorganic fert CO2
A36: =HYPERLINK("#'5.2.1.1-2 Organic Fert N2O'!A1", "5.2.1.1-2 Organic fert N2O") -> 5.2.1.1-2 Organic fert N2O
A37: =HYPERLINK("#'5.3.1.1-2 Lime CO2'!A1", "5.3.1.1-2 Lime CO2") -> 5.3.1.1-2 Lime CO2
A38: =HYPERLINK("#'5.4.1.1-4 Atmos deposition'!A1", "5.4.1.1-4 Atmos. deposition") -> 5.4.1.1-4 Atmos. deposition
A39: =HYPERLINK("#'5.5.1.1-2 Leaching and runoff'!A1", "5.5.1.1-2 Leaching & runoff") -> 5.5.1.1-2 Leaching & runoff
A40: =HYPERLINK("#'6.2.1.1-2 Pasture residue N2O'!A1", "6.2.1.1-2 Pasture residue N2O") -> 6.2.1.1-2 Pasture residue N2O
A41: =HYPERLINK("#'6.3.1.1-2 Leach runoff pasture'!A1", "6.3.1.1-2 Leach & runoff (pasture)") -> 6.3.1.1-2 Leach & runoff (pasture)
A42: =HYPERLINK("#'8.1.1.1-2 Transport fuel'!A1", "8.1.1.1-2 Transport fuel") -> 8.1.1.1-2 Transport fuel
A43: =HYPERLINK("#'8.2.1.1-2 Stationary fuel'!A1", "8.2.1.1-2 Stationary fuel") -> 8.2.1.1-2 Stationary fuel
A44: =HYPERLINK("#'10.1.1-2 Solid waste treatment'!A1", "10.1.1.1-2 Solid waste") -> 10.1.1.1-2 Solid waste
A45: =HYPERLINK("#'14.1.1-2 Purchased electricity'!A1", "14.1.1-2 Purchased electricity") -> 14.1.1-2 Purchased electricity
A46: =HYPERLINK("#'15 Scope 3'!A1", "15 Scope 3") -> 15 Scope 3
A47: =HYPERLINK("#'Calcs - Manure sent off-site'!A1", "Calcs - Manure sent off-site") -> Calcs - Manure sent off-site
A50: APPENDICES
A51: =HYPERLINK("#'Constants - Pasture Beef'!A1", "Constants - Pasture Beef") -> Constants - Pasture Beef
A52: =HYPERLINK("#'Constants - Ag Residue'!A1", "Constants - Ag residue") -> Constants - Ag residue
A53: =HYPERLINK("#'Constants - Common Livestock'!A1", "Constants - Common Livestock") -> Constants - Common Livestock
A54: =HYPERLINK("#'Constants - Electricity'!A1", "Constants - Electricity") -> Constants - Electricity
A55: =HYPERLINK("#'Constants - Fertiliser'!A1", "Constants - Fertiliser") -> Constants - Fertiliser
A56: =HYPERLINK("#'Constants - Fuel'!A1", "Constants - Fuel") -> Constants - Fuel
A57: =HYPERLINK("#'Constants - Scope 3'!A1", "Constants - Scope 3") -> Constants - Scope 3
A58: =HYPERLINK("#'Constants - Solid Waste'!A1", "Constants - Solid Waste") -> Constants - Solid Waste
A59: =HYPERLINK("#'Constants - Common'!A1", "Constants - Common") -> Constants - Common
A60: =HYPERLINK("#'Acknowledgements'!A1", "Acknowledgements") -> Acknowledgements

Sheet Input - Pasture Beef
A1: #VALUE! | C1: Input -Pasture Beef
A3: =HYPERLINK("#'Home'!A1", "Home") -> Home
A4: =HYPERLINK("#'Results - Activity period'!A1", "Results - Activity period") -> Results - Activity period
A5: =HYPERLINK("#'Results - Product EI'!A1", "Results - Product Emissions Intensity") -> Results - Product Emissions Intensity | D5: Herd movement
D7: State | E7: =X_Cell_Site_State -> 0
A8: INPUTS | D8: Livestock production region | F8: ← Please select
A9: =HYPERLINK("#'Input - Enterprise'!A1", "Enterprise") -> Enterprise | D9: Cattle breed | F9: ← Please select
A10: =HYPERLINK("#'Input - Site'!A1", "Site") -> Site
A11: =HYPERLINK("#'Input - Pasture Beef'!A1", "Pasture Beef") -> Pasture Beef
A12: =HYPERLINK("#'Input - Livestock sales'!A1", "Livestock sales") -> Livestock sales
A13: =HYPERLINK("#'Input - Beef cattle purchases'!A1", "Beef cattle purchases") -> Beef cattle purchases | D13: NOTE: VEERG states that under method 2, time periods may be seasons, months or a custom time period. In this example, method 2 time periods are months.
A14: =HYPERLINK("#'Input - Pasture'!A1", "Pasture") -> Pasture
A15: =HYPERLINK("#'Input - Fert Prod System'!A1", "Fert Prod System") -> Fert Prod System | D15: Duration on farm
A16: =HYPERLINK("#'Input - Fertiliser'!A1", "Fertiliser") -> Fertiliser | D16: Method 1 default values (do not edit) | E16: Bulls < 1 year | F16: Bulls > 1 year | G16: Cows < 1 year | H16: Cows 1-2 years | I16: Cows 2-3 years | J16: Cows > 3 years | K16: Steers < 1 year | L16: Steers 1-2 years | M16: Steers 2-3 years | N16: Steers >3 years
A17: =HYPERLINK("#'Input - Fuel'!A1", "Fuel") -> Fuel | D17: Spring | E17: =91.25 -> 91.25 | F17: =91.25 -> 91.25 | G17: =91.25 -> 91.25 | H17: =91.25 -> 91.25 | I17: =91.25 -> 91.25 | J17: =91.25 -> 91.25 | K17: =91.25 -> 91.25 | L17: =91.25 -> 91.25 | ... N17: =91.25 -> 91.25 | O17: Days
A18: =HYPERLINK("#'Input - Electricity'!A1", "Electricity") -> Electricity | D18: Summer | E18: =91.25 -> 91.25 | F18: =91.25 -> 91.25 | G18: =91.25 -> 91.25 | H18: =91.25 -> 91.25 | I18: =91.25 -> 91.25 | J18: =91.25 -> 91.25 | K18: =91.25 -> 91.25 | L18: =91.25 -> 91.25 | ... N18: =91.25 -> 91.25 | O18: Days
A19: =HYPERLINK("#'Input - Common farm inputs'!A1", "Common farm inputs") -> Common farm inputs | D19: Autumn | E19: =91.25 -> 91.25 | F19: =91.25 -> 91.25 | G19: =91.25 -> 91.25 | H19: =91.25 -> 91.25 | I19: =91.25 -> 91.25 | J19: =91.25 -> 91.25 | K19: =91.25 -> 91.25 | L19: =91.25 -> 91.25 | ... N19: =91.25 -> 91.25 | O19: Days
A20: =HYPERLINK("#'Input - Crop pasture farm input'!A1", "Crop pasture farm input") -> Crop pasture farm input | D20: Winter | E20: =91.25 -> 91.25 | F20: =91.25 -> 91.25 | G20: =91.25 -> 91.25 | H20: =91.25 -> 91.25 | I20: =91.25 -> 91.25 | J20: =91.25 -> 91.25 | K20: =91.25 -> 91.25 | L20: =91.25 -> 91.25 | ... N20: =91.25 -> 91.25 | O20: Days
A21: =HYPERLINK("#'Input - Livestock farm Inputs'!A1", "Livestock farm Inputs") -> Livestock farm Inputs
A22: =HYPERLINK("#'Input - Freight'!A1", "Freight") -> Freight | D22: Method 2 custom values (edit if known) | E22: Bulls < 1 year | F22: Bulls > 1 year | G22: Cows < 1 year | H22: Cows 1-2 years | I22: Cows 2-3 years | J22: Cows > 3 years | K22: Steers < 1 year | L22: Steers 1-2 years | M22: Steers 2-3 years | N22: Steers >3 years
A23: =HYPERLINK("#'Input - Solid waste'!A1", "Solid waste") -> Solid waste | D23: =TEXT(X_Cell_Site_StartDate, "mmmm yyyy") -> January 1900 | E23: =DAY(EOMONTH($D23,0)) -> 31 | F23: =DAY(EOMONTH($D23,0)) -> 31 | G23: =DAY(EOMONTH($D23,0)) -> 31 | H23: =DAY(EOMONTH($D23,0)) -> 31 | I23: =DAY(EOMONTH($D23,0)) -> 31 | J23: =DAY(EOMONTH($D23,0)) -> 31 | K23: =DAY(EOMONTH($D23,0)) -> 31 | L23: =DAY(EOMONTH($D23,0)) -> 31 | ... N23: =DAY(EOMONTH($D23,0)) -> 31 | O23: Days
A24: =HYPERLINK("#'Input - Manure sent off-site'!A1", "Manure sent off-site") -> Manure sent off-site | D24: =TEXT(EDATE(X_Cell_Site_StartDate,1), "mmmm yyyy") -> January 1900 | E24: =DAY(EOMONTH($D24,0)) -> 31 | F24: =DAY(EOMONTH($D24,0)) -> 31 | G24: =DAY(EOMONTH($D24,0)) -> 31 | H24: =DAY(EOMONTH($D24,0)) -> 31 | I24: =DAY(EOMONTH($D24,0)) -> 31 | J24: =DAY(EOMONTH($D24,0)) -> 31 | K24: =DAY(EOMONTH($D24,0)) -> 31 | L24: =DAY(EOMONTH($D24,0)) -> 31 | ... N24: =DAY(EOMONTH($D24,0)) -> 31 | O24: Days
A25: =HYPERLINK("#'Input - Data quality'!A1", "Data quality") -> Data quality | D25: =TEXT(EDATE(X_Cell_Site_StartDate,2), "mmmm yyyy") -> February 1900 | E25: =DAY(EOMONTH($D25,0)) -> 28 | F25: =DAY(EOMONTH($D25,0)) -> 28 | G25: =DAY(EOMONTH($D25,0)) -> 28 | H25: =DAY(EOMONTH($D25,0)) -> 28 | I25: =DAY(EOMONTH($D25,0)) -> 28 | J25: =DAY(EOMONTH($D25,0)) -> 28 | K25: =DAY(EOMONTH($D25,0)) -> 28 | L25: =DAY(EOMONTH($D25,0)) -> 28 | ... N25: =DAY(EOMONTH($D25,0)) -> 28 | O25: Days
D26: =TEXT(EDATE(X_Cell_Site_StartDate,3), "mmmm yyyy") -> March 1900 | E26: =DAY(EOMONTH($D26,0)) -> 31 | F26: =DAY(EOMONTH($D26,0)) -> 31 | G26: =DAY(EOMONTH($D26,0)) -> 31 | H26: =DAY(EOMONTH($D26,0)) -> 31 | I26: =DAY(EOMONTH($D26,0)) -> 31 | J26: =DAY(EOMONTH($D26,0)) -> 31 | K26: =DAY(EOMONTH($D26,0)) -> 31 | L26: =DAY(EOMONTH($D26,0)) -> 31 | ... N26: =DAY(EOMONTH($D26,0)) -> 31 | O26: Days
D27: =TEXT(EDATE(X_Cell_Site_StartDate,4), "mmmm yyyy") -> April 1900 | E27: =DAY(EOMONTH($D27,0)) -> 30 | F27: =DAY(EOMONTH($D27,0)) -> 30 | G27: =DAY(EOMONTH($D27,0)) -> 30 | H27: =DAY(EOMONTH($D27,0)) -> 30 | I27: =DAY(EOMONTH($D27,0)) -> 30 | J27: =DAY(EOMONTH($D27,0)) -> 30 | K27: =DAY(EOMONTH($D27,0)) -> 30 | L27: =DAY(EOMONTH($D27,0)) -> 30 | ... N27: =DAY(EOMONTH($D27,0)) -> 30 | O27: Days
A28: CALCULATIONS | D28: =TEXT(EDATE(X_Cell_Site_StartDate,5), "mmmm yyyy") -> May 1900 | E28: =DAY(EOMONTH($D28,0)) -> 31 | F28: =DAY(EOMONTH($D28,0)) -> 31 | G28: =DAY(EOMONTH($D28,0)) -> 31 | H28: =DAY(EOMONTH($D28,0)) -> 31 | I28: =DAY(EOMONTH($D28,0)) -> 31 | J28: =DAY(EOMONTH($D28,0)) -> 31 | K28: =DAY(EOMONTH($D28,0)) -> 31 | L28: =DAY(EOMONTH($D28,0)) -> 31 | ... N28: =DAY(EOMONTH($D28,0)) -> 31 | O28: Days
A29: =HYPERLINK("#'3.2.1.1-2 Enteric Methane'!A1", "3.2.1.1-2 Enteric Methane") -> 3.2.1.1-2 Enteric Methane | D29: =TEXT(EDATE(X_Cell_Site_StartDate,6), "mmmm yyyy") -> June 1900 | E29: =DAY(EOMONTH($D29,0)) -> 30 | F29: =DAY(EOMONTH($D29,0)) -> 30 | G29: =DAY(EOMONTH($D29,0)) -> 30 | H29: =DAY(EOMONTH($D29,0)) -> 30 | I29: =DAY(EOMONTH($D29,0)) -> 30 | J29: =DAY(EOMONTH($D29,0)) -> 30 | K29: =DAY(EOMONTH($D29,0)) -> 30 | L29: =DAY(EOMONTH($D29,0)) -> 30 | ... N29: =DAY(EOMONTH($D29,0)) -> 30 | O29: Days
A30: =HYPERLINK("#'4.2.1.1-2 Methane'!A1", "4.2.1.1-2 Manure methane") -> 4.2.1.1-2 Manure methane | D30: =TEXT(EDATE(X_Cell_Site_StartDate,7), "mmmm yyyy") -> July 1900 | E30: =DAY(EOMONTH($D30,0)) -> 31 | F30: =DAY(EOMONTH($D30,0)) -> 31 | G30: =DAY(EOMONTH($D30,0)) -> 31 | H30: =DAY(EOMONTH($D30,0)) -> 31 | I30: =DAY(EOMONTH($D30,0)) -> 31 | J30: =DAY(EOMONTH($D30,0)) -> 31 | K30: =DAY(EOMONTH($D30,0)) -> 31 | L30: =DAY(EOMONTH($D30,0)) -> 31 | ... N30: =DAY(EOMONTH($D30,0)) -> 31 | O30: Days
A31: =HYPERLINK("#'4.2.1.3-4 Soil direct N20'!A1", "4.2.1.3-4 Soil direct N2O") -> 4.2.1.3-4 Soil direct N2O | D31: =TEXT(EDATE(X_Cell_Site_StartDate,8), "mmmm yyyy") -> August 1900 | E31: =DAY(EOMONTH($D31,0)) -> 31 | F31: =DAY(EOMONTH($D31,0)) -> 31 | G31: =DAY(EOMONTH($D31,0)) -> 31 | H31: =DAY(EOMONTH($D31,0)) -> 31 | I31: =DAY(EOMONTH($D31,0)) -> 31 | J31: =DAY(EOMONTH($D31,0)) -> 31 | K31: =DAY(EOMONTH($D31,0)) -> 31 | L31: =DAY(EOMONTH($D31,0)) -> 31 | ... N31: =DAY(EOMONTH($D31,0)) -> 31 | O31: Days
A32: =HYPERLINK("#'4.2.1.5-6 Soil Atmos Dep'!A1", "4.2.1.5-6 Soil atm. deposition") -> 4.2.1.5-6 Soil atm. deposition | D32: =TEXT(EDATE(X_Cell_Site_StartDate,9), "mmmm yyyy") -> September 1900 | E32: =DAY(EOMONTH($D32,0)) -> 30 | F32: =DAY(EOMONTH($D32,0)) -> 30 | G32: =DAY(EOMONTH($D32,0)) -> 30 | H32: =DAY(EOMONTH($D32,0)) -> 30 | I32: =DAY(EOMONTH($D32,0)) -> 30 | J32: =DAY(EOMONTH($D32,0)) -> 30 | K32: =DAY(EOMONTH($D32,0)) -> 30 | L32: =DAY(EOMONTH($D32,0)) -> 30 | ... N32: =DAY(EOMONTH($D32,0)) -> 30 | O32: Days
A33: =HYPERLINK("#'4.2.1.7-8 Soil leach runoff'!A1", "4.2.1.7-8 Soil leach & runoff") -> 4.2.1.7-8 Soil leach & runoff | D33: =TEXT(EDATE(X_Cell_Site_StartDate,10), "mmmm yyyy") -> October 1900 | E33: =DAY(EOMONTH($D33,0)) -> 31 | F33: =DAY(EOMONTH($D33,0)) -> 31 | G33: =DAY(EOMONTH($D33,0)) -> 31 | H33: =DAY(EOMONTH($D33,0)) -> 31 | I33: =DAY(EOMONTH($D33,0)) -> 31 | J33: =DAY(EOMONTH($D33,0)) -> 31 | K33: =DAY(EOMONTH($D33,0)) -> 31 | L33: =DAY(EOMONTH($D33,0)) -> 31 | ... N33: =DAY(EOMONTH($D33,0)) -> 31 | O33: Days
A34: =HYPERLINK("#'5.1.1.1-2 Inorganic fert N2O'!A1", "5.1.1.1-2 Inorganic fert N2O") -> 5.1.1.1-2 Inorganic fert N2O | D34: =TEXT(EDATE(X_Cell_Site_StartDate,11), "mmmm yyyy") -> November 1900 | E34: =DAY(EOMONTH($D34,0)) -> 30 | F34: =DAY(EOMONTH($D34,0)) -> 30 | G34: =DAY(EOMONTH($D34,0)) -> 30 | H34: =DAY(EOMONTH($D34,0)) -> 30 | I34: =DAY(EOMONTH($D34,0)) -> 30 | J34: =DAY(EOMONTH($D34,0)) -> 30 | K34: =DAY(EOMONTH($D34,0)) -> 30 | L34: =DAY(EOMONTH($D34,0)) -> 30 | ... N34: =DAY(EOMONTH($D34,0)) -> 30 | O34: Days
A35: =HYPERLINK("#'5.1.1.3-4 Inorganic fert CO2'!A1", "5.1.1.3-4 Inorganic fert CO2") -> 5.1.1.3-4 Inorganic fert CO2
A36: =HYPERLINK("#'5.2.1.1-2 Organic Fert N2O'!A1", "5.2.1.1-2 Organic fert N2O") -> 5.2.1.1-2 Organic fert N2O
A37: =HYPERLINK("#'5.3.1.1-2 Lime CO2'!A1", "5.3.1.1-2 Lime CO2") -> 5.3.1.1-2 Lime CO2 | D37: Head
A38: =HYPERLINK("#'5.4.1.1-4 Atmos deposition'!A1", "5.4.1.1-4 Atmos. deposition") -> 5.4.1.1-4 Atmos. deposition | D38: Method 1 values | E38: Bulls < 1 year | F38: Bulls > 1 year | G38: Cows < 1 year | H38: Cows 1-2 years | I38: Cows 2-3 years | J38: Cows > 3 years | K38: Steers < 1 year | L38: Steers 1-2 years | M38: Steers 2-3 years | N38: Steers >3 years
A39: =HYPERLINK("#'5.5.1.1-2 Leaching and runoff'!A1", "5.5.1.1-2 Leaching & runoff") -> 5.5.1.1-2 Leaching & runoff | D39: Spring | O39: Head
A40: =HYPERLINK("#'6.2.1.1-2 Pasture residue N2O'!A1", "6.2.1.1-2 Pasture residue N2O") -> 6.2.1.1-2 Pasture residue N2O | D40: Summer | O40: Head
A41: =HYPERLINK("#'6.3.1.1-2 Leach runoff pasture'!A1", "6.3.1.1-2 Leach & runoff (pasture)") -> 6.3.1.1-2 Leach & runoff (pasture) | D41: Autumn | O41: Head
A42: =HYPERLINK("#'8.1.1.1-2 Transport fuel'!A1", "8.1.1.1-2 Transport fuel") -> 8.1.1.1-2 Transport fuel | D42: Winter | O42: Head
A43: =HYPERLINK("#'8.2.1.1-2 Stationary fuel'!A1", "8.2.1.1-2 Stationary fuel") -> 8.2.1.1-2 Stationary fuel
A44: =HYPERLINK("#'10.1.1-2 Solid waste treatment'!A1", "10.1.1.1-2 Solid waste") -> 10.1.1.1-2 Solid waste | D44: Method 2 values | E44: Bulls < 1 year | F44: Bulls > 1 year | G44: Cows < 1 year | H44: Cows 1-2 years | I44: Cows 2-3 years | J44: Cows > 3 years | K44: Steers < 1 year | L44: Steers 1-2 years | M44: Steers 2-3 years | N44: Steers >3 years
A45: =HYPERLINK("#'14.1.1-2 Purchased electricity'!A1", "14.1.1-2 Purchased electricity") -> 14.1.1-2 Purchased electricity | D45: =TEXT(X_Cell_Site_StartDate, "mmmm yyyy") -> January 1900 | O45: Head
A46: =HYPERLINK("#'15 Scope 3'!A1", "15 Scope 3") -> 15 Scope 3 | D46: =TEXT(EDATE(X_Cell_Site_StartDate,1), "mmmm yyyy") -> January 1900 | O46: Head
A47: =HYPERLINK("#'Calcs - Manure sent off-site'!A1", "Calcs - Manure sent off-site") -> Calcs - Manure sent off-site | D47: =TEXT(EDATE(X_Cell_Site_StartDate,2), "mmmm yyyy") -> February 1900 | O47: Head
D48: =TEXT(EDATE(X_Cell_Site_StartDate,3), "mmmm yyyy") -> March 1900 | O48: Head
D49: =TEXT(EDATE(X_Cell_Site_StartDate,4), "mmmm yyyy") -> April 1900 | O49: Head
A50: APPENDICES | D50: =TEXT(EDATE(X_Cell_Site_StartDate,5), "mmmm yyyy") -> May 1900 | O50: Head
A51: =HYPERLINK("#'Constants - Pasture Beef'!A1", "Constants - Pasture Beef") -> Constants - Pasture Beef | D51: =TEXT(EDATE(X_Cell_Site_StartDate,6), "mmmm yyyy") -> June 1900 | O51: Head
A52: =HYPERLINK("#'Constants - Ag Residue'!A1", "Constants - Ag residue") -> Constants - Ag residue | D52: =TEXT(EDATE(X_Cell_Site_StartDate,7), "mmmm yyyy") -> July 1900 | O52: Head
A53: =HYPERLINK("#'Constants - Common Livestock'!A1", "Constants - Common Livestock") -> Constants - Common Livestock | D53: =TEXT(EDATE(X_Cell_Site_StartDate,8), "mmmm yyyy") -> August 1900 | O53: Head
A54: =HYPERLINK("#'Constants - Electricity'!A1", "Constants - Electricity") -> Constants - Electricity | D54: =TEXT(EDATE(X_Cell_Site_StartDate,9), "mmmm yyyy") -> September 1900 | O54: Head
A55: =HYPERLINK("#'Constants - Fertiliser'!A1", "Constants - Fertiliser") -> Constants - Fertiliser | D55: =TEXT(EDATE(X_Cell_Site_StartDate,10), "mmmm yyyy") -> October 1900 | O55: Head
A56: =HYPERLINK("#'Constants - Fuel'!A1", "Constants - Fuel") -> Constants - Fuel | D56: =TEXT(EDATE(X_Cell_Site_StartDate,11), "mmmm yyyy") -> November 1900 | O56: Head
A57: =HYPERLINK("#'Constants - Scope 3'!A1", "Constants - Scope 3") -> Constants - Scope 3
A58: =HYPERLINK("#'Constants - Solid Waste'!A1", "Constants - Solid Waste") -> Constants - Solid Waste
A59: =HYPERLINK("#'Constants - Common'!A1", "Constants - Common") -> Constants - Common | D59: Liveweight
A60: =HYPERLINK("#'Acknowledgements'!A1", "Acknowledgements") -> Acknowledgements | D60: Method 1 default values (do not edit) | E60: Bulls < 1 year | F60: Bulls > 1 year | G60: Cows < 1 year | H60: Cows 1-2 years | I60: Cows 2-3 years | J60: Cows > 3 years | K60: Steers < 1 year | L60: Steers 1-2 years | M60: Steers 2-3 years | N60: Steers >3 years
D61: Spring | E61: =InputFunctions_PastureBeef.LookupLiveweightFromSeason($E$7,X_Cell_PastureBeef_ProductionRegion,$D61,E$60,Table_SourceData_PastureBeef_LiveweightAllStates[State],Table_SourceData_PastureBeef_LiveweightAllStates[Region],Table_SourceData_PastureBeef_LiveweightAllStates[Season],Table_SourceData_PastureBeef_LiveweightAllStates[#Headers],Table_SourceData_PastureBeef_LiveweightAllStates[#Data],Table_AustralianStates[Common Name],Table_AustralianStates[Abbreviation]) -> #N/A | F61: =InputFunctions_PastureBeef.LookupLiveweightFromSeason($E$7,X_Cell_PastureBeef_ProductionRegion,$D61,F$60,Table_SourceData_PastureBeef_LiveweightAllStates[State],Table_SourceData_PastureBeef_LiveweightAllStates[Region],Table_SourceData_PastureBeef_LiveweightAllStates[Season],Table_SourceData_PastureBeef_LiveweightAllStates[#Headers],Table_SourceData_PastureBeef_LiveweightAllStates[#Data],Table_AustralianStates[Common Name],Table_AustralianStates[Abbreviation]) -> #N/A | G61: =InputFunctions_PastureBeef.LookupLiveweightFromSeason($E$7,X_Cell_PastureBeef_ProductionRegion,$D61,G$60,Table_SourceData_PastureBeef_LiveweightAllStates[State],Table_SourceData_PastureBeef_LiveweightAllStates[Region],Table_SourceData_PastureBeef_LiveweightAllStates[Season],Table_SourceData_PastureBeef_LiveweightAllStates[#Headers],Table_SourceData_PastureBeef_LiveweightAllStates[#Data],Table_AustralianStates[Common Name],Table_AustralianStates[Abbreviation]) -> #N/A | H61: =InputFunctions_PastureBeef.LookupLiveweightFromSeason($E$7,X_Cell_PastureBeef_ProductionRegion,$D61,H$60,Table_SourceData_PastureBeef_LiveweightAllStates[State],Table_SourceData_PastureBeef_LiveweightAllStates[Region],Table_SourceData_PastureBeef_LiveweightAllStates[Season],Table_SourceData_PastureBeef_LiveweightAllStates[#Headers],Table_SourceData_PastureBeef_LiveweightAllStates[#Data],Table_AustralianStates[Common Name],Table_AustralianStates[Abbreviation]) -> #N/A | I61: =InputFunctions_PastureBeef.LookupLiveweightFromSeason($E$7,X_Cell_PastureBeef_ProductionRegion,$D61,I$60,Table_SourceData_PastureBeef_LiveweightAllStates[State],Table_SourceData_PastureBeef_LiveweightAllStates[Region],Table_SourceData_PastureBeef_LiveweightAllStates[Season],Table_SourceData_PastureBeef_LiveweightAllStates[#Headers],Table_SourceData_PastureBeef_LiveweightAllStates[#Data],Table_AustralianStates[Common Name],Table_AustralianStates[Abbreviation]) -> #N/A | J61: =InputFunctions_PastureBeef.LookupLiveweightFromSeason($E$7,X_Cell_PastureBeef_ProductionRegion,$D61,J$60,Table_SourceData_PastureBeef_LiveweightAllStates[State],Table_SourceData_PastureBeef_LiveweightAllStates[Region],Table_SourceData_PastureBeef_LiveweightAllStates[Season],Table_SourceData_PastureBeef_LiveweightAllStates[#Headers],Table_SourceData_PastureBeef_LiveweightAllStates[#Data],Table_AustralianStates[Common Name],Table_AustralianStates[Abbreviation]) -> #N/A | K61: =InputFunctions_PastureBeef.LookupLiveweightFromSeason($E$7,X_Cell_PastureBeef_ProductionRegion,$D61,K$60,Table_SourceData_PastureBeef_LiveweightAllStates[State],Table_SourceData_PastureBeef_LiveweightAllStates[Region],Table_SourceData_PastureBeef_LiveweightAllStates[Season],Table_SourceData_PastureBeef_LiveweightAllStates[#Headers],Table_SourceData_PastureBeef_LiveweightAllStates[#Data],Table_AustralianStates[Common Name],Table_AustralianStates[Abbreviation]) -> #N/A | L61: =InputFunctions_PastureBeef.LookupLiveweightFromSeason($E$7,X_Cell_PastureBeef_ProductionRegion,$D61,L$60,Table_SourceData_PastureBeef_LiveweightAllStates[State],Table_SourceData_PastureBeef_LiveweightAllStates[Region],Table_SourceData_PastureBeef_LiveweightAllStates[Season],Table_SourceData_PastureBeef_LiveweightAllStates[#Headers],Table_SourceData_PastureBeef_LiveweightAllStates[#Data],Table_AustralianStates[Common Name],Table_AustralianStates[Abbreviation]) -> #N/A | ... N61: =InputFunctions_PastureBeef.LookupLiveweightFromSeason($E$7,X_Cell_PastureBeef_ProductionRegion,$D61,N$60,Table_SourceData_PastureBeef_LiveweightAllStates[State],Table_SourceData_PastureBeef_LiveweightAllStates[Region],Table_SourceData_PastureBeef_LiveweightAllStates[Season],Table_SourceData_PastureBeef_LiveweightAllStates[#Headers],Table_SourceData_PastureBeef_LiveweightAllStates[#Data],Table_AustralianStates[Common Name],Table_AustralianStates[Abbreviation]) -> #N/A | O61: kg/head
D62: Summer | E62: =InputFunctions_PastureBeef.LookupLiveweightFromSeason($E$7,X_Cell_PastureBeef_ProductionRegion,$D62,E$60,Table_SourceData_PastureBeef_LiveweightAllStates[State],Table_SourceData_PastureBeef_LiveweightAllStates[Region],Table_SourceData_PastureBeef_LiveweightAllStates[Season],Table_SourceData_PastureBeef_LiveweightAllStates[#Headers],Table_SourceData_PastureBeef_LiveweightAllStates[#Data],Table_AustralianStates[Common Name],Table_AustralianStates[Abbreviation]) -> #N/A | F62: =InputFunctions_PastureBeef.LookupLiveweightFromSeason($E$7,X_Cell_PastureBeef_ProductionRegion,$D62,F$60,Table_SourceData_PastureBeef_LiveweightAllStates[State],Table_SourceData_PastureBeef_LiveweightAllStates[Region],Table_SourceData_PastureBeef_LiveweightAllStates[Season],Table_SourceData_PastureBeef_LiveweightAllStates[#Headers],Table_SourceData_PastureBeef_LiveweightAllStates[#Data],Table_AustralianStates[Common Name],Table_AustralianStates[Abbreviation]) -> #N/A | G62: =InputFunctions_PastureBeef.LookupLiveweightFromSeason($E$7,X_Cell_PastureBeef_ProductionRegion,$D62,G$60,Table_SourceData_PastureBeef_LiveweightAllStates[State],Table_SourceData_PastureBeef_LiveweightAllStates[Region],Table_SourceData_PastureBeef_LiveweightAllStates[Season],Table_SourceData_PastureBeef_LiveweightAllStates[#Headers],Table_SourceData_PastureBeef_LiveweightAllStates[#Data],Table_AustralianStates[Common Name],Table_AustralianStates[Abbreviation]) -> #N/A | H62: =InputFunctions_PastureBeef.LookupLiveweightFromSeason($E$7,X_Cell_PastureBeef_ProductionRegion,$D62,H$60,Table_SourceData_PastureBeef_LiveweightAllStates[State],Table_SourceData_PastureBeef_LiveweightAllStates[Region],Table_SourceData_PastureBeef_LiveweightAllStates[Season],Table_SourceData_PastureBeef_LiveweightAllStates[#Headers],Table_SourceData_PastureBeef_LiveweightAllStates[#Data],Table_AustralianStates[Common Name],Table_AustralianStates[Abbreviation]) -> #N/A | I62: =InputFunctions_PastureBeef.LookupLiveweightFromSeason($E$7,X_Cell_PastureBeef_ProductionRegion,$D62,I$60,Table_SourceData_PastureBeef_LiveweightAllStates[State],Table_SourceData_PastureBeef_LiveweightAllStates[Region],Table_SourceData_PastureBeef_LiveweightAllStates[Season],Table_SourceData_PastureBeef_LiveweightAllStates[#Headers],Table_SourceData_PastureBeef_LiveweightAllStates[#Data],Table_AustralianStates[Common Name],Table_AustralianStates[Abbreviation]) -> #N/A | J62: =InputFunctions_PastureBeef.LookupLiveweightFromSeason($E$7,X_Cell_PastureBeef_ProductionRegion,$D62,J$60,Table_SourceData_PastureBeef_LiveweightAllStates[State],Table_SourceData_PastureBeef_LiveweightAllStates[Region],Table_SourceData_PastureBeef_LiveweightAllStates[Season],Table_SourceData_PastureBeef_LiveweightAllStates[#Headers],Table_SourceData_PastureBeef_LiveweightAllStates[#Data],Table_AustralianStates[Common Name],Table_AustralianStates[Abbreviation]) -> #N/A | K62: =InputFunctions_PastureBeef.LookupLiveweightFromSeason($E$7,X_Cell_PastureBeef_ProductionRegion,$D62,K$60,Table_SourceData_PastureBeef_LiveweightAllStates[State],Table_SourceData_PastureBeef_LiveweightAllStates[Region],Table_SourceData_PastureBeef_LiveweightAllStates[Season],Table_SourceData_PastureBeef_LiveweightAllStates[#Headers],Table_SourceData_PastureBeef_LiveweightAllStates[#Data],Table_AustralianStates[Common Name],Table_AustralianStates[Abbreviation]) -> #N/A | L62: =InputFunctions_PastureBeef.LookupLiveweightFromSeason($E$7,X_Cell_PastureBeef_ProductionRegion,$D62,L$60,Table_SourceData_PastureBeef_LiveweightAllStates[State],Table_SourceData_PastureBeef_LiveweightAllStates[Region],Table_SourceData_PastureBeef_LiveweightAllStates[Season],Table_SourceData_PastureBeef_LiveweightAllStates[#Headers],Table_SourceData_PastureBeef_LiveweightAllStates[#Data],Table_AustralianStates[Common Name],Table_AustralianStates[Abbreviation]) -> #N/A | ... N62: =InputFunctions_PastureBeef.LookupLiveweightFromSeason($E$7,X_Cell_PastureBeef_ProductionRegion,$D62,N$60,Table_SourceData_PastureBeef_LiveweightAllStates[State],Table_SourceData_PastureBeef_LiveweightAllStates[Region],Table_SourceData_PastureBeef_LiveweightAllStates[Season],Table_SourceData_PastureBeef_LiveweightAllStates[#Headers],Table_SourceData_PastureBeef_LiveweightAllStates[#Data],Table_AustralianStates[Common Name],Table_AustralianStates[Abbreviation]) -> #N/A | O62: kg/head
D63: Autumn | E63: =InputFunctions_PastureBeef.LookupLiveweightFromSeason($E$7,X_Cell_PastureBeef_ProductionRegion,$D63,E$60,Table_SourceData_PastureBeef_LiveweightAllStates[State],Table_SourceData_PastureBeef_LiveweightAllStates[Region],Table_SourceData_PastureBeef_LiveweightAllStates[Season],Table_SourceData_PastureBeef_LiveweightAllStates[#Headers],Table_SourceData_PastureBeef_LiveweightAllStates[#Data],Table_AustralianStates[Common Name],Table_AustralianStates[Abbreviation]) -> #N/A | F63: =InputFunctions_PastureBeef.LookupLiveweightFromSeason($E$7,X_Cell_PastureBeef_ProductionRegion,$D63,F$60,Table_SourceData_PastureBeef_LiveweightAllStates[State],Table_SourceData_PastureBeef_LiveweightAllStates[Region],Table_SourceData_PastureBeef_LiveweightAllStates[Season],Table_SourceData_PastureBeef_LiveweightAllStates[#Headers],Table_SourceData_PastureBeef_LiveweightAllStates[#Data],Table_AustralianStates[Common Name],Table_AustralianStates[Abbreviation]) -> #N/A | G63: =InputFunctions_PastureBeef.LookupLiveweightFromSeason($E$7,X_Cell_PastureBeef_ProductionRegion,$D63,G$60,Table_SourceData_PastureBeef_LiveweightAllStates[State],Table_SourceData_PastureBeef_LiveweightAllStates[Region],Table_SourceData_PastureBeef_LiveweightAllStates[Season],Table_SourceData_PastureBeef_LiveweightAllStates[#Headers],Table_SourceData_PastureBeef_LiveweightAllStates[#Data],Table_AustralianStates[Common Name],Table_AustralianStates[Abbreviation]) -> #N/A | H63: =InputFunctions_PastureBeef.LookupLiveweightFromSeason($E$7,X_Cell_PastureBeef_ProductionRegion,$D63,H$60,Table_SourceData_PastureBeef_LiveweightAllStates[State],Table_SourceData_PastureBeef_LiveweightAllStates[Region],Table_SourceData_PastureBeef_LiveweightAllStates[Season],Table_SourceData_PastureBeef_LiveweightAllStates[#Headers],Table_SourceData_PastureBeef_LiveweightAllStates[#Data],Table_AustralianStates[Common Name],Table_AustralianStates[Abbreviation]) -> #N/A | I63: =InputFunctions_PastureBeef.LookupLiveweightFromSeason($E$7,X_Cell_PastureBeef_ProductionRegion,$D63,I$60,Table_SourceData_PastureBeef_LiveweightAllStates[State],Table_SourceData_PastureBeef_LiveweightAllStates[Region],Table_SourceData_PastureBeef_LiveweightAllStates[Season],Table_SourceData_PastureBeef_LiveweightAllStates[#Headers],Table_SourceData_PastureBeef_LiveweightAllStates[#Data],Table_AustralianStates[Common Name],Table_AustralianStates[Abbreviation]) -> #N/A | J63: =InputFunctions_PastureBeef.LookupLiveweightFromSeason($E$7,X_Cell_PastureBeef_ProductionRegion,$D63,J$60,Table_SourceData_PastureBeef_LiveweightAllStates[State],Table_SourceData_PastureBeef_LiveweightAllStates[Region],Table_SourceData_PastureBeef_LiveweightAllStates[Season],Table_SourceData_PastureBeef_LiveweightAllStates[#Headers],Table_SourceData_PastureBeef_LiveweightAllStates[#Data],Table_AustralianStates[Common Name],Table_AustralianStates[Abbreviation]) -> #N/A | K63: =InputFunctions_PastureBeef.LookupLiveweightFromSeason($E$7,X_Cell_PastureBeef_ProductionRegion,$D63,K$60,Table_SourceData_PastureBeef_LiveweightAllStates[State],Table_SourceData_PastureBeef_LiveweightAllStates[Region],Table_SourceData_PastureBeef_LiveweightAllStates[Season],Table_SourceData_PastureBeef_LiveweightAllStates[#Headers],Table_SourceData_PastureBeef_LiveweightAllStates[#Data],Table_AustralianStates[Common Name],Table_AustralianStates[Abbreviation]) -> #N/A | L63: =InputFunctions_PastureBeef.LookupLiveweightFromSeason($E$7,X_Cell_PastureBeef_ProductionRegion,$D63,L$60,Table_SourceData_PastureBeef_LiveweightAllStates[State],Table_SourceData_PastureBeef_LiveweightAllStates[Region],Table_SourceData_PastureBeef_LiveweightAllStates[Season],Table_SourceData_PastureBeef_LiveweightAllStates[#Headers],Table_SourceData_PastureBeef_LiveweightAllStates[#Data],Table_AustralianStates[Common Name],Table_AustralianStates[Abbreviation]) -> #N/A | ... N63: =InputFunctions_PastureBeef.LookupLiveweightFromSeason($E$7,X_Cell_PastureBeef_ProductionRegion,$D63,N$60,Table_SourceData_PastureBeef_LiveweightAllStates[State],Table_SourceData_PastureBeef_LiveweightAllStates[Region],Table_SourceData_PastureBeef_LiveweightAllStates[Season],Table_SourceData_PastureBeef_LiveweightAllStates[#Headers],Table_SourceData_PastureBeef_LiveweightAllStates[#Data],Table_AustralianStates[Common Name],Table_AustralianStates[Abbreviation]) -> #N/A | O63: kg/head
D64: Winter | E64: =InputFunctions_PastureBeef.LookupLiveweightFromSeason($E$7,X_Cell_PastureBeef_ProductionRegion,$D64,E$60,Table_SourceData_PastureBeef_LiveweightAllStates[State],Table_SourceData_PastureBeef_LiveweightAllStates[Region],Table_SourceData_PastureBeef_LiveweightAllStates[Season],Table_SourceData_PastureBeef_LiveweightAllStates[#Headers],Table_SourceData_PastureBeef_LiveweightAllStates[#Data],Table_AustralianStates[Common Name],Table_AustralianStates[Abbreviation]) -> #N/A | F64: =InputFunctions_PastureBeef.LookupLiveweightFromSeason($E$7,X_Cell_PastureBeef_ProductionRegion,$D64,F$60,Table_SourceData_PastureBeef_LiveweightAllStates[State],Table_SourceData_PastureBeef_LiveweightAllStates[Region],Table_SourceData_PastureBeef_LiveweightAllStates[Season],Table_SourceData_PastureBeef_LiveweightAllStates[#Headers],Table_SourceData_PastureBeef_LiveweightAllStates[#Data],Table_AustralianStates[Common Name],Table_AustralianStates[Abbreviation]) -> #N/A | G64: =InputFunctions_PastureBeef.LookupLiveweightFromSeason($E$7,X_Cell_PastureBeef_ProductionRegion,$D64,G$60,Table_SourceData_PastureBeef_LiveweightAllStates[State],Table_SourceData_PastureBeef_LiveweightAllStates[Region],Table_SourceData_PastureBeef_LiveweightAllStates[Season],Table_SourceData_PastureBeef_LiveweightAllStates[#Headers],Table_SourceData_PastureBeef_LiveweightAllStates[#Data],Table_AustralianStates[Common Name],Table_AustralianStates[Abbreviation]) -> #N/A | H64: =InputFunctions_PastureBeef.LookupLiveweightFromSeason($E$7,X_Cell_PastureBeef_ProductionRegion,$D64,H$60,Table_SourceData_PastureBeef_LiveweightAllStates[State],Table_SourceData_PastureBeef_LiveweightAllStates[Region],Table_SourceData_PastureBeef_LiveweightAllStates[Season],Table_SourceData_PastureBeef_LiveweightAllStates[#Headers],Table_SourceData_PastureBeef_LiveweightAllStates[#Data],Table_AustralianStates[Common Name],Table_AustralianStates[Abbreviation]) -> #N/A | I64: =InputFunctions_PastureBeef.LookupLiveweightFromSeason($E$7,X_Cell_PastureBeef_ProductionRegion,$D64,I$60,Table_SourceData_PastureBeef_LiveweightAllStates[State],Table_SourceData_PastureBeef_LiveweightAllStates[Region],Table_SourceData_PastureBeef_LiveweightAllStates[Season],Table_SourceData_PastureBeef_LiveweightAllStates[#Headers],Table_SourceData_PastureBeef_LiveweightAllStates[#Data],Table_AustralianStates[Common Name],Table_AustralianStates[Abbreviation]) -> #N/A | J64: =InputFunctions_PastureBeef.LookupLiveweightFromSeason($E$7,X_Cell_PastureBeef_ProductionRegion,$D64,J$60,Table_SourceData_PastureBeef_LiveweightAllStates[State],Table_SourceData_PastureBeef_LiveweightAllStates[Region],Table_SourceData_PastureBeef_LiveweightAllStates[Season],Table_SourceData_PastureBeef_LiveweightAllStates[#Headers],Table_SourceData_PastureBeef_LiveweightAllStates[#Data],Table_AustralianStates[Common Name],Table_AustralianStates[Abbreviation]) -> #N/A | K64: =InputFunctions_PastureBeef.LookupLiveweightFromSeason($E$7,X_Cell_PastureBeef_ProductionRegion,$D64,K$60,Table_SourceData_PastureBeef_LiveweightAllStates[State],Table_SourceData_PastureBeef_LiveweightAllStates[Region],Table_SourceData_PastureBeef_LiveweightAllStates[Season],Table_SourceData_PastureBeef_LiveweightAllStates[#Headers],Table_SourceData_PastureBeef_LiveweightAllStates[#Data],Table_AustralianStates[Common Name],Table_AustralianStates[Abbreviation]) -> #N/A | L64: =InputFunctions_PastureBeef.LookupLiveweightFromSeason($E$7,X_Cell_PastureBeef_ProductionRegion,$D64,L$60,Table_SourceData_PastureBeef_LiveweightAllStates[State],Table_SourceData_PastureBeef_LiveweightAllStates[Region],Table_SourceData_PastureBeef_LiveweightAllStates[Season],Table_SourceData_PastureBeef_LiveweightAllStates[#Headers],Table_SourceData_PastureBeef_LiveweightAllStates[#Data],Table_AustralianStates[Common Name],Table_AustralianStates[Abbreviation]) -> #N/A | ... N64: =InputFunctions_PastureBeef.LookupLiveweightFromSeason($E$7,X_Cell_PastureBeef_ProductionRegion,$D64,N$60,Table_SourceData_PastureBeef_LiveweightAllStates[State],Table_SourceData_PastureBeef_LiveweightAllStates[Region],Table_SourceData_PastureBeef_LiveweightAllStates[Season],Table_SourceData_PastureBeef_LiveweightAllStates[#Headers],Table_SourceData_PastureBeef_LiveweightAllStates[#Data],Table_AustralianStates[Common Name],Table_AustralianStates[Abbreviation]) -> #N/A | O64: kg/head
D66: Method 2 custom values (edit if known) | E66: Bulls < 1 year | F66: Bulls > 1 year | G66: Cows < 1 year | H66: Cows 1-2 years | I66: Cows 2-3 years | J66: Cows > 3 years | K66: Steers < 1 year | L66: Steers 1-2 years | M66: Steers 2-3 years | N66: Steers >3 years
D67: =TEXT(X_Cell_Site_StartDate, "mmmm yyyy") -> January 1900 | E67: =InputFunctions_PastureBeef.LookupLiveweightFromMonth($E$7,X_Cell_PastureBeef_ProductionRegion,$D67,E$66,Table_SourceData_PastureBeef_LiveweightAllStates[State],Table_SourceData_PastureBeef_LiveweightAllStates[Region],Table_SourceData_PastureBeef_LiveweightAllStates[Season],Table_SourceData_PastureBeef_LiveweightAllStates[#Headers],Table_SourceData_PastureBeef_LiveweightAllStates[#Data],Table_AustralianStates[Common Name],Table_AustralianStates[Abbreviation],Table_SourceData_Common_MonthToSeason[Month],Table_SourceData_Common_MonthToSeason[Season]) -> #N/A | F67: =InputFunctions_PastureBeef.LookupLiveweightFromMonth($E$7,X_Cell_PastureBeef_ProductionRegion,$D67,F$66,Table_SourceData_PastureBeef_LiveweightAllStates[State],Table_SourceData_PastureBeef_LiveweightAllStates[Region],Table_SourceData_PastureBeef_LiveweightAllStates[Season],Table_SourceData_PastureBeef_LiveweightAllStates[#Headers],Table_SourceData_PastureBeef_LiveweightAllStates[#Data],Table_AustralianStates[Common Name],Table_AustralianStates[Abbreviation],Table_SourceData_Common_MonthToSeason[Month],Table_SourceData_Common_MonthToSeason[Season]) -> #N/A | G67: =InputFunctions_PastureBeef.LookupLiveweightFromMonth($E$7,X_Cell_PastureBeef_ProductionRegion,$D67,G$66,Table_SourceData_PastureBeef_LiveweightAllStates[State],Table_SourceData_PastureBeef_LiveweightAllStates[Region],Table_SourceData_PastureBeef_LiveweightAllStates[Season],Table_SourceData_PastureBeef_LiveweightAllStates[#Headers],Table_SourceData_PastureBeef_LiveweightAllStates[#Data],Table_AustralianStates[Common Name],Table_AustralianStates[Abbreviation],Table_SourceData_Common_MonthToSeason[Month],Table_SourceData_Common_MonthToSeason[Season]) -> #N/A | H67: =InputFunctions_PastureBeef.LookupLiveweightFromMonth($E$7,X_Cell_PastureBeef_ProductionRegion,$D67,H$66,Table_SourceData_PastureBeef_LiveweightAllStates[State],Table_SourceData_PastureBeef_LiveweightAllStates[Region],Table_SourceData_PastureBeef_LiveweightAllStates[Season],Table_SourceData_PastureBeef_LiveweightAllStates[#Headers],Table_SourceData_PastureBeef_LiveweightAllStates[#Data],Table_AustralianStates[Common Name],Table_AustralianStates[Abbreviation],Table_SourceData_Common_MonthToSeason[Month],Table_SourceData_Common_MonthToSeason[Season]) -> #N/A | I67: =InputFunctions_PastureBeef.LookupLiveweightFromMonth($E$7,X_Cell_PastureBeef_ProductionRegion,$D67,I$66,Table_SourceData_PastureBeef_LiveweightAllStates[State],Table_SourceData_PastureBeef_LiveweightAllStates[Region],Table_SourceData_PastureBeef_LiveweightAllStates[Season],Table_SourceData_PastureBeef_LiveweightAllStates[#Headers],Table_SourceData_PastureBeef_LiveweightAllStates[#Data],Table_AustralianStates[Common Name],Table_AustralianStates[Abbreviation],Table_SourceData_Common_MonthToSeason[Month],Table_SourceData_Common_MonthToSeason[Season]) -> #N/A | J67: =InputFunctions_PastureBeef.LookupLiveweightFromMonth($E$7,X_Cell_PastureBeef_ProductionRegion,$D67,J$66,Table_SourceData_PastureBeef_LiveweightAllStates[State],Table_SourceData_PastureBeef_LiveweightAllStates[Region],Table_SourceData_PastureBeef_LiveweightAllStates[Season],Table_SourceData_PastureBeef_LiveweightAllStates[#Headers],Table_SourceData_PastureBeef_LiveweightAllStates[#Data],Table_AustralianStates[Common Name],Table_AustralianStates[Abbreviation],Table_SourceData_Common_MonthToSeason[Month],Table_SourceData_Common_MonthToSeason[Season]) -> #N/A | K67: =InputFunctions_PastureBeef.LookupLiveweightFromMonth($E$7,X_Cell_PastureBeef_ProductionRegion,$D67,K$66,Table_SourceData_PastureBeef_LiveweightAllStates[State],Table_SourceData_PastureBeef_LiveweightAllStates[Region],Table_SourceData_PastureBeef_LiveweightAllStates[Season],Table_SourceData_PastureBeef_LiveweightAllStates[#Headers],Table_SourceData_PastureBeef_LiveweightAllStates[#Data],Table_AustralianStates[Common Name],Table_AustralianStates[Abbreviation],Table_SourceData_Common_MonthToSeason[Month],Table_SourceData_Common_MonthToSeason[Season]) -> #N/A | L67: =InputFunctions_PastureBeef.LookupLiveweightFromMonth($E$7,X_Cell_PastureBeef_ProductionRegion,$D67,L$66,Table_SourceData_PastureBeef_LiveweightAllStates[State],Table_SourceData_PastureBeef_LiveweightAllStates[Region],Table_SourceData_PastureBeef_LiveweightAllStates[Season],Table_SourceData_PastureBeef_LiveweightAllStates[#Headers],Table_SourceData_PastureBeef_LiveweightAllStates[#Data],Table_AustralianStates[Common Name],Table_AustralianStates[Abbreviation],Table_SourceData_Common_MonthToSeason[Month],Table_SourceData_Common_MonthToSeason[Season]) -> #N/A | ... N67: =InputFunctions_PastureBeef.LookupLiveweightFromMonth($E$7,X_Cell_PastureBeef_ProductionRegion,$D67,N$66,Table_SourceData_PastureBeef_LiveweightAllStates[State],Table_SourceData_PastureBeef_LiveweightAllStates[Region],Table_SourceData_PastureBeef_LiveweightAllStates[Season],Table_SourceData_PastureBeef_LiveweightAllStates[#Headers],Table_SourceData_PastureBeef_LiveweightAllStates[#Data],Table_AustralianStates[Common Name],Table_AustralianStates[Abbreviation],Table_SourceData_Common_MonthToSeason[Month],Table_SourceData_Common_MonthToSeason[Season]) -> #N/A | O67: kg/head
D68: =TEXT(EDATE(X_Cell_Site_StartDate,1), "mmmm yyyy") -> January 1900 | E68: =InputFunctions_PastureBeef.LookupLiveweightFromMonth($E$7,X_Cell_PastureBeef_ProductionRegion,$D68,E$66,Table_SourceData_PastureBeef_LiveweightAllStates[State],Table_SourceData_PastureBeef_LiveweightAllStates[Region],Table_SourceData_PastureBeef_LiveweightAllStates[Season],Table_SourceData_PastureBeef_LiveweightAllStates[#Headers],Table_SourceData_PastureBeef_LiveweightAllStates[#Data],Table_AustralianStates[Common Name],Table_AustralianStates[Abbreviation],Table_SourceData_Common_MonthToSeason[Month],Table_SourceData_Common_MonthToSeason[Season]) -> #N/A | F68: =InputFunctions_PastureBeef.LookupLiveweightFromMonth($E$7,X_Cell_PastureBeef_ProductionRegion,$D68,F$66,Table_SourceData_PastureBeef_LiveweightAllStates[State],Table_SourceData_PastureBeef_LiveweightAllStates[Region],Table_SourceData_PastureBeef_LiveweightAllStates[Season],Table_SourceData_PastureBeef_LiveweightAllStates[#Headers],Table_SourceData_PastureBeef_LiveweightAllStates[#Data],Table_AustralianStates[Common Name],Table_AustralianStates[Abbreviation],Table_SourceData_Common_MonthToSeason[Month],Table_SourceData_Common_MonthToSeason[Season]) -> #N/A | G68: =InputFunctions_PastureBeef.LookupLiveweightFromMonth($E$7,X_Cell_PastureBeef_ProductionRegion,$D68,G$66,Table_SourceData_PastureBeef_LiveweightAllStates[State],Table_SourceData_PastureBeef_LiveweightAllStates[Region],Table_SourceData_PastureBeef_LiveweightAllStates[Season],Table_SourceData_PastureBeef_LiveweightAllStates[#Headers],Table_SourceData_PastureBeef_LiveweightAllStates[#Data],Table_AustralianStates[Common Name],Table_AustralianStates[Abbreviation],Table_SourceData_Common_MonthToSeason[Month],Table_SourceData_Common_MonthToSeason[Season]) -> #N/A | H68: =InputFunctions_PastureBeef.LookupLiveweightFromMonth($E$7,X_Cell_PastureBeef_ProductionRegion,$D68,H$66,Table_SourceData_PastureBeef_LiveweightAllStates[State],Table_SourceData_PastureBeef_LiveweightAllStates[Region],Table_SourceData_PastureBeef_LiveweightAllStates[Season],Table_SourceData_PastureBeef_LiveweightAllStates[#Headers],Table_SourceData_PastureBeef_LiveweightAllStates[#Data],Table_AustralianStates[Common Name],Table_AustralianStates[Abbreviation],Table_SourceData_Common_MonthToSeason[Month],Table_SourceData_Common_MonthToSeason[Season]) -> #N/A | I68: =InputFunctions_PastureBeef.LookupLiveweightFromMonth($E$7,X_Cell_PastureBeef_ProductionRegion,$D68,I$66,Table_SourceData_PastureBeef_LiveweightAllStates[State],Table_SourceData_PastureBeef_LiveweightAllStates[Region],Table_SourceData_PastureBeef_LiveweightAllStates[Season],Table_SourceData_PastureBeef_LiveweightAllStates[#Headers],Table_SourceData_PastureBeef_LiveweightAllStates[#Data],Table_AustralianStates[Common Name],Table_AustralianStates[Abbreviation],Table_SourceData_Common_MonthToSeason[Month],Table_SourceData_Common_MonthToSeason[Season]) -> #N/A | J68: =InputFunctions_PastureBeef.LookupLiveweightFromMonth($E$7,X_Cell_PastureBeef_ProductionRegion,$D68,J$66,Table_SourceData_PastureBeef_LiveweightAllStates[State],Table_SourceData_PastureBeef_LiveweightAllStates[Region],Table_SourceData_PastureBeef_LiveweightAllStates[Season],Table_SourceData_PastureBeef_LiveweightAllStates[#Headers],Table_SourceData_PastureBeef_LiveweightAllStates[#Data],Table_AustralianStates[Common Name],Table_AustralianStates[Abbreviation],Table_SourceData_Common_MonthToSeason[Month],Table_SourceData_Common_MonthToSeason[Season]) -> #N/A | K68: =InputFunctions_PastureBeef.LookupLiveweightFromMonth($E$7,X_Cell_PastureBeef_ProductionRegion,$D68,K$66,Table_SourceData_PastureBeef_LiveweightAllStates[State],Table_SourceData_PastureBeef_LiveweightAllStates[Region],Table_SourceData_PastureBeef_LiveweightAllStates[Season],Table_SourceData_PastureBeef_LiveweightAllStates[#Headers],Table_SourceData_PastureBeef_LiveweightAllStates[#Data],Table_AustralianStates[Common Name],Table_AustralianStates[Abbreviation],Table_SourceData_Common_MonthToSeason[Month],Table_SourceData_Common_MonthToSeason[Season]) -> #N/A | L68: =InputFunctions_PastureBeef.LookupLiveweightFromMonth($E$7,X_Cell_PastureBeef_ProductionRegion,$D68,L$66,Table_SourceData_PastureBeef_LiveweightAllStates[State],Table_SourceData_PastureBeef_LiveweightAllStates[Region],Table_SourceData_PastureBeef_LiveweightAllStates[Season],Table_SourceData_PastureBeef_LiveweightAllStates[#Headers],Table_SourceData_PastureBeef_LiveweightAllStates[#Data],Table_AustralianStates[Common Name],Table_AustralianStates[Abbreviation],Table_SourceData_Common_MonthToSeason[Month],Table_SourceData_Common_MonthToSeason[Season]) -> #N/A | ... N68: =InputFunctions_PastureBeef.LookupLiveweightFromMonth($E$7,X_Cell_PastureBeef_ProductionRegion,$D68,N$66,Table_SourceData_PastureBeef_LiveweightAllStates[State],Table_SourceData_PastureBeef_LiveweightAllStates[Region],Table_SourceData_PastureBeef_LiveweightAllStates[Season],Table_SourceData_PastureBeef_LiveweightAllStates[#Headers],Table_SourceData_PastureBeef_LiveweightAllStates[#Data],Table_AustralianStates[Common Name],Table_AustralianStates[Abbreviation],Table_SourceData_Common_MonthToSeason[Month],Table_SourceData_Common_MonthToSeason[Season]) -> #N/A | O68: kg/head
D69: =TEXT(EDATE(X_Cell_Site_StartDate,2), "mmmm yyyy") -> February 1900 | E69: =InputFunctions_PastureBeef.LookupLiveweightFromMonth($E$7,X_Cell_PastureBeef_ProductionRegion,$D69,E$66,Table_SourceData_PastureBeef_LiveweightAllStates[State],Table_SourceData_PastureBeef_LiveweightAllStates[Region],Table_SourceData_PastureBeef_LiveweightAllStates[Season],Table_SourceData_PastureBeef_LiveweightAllStates[#Headers],Table_SourceData_PastureBeef_LiveweightAllStates[#Data],Table_AustralianStates[Common Name],Table_AustralianStates[Abbreviation],Table_SourceData_Common_MonthToSeason[Month],Table_SourceData_Common_MonthToSeason[Season]) -> #N/A | F69: =InputFunctions_PastureBeef.LookupLiveweightFromMonth($E$7,X_Cell_PastureBeef_ProductionRegion,$D69,F$66,Table_SourceData_PastureBeef_LiveweightAllStates[State],Table_SourceData_PastureBeef_LiveweightAllStates[Region],Table_SourceData_PastureBeef_LiveweightAllStates[Season],Table_SourceData_PastureBeef_LiveweightAllStates[#Headers],Table_SourceData_PastureBeef_LiveweightAllStates[#Data],Table_AustralianStates[Common Name],Table_AustralianStates[Abbreviation],Table_SourceData_Common_MonthToSeason[Month],Table_SourceData_Common_MonthToSeason[Season]) -> #N/A | G69: =InputFunctions_PastureBeef.LookupLiveweightFromMonth($E$7,X_Cell_PastureBeef_ProductionRegion,$D69,G$66,Table_SourceData_PastureBeef_LiveweightAllStates[State],Table_SourceData_PastureBeef_LiveweightAllStates[Region],Table_SourceData_PastureBeef_LiveweightAllStates[Season],Table_SourceData_PastureBeef_LiveweightAllStates[#Headers],Table_SourceData_PastureBeef_LiveweightAllStates[#Data],Table_AustralianStates[Common Name],Table_AustralianStates[Abbreviation],Table_SourceData_Common_MonthToSeason[Month],Table_SourceData_Common_MonthToSeason[Season]) -> #N/A | H69: =InputFunctions_PastureBeef.LookupLiveweightFromMonth($E$7,X_Cell_PastureBeef_ProductionRegion,$D69,H$66,Table_SourceData_PastureBeef_LiveweightAllStates[State],Table_SourceData_PastureBeef_LiveweightAllStates[Region],Table_SourceData_PastureBeef_LiveweightAllStates[Season],Table_SourceData_PastureBeef_LiveweightAllStates[#Headers],Table_SourceData_PastureBeef_LiveweightAllStates[#Data],Table_AustralianStates[Common Name],Table_AustralianStates[Abbreviation],Table_SourceData_Common_MonthToSeason[Month],Table_SourceData_Common_MonthToSeason[Season]) -> #N/A | I69: =InputFunctions_PastureBeef.LookupLiveweightFromMonth($E$7,X_Cell_PastureBeef_ProductionRegion,$D69,I$66,Table_SourceData_PastureBeef_LiveweightAllStates[State],Table_SourceData_PastureBeef_LiveweightAllStates[Region],Table_SourceData_PastureBeef_LiveweightAllStates[Season],Table_SourceData_PastureBeef_LiveweightAllStates[#Headers],Table_SourceData_PastureBeef_LiveweightAllStates[#Data],Table_AustralianStates[Common Name],Table_AustralianStates[Abbreviation],Table_SourceData_Common_MonthToSeason[Month],Table_SourceData_Common_MonthToSeason[Season]) -> #N/A | J69: =InputFunctions_PastureBeef.LookupLiveweightFromMonth($E$7,X_Cell_PastureBeef_ProductionRegion,$D69,J$66,Table_SourceData_PastureBeef_LiveweightAllStates[State],Table_SourceData_PastureBeef_LiveweightAllStates[Region],Table_SourceData_PastureBeef_LiveweightAllStates[Season],Table_SourceData_PastureBeef_LiveweightAllStates[#Headers],Table_SourceData_PastureBeef_LiveweightAllStates[#Data],Table_AustralianStates[Common Name],Table_AustralianStates[Abbreviation],Table_SourceData_Common_MonthToSeason[Month],Table_SourceData_Common_MonthToSeason[Season]) -> #N/A | K69: =InputFunctions_PastureBeef.LookupLiveweightFromMonth($E$7,X_Cell_PastureBeef_ProductionRegion,$D69,K$66,Table_SourceData_PastureBeef_LiveweightAllStates[State],Table_SourceData_PastureBeef_LiveweightAllStates[Region],Table_SourceData_PastureBeef_LiveweightAllStates[Season],Table_SourceData_PastureBeef_LiveweightAllStates[#Headers],Table_SourceData_PastureBeef_LiveweightAllStates[#Data],Table_AustralianStates[Common Name],Table_AustralianStates[Abbreviation],Table_SourceData_Common_MonthToSeason[Month],Table_SourceData_Common_MonthToSeason[Season]) -> #N/A | L69: =InputFunctions_PastureBeef.LookupLiveweightFromMonth($E$7,X_Cell_PastureBeef_ProductionRegion,$D69,L$66,Table_SourceData_PastureBeef_LiveweightAllStates[State],Table_SourceData_PastureBeef_LiveweightAllStates[Region],Table_SourceData_PastureBeef_LiveweightAllStates[Season],Table_SourceData_PastureBeef_LiveweightAllStates[#Headers],Table_SourceData_PastureBeef_LiveweightAllStates[#Data],Table_AustralianStates[Common Name],Table_AustralianStates[Abbreviation],Table_SourceData_Common_MonthToSeason[Month],Table_SourceData_Common_MonthToSeason[Season]) -> #N/A | ... N69: =InputFunctions_PastureBeef.LookupLiveweightFromMonth($E$7,X_Cell_PastureBeef_ProductionRegion,$D69,N$66,Table_SourceData_PastureBeef_LiveweightAllStates[State],Table_SourceData_PastureBeef_LiveweightAllStates[Region],Table_SourceData_PastureBeef_LiveweightAllStates[Season],Table_SourceData_PastureBeef_LiveweightAllStates[#Headers],Table_SourceData_PastureBeef_LiveweightAllStates[#Data],Table_AustralianStates[Common Name],Table_AustralianStates[Abbreviation],Table_SourceData_Common_MonthToSeason[Month],Table_SourceData_Common_MonthToSeason[Season]) -> #N/A | O69: kg/head
D70: =TEXT(EDATE(X_Cell_Site_StartDate,3), "mmmm yyyy") -> March 1900 | E70: =InputFunctions_PastureBeef.LookupLiveweightFromMonth($E$7,X_Cell_PastureBeef_ProductionRegion,$D70,E$66,Table_SourceData_PastureBeef_LiveweightAllStates[State],Table_SourceData_PastureBeef_LiveweightAllStates[Region],Table_SourceData_PastureBeef_LiveweightAllStates[Season],Table_SourceData_PastureBeef_LiveweightAllStates[#Headers],Table_SourceData_PastureBeef_LiveweightAllStates[#Data],Table_AustralianStates[Common Name],Table_AustralianStates[Abbreviation],Table_SourceData_Common_MonthToSeason[Month],Table_SourceData_Common_MonthToSeason[Season]) -> #N/A | F70: =InputFunctions_PastureBeef.LookupLiveweightFromMonth($E$7,X_Cell_PastureBeef_ProductionRegion,$D70,F$66,Table_SourceData_PastureBeef_LiveweightAllStates[State],Table_SourceData_PastureBeef_LiveweightAllStates[Region],Table_SourceData_PastureBeef_LiveweightAllStates[Season],Table_SourceData_PastureBeef_LiveweightAllStates[#Headers],Table_SourceData_PastureBeef_LiveweightAllStates[#Data],Table_AustralianStates[Common Name],Table_AustralianStates[Abbreviation],Table_SourceData_Common_MonthToSeason[Month],Table_SourceData_Common_MonthToSeason[Season]) -> #N/A | G70: =InputFunctions_PastureBeef.LookupLiveweightFromMonth($E$7,X_Cell_PastureBeef_ProductionRegion,$D70,G$66,Table_SourceData_PastureBeef_LiveweightAllStates[State],Table_SourceData_PastureBeef_LiveweightAllStates[Region],Table_SourceData_PastureBeef_LiveweightAllStates[Season],Table_SourceData_PastureBeef_LiveweightAllStates[#Headers],Table_SourceData_PastureBeef_LiveweightAllStates[#Data],Table_AustralianStates[Common Name],Table_AustralianStates[Abbreviation],Table_SourceData_Common_MonthToSeason[Month],Table_SourceData_Common_MonthToSeason[Season]) -> #N/A | H70: =InputFunctions_PastureBeef.LookupLiveweightFromMonth($E$7,X_Cell_PastureBeef_ProductionRegion,$D70,H$66,Table_SourceData_PastureBeef_LiveweightAllStates[State],Table_SourceData_PastureBeef_LiveweightAllStates[Region],Table_SourceData_PastureBeef_LiveweightAllStates[Season],Table_SourceData_PastureBeef_LiveweightAllStates[#Headers],Table_SourceData_PastureBeef_LiveweightAllStates[#Data],Table_AustralianStates[Common Name],Table_AustralianStates[Abbreviation],Table_SourceData_Common_MonthToSeason[Month],Table_SourceData_Common_MonthToSeason[Season]) -> #N/A | I70: =InputFunctions_PastureBeef.LookupLiveweightFromMonth($E$7,X_Cell_PastureBeef_ProductionRegion,$D70,I$66,Table_SourceData_PastureBeef_LiveweightAllStates[State],Table_SourceData_PastureBeef_LiveweightAllStates[Region],Table_SourceData_PastureBeef_LiveweightAllStates[Season],Table_SourceData_PastureBeef_LiveweightAllStates[#Headers],Table_SourceData_PastureBeef_LiveweightAllStates[#Data],Table_AustralianStates[Common Name],Table_AustralianStates[Abbreviation],Table_SourceData_Common_MonthToSeason[Month],Table_SourceData_Common_MonthToSeason[Season]) -> #N/A | J70: =InputFunctions_PastureBeef.LookupLiveweightFromMonth($E$7,X_Cell_PastureBeef_ProductionRegion,$D70,J$66,Table_SourceData_PastureBeef_LiveweightAllStates[State],Table_SourceData_PastureBeef_LiveweightAllStates[Region],Table_SourceData_PastureBeef_LiveweightAllStates[Season],Table_SourceData_PastureBeef_LiveweightAllStates[#Headers],Table_SourceData_PastureBeef_LiveweightAllStates[#Data],Table_AustralianStates[Common Name],Table_AustralianStates[Abbreviation],Table_SourceData_Common_MonthToSeason[Month],Table_SourceData_Common_MonthToSeason[Season]) -> #N/A | K70: =InputFunctions_PastureBeef.LookupLiveweightFromMonth($E$7,X_Cell_PastureBeef_ProductionRegion,$D70,K$66,Table_SourceData_PastureBeef_LiveweightAllStates[State],Table_SourceData_PastureBeef_LiveweightAllStates[Region],Table_SourceData_PastureBeef_LiveweightAllStates[Season],Table_SourceData_PastureBeef_LiveweightAllStates[#Headers],Table_SourceData_PastureBeef_LiveweightAllStates[#Data],Table_AustralianStates[Common Name],Table_AustralianStates[Abbreviation],Table_SourceData_Common_MonthToSeason[Month],Table_SourceData_Common_MonthToSeason[Season]) -> #N/A | L70: =InputFunctions_PastureBeef.LookupLiveweightFromMonth($E$7,X_Cell_PastureBeef_ProductionRegion,$D70,L$66,Table_SourceData_PastureBeef_LiveweightAllStates[State],Table_SourceData_PastureBeef_LiveweightAllStates[Region],Table_SourceData_PastureBeef_LiveweightAllStates[Season],Table_SourceData_PastureBeef_LiveweightAllStates[#Headers],Table_SourceData_PastureBeef_LiveweightAllStates[#Data],Table_AustralianStates[Common Name],Table_AustralianStates[Abbreviation],Table_SourceData_Common_MonthToSeason[Month],Table_SourceData_Common_MonthToSeason[Season]) -> #N/A | ... N70: =InputFunctions_PastureBeef.LookupLiveweightFromMonth($E$7,X_Cell_PastureBeef_ProductionRegion,$D70,N$66,Table_SourceData_PastureBeef_LiveweightAllStates[State],Table_SourceData_PastureBeef_LiveweightAllStates[Region],Table_SourceData_PastureBeef_LiveweightAllStates[Season],Table_SourceData_PastureBeef_LiveweightAllStates[#Headers],Table_SourceData_PastureBeef_LiveweightAllStates[#Data],Table_AustralianStates[Common Name],Table_AustralianStates[Abbreviation],Table_SourceData_Common_MonthToSeason[Month],Table_SourceData_Common_MonthToSeason[Season]) -> #N/A | O70: kg/head
D71: =TEXT(EDATE(X_Cell_Site_StartDate,4), "mmmm yyyy") -> April 1900 | E71: =InputFunctions_PastureBeef.LookupLiveweightFromMonth($E$7,X_Cell_PastureBeef_ProductionRegion,$D71,E$66,Table_SourceData_PastureBeef_LiveweightAllStates[State],Table_SourceData_PastureBeef_LiveweightAllStates[Region],Table_SourceData_PastureBeef_LiveweightAllStates[Season],Table_SourceData_PastureBeef_LiveweightAllStates[#Headers],Table_SourceData_PastureBeef_LiveweightAllStates[#Data],Table_AustralianStates[Common Name],Table_AustralianStates[Abbreviation],Table_SourceData_Common_MonthToSeason[Month],Table_SourceData_Common_MonthToSeason[Season]) -> #N/A | F71: =InputFunctions_PastureBeef.LookupLiveweightFromMonth($E$7,X_Cell_PastureBeef_ProductionRegion,$D71,F$66,Table_SourceData_PastureBeef_LiveweightAllStates[State],Table_SourceData_PastureBeef_LiveweightAllStates[Region],Table_SourceData_PastureBeef_LiveweightAllStates[Season],Table_SourceData_PastureBeef_LiveweightAllStates[#Headers],Table_SourceData_PastureBeef_LiveweightAllStates[#Data],Table_AustralianStates[Common Name],Table_AustralianStates[Abbreviation],Table_SourceData_Common_MonthToSeason[Month],Table_SourceData_Common_MonthToSeason[Season]) -> #N/A | G71: =InputFunctions_PastureBeef.LookupLiveweightFromMonth($E$7,X_Cell_PastureBeef_ProductionRegion,$D71,G$66,Table_SourceData_PastureBeef_LiveweightAllStates[State],Table_SourceData_PastureBeef_LiveweightAllStates[Region],Table_SourceData_PastureBeef_LiveweightAllStates[Season],Table_SourceData_PastureBeef_LiveweightAllStates[#Headers],Table_SourceData_PastureBeef_LiveweightAllStates[#Data],Table_AustralianStates[Common Name],Table_AustralianStates[Abbreviation],Table_SourceData_Common_MonthToSeason[Month],Table_SourceData_Common_MonthToSeason[Season]) -> #N/A | H71: =InputFunctions_PastureBeef.LookupLiveweightFromMonth($E$7,X_Cell_PastureBeef_ProductionRegion,$D71,H$66,Table_SourceData_PastureBeef_LiveweightAllStates[State],Table_SourceData_PastureBeef_LiveweightAllStates[Region],Table_SourceData_PastureBeef_LiveweightAllStates[Season],Table_SourceData_PastureBeef_LiveweightAllStates[#Headers],Table_SourceData_PastureBeef_LiveweightAllStates[#Data],Table_AustralianStates[Common Name],Table_AustralianStates[Abbreviation],Table_SourceData_Common_MonthToSeason[Month],Table_SourceData_Common_MonthToSeason[Season]) -> #N/A | I71: =InputFunctions_PastureBeef.LookupLiveweightFromMonth($E$7,X_Cell_PastureBeef_ProductionRegion,$D71,I$66,Table_SourceData_PastureBeef_LiveweightAllStates[State],Table_SourceData_PastureBeef_LiveweightAllStates[Region],Table_SourceData_PastureBeef_LiveweightAllStates[Season],Table_SourceData_PastureBeef_LiveweightAllStates[#Headers],Table_SourceData_PastureBeef_LiveweightAllStates[#Data],Table_AustralianStates[Common Name],Table_AustralianStates[Abbreviation],Table_SourceData_Common_MonthToSeason[Month],Table_SourceData_Common_MonthToSeason[Season]) -> #N/A | J71: =InputFunctions_PastureBeef.LookupLiveweightFromMonth($E$7,X_Cell_PastureBeef_ProductionRegion,$D71,J$66,Table_SourceData_PastureBeef_LiveweightAllStates[State],Table_SourceData_PastureBeef_LiveweightAllStates[Region],Table_SourceData_PastureBeef_LiveweightAllStates[Season],Table_SourceData_PastureBeef_LiveweightAllStates[#Headers],Table_SourceData_PastureBeef_LiveweightAllStates[#Data],Table_AustralianStates[Common Name],Table_AustralianStates[Abbreviation],Table_SourceData_Common_MonthToSeason[Month],Table_SourceData_Common_MonthToSeason[Season]) -> #N/A | K71: =InputFunctions_PastureBeef.LookupLiveweightFromMonth($E$7,X_Cell_PastureBeef_ProductionRegion,$D71,K$66,Table_SourceData_PastureBeef_LiveweightAllStates[State],Table_SourceData_PastureBeef_LiveweightAllStates[Region],Table_SourceData_PastureBeef_LiveweightAllStates[Season],Table_SourceData_PastureBeef_LiveweightAllStates[#Headers],Table_SourceData_PastureBeef_LiveweightAllStates[#Data],Table_AustralianStates[Common Name],Table_AustralianStates[Abbreviation],Table_SourceData_Common_MonthToSeason[Month],Table_SourceData_Common_MonthToSeason[Season]) -> #N/A | L71: =InputFunctions_PastureBeef.LookupLiveweightFromMonth($E$7,X_Cell_PastureBeef_ProductionRegion,$D71,L$66,Table_SourceData_PastureBeef_LiveweightAllStates[State],Table_SourceData_PastureBeef_LiveweightAllStates[Region],Table_SourceData_PastureBeef_LiveweightAllStates[Season],Table_SourceData_PastureBeef_LiveweightAllStates[#Headers],Table_SourceData_PastureBeef_LiveweightAllStates[#Data],Table_AustralianStates[Common Name],Table_AustralianStates[Abbreviation],Table_SourceData_Common_MonthToSeason[Month],Table_SourceData_Common_MonthToSeason[Season]) -> #N/A | ... N71: =InputFunctions_PastureBeef.LookupLiveweightFromMonth($E$7,X_Cell_PastureBeef_ProductionRegion,$D71,N$66,Table_SourceData_PastureBeef_LiveweightAllStates[State],Table_SourceData_PastureBeef_LiveweightAllStates[Region],Table_SourceData_PastureBeef_LiveweightAllStates[Season],Table_SourceData_PastureBeef_LiveweightAllStates[#Headers],Table_SourceData_PastureBeef_LiveweightAllStates[#Data],Table_AustralianStates[Common Name],Table_AustralianStates[Abbreviation],Table_SourceData_Common_MonthToSeason[Month],Table_SourceData_Common_MonthToSeason[Season]) -> #N/A | O71: kg/head
D72: =TEXT(EDATE(X_Cell_Site_StartDate,5), "mmmm yyyy") -> May 1900 | E72: =InputFunctions_PastureBeef.LookupLiveweightFromMonth($E$7,X_Cell_PastureBeef_ProductionRegion,$D72,E$66,Table_SourceData_PastureBeef_LiveweightAllStates[State],Table_SourceData_PastureBeef_LiveweightAllStates[Region],Table_SourceData_PastureBeef_LiveweightAllStates[Season],Table_SourceData_PastureBeef_LiveweightAllStates[#Headers],Table_SourceData_PastureBeef_LiveweightAllStates[#Data],Table_AustralianStates[Common Name],Table_AustralianStates[Abbreviation],Table_SourceData_Common_MonthToSeason[Month],Table_SourceData_Common_MonthToSeason[Season]) -> #N/A | F72: =InputFunctions_PastureBeef.LookupLiveweightFromMonth($E$7,X_Cell_PastureBeef_ProductionRegion,$D72,F$66,Table_SourceData_PastureBeef_LiveweightAllStates[State],Table_SourceData_PastureBeef_LiveweightAllStates[Region],Table_SourceData_PastureBeef_LiveweightAllStates[Season],Table_SourceData_PastureBeef_LiveweightAllStates[#Headers],Table_SourceData_PastureBeef_LiveweightAllStates[#Data],Table_AustralianStates[Common Name],Table_AustralianStates[Abbreviation],Table_SourceData_Common_MonthToSeason[Month],Table_SourceData_Common_MonthToSeason[Season]) -> #N/A | G72: =InputFunctions_PastureBeef.LookupLiveweightFromMonth($E$7,X_Cell_PastureBeef_ProductionRegion,$D72,G$66,Table_SourceData_PastureBeef_LiveweightAllStates[State],Table_SourceData_PastureBeef_LiveweightAllStates[Region],Table_SourceData_PastureBeef_LiveweightAllStates[Season],Table_SourceData_PastureBeef_LiveweightAllStates[#Headers],Table_SourceData_PastureBeef_LiveweightAllStates[#Data],Table_AustralianStates[Common Name],Table_AustralianStates[Abbreviation],Table_SourceData_Common_MonthToSeason[Month],Table_SourceData_Common_MonthToSeason[Season]) -> #N/A | H72: =InputFunctions_PastureBeef.LookupLiveweightFromMonth($E$7,X_Cell_PastureBeef_ProductionRegion,$D72,H$66,Table_SourceData_PastureBeef_LiveweightAllStates[State],Table_SourceData_PastureBeef_LiveweightAllStates[Region],Table_SourceData_PastureBeef_LiveweightAllStates[Season],Table_SourceData_PastureBeef_LiveweightAllStates[#Headers],Table_SourceData_PastureBeef_LiveweightAllStates[#Data],Table_AustralianStates[Common Name],Table_AustralianStates[Abbreviation],Table_SourceData_Common_MonthToSeason[Month],Table_SourceData_Common_MonthToSeason[Season]) -> #N/A | I72: =InputFunctions_PastureBeef.LookupLiveweightFromMonth($E$7,X_Cell_PastureBeef_ProductionRegion,$D72,I$66,Table_SourceData_PastureBeef_LiveweightAllStates[State],Table_SourceData_PastureBeef_LiveweightAllStates[Region],Table_SourceData_PastureBeef_LiveweightAllStates[Season],Table_SourceData_PastureBeef_LiveweightAllStates[#Headers],Table_SourceData_PastureBeef_LiveweightAllStates[#Data],Table_AustralianStates[Common Name],Table_AustralianStates[Abbreviation],Table_SourceData_Common_MonthToSeason[Month],Table_SourceData_Common_MonthToSeason[Season]) -> #N/A | J72: =InputFunctions_PastureBeef.LookupLiveweightFromMonth($E$7,X_Cell_PastureBeef_ProductionRegion,$D72,J$66,Table_SourceData_PastureBeef_LiveweightAllStates[State],Table_SourceData_PastureBeef_LiveweightAllStates[Region],Table_SourceData_PastureBeef_LiveweightAllStates[Season],Table_SourceData_PastureBeef_LiveweightAllStates[#Headers],Table_SourceData_PastureBeef_LiveweightAllStates[#Data],Table_AustralianStates[Common Name],Table_AustralianStates[Abbreviation],Table_SourceData_Common_MonthToSeason[Month],Table_SourceData_Common_MonthToSeason[Season]) -> #N/A | K72: =InputFunctions_PastureBeef.LookupLiveweightFromMonth($E$7,X_Cell_PastureBeef_ProductionRegion,$D72,K$66,Table_SourceData_PastureBeef_LiveweightAllStates[State],Table_SourceData_PastureBeef_LiveweightAllStates[Region],Table_SourceData_PastureBeef_LiveweightAllStates[Season],Table_SourceData_PastureBeef_LiveweightAllStates[#Headers],Table_SourceData_PastureBeef_LiveweightAllStates[#Data],Table_AustralianStates[Common Name],Table_AustralianStates[Abbreviation],Table_SourceData_Common_MonthToSeason[Month],Table_SourceData_Common_MonthToSeason[Season]) -> #N/A | L72: =InputFunctions_PastureBeef.LookupLiveweightFromMonth($E$7,X_Cell_PastureBeef_ProductionRegion,$D72,L$66,Table_SourceData_PastureBeef_LiveweightAllStates[State],Table_SourceData_PastureBeef_LiveweightAllStates[Region],Table_SourceData_PastureBeef_LiveweightAllStates[Season],Table_SourceData_PastureBeef_LiveweightAllStates[#Headers],Table_SourceData_PastureBeef_LiveweightAllStates[#Data],Table_AustralianStates[Common Name],Table_AustralianStates[Abbreviation],Table_SourceData_Common_MonthToSeason[Month],Table_SourceData_Common_MonthToSeason[Season]) -> #N/A | ... N72: =InputFunctions_PastureBeef.LookupLiveweightFromMonth($E$7,X_Cell_PastureBeef_ProductionRegion,$D72,N$66,Table_SourceData_PastureBeef_LiveweightAllStates[State],Table_SourceData_PastureBeef_LiveweightAllStates[Region],Table_SourceData_PastureBeef_LiveweightAllStates[Season],Table_SourceData_PastureBeef_LiveweightAllStates[#Headers],Table_SourceData_PastureBeef_LiveweightAllStates[#Data],Table_AustralianStates[Common Name],Table_AustralianStates[Abbreviation],Table_SourceData_Common_MonthToSeason[Month],Table_SourceData_Common_MonthToSeason[Season]) -> #N/A | O72: kg/head
D73: =TEXT(EDATE(X_Cell_Site_StartDate,6), "mmmm yyyy") -> June 1900 | E73: =InputFunctions_PastureBeef.LookupLiveweightFromMonth($E$7,X_Cell_PastureBeef_ProductionRegion,$D73,E$66,Table_SourceData_PastureBeef_LiveweightAllStates[State],Table_SourceData_PastureBeef_LiveweightAllStates[Region],Table_SourceData_PastureBeef_LiveweightAllStates[Season],Table_SourceData_PastureBeef_LiveweightAllStates[#Headers],Table_SourceData_PastureBeef_LiveweightAllStates[#Data],Table_AustralianStates[Common Name],Table_AustralianStates[Abbreviation],Table_SourceData_Common_MonthToSeason[Month],Table_SourceData_Common_MonthToSeason[Season]) -> #N/A | F73: =InputFunctions_PastureBeef.LookupLiveweightFromMonth($E$7,X_Cell_PastureBeef_ProductionRegion,$D73,F$66,Table_SourceData_PastureBeef_LiveweightAllStates[State],Table_SourceData_PastureBeef_LiveweightAllStates[Region],Table_SourceData_PastureBeef_LiveweightAllStates[Season],Table_SourceData_PastureBeef_LiveweightAllStates[#Headers],Table_SourceData_PastureBeef_LiveweightAllStates[#Data],Table_AustralianStates[Common Name],Table_AustralianStates[Abbreviation],Table_SourceData_Common_MonthToSeason[Month],Table_SourceData_Common_MonthToSeason[Season]) -> #N/A | G73: =InputFunctions_PastureBeef.LookupLiveweightFromMonth($E$7,X_Cell_PastureBeef_ProductionRegion,$D73,G$66,Table_SourceData_PastureBeef_LiveweightAllStates[State],Table_SourceData_PastureBeef_LiveweightAllStates[Region],Table_SourceData_PastureBeef_LiveweightAllStates[Season],Table_SourceData_PastureBeef_LiveweightAllStates[#Headers],Table_SourceData_PastureBeef_LiveweightAllStates[#Data],Table_AustralianStates[Common Name],Table_AustralianStates[Abbreviation],Table_SourceData_Common_MonthToSeason[Month],Table_SourceData_Common_MonthToSeason[Season]) -> #N/A | H73: =InputFunctions_PastureBeef.LookupLiveweightFromMonth($E$7,X_Cell_PastureBeef_ProductionRegion,$D73,H$66,Table_SourceData_PastureBeef_LiveweightAllStates[State],Table_SourceData_PastureBeef_LiveweightAllStates[Region],Table_SourceData_PastureBeef_LiveweightAllStates[Season],Table_SourceData_PastureBeef_LiveweightAllStates[#Headers],Table_SourceData_PastureBeef_LiveweightAllStates[#Data],Table_AustralianStates[Common Name],Table_AustralianStates[Abbreviation],Table_SourceData_Common_MonthToSeason[Month],Table_SourceData_Common_MonthToSeason[Season]) -> #N/A | I73: =InputFunctions_PastureBeef.LookupLiveweightFromMonth($E$7,X_Cell_PastureBeef_ProductionRegion,$D73,I$66,Table_SourceData_PastureBeef_LiveweightAllStates[State],Table_SourceData_PastureBeef_LiveweightAllStates[Region],Table_SourceData_PastureBeef_LiveweightAllStates[Season],Table_SourceData_PastureBeef_LiveweightAllStates[#Headers],Table_SourceData_PastureBeef_LiveweightAllStates[#Data],Table_AustralianStates[Common Name],Table_AustralianStates[Abbreviation],Table_SourceData_Common_MonthToSeason[Month],Table_SourceData_Common_MonthToSeason[Season]) -> #N/A | J73: =InputFunctions_PastureBeef.LookupLiveweightFromMonth($E$7,X_Cell_PastureBeef_ProductionRegion,$D73,J$66,Table_SourceData_PastureBeef_LiveweightAllStates[State],Table_SourceData_PastureBeef_LiveweightAllStates[Region],Table_SourceData_PastureBeef_LiveweightAllStates[Season],Table_SourceData_PastureBeef_LiveweightAllStates[#Headers],Table_SourceData_PastureBeef_LiveweightAllStates[#Data],Table_AustralianStates[Common Name],Table_AustralianStates[Abbreviation],Table_SourceData_Common_MonthToSeason[Month],Table_SourceData_Common_MonthToSeason[Season]) -> #N/A | K73: =InputFunctions_PastureBeef.LookupLiveweightFromMonth($E$7,X_Cell_PastureBeef_ProductionRegion,$D73,K$66,Table_SourceData_PastureBeef_LiveweightAllStates[State],Table_SourceData_PastureBeef_LiveweightAllStates[Region],Table_SourceData_PastureBeef_LiveweightAllStates[Season],Table_SourceData_PastureBeef_LiveweightAllStates[#Headers],Table_SourceData_PastureBeef_LiveweightAllStates[#Data],Table_AustralianStates[Common Name],Table_AustralianStates[Abbreviation],Table_SourceData_Common_MonthToSeason[Month],Table_SourceData_Common_MonthToSeason[Season]) -> #N/A | L73: =InputFunctions_PastureBeef.LookupLiveweightFromMonth($E$7,X_Cell_PastureBeef_ProductionRegion,$D73,L$66,Table_SourceData_PastureBeef_LiveweightAllStates[State],Table_SourceData_PastureBeef_LiveweightAllStates[Region],Table_SourceData_PastureBeef_LiveweightAllStates[Season],Table_SourceData_PastureBeef_LiveweightAllStates[#Headers],Table_SourceData_PastureBeef_LiveweightAllStates[#Data],Table_AustralianStates[Common Name],Table_AustralianStates[Abbreviation],Table_SourceData_Common_MonthToSeason[Month],Table_SourceData_Common_MonthToSeason[Season]) -> #N/A | ... N73: =InputFunctions_PastureBeef.LookupLiveweightFromMonth($E$7,X_Cell_PastureBeef_ProductionRegion,$D73,N$66,Table_SourceData_PastureBeef_LiveweightAllStates[State],Table_SourceData_PastureBeef_LiveweightAllStates[Region],Table_SourceData_PastureBeef_LiveweightAllStates[Season],Table_SourceData_PastureBeef_LiveweightAllStates[#Headers],Table_SourceData_PastureBeef_LiveweightAllStates[#Data],Table_AustralianStates[Common Name],Table_AustralianStates[Abbreviation],Table_SourceData_Common_MonthToSeason[Month],Table_SourceData_Common_MonthToSeason[Season]) -> #N/A | O73: kg/head
D74: =TEXT(EDATE(X_Cell_Site_StartDate,7), "mmmm yyyy") -> July 1900 | E74: =InputFunctions_PastureBeef.LookupLiveweightFromMonth($E$7,X_Cell_PastureBeef_ProductionRegion,$D74,E$66,Table_SourceData_PastureBeef_LiveweightAllStates[State],Table_SourceData_PastureBeef_LiveweightAllStates[Region],Table_SourceData_PastureBeef_LiveweightAllStates[Season],Table_SourceData_PastureBeef_LiveweightAllStates[#Headers],Table_SourceData_PastureBeef_LiveweightAllStates[#Data],Table_AustralianStates[Common Name],Table_AustralianStates[Abbreviation],Table_SourceData_Common_MonthToSeason[Month],Table_SourceData_Common_MonthToSeason[Season]) -> #N/A | F74: =InputFunctions_PastureBeef.LookupLiveweightFromMonth($E$7,X_Cell_PastureBeef_ProductionRegion,$D74,F$66,Table_SourceData_PastureBeef_LiveweightAllStates[State],Table_SourceData_PastureBeef_LiveweightAllStates[Region],Table_SourceData_PastureBeef_LiveweightAllStates[Season],Table_SourceData_PastureBeef_LiveweightAllStates[#Headers],Table_SourceData_PastureBeef_LiveweightAllStates[#Data],Table_AustralianStates[Common Name],Table_AustralianStates[Abbreviation],Table_SourceData_Common_MonthToSeason[Month],Table_SourceData_Common_MonthToSeason[Season]) -> #N/A | G74: =InputFunctions_PastureBeef.LookupLiveweightFromMonth($E$7,X_Cell_PastureBeef_ProductionRegion,$D74,G$66,Table_SourceData_PastureBeef_LiveweightAllStates[State],Table_SourceData_PastureBeef_LiveweightAllStates[Region],Table_SourceData_PastureBeef_LiveweightAllStates[Season],Table_SourceData_PastureBeef_LiveweightAllStates[#Headers],Table_SourceData_PastureBeef_LiveweightAllStates[#Data],Table_AustralianStates[Common Name],Table_AustralianStates[Abbreviation],Table_SourceData_Common_MonthToSeason[Month],Table_SourceData_Common_MonthToSeason[Season]) -> #N/A | H74: =InputFunctions_PastureBeef.LookupLiveweightFromMonth($E$7,X_Cell_PastureBeef_ProductionRegion,$D74,H$66,Table_SourceData_PastureBeef_LiveweightAllStates[State],Table_SourceData_PastureBeef_LiveweightAllStates[Region],Table_SourceData_PastureBeef_LiveweightAllStates[Season],Table_SourceData_PastureBeef_LiveweightAllStates[#Headers],Table_SourceData_PastureBeef_LiveweightAllStates[#Data],Table_AustralianStates[Common Name],Table_AustralianStates[Abbreviation],Table_SourceData_Common_MonthToSeason[Month],Table_SourceData_Common_MonthToSeason[Season]) -> #N/A | I74: =InputFunctions_PastureBeef.LookupLiveweightFromMonth($E$7,X_Cell_PastureBeef_ProductionRegion,$D74,I$66,Table_SourceData_PastureBeef_LiveweightAllStates[State],Table_SourceData_PastureBeef_LiveweightAllStates[Region],Table_SourceData_PastureBeef_LiveweightAllStates[Season],Table_SourceData_PastureBeef_LiveweightAllStates[#Headers],Table_SourceData_PastureBeef_LiveweightAllStates[#Data],Table_AustralianStates[Common Name],Table_AustralianStates[Abbreviation],Table_SourceData_Common_MonthToSeason[Month],Table_SourceData_Common_MonthToSeason[Season]) -> #N/A | J74: =InputFunctions_PastureBeef.LookupLiveweightFromMonth($E$7,X_Cell_PastureBeef_ProductionRegion,$D74,J$66,Table_SourceData_PastureBeef_LiveweightAllStates[State],Table_SourceData_PastureBeef_LiveweightAllStates[Region],Table_SourceData_PastureBeef_LiveweightAllStates[Season],Table_SourceData_PastureBeef_LiveweightAllStates[#Headers],Table_SourceData_PastureBeef_LiveweightAllStates[#Data],Table_AustralianStates[Common Name],Table_AustralianStates[Abbreviation],Table_SourceData_Common_MonthToSeason[Month],Table_SourceData_Common_MonthToSeason[Season]) -> #N/A | K74: =InputFunctions_PastureBeef.LookupLiveweightFromMonth($E$7,X_Cell_PastureBeef_ProductionRegion,$D74,K$66,Table_SourceData_PastureBeef_LiveweightAllStates[State],Table_SourceData_PastureBeef_LiveweightAllStates[Region],Table_SourceData_PastureBeef_LiveweightAllStates[Season],Table_SourceData_PastureBeef_LiveweightAllStates[#Headers],Table_SourceData_PastureBeef_LiveweightAllStates[#Data],Table_AustralianStates[Common Name],Table_AustralianStates[Abbreviation],Table_SourceData_Common_MonthToSeason[Month],Table_SourceData_Common_MonthToSeason[Season]) -> #N/A | L74: =InputFunctions_PastureBeef.LookupLiveweightFromMonth($E$7,X_Cell_PastureBeef_ProductionRegion,$D74,L$66,Table_SourceData_PastureBeef_LiveweightAllStates[State],Table_SourceData_PastureBeef_LiveweightAllStates[Region],Table_SourceData_PastureBeef_LiveweightAllStates[Season],Table_SourceData_PastureBeef_LiveweightAllStates[#Headers],Table_SourceData_PastureBeef_LiveweightAllStates[#Data],Table_AustralianStates[Common Name],Table_AustralianStates[Abbreviation],Table_SourceData_Common_MonthToSeason[Month],Table_SourceData_Common_MonthToSeason[Season]) -> #N/A | ... N74: =InputFunctions_PastureBeef.LookupLiveweightFromMonth($E$7,X_Cell_PastureBeef_ProductionRegion,$D74,N$66,Table_SourceData_PastureBeef_LiveweightAllStates[State],Table_SourceData_PastureBeef_LiveweightAllStates[Region],Table_SourceData_PastureBeef_LiveweightAllStates[Season],Table_SourceData_PastureBeef_LiveweightAllStates[#Headers],Table_SourceData_PastureBeef_LiveweightAllStates[#Data],Table_AustralianStates[Common Name],Table_AustralianStates[Abbreviation],Table_SourceData_Common_MonthToSeason[Month],Table_SourceData_Common_MonthToSeason[Season]) -> #N/A | O74: kg/head
D75: =TEXT(EDATE(X_Cell_Site_StartDate,8), "mmmm yyyy") -> August 1900 | E75: =InputFunctions_PastureBeef.LookupLiveweightFromMonth($E$7,X_Cell_PastureBeef_ProductionRegion,$D75,E$66,Table_SourceData_PastureBeef_LiveweightAllStates[State],Table_SourceData_PastureBeef_LiveweightAllStates[Region],Table_SourceData_PastureBeef_LiveweightAllStates[Season],Table_SourceData_PastureBeef_LiveweightAllStates[#Headers],Table_SourceData_PastureBeef_LiveweightAllStates[#Data],Table_AustralianStates[Common Name],Table_AustralianStates[Abbreviation],Table_SourceData_Common_MonthToSeason[Month],Table_SourceData_Common_MonthToSeason[Season]) -> #N/A | F75: =InputFunctions_PastureBeef.LookupLiveweightFromMonth($E$7,X_Cell_PastureBeef_ProductionRegion,$D75,F$66,Table_SourceData_PastureBeef_LiveweightAllStates[State],Table_SourceData_PastureBeef_LiveweightAllStates[Region],Table_SourceData_PastureBeef_LiveweightAllStates[Season],Table_SourceData_PastureBeef_LiveweightAllStates[#Headers],Table_SourceData_PastureBeef_LiveweightAllStates[#Data],Table_AustralianStates[Common Name],Table_AustralianStates[Abbreviation],Table_SourceData_Common_MonthToSeason[Month],Table_SourceData_Common_MonthToSeason[Season]) -> #N/A | G75: =InputFunctions_PastureBeef.LookupLiveweightFromMonth($E$7,X_Cell_PastureBeef_ProductionRegion,$D75,G$66,Table_SourceData_PastureBeef_LiveweightAllStates[State],Table_SourceData_PastureBeef_LiveweightAllStates[Region],Table_SourceData_PastureBeef_LiveweightAllStates[Season],Table_SourceData_PastureBeef_LiveweightAllStates[#Headers],Table_SourceData_PastureBeef_LiveweightAllStates[#Data],Table_AustralianStates[Common Name],Table_AustralianStates[Abbreviation],Table_SourceData_Common_MonthToSeason[Month],Table_SourceData_Common_MonthToSeason[Season]) -> #N/A | H75: =InputFunctions_PastureBeef.LookupLiveweightFromMonth($E$7,X_Cell_PastureBeef_ProductionRegion,$D75,H$66,Table_SourceData_PastureBeef_LiveweightAllStates[State],Table_SourceData_PastureBeef_LiveweightAllStates[Region],Table_SourceData_PastureBeef_LiveweightAllStates[Season],Table_SourceData_PastureBeef_LiveweightAllStates[#Headers],Table_SourceData_PastureBeef_LiveweightAllStates[#Data],Table_AustralianStates[Common Name],Table_AustralianStates[Abbreviation],Table_SourceData_Common_MonthToSeason[Month],Table_SourceData_Common_MonthToSeason[Season]) -> #N/A | I75: =InputFunctions_PastureBeef.LookupLiveweightFromMonth($E$7,X_Cell_PastureBeef_ProductionRegion,$D75,I$66,Table_SourceData_PastureBeef_LiveweightAllStates[State],Table_SourceData_PastureBeef_LiveweightAllStates[Region],Table_SourceData_PastureBeef_LiveweightAllStates[Season],Table_SourceData_PastureBeef_LiveweightAllStates[#Headers],Table_SourceData_PastureBeef_LiveweightAllStates[#Data],Table_AustralianStates[Common Name],Table_AustralianStates[Abbreviation],Table_SourceData_Common_MonthToSeason[Month],Table_SourceData_Common_MonthToSeason[Season]) -> #N/A | J75: =InputFunctions_PastureBeef.LookupLiveweightFromMonth($E$7,X_Cell_PastureBeef_ProductionRegion,$D75,J$66,Table_SourceData_PastureBeef_LiveweightAllStates[State],Table_SourceData_PastureBeef_LiveweightAllStates[Region],Table_SourceData_PastureBeef_LiveweightAllStates[Season],Table_SourceData_PastureBeef_LiveweightAllStates[#Headers],Table_SourceData_PastureBeef_LiveweightAllStates[#Data],Table_AustralianStates[Common Name],Table_AustralianStates[Abbreviation],Table_SourceData_Common_MonthToSeason[Month],Table_SourceData_Common_MonthToSeason[Season]) -> #N/A | K75: =InputFunctions_PastureBeef.LookupLiveweightFromMonth($E$7,X_Cell_PastureBeef_ProductionRegion,$D75,K$66,Table_SourceData_PastureBeef_LiveweightAllStates[State],Table_SourceData_PastureBeef_LiveweightAllStates[Region],Table_SourceData_PastureBeef_LiveweightAllStates[Season],Table_SourceData_PastureBeef_LiveweightAllStates[#Headers],Table_SourceData_PastureBeef_LiveweightAllStates[#Data],Table_AustralianStates[Common Name],Table_AustralianStates[Abbreviation],Table_SourceData_Common_MonthToSeason[Month],Table_SourceData_Common_MonthToSeason[Season]) -> #N/A | L75: =InputFunctions_PastureBeef.LookupLiveweightFromMonth($E$7,X_Cell_PastureBeef_ProductionRegion,$D75,L$66,Table_SourceData_PastureBeef_LiveweightAllStates[State],Table_SourceData_PastureBeef_LiveweightAllStates[Region],Table_SourceData_PastureBeef_LiveweightAllStates[Season],Table_SourceData_PastureBeef_LiveweightAllStates[#Headers],Table_SourceData_PastureBeef_LiveweightAllStates[#Data],Table_AustralianStates[Common Name],Table_AustralianStates[Abbreviation],Table_SourceData_Common_MonthToSeason[Month],Table_SourceData_Common_MonthToSeason[Season]) -> #N/A | ... N75: =InputFunctions_PastureBeef.LookupLiveweightFromMonth($E$7,X_Cell_PastureBeef_ProductionRegion,$D75,N$66,Table_SourceData_PastureBeef_LiveweightAllStates[State],Table_SourceData_PastureBeef_LiveweightAllStates[Region],Table_SourceData_PastureBeef_LiveweightAllStates[Season],Table_SourceData_PastureBeef_LiveweightAllStates[#Headers],Table_SourceData_PastureBeef_LiveweightAllStates[#Data],Table_AustralianStates[Common Name],Table_AustralianStates[Abbreviation],Table_SourceData_Common_MonthToSeason[Month],Table_SourceData_Common_MonthToSeason[Season]) -> #N/A | O75: kg/head
D76: =TEXT(EDATE(X_Cell_Site_StartDate,9), "mmmm yyyy") -> September 1900 | E76: =InputFunctions_PastureBeef.LookupLiveweightFromMonth($E$7,X_Cell_PastureBeef_ProductionRegion,$D76,E$66,Table_SourceData_PastureBeef_LiveweightAllStates[State],Table_SourceData_PastureBeef_LiveweightAllStates[Region],Table_SourceData_PastureBeef_LiveweightAllStates[Season],Table_SourceData_PastureBeef_LiveweightAllStates[#Headers],Table_SourceData_PastureBeef_LiveweightAllStates[#Data],Table_AustralianStates[Common Name],Table_AustralianStates[Abbreviation],Table_SourceData_Common_MonthToSeason[Month],Table_SourceData_Common_MonthToSeason[Season]) -> #N/A | F76: =InputFunctions_PastureBeef.LookupLiveweightFromMonth($E$7,X_Cell_PastureBeef_ProductionRegion,$D76,F$66,Table_SourceData_PastureBeef_LiveweightAllStates[State],Table_SourceData_PastureBeef_LiveweightAllStates[Region],Table_SourceData_PastureBeef_LiveweightAllStates[Season],Table_SourceData_PastureBeef_LiveweightAllStates[#Headers],Table_SourceData_PastureBeef_LiveweightAllStates[#Data],Table_AustralianStates[Common Name],Table_AustralianStates[Abbreviation],Table_SourceData_Common_MonthToSeason[Month],Table_SourceData_Common_MonthToSeason[Season]) -> #N/A | G76: =InputFunctions_PastureBeef.LookupLiveweightFromMonth($E$7,X_Cell_PastureBeef_ProductionRegion,$D76,G$66,Table_SourceData_PastureBeef_LiveweightAllStates[State],Table_SourceData_PastureBeef_LiveweightAllStates[Region],Table_SourceData_PastureBeef_LiveweightAllStates[Season],Table_SourceData_PastureBeef_LiveweightAllStates[#Headers],Table_SourceData_PastureBeef_LiveweightAllStates[#Data],Table_AustralianStates[Common Name],Table_AustralianStates[Abbreviation],Table_SourceData_Common_MonthToSeason[Month],Table_SourceData_Common_MonthToSeason[Season]) -> #N/A | H76: =InputFunctions_PastureBeef.LookupLiveweightFromMonth($E$7,X_Cell_PastureBeef_ProductionRegion,$D76,H$66,Table_SourceData_PastureBeef_LiveweightAllStates[State],Table_SourceData_PastureBeef_LiveweightAllStates[Region],Table_SourceData_PastureBeef_LiveweightAllStates[Season],Table_SourceData_PastureBeef_LiveweightAllStates[#Headers],Table_SourceData_PastureBeef_LiveweightAllStates[#Data],Table_AustralianStates[Common Name],Table_AustralianStates[Abbreviation],Table_SourceData_Common_MonthToSeason[Month],Table_SourceData_Common_MonthToSeason[Season]) -> #N/A | I76: =InputFunctions_PastureBeef.LookupLiveweightFromMonth($E$7,X_Cell_PastureBeef_ProductionRegion,$D76,I$66,Table_SourceData_PastureBeef_LiveweightAllStates[State],Table_SourceData_PastureBeef_LiveweightAllStates[Region],Table_SourceData_PastureBeef_LiveweightAllStates[Season],Table_SourceData_PastureBeef_LiveweightAllStates[#Headers],Table_SourceData_PastureBeef_LiveweightAllStates[#Data],Table_AustralianStates[Common Name],Table_AustralianStates[Abbreviation],Table_SourceData_Common_MonthToSeason[Month],Table_SourceData_Common_MonthToSeason[Season]) -> #N/A | J76: =InputFunctions_PastureBeef.LookupLiveweightFromMonth($E$7,X_Cell_PastureBeef_ProductionRegion,$D76,J$66,Table_SourceData_PastureBeef_LiveweightAllStates[State],Table_SourceData_PastureBeef_LiveweightAllStates[Region],Table_SourceData_PastureBeef_LiveweightAllStates[Season],Table_SourceData_PastureBeef_LiveweightAllStates[#Headers],Table_SourceData_PastureBeef_LiveweightAllStates[#Data],Table_AustralianStates[Common Name],Table_AustralianStates[Abbreviation],Table_SourceData_Common_MonthToSeason[Month],Table_SourceData_Common_MonthToSeason[Season]) -> #N/A | K76: =InputFunctions_PastureBeef.LookupLiveweightFromMonth($E$7,X_Cell_PastureBeef_ProductionRegion,$D76,K$66,Table_SourceData_PastureBeef_LiveweightAllStates[State],Table_SourceData_PastureBeef_LiveweightAllStates[Region],Table_SourceData_PastureBeef_LiveweightAllStates[Season],Table_SourceData_PastureBeef_LiveweightAllStates[#Headers],Table_SourceData_PastureBeef_LiveweightAllStates[#Data],Table_AustralianStates[Common Name],Table_AustralianStates[Abbreviation],Table_SourceData_Common_MonthToSeason[Month],Table_SourceData_Common_MonthToSeason[Season]) -> #N/A | L76: =InputFunctions_PastureBeef.LookupLiveweightFromMonth($E$7,X_Cell_PastureBeef_ProductionRegion,$D76,L$66,Table_SourceData_PastureBeef_LiveweightAllStates[State],Table_SourceData_PastureBeef_LiveweightAllStates[Region],Table_SourceData_PastureBeef_LiveweightAllStates[Season],Table_SourceData_PastureBeef_LiveweightAllStates[#Headers],Table_SourceData_PastureBeef_LiveweightAllStates[#Data],Table_AustralianStates[Common Name],Table_AustralianStates[Abbreviation],Table_SourceData_Common_MonthToSeason[Month],Table_SourceData_Common_MonthToSeason[Season]) -> #N/A | ... N76: =InputFunctions_PastureBeef.LookupLiveweightFromMonth($E$7,X_Cell_PastureBeef_ProductionRegion,$D76,N$66,Table_SourceData_PastureBeef_LiveweightAllStates[State],Table_SourceData_PastureBeef_LiveweightAllStates[Region],Table_SourceData_PastureBeef_LiveweightAllStates[Season],Table_SourceData_PastureBeef_LiveweightAllStates[#Headers],Table_SourceData_PastureBeef_LiveweightAllStates[#Data],Table_AustralianStates[Common Name],Table_AustralianStates[Abbreviation],Table_SourceData_Common_MonthToSeason[Month],Table_SourceData_Common_MonthToSeason[Season]) -> #N/A | O76: kg/head
D77: =TEXT(EDATE(X_Cell_Site_StartDate,10), "mmmm yyyy") -> October 1900 | E77: =InputFunctions_PastureBeef.LookupLiveweightFromMonth($E$7,X_Cell_PastureBeef_ProductionRegion,$D77,E$66,Table_SourceData_PastureBeef_LiveweightAllStates[State],Table_SourceData_PastureBeef_LiveweightAllStates[Region],Table_SourceData_PastureBeef_LiveweightAllStates[Season],Table_SourceData_PastureBeef_LiveweightAllStates[#Headers],Table_SourceData_PastureBeef_LiveweightAllStates[#Data],Table_AustralianStates[Common Name],Table_AustralianStates[Abbreviation],Table_SourceData_Common_MonthToSeason[Month],Table_SourceData_Common_MonthToSeason[Season]) -> #N/A | F77: =InputFunctions_PastureBeef.LookupLiveweightFromMonth($E$7,X_Cell_PastureBeef_ProductionRegion,$D77,F$66,Table_SourceData_PastureBeef_LiveweightAllStates[State],Table_SourceData_PastureBeef_LiveweightAllStates[Region],Table_SourceData_PastureBeef_LiveweightAllStates[Season],Table_SourceData_PastureBeef_LiveweightAllStates[#Headers],Table_SourceData_PastureBeef_LiveweightAllStates[#Data],Table_AustralianStates[Common Name],Table_AustralianStates[Abbreviation],Table_SourceData_Common_MonthToSeason[Month],Table_SourceData_Common_MonthToSeason[Season]) -> #N/A | G77: =InputFunctions_PastureBeef.LookupLiveweightFromMonth($E$7,X_Cell_PastureBeef_ProductionRegion,$D77,G$66,Table_SourceData_PastureBeef_LiveweightAllStates[State],Table_SourceData_PastureBeef_LiveweightAllStates[Region],Table_SourceData_PastureBeef_LiveweightAllStates[Season],Table_SourceData_PastureBeef_LiveweightAllStates[#Headers],Table_SourceData_PastureBeef_LiveweightAllStates[#Data],Table_AustralianStates[Common Name],Table_AustralianStates[Abbreviation],Table_SourceData_Common_MonthToSeason[Month],Table_SourceData_Common_MonthToSeason[Season]) -> #N/A | H77: =InputFunctions_PastureBeef.LookupLiveweightFromMonth($E$7,X_Cell_PastureBeef_ProductionRegion,$D77,H$66,Table_SourceData_PastureBeef_LiveweightAllStates[State],Table_SourceData_PastureBeef_LiveweightAllStates[Region],Table_SourceData_PastureBeef_LiveweightAllStates[Season],Table_SourceData_PastureBeef_LiveweightAllStates[#Headers],Table_SourceData_PastureBeef_LiveweightAllStates[#Data],Table_AustralianStates[Common Name],Table_AustralianStates[Abbreviation],Table_SourceData_Common_MonthToSeason[Month],Table_SourceData_Common_MonthToSeason[Season]) -> #N/A | I77: =InputFunctions_PastureBeef.LookupLiveweightFromMonth($E$7,X_Cell_PastureBeef_ProductionRegion,$D77,I$66,Table_SourceData_PastureBeef_LiveweightAllStates[State],Table_SourceData_PastureBeef_LiveweightAllStates[Region],Table_SourceData_PastureBeef_LiveweightAllStates[Season],Table_SourceData_PastureBeef_LiveweightAllStates[#Headers],Table_SourceData_PastureBeef_LiveweightAllStates[#Data],Table_AustralianStates[Common Name],Table_AustralianStates[Abbreviation],Table_SourceData_Common_MonthToSeason[Month],Table_SourceData_Common_MonthToSeason[Season]) -> #N/A | J77: =InputFunctions_PastureBeef.LookupLiveweightFromMonth($E$7,X_Cell_PastureBeef_ProductionRegion,$D77,J$66,Table_SourceData_PastureBeef_LiveweightAllStates[State],Table_SourceData_PastureBeef_LiveweightAllStates[Region],Table_SourceData_PastureBeef_LiveweightAllStates[Season],Table_SourceData_PastureBeef_LiveweightAllStates[#Headers],Table_SourceData_PastureBeef_LiveweightAllStates[#Data],Table_AustralianStates[Common Name],Table_AustralianStates[Abbreviation],Table_SourceData_Common_MonthToSeason[Month],Table_SourceData_Common_MonthToSeason[Season]) -> #N/A | K77: =InputFunctions_PastureBeef.LookupLiveweightFromMonth($E$7,X_Cell_PastureBeef_ProductionRegion,$D77,K$66,Table_SourceData_PastureBeef_LiveweightAllStates[State],Table_SourceData_PastureBeef_LiveweightAllStates[Region],Table_SourceData_PastureBeef_LiveweightAllStates[Season],Table_SourceData_PastureBeef_LiveweightAllStates[#Headers],Table_SourceData_PastureBeef_LiveweightAllStates[#Data],Table_AustralianStates[Common Name],Table_AustralianStates[Abbreviation],Table_SourceData_Common_MonthToSeason[Month],Table_SourceData_Common_MonthToSeason[Season]) -> #N/A | L77: =InputFunctions_PastureBeef.LookupLiveweightFromMonth($E$7,X_Cell_PastureBeef_ProductionRegion,$D77,L$66,Table_SourceData_PastureBeef_LiveweightAllStates[State],Table_SourceData_PastureBeef_LiveweightAllStates[Region],Table_SourceData_PastureBeef_LiveweightAllStates[Season],Table_SourceData_PastureBeef_LiveweightAllStates[#Headers],Table_SourceData_PastureBeef_LiveweightAllStates[#Data],Table_AustralianStates[Common Name],Table_AustralianStates[Abbreviation],Table_SourceData_Common_MonthToSeason[Month],Table_SourceData_Common_MonthToSeason[Season]) -> #N/A | ... N77: =InputFunctions_PastureBeef.LookupLiveweightFromMonth($E$7,X_Cell_PastureBeef_ProductionRegion,$D77,N$66,Table_SourceData_PastureBeef_LiveweightAllStates[State],Table_SourceData_PastureBeef_LiveweightAllStates[Region],Table_SourceData_PastureBeef_LiveweightAllStates[Season],Table_SourceData_PastureBeef_LiveweightAllStates[#Headers],Table_SourceData_PastureBeef_LiveweightAllStates[#Data],Table_AustralianStates[Common Name],Table_AustralianStates[Abbreviation],Table_SourceData_Common_MonthToSeason[Month],Table_SourceData_Common_MonthToSeason[Season]) -> #N/A | O77: kg/head
D78: =TEXT(EDATE(X_Cell_Site_StartDate,11), "mmmm yyyy") -> November 1900 | E78: =InputFunctions_PastureBeef.LookupLiveweightFromMonth($E$7,X_Cell_PastureBeef_ProductionRegion,$D78,E$66,Table_SourceData_PastureBeef_LiveweightAllStates[State],Table_SourceData_PastureBeef_LiveweightAllStates[Region],Table_SourceData_PastureBeef_LiveweightAllStates[Season],Table_SourceData_PastureBeef_LiveweightAllStates[#Headers],Table_SourceData_PastureBeef_LiveweightAllStates[#Data],Table_AustralianStates[Common Name],Table_AustralianStates[Abbreviation],Table_SourceData_Common_MonthToSeason[Month],Table_SourceData_Common_MonthToSeason[Season]) -> #N/A | F78: =InputFunctions_PastureBeef.LookupLiveweightFromMonth($E$7,X_Cell_PastureBeef_ProductionRegion,$D78,F$66,Table_SourceData_PastureBeef_LiveweightAllStates[State],Table_SourceData_PastureBeef_LiveweightAllStates[Region],Table_SourceData_PastureBeef_LiveweightAllStates[Season],Table_SourceData_PastureBeef_LiveweightAllStates[#Headers],Table_SourceData_PastureBeef_LiveweightAllStates[#Data],Table_AustralianStates[Common Name],Table_AustralianStates[Abbreviation],Table_SourceData_Common_MonthToSeason[Month],Table_SourceData_Common_MonthToSeason[Season]) -> #N/A | G78: =InputFunctions_PastureBeef.LookupLiveweightFromMonth($E$7,X_Cell_PastureBeef_ProductionRegion,$D78,G$66,Table_SourceData_PastureBeef_LiveweightAllStates[State],Table_SourceData_PastureBeef_LiveweightAllStates[Region],Table_SourceData_PastureBeef_LiveweightAllStates[Season],Table_SourceData_PastureBeef_LiveweightAllStates[#Headers],Table_SourceData_PastureBeef_LiveweightAllStates[#Data],Table_AustralianStates[Common Name],Table_AustralianStates[Abbreviation],Table_SourceData_Common_MonthToSeason[Month],Table_SourceData_Common_MonthToSeason[Season]) -> #N/A | H78: =InputFunctions_PastureBeef.LookupLiveweightFromMonth($E$7,X_Cell_PastureBeef_ProductionRegion,$D78,H$66,Table_SourceData_PastureBeef_LiveweightAllStates[State],Table_SourceData_PastureBeef_LiveweightAllStates[Region],Table_SourceData_PastureBeef_LiveweightAllStates[Season],Table_SourceData_PastureBeef_LiveweightAllStates[#Headers],Table_SourceData_PastureBeef_LiveweightAllStates[#Data],Table_AustralianStates[Common Name],Table_AustralianStates[Abbreviation],Table_SourceData_Common_MonthToSeason[Month],Table_SourceData_Common_MonthToSeason[Season]) -> #N/A | I78: =InputFunctions_PastureBeef.LookupLiveweightFromMonth($E$7,X_Cell_PastureBeef_ProductionRegion,$D78,I$66,Table_SourceData_PastureBeef_LiveweightAllStates[State],Table_SourceData_PastureBeef_LiveweightAllStates[Region],Table_SourceData_PastureBeef_LiveweightAllStates[Season],Table_SourceData_PastureBeef_LiveweightAllStates[#Headers],Table_SourceData_PastureBeef_LiveweightAllStates[#Data],Table_AustralianStates[Common Name],Table_AustralianStates[Abbreviation],Table_SourceData_Common_MonthToSeason[Month],Table_SourceData_Common_MonthToSeason[Season]) -> #N/A | J78: =InputFunctions_PastureBeef.LookupLiveweightFromMonth($E$7,X_Cell_PastureBeef_ProductionRegion,$D78,J$66,Table_SourceData_PastureBeef_LiveweightAllStates[State],Table_SourceData_PastureBeef_LiveweightAllStates[Region],Table_SourceData_PastureBeef_LiveweightAllStates[Season],Table_SourceData_PastureBeef_LiveweightAllStates[#Headers],Table_SourceData_PastureBeef_LiveweightAllStates[#Data],Table_AustralianStates[Common Name],Table_AustralianStates[Abbreviation],Table_SourceData_Common_MonthToSeason[Month],Table_SourceData_Common_MonthToSeason[Season]) -> #N/A | K78: =InputFunctions_PastureBeef.LookupLiveweightFromMonth($E$7,X_Cell_PastureBeef_ProductionRegion,$D78,K$66,Table_SourceData_PastureBeef_LiveweightAllStates[State],Table_SourceData_PastureBeef_LiveweightAllStates[Region],Table_SourceData_PastureBeef_LiveweightAllStates[Season],Table_SourceData_PastureBeef_LiveweightAllStates[#Headers],Table_SourceData_PastureBeef_LiveweightAllStates[#Data],Table_AustralianStates[Common Name],Table_AustralianStates[Abbreviation],Table_SourceData_Common_MonthToSeason[Month],Table_SourceData_Common_MonthToSeason[Season]) -> #N/A | L78: =InputFunctions_PastureBeef.LookupLiveweightFromMonth($E$7,X_Cell_PastureBeef_ProductionRegion,$D78,L$66,Table_SourceData_PastureBeef_LiveweightAllStates[State],Table_SourceData_PastureBeef_LiveweightAllStates[Region],Table_SourceData_PastureBeef_LiveweightAllStates[Season],Table_SourceData_PastureBeef_LiveweightAllStates[#Headers],Table_SourceData_PastureBeef_LiveweightAllStates[#Data],Table_AustralianStates[Common Name],Table_AustralianStates[Abbreviation],Table_SourceData_Common_MonthToSeason[Month],Table_SourceData_Common_MonthToSeason[Season]) -> #N/A | ... N78: =InputFunctions_PastureBeef.LookupLiveweightFromMonth($E$7,X_Cell_PastureBeef_ProductionRegion,$D78,N$66,Table_SourceData_PastureBeef_LiveweightAllStates[State],Table_SourceData_PastureBeef_LiveweightAllStates[Region],Table_SourceData_PastureBeef_LiveweightAllStates[Season],Table_SourceData_PastureBeef_LiveweightAllStates[#Headers],Table_SourceData_PastureBeef_LiveweightAllStates[#Data],Table_AustralianStates[Common Name],Table_AustralianStates[Abbreviation],Table_SourceData_Common_MonthToSeason[Month],Table_SourceData_Common_MonthToSeason[Season]) -> #N/A | O78: kg/head
D81: Liveweight gain
D82: Method 1 default values (do not edit) | E82: Bulls < 1 year | F82: Bulls > 1 year | G82: Cows < 1 year | H82: Cows 1-2 years | I82: Cows 2-3 years | J82: Cows > 3 years | K82: Steers < 1 year | L82: Steers 1-2 years | M82: Steers 2-3 years | N82: Steers >3 years
D83: Spring | E83: =InputFunctions_PastureBeef.LookupLiveweightFromSeason($E$7,X_Cell_PastureBeef_ProductionRegion,$D83,E$82,Table_SourceData_PastureBeef_LiveweightGainAllStates[State],Table_SourceData_PastureBeef_LiveweightGainAllStates[Region],Table_SourceData_PastureBeef_LiveweightGainAllStates[Season],Table_SourceData_PastureBeef_LiveweightGainAllStates[#Headers],Table_SourceData_PastureBeef_LiveweightGainAllStates[#Data],Table_AustralianStates[Common Name],Table_AustralianStates[Abbreviation]) -> #N/A | F83: =InputFunctions_PastureBeef.LookupLiveweightFromSeason($E$7,X_Cell_PastureBeef_ProductionRegion,$D83,F$82,Table_SourceData_PastureBeef_LiveweightGainAllStates[State],Table_SourceData_PastureBeef_LiveweightGainAllStates[Region],Table_SourceData_PastureBeef_LiveweightGainAllStates[Season],Table_SourceData_PastureBeef_LiveweightGainAllStates[#Headers],Table_SourceData_PastureBeef_LiveweightGainAllStates[#Data],Table_AustralianStates[Common Name],Table_AustralianStates[Abbreviation]) -> #N/A | G83: =InputFunctions_PastureBeef.LookupLiveweightFromSeason($E$7,X_Cell_PastureBeef_ProductionRegion,$D83,G$82,Table_SourceData_PastureBeef_LiveweightGainAllStates[State],Table_SourceData_PastureBeef_LiveweightGainAllStates[Region],Table_SourceData_PastureBeef_LiveweightGainAllStates[Season],Table_SourceData_PastureBeef_LiveweightGainAllStates[#Headers],Table_SourceData_PastureBeef_LiveweightGainAllStates[#Data],Table_AustralianStates[Common Name],Table_AustralianStates[Abbreviation]) -> #N/A | H83: =InputFunctions_PastureBeef.LookupLiveweightFromSeason($E$7,X_Cell_PastureBeef_ProductionRegion,$D83,H$82,Table_SourceData_PastureBeef_LiveweightGainAllStates[State],Table_SourceData_PastureBeef_LiveweightGainAllStates[Region],Table_SourceData_PastureBeef_LiveweightGainAllStates[Season],Table_SourceData_PastureBeef_LiveweightGainAllStates[#Headers],Table_SourceData_PastureBeef_LiveweightGainAllStates[#Data],Table_AustralianStates[Common Name],Table_AustralianStates[Abbreviation]) -> #N/A | I83: =InputFunctions_PastureBeef.LookupLiveweightFromSeason($E$7,X_Cell_PastureBeef_ProductionRegion,$D83,I$82,Table_SourceData_PastureBeef_LiveweightGainAllStates[State],Table_SourceData_PastureBeef_LiveweightGainAllStates[Region],Table_SourceData_PastureBeef_LiveweightGainAllStates[Season],Table_SourceData_PastureBeef_LiveweightGainAllStates[#Headers],Table_SourceData_PastureBeef_LiveweightGainAllStates[#Data],Table_AustralianStates[Common Name],Table_AustralianStates[Abbreviation]) -> #N/A | J83: =InputFunctions_PastureBeef.LookupLiveweightFromSeason($E$7,X_Cell_PastureBeef_ProductionRegion,$D83,J$82,Table_SourceData_PastureBeef_LiveweightGainAllStates[State],Table_SourceData_PastureBeef_LiveweightGainAllStates[Region],Table_SourceData_PastureBeef_LiveweightGainAllStates[Season],Table_SourceData_PastureBeef_LiveweightGainAllStates[#Headers],Table_SourceData_PastureBeef_LiveweightGainAllStates[#Data],Table_AustralianStates[Common Name],Table_AustralianStates[Abbreviation]) -> #N/A | K83: =InputFunctions_PastureBeef.LookupLiveweightFromSeason($E$7,X_Cell_PastureBeef_ProductionRegion,$D83,K$82,Table_SourceData_PastureBeef_LiveweightGainAllStates[State],Table_SourceData_PastureBeef_LiveweightGainAllStates[Region],Table_SourceData_PastureBeef_LiveweightGainAllStates[Season],Table_SourceData_PastureBeef_LiveweightGainAllStates[#Headers],Table_SourceData_PastureBeef_LiveweightGainAllStates[#Data],Table_AustralianStates[Common Name],Table_AustralianStates[Abbreviation]) -> #N/A | L83: =InputFunctions_PastureBeef.LookupLiveweightFromSeason($E$7,X_Cell_PastureBeef_ProductionRegion,$D83,L$82,Table_SourceData_PastureBeef_LiveweightGainAllStates[State],Table_SourceData_PastureBeef_LiveweightGainAllStates[Region],Table_SourceData_PastureBeef_LiveweightGainAllStates[Season],Table_SourceData_PastureBeef_LiveweightGainAllStates[#Headers],Table_SourceData_PastureBeef_LiveweightGainAllStates[#Data],Table_AustralianStates[Common Name],Table_AustralianStates[Abbreviation]) -> #N/A | ... N83: =InputFunctions_PastureBeef.LookupLiveweightFromSeason($E$7,X_Cell_PastureBeef_ProductionRegion,$D83,N$82,Table_SourceData_PastureBeef_LiveweightGainAllStates[State],Table_SourceData_PastureBeef_LiveweightGainAllStates[Region],Table_SourceData_PastureBeef_LiveweightGainAllStates[Season],Table_SourceData_PastureBeef_LiveweightGainAllStates[#Headers],Table_SourceData_PastureBeef_LiveweightGainAllStates[#Data],Table_AustralianStates[Common Name],Table_AustralianStates[Abbreviation]) -> #N/A | O83: kg/head/day
D84: Summer | E84: =InputFunctions_PastureBeef.LookupLiveweightFromSeason($E$7,X_Cell_PastureBeef_ProductionRegion,$D84,E$82,Table_SourceData_PastureBeef_LiveweightGainAllStates[State],Table_SourceData_PastureBeef_LiveweightGainAllStates[Region],Table_SourceData_PastureBeef_LiveweightGainAllStates[Season],Table_SourceData_PastureBeef_LiveweightGainAllStates[#Headers],Table_SourceData_PastureBeef_LiveweightGainAllStates[#Data],Table_AustralianStates[Common Name],Table_AustralianStates[Abbreviation]) -> #N/A | F84: =InputFunctions_PastureBeef.LookupLiveweightFromSeason($E$7,X_Cell_PastureBeef_ProductionRegion,$D84,F$82,Table_SourceData_PastureBeef_LiveweightGainAllStates[State],Table_SourceData_PastureBeef_LiveweightGainAllStates[Region],Table_SourceData_PastureBeef_LiveweightGainAllStates[Season],Table_SourceData_PastureBeef_LiveweightGainAllStates[#Headers],Table_SourceData_PastureBeef_LiveweightGainAllStates[#Data],Table_AustralianStates[Common Name],Table_AustralianStates[Abbreviation]) -> #N/A | G84: =InputFunctions_PastureBeef.LookupLiveweightFromSeason($E$7,X_Cell_PastureBeef_ProductionRegion,$D84,G$82,Table_SourceData_PastureBeef_LiveweightGainAllStates[State],Table_SourceData_PastureBeef_LiveweightGainAllStates[Region],Table_SourceData_PastureBeef_LiveweightGainAllStates[Season],Table_SourceData_PastureBeef_LiveweightGainAllStates[#Headers],Table_SourceData_PastureBeef_LiveweightGainAllStates[#Data],Table_AustralianStates[Common Name],Table_AustralianStates[Abbreviation]) -> #N/A | H84: =InputFunctions_PastureBeef.LookupLiveweightFromSeason($E$7,X_Cell_PastureBeef_ProductionRegion,$D84,H$82,Table_SourceData_PastureBeef_LiveweightGainAllStates[State],Table_SourceData_PastureBeef_LiveweightGainAllStates[Region],Table_SourceData_PastureBeef_LiveweightGainAllStates[Season],Table_SourceData_PastureBeef_LiveweightGainAllStates[#Headers],Table_SourceData_PastureBeef_LiveweightGainAllStates[#Data],Table_AustralianStates[Common Name],Table_AustralianStates[Abbreviation]) -> #N/A | I84: =InputFunctions_PastureBeef.LookupLiveweightFromSeason($E$7,X_Cell_PastureBeef_ProductionRegion,$D84,I$82,Table_SourceData_PastureBeef_LiveweightGainAllStates[State],Table_SourceData_PastureBeef_LiveweightGainAllStates[Region],Table_SourceData_PastureBeef_LiveweightGainAllStates[Season],Table_SourceData_PastureBeef_LiveweightGainAllStates[#Headers],Table_SourceData_PastureBeef_LiveweightGainAllStates[#Data],Table_AustralianStates[Common Name],Table_AustralianStates[Abbreviation]) -> #N/A | J84: =InputFunctions_PastureBeef.LookupLiveweightFromSeason($E$7,X_Cell_PastureBeef_ProductionRegion,$D84,J$82,Table_SourceData_PastureBeef_LiveweightGainAllStates[State],Table_SourceData_PastureBeef_LiveweightGainAllStates[Region],Table_SourceData_PastureBeef_LiveweightGainAllStates[Season],Table_SourceData_PastureBeef_LiveweightGainAllStates[#Headers],Table_SourceData_PastureBeef_LiveweightGainAllStates[#Data],Table_AustralianStates[Common Name],Table_AustralianStates[Abbreviation]) -> #N/A | K84: =InputFunctions_PastureBeef.LookupLiveweightFromSeason($E$7,X_Cell_PastureBeef_ProductionRegion,$D84,K$82,Table_SourceData_PastureBeef_LiveweightGainAllStates[State],Table_SourceData_PastureBeef_LiveweightGainAllStates[Region],Table_SourceData_PastureBeef_LiveweightGainAllStates[Season],Table_SourceData_PastureBeef_LiveweightGainAllStates[#Headers],Table_SourceData_PastureBeef_LiveweightGainAllStates[#Data],Table_AustralianStates[Common Name],Table_AustralianStates[Abbreviation]) -> #N/A | L84: =InputFunctions_PastureBeef.LookupLiveweightFromSeason($E$7,X_Cell_PastureBeef_ProductionRegion,$D84,L$82,Table_SourceData_PastureBeef_LiveweightGainAllStates[State],Table_SourceData_PastureBeef_LiveweightGainAllStates[Region],Table_SourceData_PastureBeef_LiveweightGainAllStates[Season],Table_SourceData_PastureBeef_LiveweightGainAllStates[#Headers],Table_SourceData_PastureBeef_LiveweightGainAllStates[#Data],Table_AustralianStates[Common Name],Table_AustralianStates[Abbreviation]) -> #N/A | ... N84: =InputFunctions_PastureBeef.LookupLiveweightFromSeason($E$7,X_Cell_PastureBeef_ProductionRegion,$D84,N$82,Table_SourceData_PastureBeef_LiveweightGainAllStates[State],Table_SourceData_PastureBeef_LiveweightGainAllStates[Region],Table_SourceData_PastureBeef_LiveweightGainAllStates[Season],Table_SourceData_PastureBeef_LiveweightGainAllStates[#Headers],Table_SourceData_PastureBeef_LiveweightGainAllStates[#Data],Table_AustralianStates[Common Name],Table_AustralianStates[Abbreviation]) -> #N/A | O84: kg/head/day
D85: Autumn | E85: =InputFunctions_PastureBeef.LookupLiveweightFromSeason($E$7,X_Cell_PastureBeef_ProductionRegion,$D85,E$82,Table_SourceData_PastureBeef_LiveweightGainAllStates[State],Table_SourceData_PastureBeef_LiveweightGainAllStates[Region],Table_SourceData_PastureBeef_LiveweightGainAllStates[Season],Table_SourceData_PastureBeef_LiveweightGainAllStates[#Headers],Table_SourceData_PastureBeef_LiveweightGainAllStates[#Data],Table_AustralianStates[Common Name],Table_AustralianStates[Abbreviation]) -> #N/A | F85: =InputFunctions_PastureBeef.LookupLiveweightFromSeason($E$7,X_Cell_PastureBeef_ProductionRegion,$D85,F$82,Table_SourceData_PastureBeef_LiveweightGainAllStates[State],Table_SourceData_PastureBeef_LiveweightGainAllStates[Region],Table_SourceData_PastureBeef_LiveweightGainAllStates[Season],Table_SourceData_PastureBeef_LiveweightGainAllStates[#Headers],Table_SourceData_PastureBeef_LiveweightGainAllStates[#Data],Table_AustralianStates[Common Name],Table_AustralianStates[Abbreviation]) -> #N/A | G85: =InputFunctions_PastureBeef.LookupLiveweightFromSeason($E$7,X_Cell_PastureBeef_ProductionRegion,$D85,G$82,Table_SourceData_PastureBeef_LiveweightGainAllStates[State],Table_SourceData_PastureBeef_LiveweightGainAllStates[Region],Table_SourceData_PastureBeef_LiveweightGainAllStates[Season],Table_SourceData_PastureBeef_LiveweightGainAllStates[#Headers],Table_SourceData_PastureBeef_LiveweightGainAllStates[#Data],Table_AustralianStates[Common Name],Table_AustralianStates[Abbreviation]) -> #N/A | H85: =InputFunctions_PastureBeef.LookupLiveweightFromSeason($E$7,X_Cell_PastureBeef_ProductionRegion,$D85,H$82,Table_SourceData_PastureBeef_LiveweightGainAllStates[State],Table_SourceData_PastureBeef_LiveweightGainAllStates[Region],Table_SourceData_PastureBeef_LiveweightGainAllStates[Season],Table_SourceData_PastureBeef_LiveweightGainAllStates[#Headers],Table_SourceData_PastureBeef_LiveweightGainAllStates[#Data],Table_AustralianStates[Common Name],Table_AustralianStates[Abbreviation]) -> #N/A | I85: =InputFunctions_PastureBeef.LookupLiveweightFromSeason($E$7,X_Cell_PastureBeef_ProductionRegion,$D85,I$82,Table_SourceData_PastureBeef_LiveweightGainAllStates[State],Table_SourceData_PastureBeef_LiveweightGainAllStates[Region],Table_SourceData_PastureBeef_LiveweightGainAllStates[Season],Table_SourceData_PastureBeef_LiveweightGainAllStates[#Headers],Table_SourceData_PastureBeef_LiveweightGainAllStates[#Data],Table_AustralianStates[Common Name],Table_AustralianStates[Abbreviation]) -> #N/A | J85: =InputFunctions_PastureBeef.LookupLiveweightFromSeason($E$7,X_Cell_PastureBeef_ProductionRegion,$D85,J$82,Table_SourceData_PastureBeef_LiveweightGainAllStates[State],Table_SourceData_PastureBeef_LiveweightGainAllStates[Region],Table_SourceData_PastureBeef_LiveweightGainAllStates[Season],Table_SourceData_PastureBeef_LiveweightGainAllStates[#Headers],Table_SourceData_PastureBeef_LiveweightGainAllStates[#Data],Table_AustralianStates[Common Name],Table_AustralianStates[Abbreviation]) -> #N/A | K85: =InputFunctions_PastureBeef.LookupLiveweightFromSeason($E$7,X_Cell_PastureBeef_ProductionRegion,$D85,K$82,Table_SourceData_PastureBeef_LiveweightGainAllStates[State],Table_SourceData_PastureBeef_LiveweightGainAllStates[Region],Table_SourceData_PastureBeef_LiveweightGainAllStates[Season],Table_SourceData_PastureBeef_LiveweightGainAllStates[#Headers],Table_SourceData_PastureBeef_LiveweightGainAllStates[#Data],Table_AustralianStates[Common Name],Table_AustralianStates[Abbreviation]) -> #N/A | L85: =InputFunctions_PastureBeef.LookupLiveweightFromSeason($E$7,X_Cell_PastureBeef_ProductionRegion,$D85,L$82,Table_SourceData_PastureBeef_LiveweightGainAllStates[State],Table_SourceData_PastureBeef_LiveweightGainAllStates[Region],Table_SourceData_PastureBeef_LiveweightGainAllStates[Season],Table_SourceData_PastureBeef_LiveweightGainAllStates[#Headers],Table_SourceData_PastureBeef_LiveweightGainAllStates[#Data],Table_AustralianStates[Common Name],Table_AustralianStates[Abbreviation]) -> #N/A | ... N85: =InputFunctions_PastureBeef.LookupLiveweightFromSeason($E$7,X_Cell_PastureBeef_ProductionRegion,$D85,N$82,Table_SourceData_PastureBeef_LiveweightGainAllStates[State],Table_SourceData_PastureBeef_LiveweightGainAllStates[Region],Table_SourceData_PastureBeef_LiveweightGainAllStates[Season],Table_SourceData_PastureBeef_LiveweightGainAllStates[#Headers],Table_SourceData_PastureBeef_LiveweightGainAllStates[#Data],Table_AustralianStates[Common Name],Table_AustralianStates[Abbreviation]) -> #N/A | O85: kg/head/day
D86: Winter | E86: =InputFunctions_PastureBeef.LookupLiveweightFromSeason($E$7,X_Cell_PastureBeef_ProductionRegion,$D86,E$82,Table_SourceData_PastureBeef_LiveweightGainAllStates[State],Table_SourceData_PastureBeef_LiveweightGainAllStates[Region],Table_SourceData_PastureBeef_LiveweightGainAllStates[Season],Table_SourceData_PastureBeef_LiveweightGainAllStates[#Headers],Table_SourceData_PastureBeef_LiveweightGainAllStates[#Data],Table_AustralianStates[Common Name],Table_AustralianStates[Abbreviation]) -> #N/A | F86: =InputFunctions_PastureBeef.LookupLiveweightFromSeason($E$7,X_Cell_PastureBeef_ProductionRegion,$D86,F$82,Table_SourceData_PastureBeef_LiveweightGainAllStates[State],Table_SourceData_PastureBeef_LiveweightGainAllStates[Region],Table_SourceData_PastureBeef_LiveweightGainAllStates[Season],Table_SourceData_PastureBeef_LiveweightGainAllStates[#Headers],Table_SourceData_PastureBeef_LiveweightGainAllStates[#Data],Table_AustralianStates[Common Name],Table_AustralianStates[Abbreviation]) -> #N/A | G86: =InputFunctions_PastureBeef.LookupLiveweightFromSeason($E$7,X_Cell_PastureBeef_ProductionRegion,$D86,G$82,Table_SourceData_PastureBeef_LiveweightGainAllStates[State],Table_SourceData_PastureBeef_LiveweightGainAllStates[Region],Table_SourceData_PastureBeef_LiveweightGainAllStates[Season],Table_SourceData_PastureBeef_LiveweightGainAllStates[#Headers],Table_SourceData_PastureBeef_LiveweightGainAllStates[#Data],Table_AustralianStates[Common Name],Table_AustralianStates[Abbreviation]) -> #N/A | H86: =InputFunctions_PastureBeef.LookupLiveweightFromSeason($E$7,X_Cell_PastureBeef_ProductionRegion,$D86,H$82,Table_SourceData_PastureBeef_LiveweightGainAllStates[State],Table_SourceData_PastureBeef_LiveweightGainAllStates[Region],Table_SourceData_PastureBeef_LiveweightGainAllStates[Season],Table_SourceData_PastureBeef_LiveweightGainAllStates[#Headers],Table_SourceData_PastureBeef_LiveweightGainAllStates[#Data],Table_AustralianStates[Common Name],Table_AustralianStates[Abbreviation]) -> #N/A | I86: =InputFunctions_PastureBeef.LookupLiveweightFromSeason($E$7,X_Cell_PastureBeef_ProductionRegion,$D86,I$82,Table_SourceData_PastureBeef_LiveweightGainAllStates[State],Table_SourceData_PastureBeef_LiveweightGainAllStates[Region],Table_SourceData_PastureBeef_LiveweightGainAllStates[Season],Table_SourceData_PastureBeef_LiveweightGainAllStates[#Headers],Table_SourceData_PastureBeef_LiveweightGainAllStates[#Data],Table_AustralianStates[Common Name],Table_AustralianStates[Abbreviation]) -> #N/A | J86: =InputFunctions_PastureBeef.LookupLiveweightFromSeason($E$7,X_Cell_PastureBeef_ProductionRegion,$D86,J$82,Table_SourceData_PastureBeef_LiveweightGainAllStates[State],Table_SourceData_PastureBeef_LiveweightGainAllStates[Region],Table_SourceData_PastureBeef_LiveweightGainAllStates[Season],Table_SourceData_PastureBeef_LiveweightGainAllStates[#Headers],Table_SourceData_PastureBeef_LiveweightGainAllStates[#Data],Table_AustralianStates[Common Name],Table_AustralianStates[Abbreviation]) -> #N/A | K86: =InputFunctions_PastureBeef.LookupLiveweightFromSeason($E$7,X_Cell_PastureBeef_ProductionRegion,$D86,K$82,Table_SourceData_PastureBeef_LiveweightGainAllStates[State],Table_SourceData_PastureBeef_LiveweightGainAllStates[Region],Table_SourceData_PastureBeef_LiveweightGainAllStates[Season],Table_SourceData_PastureBeef_LiveweightGainAllStates[#Headers],Table_SourceData_PastureBeef_LiveweightGainAllStates[#Data],Table_AustralianStates[Common Name],Table_AustralianStates[Abbreviation]) -> #N/A | L86: =InputFunctions_PastureBeef.LookupLiveweightFromSeason($E$7,X_Cell_PastureBeef_ProductionRegion,$D86,L$82,Table_SourceData_PastureBeef_LiveweightGainAllStates[State],Table_SourceData_PastureBeef_LiveweightGainAllStates[Region],Table_SourceData_PastureBeef_LiveweightGainAllStates[Season],Table_SourceData_PastureBeef_LiveweightGainAllStates[#Headers],Table_SourceData_PastureBeef_LiveweightGainAllStates[#Data],Table_AustralianStates[Common Name],Table_AustralianStates[Abbreviation]) -> #N/A | ... N86: =InputFunctions_PastureBeef.LookupLiveweightFromSeason($E$7,X_Cell_PastureBeef_ProductionRegion,$D86,N$82,Table_SourceData_PastureBeef_LiveweightGainAllStates[State],Table_SourceData_PastureBeef_LiveweightGainAllStates[Region],Table_SourceData_PastureBeef_LiveweightGainAllStates[Season],Table_SourceData_PastureBeef_LiveweightGainAllStates[#Headers],Table_SourceData_PastureBeef_LiveweightGainAllStates[#Data],Table_AustralianStates[Common Name],Table_AustralianStates[Abbreviation]) -> #N/A | O86: kg/head/day
D88: Method 2 custom values (edit if known) | E88: Bulls < 1 year | F88: Bulls > 1 year | G88: Cows < 1 year | H88: Cows 1-2 years | I88: Cows 2-3 years | J88: Cows > 3 years | K88: Steers < 1 year | L88: Steers 1-2 years | M88: Steers 2-3 years | N88: Steers >3 years
D89: =TEXT(X_Cell_Site_StartDate, "mmmm yyyy") -> January 1900 | E89: =InputFunctions_PastureBeef.LookupLiveweightFromMonth($E$7,X_Cell_PastureBeef_ProductionRegion,$D89,E$88,Table_SourceData_PastureBeef_LiveweightGainAllStates[State],Table_SourceData_PastureBeef_LiveweightGainAllStates[Region],Table_SourceData_PastureBeef_LiveweightGainAllStates[Season],Table_SourceData_PastureBeef_LiveweightGainAllStates[#Headers],Table_SourceData_PastureBeef_LiveweightGainAllStates[#Data],Table_AustralianStates[Common Name],Table_AustralianStates[Abbreviation],Table_SourceData_Common_MonthToSeason[Month],Table_SourceData_Common_MonthToSeason[Season]) -> #N/A | F89: =InputFunctions_PastureBeef.LookupLiveweightFromMonth($E$7,X_Cell_PastureBeef_ProductionRegion,$D89,F$88,Table_SourceData_PastureBeef_LiveweightGainAllStates[State],Table_SourceData_PastureBeef_LiveweightGainAllStates[Region],Table_SourceData_PastureBeef_LiveweightGainAllStates[Season],Table_SourceData_PastureBeef_LiveweightGainAllStates[#Headers],Table_SourceData_PastureBeef_LiveweightGainAllStates[#Data],Table_AustralianStates[Common Name],Table_AustralianStates[Abbreviation],Table_SourceData_Common_MonthToSeason[Month],Table_SourceData_Common_MonthToSeason[Season]) -> #N/A | G89: =InputFunctions_PastureBeef.LookupLiveweightFromMonth($E$7,X_Cell_PastureBeef_ProductionRegion,$D89,G$88,Table_SourceData_PastureBeef_LiveweightGainAllStates[State],Table_SourceData_PastureBeef_LiveweightGainAllStates[Region],Table_SourceData_PastureBeef_LiveweightGainAllStates[Season],Table_SourceData_PastureBeef_LiveweightGainAllStates[#Headers],Table_SourceData_PastureBeef_LiveweightGainAllStates[#Data],Table_AustralianStates[Common Name],Table_AustralianStates[Abbreviation],Table_SourceData_Common_MonthToSeason[Month],Table_SourceData_Common_MonthToSeason[Season]) -> #N/A | H89: =InputFunctions_PastureBeef.LookupLiveweightFromMonth($E$7,X_Cell_PastureBeef_ProductionRegion,$D89,H$88,Table_SourceData_PastureBeef_LiveweightGainAllStates[State],Table_SourceData_PastureBeef_LiveweightGainAllStates[Region],Table_SourceData_PastureBeef_LiveweightGainAllStates[Season],Table_SourceData_PastureBeef_LiveweightGainAllStates[#Headers],Table_SourceData_PastureBeef_LiveweightGainAllStates[#Data],Table_AustralianStates[Common Name],Table_AustralianStates[Abbreviation],Table_SourceData_Common_MonthToSeason[Month],Table_SourceData_Common_MonthToSeason[Season]) -> #N/A | I89: =InputFunctions_PastureBeef.LookupLiveweightFromMonth($E$7,X_Cell_PastureBeef_ProductionRegion,$D89,I$88,Table_SourceData_PastureBeef_LiveweightGainAllStates[State],Table_SourceData_PastureBeef_LiveweightGainAllStates[Region],Table_SourceData_PastureBeef_LiveweightGainAllStates[Season],Table_SourceData_PastureBeef_LiveweightGainAllStates[#Headers],Table_SourceData_PastureBeef_LiveweightGainAllStates[#Data],Table_AustralianStates[Common Name],Table_AustralianStates[Abbreviation],Table_SourceData_Common_MonthToSeason[Month],Table_SourceData_Common_MonthToSeason[Season]) -> #N/A | J89: =InputFunctions_PastureBeef.LookupLiveweightFromMonth($E$7,X_Cell_PastureBeef_ProductionRegion,$D89,J$88,Table_SourceData_PastureBeef_LiveweightGainAllStates[State],Table_SourceData_PastureBeef_LiveweightGainAllStates[Region],Table_SourceData_PastureBeef_LiveweightGainAllStates[Season],Table_SourceData_PastureBeef_LiveweightGainAllStates[#Headers],Table_SourceData_PastureBeef_LiveweightGainAllStates[#Data],Table_AustralianStates[Common Name],Table_AustralianStates[Abbreviation],Table_SourceData_Common_MonthToSeason[Month],Table_SourceData_Common_MonthToSeason[Season]) -> #N/A | K89: =InputFunctions_PastureBeef.LookupLiveweightFromMonth($E$7,X_Cell_PastureBeef_ProductionRegion,$D89,K$88,Table_SourceData_PastureBeef_LiveweightGainAllStates[State],Table_SourceData_PastureBeef_LiveweightGainAllStates[Region],Table_SourceData_PastureBeef_LiveweightGainAllStates[Season],Table_SourceData_PastureBeef_LiveweightGainAllStates[#Headers],Table_SourceData_PastureBeef_LiveweightGainAllStates[#Data],Table_AustralianStates[Common Name],Table_AustralianStates[Abbreviation],Table_SourceData_Common_MonthToSeason[Month],Table_SourceData_Common_MonthToSeason[Season]) -> #N/A | L89: =InputFunctions_PastureBeef.LookupLiveweightFromMonth($E$7,X_Cell_PastureBeef_ProductionRegion,$D89,L$88,Table_SourceData_PastureBeef_LiveweightGainAllStates[State],Table_SourceData_PastureBeef_LiveweightGainAllStates[Region],Table_SourceData_PastureBeef_LiveweightGainAllStates[Season],Table_SourceData_PastureBeef_LiveweightGainAllStates[#Headers],Table_SourceData_PastureBeef_LiveweightGainAllStates[#Data],Table_AustralianStates[Common Name],Table_AustralianStates[Abbreviation],Table_SourceData_Common_MonthToSeason[Month],Table_SourceData_Common_MonthToSeason[Season]) -> #N/A | ... N89: =InputFunctions_PastureBeef.LookupLiveweightFromMonth($E$7,X_Cell_PastureBeef_ProductionRegion,$D89,N$88,Table_SourceData_PastureBeef_LiveweightGainAllStates[State],Table_SourceData_PastureBeef_LiveweightGainAllStates[Region],Table_SourceData_PastureBeef_LiveweightGainAllStates[Season],Table_SourceData_PastureBeef_LiveweightGainAllStates[#Headers],Table_SourceData_PastureBeef_LiveweightGainAllStates[#Data],Table_AustralianStates[Common Name],Table_AustralianStates[Abbreviation],Table_SourceData_Common_MonthToSeason[Month],Table_SourceData_Common_MonthToSeason[Season]) -> #N/A | O89: kg/head/day
D90: =TEXT(EDATE(X_Cell_Site_StartDate,1), "mmmm yyyy") -> January 1900 | E90: =InputFunctions_PastureBeef.LookupLiveweightFromMonth($E$7,X_Cell_PastureBeef_ProductionRegion,$D90,E$88,Table_SourceData_PastureBeef_LiveweightGainAllStates[State],Table_SourceData_PastureBeef_LiveweightGainAllStates[Region],Table_SourceData_PastureBeef_LiveweightGainAllStates[Season],Table_SourceData_PastureBeef_LiveweightGainAllStates[#Headers],Table_SourceData_PastureBeef_LiveweightGainAllStates[#Data],Table_AustralianStates[Common Name],Table_AustralianStates[Abbreviation],Table_SourceData_Common_MonthToSeason[Month],Table_SourceData_Common_MonthToSeason[Season]) -> #N/A | F90: =InputFunctions_PastureBeef.LookupLiveweightFromMonth($E$7,X_Cell_PastureBeef_ProductionRegion,$D90,F$88,Table_SourceData_PastureBeef_LiveweightGainAllStates[State],Table_SourceData_PastureBeef_LiveweightGainAllStates[Region],Table_SourceData_PastureBeef_LiveweightGainAllStates[Season],Table_SourceData_PastureBeef_LiveweightGainAllStates[#Headers],Table_SourceData_PastureBeef_LiveweightGainAllStates[#Data],Table_AustralianStates[Common Name],Table_AustralianStates[Abbreviation],Table_SourceData_Common_MonthToSeason[Month],Table_SourceData_Common_MonthToSeason[Season]) -> #N/A | G90: =InputFunctions_PastureBeef.LookupLiveweightFromMonth($E$7,X_Cell_PastureBeef_ProductionRegion,$D90,G$88,Table_SourceData_PastureBeef_LiveweightGainAllStates[State],Table_SourceData_PastureBeef_LiveweightGainAllStates[Region],Table_SourceData_PastureBeef_LiveweightGainAllStates[Season],Table_SourceData_PastureBeef_LiveweightGainAllStates[#Headers],Table_SourceData_PastureBeef_LiveweightGainAllStates[#Data],Table_AustralianStates[Common Name],Table_AustralianStates[Abbreviation],Table_SourceData_Common_MonthToSeason[Month],Table_SourceData_Common_MonthToSeason[Season]) -> #N/A | H90: =InputFunctions_PastureBeef.LookupLiveweightFromMonth($E$7,X_Cell_PastureBeef_ProductionRegion,$D90,H$88,Table_SourceData_PastureBeef_LiveweightGainAllStates[State],Table_SourceData_PastureBeef_LiveweightGainAllStates[Region],Table_SourceData_PastureBeef_LiveweightGainAllStates[Season],Table_SourceData_PastureBeef_LiveweightGainAllStates[#Headers],Table_SourceData_PastureBeef_LiveweightGainAllStates[#Data],Table_AustralianStates[Common Name],Table_AustralianStates[Abbreviation],Table_SourceData_Common_MonthToSeason[Month],Table_SourceData_Common_MonthToSeason[Season]) -> #N/A | I90: =InputFunctions_PastureBeef.LookupLiveweightFromMonth($E$7,X_Cell_PastureBeef_ProductionRegion,$D90,I$88,Table_SourceData_PastureBeef_LiveweightGainAllStates[State],Table_SourceData_PastureBeef_LiveweightGainAllStates[Region],Table_SourceData_PastureBeef_LiveweightGainAllStates[Season],Table_SourceData_PastureBeef_LiveweightGainAllStates[#Headers],Table_SourceData_PastureBeef_LiveweightGainAllStates[#Data],Table_AustralianStates[Common Name],Table_AustralianStates[Abbreviation],Table_SourceData_Common_MonthToSeason[Month],Table_SourceData_Common_MonthToSeason[Season]) -> #N/A | J90: =InputFunctions_PastureBeef.LookupLiveweightFromMonth($E$7,X_Cell_PastureBeef_ProductionRegion,$D90,J$88,Table_SourceData_PastureBeef_LiveweightGainAllStates[State],Table_SourceData_PastureBeef_LiveweightGainAllStates[Region],Table_SourceData_PastureBeef_LiveweightGainAllStates[Season],Table_SourceData_PastureBeef_LiveweightGainAllStates[#Headers],Table_SourceData_PastureBeef_LiveweightGainAllStates[#Data],Table_AustralianStates[Common Name],Table_AustralianStates[Abbreviation],Table_SourceData_Common_MonthToSeason[Month],Table_SourceData_Common_MonthToSeason[Season]) -> #N/A | K90: =InputFunctions_PastureBeef.LookupLiveweightFromMonth($E$7,X_Cell_PastureBeef_ProductionRegion,$D90,K$88,Table_SourceData_PastureBeef_LiveweightGainAllStates[State],Table_SourceData_PastureBeef_LiveweightGainAllStates[Region],Table_SourceData_PastureBeef_LiveweightGainAllStates[Season],Table_SourceData_PastureBeef_LiveweightGainAllStates[#Headers],Table_SourceData_PastureBeef_LiveweightGainAllStates[#Data],Table_AustralianStates[Common Name],Table_AustralianStates[Abbreviation],Table_SourceData_Common_MonthToSeason[Month],Table_SourceData_Common_MonthToSeason[Season]) -> #N/A | L90: =InputFunctions_PastureBeef.LookupLiveweightFromMonth($E$7,X_Cell_PastureBeef_ProductionRegion,$D90,L$88,Table_SourceData_PastureBeef_LiveweightGainAllStates[State],Table_SourceData_PastureBeef_LiveweightGainAllStates[Region],Table_SourceData_PastureBeef_LiveweightGainAllStates[Season],Table_SourceData_PastureBeef_LiveweightGainAllStates[#Headers],Table_SourceData_PastureBeef_LiveweightGainAllStates[#Data],Table_AustralianStates[Common Name],Table_AustralianStates[Abbreviation],Table_SourceData_Common_MonthToSeason[Month],Table_SourceData_Common_MonthToSeason[Season]) -> #N/A | ... N90: =InputFunctions_PastureBeef.LookupLiveweightFromMonth($E$7,X_Cell_PastureBeef_ProductionRegion,$D90,N$88,Table_SourceData_PastureBeef_LiveweightGainAllStates[State],Table_SourceData_PastureBeef_LiveweightGainAllStates[Region],Table_SourceData_PastureBeef_LiveweightGainAllStates[Season],Table_SourceData_PastureBeef_LiveweightGainAllStates[#Headers],Table_SourceData_PastureBeef_LiveweightGainAllStates[#Data],Table_AustralianStates[Common Name],Table_AustralianStates[Abbreviation],Table_SourceData_Common_MonthToSeason[Month],Table_SourceData_Common_MonthToSeason[Season]) -> #N/A | O90: kg/head/day
D91: =TEXT(EDATE(X_Cell_Site_StartDate,2), "mmmm yyyy") -> February 1900 | E91: =InputFunctions_PastureBeef.LookupLiveweightFromMonth($E$7,X_Cell_PastureBeef_ProductionRegion,$D91,E$88,Table_SourceData_PastureBeef_LiveweightGainAllStates[State],Table_SourceData_PastureBeef_LiveweightGainAllStates[Region],Table_SourceData_PastureBeef_LiveweightGainAllStates[Season],Table_SourceData_PastureBeef_LiveweightGainAllStates[#Headers],Table_SourceData_PastureBeef_LiveweightGainAllStates[#Data],Table_AustralianStates[Common Name],Table_AustralianStates[Abbreviation],Table_SourceData_Common_MonthToSeason[Month],Table_SourceData_Common_MonthToSeason[Season]) -> #N/A | F91: =InputFunctions_PastureBeef.LookupLiveweightFromMonth($E$7,X_Cell_PastureBeef_ProductionRegion,$D91,F$88,Table_SourceData_PastureBeef_LiveweightGainAllStates[State],Table_SourceData_PastureBeef_LiveweightGainAllStates[Region],Table_SourceData_PastureBeef_LiveweightGainAllStates[Season],Table_SourceData_PastureBeef_LiveweightGainAllStates[#Headers],Table_SourceData_PastureBeef_LiveweightGainAllStates[#Data],Table_AustralianStates[Common Name],Table_AustralianStates[Abbreviation],Table_SourceData_Common_MonthToSeason[Month],Table_SourceData_Common_MonthToSeason[Season]) -> #N/A | G91: =InputFunctions_PastureBeef.LookupLiveweightFromMonth($E$7,X_Cell_PastureBeef_ProductionRegion,$D91,G$88,Table_SourceData_PastureBeef_LiveweightGainAllStates[State],Table_SourceData_PastureBeef_LiveweightGainAllStates[Region],Table_SourceData_PastureBeef_LiveweightGainAllStates[Season],Table_SourceData_PastureBeef_LiveweightGainAllStates[#Headers],Table_SourceData_PastureBeef_LiveweightGainAllStates[#Data],Table_AustralianStates[Common Name],Table_AustralianStates[Abbreviation],Table_SourceData_Common_MonthToSeason[Month],Table_SourceData_Common_MonthToSeason[Season]) -> #N/A | H91: =InputFunctions_PastureBeef.LookupLiveweightFromMonth($E$7,X_Cell_PastureBeef_ProductionRegion,$D91,H$88,Table_SourceData_PastureBeef_LiveweightGainAllStates[State],Table_SourceData_PastureBeef_LiveweightGainAllStates[Region],Table_SourceData_PastureBeef_LiveweightGainAllStates[Season],Table_SourceData_PastureBeef_LiveweightGainAllStates[#Headers],Table_SourceData_PastureBeef_LiveweightGainAllStates[#Data],Table_AustralianStates[Common Name],Table_AustralianStates[Abbreviation],Table_SourceData_Common_MonthToSeason[Month],Table_SourceData_Common_MonthToSeason[Season]) -> #N/A | I91: =InputFunctions_PastureBeef.LookupLiveweightFromMonth($E$7,X_Cell_PastureBeef_ProductionRegion,$D91,I$88,Table_SourceData_PastureBeef_LiveweightGainAllStates[State],Table_SourceData_PastureBeef_LiveweightGainAllStates[Region],Table_SourceData_PastureBeef_LiveweightGainAllStates[Season],Table_SourceData_PastureBeef_LiveweightGainAllStates[#Headers],Table_SourceData_PastureBeef_LiveweightGainAllStates[#Data],Table_AustralianStates[Common Name],Table_AustralianStates[Abbreviation],Table_SourceData_Common_MonthToSeason[Month],Table_SourceData_Common_MonthToSeason[Season]) -> #N/A | J91: =InputFunctions_PastureBeef.LookupLiveweightFromMonth($E$7,X_Cell_PastureBeef_ProductionRegion,$D91,J$88,Table_SourceData_PastureBeef_LiveweightGainAllStates[State],Table_SourceData_PastureBeef_LiveweightGainAllStates[Region],Table_SourceData_PastureBeef_LiveweightGainAllStates[Season],Table_SourceData_PastureBeef_LiveweightGainAllStates[#Headers],Table_SourceData_PastureBeef_LiveweightGainAllStates[#Data],Table_AustralianStates[Common Name],Table_AustralianStates[Abbreviation],Table_SourceData_Common_MonthToSeason[Month],Table_SourceData_Common_MonthToSeason[Season]) -> #N/A | K91: =InputFunctions_PastureBeef.LookupLiveweightFromMonth($E$7,X_Cell_PastureBeef_ProductionRegion,$D91,K$88,Table_SourceData_PastureBeef_LiveweightGainAllStates[State],Table_SourceData_PastureBeef_LiveweightGainAllStates[Region],Table_SourceData_PastureBeef_LiveweightGainAllStates[Season],Table_SourceData_PastureBeef_LiveweightGainAllStates[#Headers],Table_SourceData_PastureBeef_LiveweightGainAllStates[#Data],Table_AustralianStates[Common Name],Table_AustralianStates[Abbreviation],Table_SourceData_Common_MonthToSeason[Month],Table_SourceData_Common_MonthToSeason[Season]) -> #N/A | L91: =InputFunctions_PastureBeef.LookupLiveweightFromMonth($E$7,X_Cell_PastureBeef_ProductionRegion,$D91,L$88,Table_SourceData_PastureBeef_LiveweightGainAllStates[State],Table_SourceData_PastureBeef_LiveweightGainAllStates[Region],Table_SourceData_PastureBeef_LiveweightGainAllStates[Season],Table_SourceData_PastureBeef_LiveweightGainAllStates[#Headers],Table_SourceData_PastureBeef_LiveweightGainAllStates[#Data],Table_AustralianStates[Common Name],Table_AustralianStates[Abbreviation],Table_SourceData_Common_MonthToSeason[Month],Table_SourceData_Common_MonthToSeason[Season]) -> #N/A | ... N91: =InputFunctions_PastureBeef.LookupLiveweightFromMonth($E$7,X_Cell_PastureBeef_ProductionRegion,$D91,N$88,Table_SourceData_PastureBeef_LiveweightGainAllStates[State],Table_SourceData_PastureBeef_LiveweightGainAllStates[Region],Table_SourceData_PastureBeef_LiveweightGainAllStates[Season],Table_SourceData_PastureBeef_LiveweightGainAllStates[#Headers],Table_SourceData_PastureBeef_LiveweightGainAllStates[#Data],Table_AustralianStates[Common Name],Table_AustralianStates[Abbreviation],Table_SourceData_Common_MonthToSeason[Month],Table_SourceData_Common_MonthToSeason[Season]) -> #N/A | O91: kg/head/day
D92: =TEXT(EDATE(X_Cell_Site_StartDate,3), "mmmm yyyy") -> March 1900 | E92: =InputFunctions_PastureBeef.LookupLiveweightFromMonth($E$7,X_Cell_PastureBeef_ProductionRegion,$D92,E$88,Table_SourceData_PastureBeef_LiveweightGainAllStates[State],Table_SourceData_PastureBeef_LiveweightGainAllStates[Region],Table_SourceData_PastureBeef_LiveweightGainAllStates[Season],Table_SourceData_PastureBeef_LiveweightGainAllStates[#Headers],Table_SourceData_PastureBeef_LiveweightGainAllStates[#Data],Table_AustralianStates[Common Name],Table_AustralianStates[Abbreviation],Table_SourceData_Common_MonthToSeason[Month],Table_SourceData_Common_MonthToSeason[Season]) -> #N/A | F92: =InputFunctions_PastureBeef.LookupLiveweightFromMonth($E$7,X_Cell_PastureBeef_ProductionRegion,$D92,F$88,Table_SourceData_PastureBeef_LiveweightGainAllStates[State],Table_SourceData_PastureBeef_LiveweightGainAllStates[Region],Table_SourceData_PastureBeef_LiveweightGainAllStates[Season],Table_SourceData_PastureBeef_LiveweightGainAllStates[#Headers],Table_SourceData_PastureBeef_LiveweightGainAllStates[#Data],Table_AustralianStates[Common Name],Table_AustralianStates[Abbreviation],Table_SourceData_Common_MonthToSeason[Month],Table_SourceData_Common_MonthToSeason[Season]) -> #N/A | G92: =InputFunctions_PastureBeef.LookupLiveweightFromMonth($E$7,X_Cell_PastureBeef_ProductionRegion,$D92,G$88,Table_SourceData_PastureBeef_LiveweightGainAllStates[State],Table_SourceData_PastureBeef_LiveweightGainAllStates[Region],Table_SourceData_PastureBeef_LiveweightGainAllStates[Season],Table_SourceData_PastureBeef_LiveweightGainAllStates[#Headers],Table_SourceData_PastureBeef_LiveweightGainAllStates[#Data],Table_AustralianStates[Common Name],Table_AustralianStates[Abbreviation],Table_SourceData_Common_MonthToSeason[Month],Table_SourceData_Common_MonthToSeason[Season]) -> #N/A | H92: =InputFunctions_PastureBeef.LookupLiveweightFromMonth($E$7,X_Cell_PastureBeef_ProductionRegion,$D92,H$88,Table_SourceData_PastureBeef_LiveweightGainAllStates[State],Table_SourceData_PastureBeef_LiveweightGainAllStates[Region],Table_SourceData_PastureBeef_LiveweightGainAllStates[Season],Table_SourceData_PastureBeef_LiveweightGainAllStates[#Headers],Table_SourceData_PastureBeef_LiveweightGainAllStates[#Data],Table_AustralianStates[Common Name],Table_AustralianStates[Abbreviation],Table_SourceData_Common_MonthToSeason[Month],Table_SourceData_Common_MonthToSeason[Season]) -> #N/A | I92: =InputFunctions_PastureBeef.LookupLiveweightFromMonth($E$7,X_Cell_PastureBeef_ProductionRegion,$D92,I$88,Table_SourceData_PastureBeef_LiveweightGainAllStates[State],Table_SourceData_PastureBeef_LiveweightGainAllStates[Region],Table_SourceData_PastureBeef_LiveweightGainAllStates[Season],Table_SourceData_PastureBeef_LiveweightGainAllStates[#Headers],Table_SourceData_PastureBeef_LiveweightGainAllStates[#Data],Table_AustralianStates[Common Name],Table_AustralianStates[Abbreviation],Table_SourceData_Common_MonthToSeason[Month],Table_SourceData_Common_MonthToSeason[Season]) -> #N/A | J92: =InputFunctions_PastureBeef.LookupLiveweightFromMonth($E$7,X_Cell_PastureBeef_ProductionRegion,$D92,J$88,Table_SourceData_PastureBeef_LiveweightGainAllStates[State],Table_SourceData_PastureBeef_LiveweightGainAllStates[Region],Table_SourceData_PastureBeef_LiveweightGainAllStates[Season],Table_SourceData_PastureBeef_LiveweightGainAllStates[#Headers],Table_SourceData_PastureBeef_LiveweightGainAllStates[#Data],Table_AustralianStates[Common Name],Table_AustralianStates[Abbreviation],Table_SourceData_Common_MonthToSeason[Month],Table_SourceData_Common_MonthToSeason[Season]) -> #N/A | K92: =InputFunctions_PastureBeef.LookupLiveweightFromMonth($E$7,X_Cell_PastureBeef_ProductionRegion,$D92,K$88,Table_SourceData_PastureBeef_LiveweightGainAllStates[State],Table_SourceData_PastureBeef_LiveweightGainAllStates[Region],Table_SourceData_PastureBeef_LiveweightGainAllStates[Season],Table_SourceData_PastureBeef_LiveweightGainAllStates[#Headers],Table_SourceData_PastureBeef_LiveweightGainAllStates[#Data],Table_AustralianStates[Common Name],Table_AustralianStates[Abbreviation],Table_SourceData_Common_MonthToSeason[Month],Table_SourceData_Common_MonthToSeason[Season]) -> #N/A | L92: =InputFunctions_PastureBeef.LookupLiveweightFromMonth($E$7,X_Cell_PastureBeef_ProductionRegion,$D92,L$88,Table_SourceData_PastureBeef_LiveweightGainAllStates[State],Table_SourceData_PastureBeef_LiveweightGainAllStates[Region],Table_SourceData_PastureBeef_LiveweightGainAllStates[Season],Table_SourceData_PastureBeef_LiveweightGainAllStates[#Headers],Table_SourceData_PastureBeef_LiveweightGainAllStates[#Data],Table_AustralianStates[Common Name],Table_AustralianStates[Abbreviation],Table_SourceData_Common_MonthToSeason[Month],Table_SourceData_Common_MonthToSeason[Season]) -> #N/A | ... N92: =InputFunctions_PastureBeef.LookupLiveweightFromMonth($E$7,X_Cell_PastureBeef_ProductionRegion,$D92,N$88,Table_SourceData_PastureBeef_LiveweightGainAllStates[State],Table_SourceData_PastureBeef_LiveweightGainAllStates[Region],Table_SourceData_PastureBeef_LiveweightGainAllStates[Season],Table_SourceData_PastureBeef_LiveweightGainAllStates[#Headers],Table_SourceData_PastureBeef_LiveweightGainAllStates[#Data],Table_AustralianStates[Common Name],Table_AustralianStates[Abbreviation],Table_SourceData_Common_MonthToSeason[Month],Table_SourceData_Common_MonthToSeason[Season]) -> #N/A | O92: kg/head/day
