Workbook
Name _Toc225350871: '5.4.1.1-4 Atmos deposition'!$C$1
Name _Toc225350871: '5.5.1.1-2 Leaching and runoff'!$C$1
Name AgResidue_Equations_CropResidue.VEERG_6_1_1_1__1__NitrousOxideEmissionsFromCropResidues: _xlfn.LAMBDA(_xlpm.M_c,_xlpm.EF_Ni,_xlpm.C_N2O, _xlpm.M_c * _xlpm.EF_Ni * _xlpm.C_N2O * 10 ^ (-3))
Name AgResidue_Equations_CropResidue.VEERG_6_1_1_1__1__NitrousOxideEmissionsFromCropResidues_FunctionName: _xlfn.LAMBDA("VEERG_6_1_1_1__1__NitrousOxideEmissionsFromCropResidues")
Name AgResidue_Equations_CropResidue.VEERG_6_1_1_1__1__NitrousOxideEmissionsFromCropResidues_LatexEquation: _xlfn.LAMBDA("E=\sum\nolimits_c\left(M_{c}\times EF_{N}\right)\times C_{g,N2O}\times 10^{-3}")
Name AgResidue_Equations_CropResidue.VEERG_6_1_1_1__1__NitrousOxideEmissionsFromCropResidues_NIRReference: _xlfn.LAMBDA("")
Name AgResidue_Equations_CropResidue.VEERG_6_1_1_1__1__NitrousOxideEmissionsFromCropResidues_Source: _xlfn.LAMBDA("VEERG 2026: 6.1.1.1, Equation (1)")
Name AgResidue_Equations_CropResidue.VEERG_6_1_1_1__1__NitrousOxideEmissionsFromCropResidues_Title: _xlfn.LAMBDA("Nitrous oxide emissions from the return of crop residues across all crops c to the soil")
Name AgResidue_Equations_CropResidue.VEERG_6_1_1_1__1__NitrousOxideEmissionsFromCropResidues_Unit: _xlfn.LAMBDA("t N2O")
Name AgResidue_Equations_CropResidue.VEERG_6_1_1_1__1__NitrousOxideEmissionsFromCropResidues_Variable: _xlfn.LAMBDA("E")
Name AgResidue_Equations_CropResidue.VEERG_6_1_1_1__2__MassOfNitrogenInCropResidues_LatexEquation: _xlfn.LAMBDA("M_{c}=(P_{c}\times R_{AGc}\times(1-F_{c}-FFOD_{c})\times DM_{c}\times NC_{AGc})+(P_{c}\times R_{AGc}\times R_{BGc}\times DM_{c}\times NC_{BGc})")
Name AgResidue_Equations_CropResidue.VEERG_6_1_1_1__2__MassOfNitrogenInCropResidues_NIRReference: _xlfn.LAMBDA("")
Name AgResidue_Equations_CropResidue.VEERG_6_1_1_1__2__MassOfNitrogenInCropResidues_Source: _xlfn.LAMBDA("VEERG 2026: 6.1.1.1, Equation (2)")
Name AgResidue_Equations_CropResidue.VEERG_6_1_1_1__2__MassOfNitrogenInCropResidues_Title: _xlfn.LAMBDA("Mass of nitrogen in crop residues returned to the soil")
Name AgResidue_Equations_CropResidue.VEERG_6_1_1_1__2__MassOfNitrogenInCropResidues_Unit: _xlfn.LAMBDA("kg N")
Name AgResidue_Equations_CropResidue.VEERG_6_1_1_1__2__MassOfNitrogenInCropResidues_Variable: _xlfn.LAMBDA("M_c")
Name AgResidue_Equations_CropResidue.VEERG_6_1_1_2__1__FractionOfCropResidueRemovedBaled: _xlfn.LAMBDA(_xlpm.B,_xlpm.M_B,_xlpm.P_c,_xlpm.R_AGc, IFERROR((_xlpm.B * _xlpm.M_B) / (_xlpm.P_c * _xlpm.R_AGc), 0))
Name AgResidue_Equations_CropResidue.VEERG_6_1_1_2__1__FractionOfCropResidueRemovedBaled_LatexEquation: _xlfn.LAMBDA("FFOD_{c}=\frac{B\times M_{B}}{P_{c}\times R_{AG,c}}")
Name AgResidue_Equations_CropResidue.VEERG_6_1_1_2__1__FractionOfCropResidueRemovedBaled_NIRReference: _xlfn.LAMBDA("")
Name AgResidue_Equations_CropResidue.VEERG_6_1_1_2__1__FractionOfCropResidueRemovedBaled_Source: _xlfn.LAMBDA("VEERG 2026: 6.1.1.2, Equation (1)")
Name AgResidue_Equations_CropResidue.VEERG_6_1_1_2__1__FractionOfCropResidueRemovedBaled_Title: _xlfn.LAMBDA("Fraction of crop residue that is removed for crop c, calculated where residues are baled")
Name AgResidue_Equations_CropResidue.VEERG_6_1_1_2__1__FractionOfCropResidueRemovedBaled_Unit: _xlfn.LAMBDA("fraction")
Name AgResidue_Equations_CropResidue.VEERG_6_1_1_2__1__FractionOfCropResidueRemovedBaled_Variable: _xlfn.LAMBDA("FFOD_c")
Name AgResidue_Equations_CropResidue.VEERG_6_1_1_2__1__FractionOfCropResidueRemovedBaled_Variation: _xlfn.LAMBDA("")
Name AgResidue_Equations_FieldBurning.VEERG_6_4_1_1__1__MethaneEmissionsFromBurningOfCropResidues: _xlfn.LAMBDA(_xlpm.Mburnc,_xlpm.CCc,_xlpm.EFCH4,_xlpm.C_CH4, _xlpm.Mburnc * _xlpm.CCc * _xlpm.EFCH4 * _xlpm.C_CH4 * 10 ^ (-3))
Name AgResidue_Equations_FieldBurning.VEERG_6_4_1_1__1__MethaneEmissionsFromBurningOfCropResidues: _xlfn.LAMBDA(_xlpm.Mburnc,_xlpm.CCc,_xlpm.EFCH4,_xlpm.C_CH4, _xlpm.Mburnc * _xlpm.CCc * _xlpm.EFCH4 * _xlpm.C_CH4 * 10 ^ (-3))
Name AgResidue_Equations_FieldBurning.VEERG_6_4_1_1__1__MethaneEmissionsFromBurningOfCropResidues: _xlfn.LAMBDA(_xlpm.Mburnc,_xlpm.CCc,_xlpm.EFCH4,_xlpm.C_CH4, _xlpm.Mburnc * _xlpm.CCc * _xlpm.EFCH4 * _xlpm.C_CH4 * 10 ^ (-3))
Name AgResidue_Equations_FieldBurning.VEERG_6_4_1_1__1__MethaneEmissionsFromBurningOfCropResidues: _xlfn.LAMBDA(_xlpm.Mburnc,_xlpm.CCc,_xlpm.EFCH4,_xlpm.C_CH4, _xlpm.Mburnc * _xlpm.CCc * _xlpm.EFCH4 * _xlpm.C_CH4 * 10 ^ (-3))
Name AgResidue_Equations_FieldBurning.VEERG_6_4_1_1__1__MethaneEmissionsFromBurningOfCropResidues: _xlfn.LAMBDA(_xlpm.Mburnc,_xlpm.CCc,_xlpm.EFCH4,_xlpm.C_CH4, _xlpm.Mburnc * _xlpm.CCc * _xlpm.EFCH4 * _xlpm.C_CH4 * 10 ^ (-3))
Name AgResidue_Equations_FieldBurning.VEERG_6_4_1_1__1__MethaneEmissionsFromBurningOfCropResidues: _xlfn.LAMBDA(_xlpm.Mburnc,_xlpm.CCc,_xlpm.EFCH4,_xlpm.C_CH4, _xlpm.Mburnc * _xlpm.CCc * _xlpm.EFCH4 * _xlpm.C_CH4 * 10 ^ (-3))
Name AgResidue_Equations_FieldBurning.VEERG_6_4_1_1__1__MethaneEmissionsFromBurningOfCropResidues: _xlfn.LAMBDA(_xlpm.Mburnc,_xlpm.CCc,_xlpm.EFCH4,_xlpm.C_CH4, _xlpm.Mburnc * _xlpm.CCc * _xlpm.EFCH4 * _xlpm.C_CH4 * 10 ^ (-3))
Name AgResidue_Equations_FieldBurning.VEERG_6_4_1_1__1__MethaneEmissionsFromBurningOfCropResidues: _xlfn.LAMBDA(_xlpm.Mburnc,_xlpm.CCc,_xlpm.EFCH4,_xlpm.C_CH4, _xlpm.Mburnc * _xlpm.CCc * _xlpm.EFCH4 * _xlpm.C_CH4 * 10 ^ (-3))
Name AgResidue_Equations_FieldBurning.VEERG_6_4_1_1__1__MethaneEmissionsFromBurningOfCropResidues: _xlfn.LAMBDA(_xlpm.Mburnc,_xlpm.CCc,_xlpm.EFCH4,_xlpm.C_CH4, _xlpm.Mburnc * _xlpm.CCc * _xlpm.EFCH4 * _xlpm.C_CH4 * 10 ^ (-3))
Name AgResidue_Equations_FieldBurning.VEERG_6_4_1_1__1__MethaneEmissionsFromBurningOfCropResidues: _xlfn.LAMBDA(_xlpm.M_burnc,_xlpm.CC_c,_xlpm.EF_CH4,_xlpm.C_CH4, (_xlpm.M_burnc * _xlpm.CC_c) * _xlpm.EF_CH4 * _xlpm.C_CH4 * 10 ^ (-3))
Name AgResidue_Equations_FieldBurning.VEERG_6_4_1_1__1__MethaneEmissionsFromBurningOfCropResidues_FunctionName: _xlfn.LAMBDA("VEERG_6_4_1_1__1__MethaneEmissionsFromBurningOfCropResidues")
Name AgResidue_Equations_FieldBurning.VEERG_6_4_1_1__1__MethaneEmissionsFromBurningOfCropResidues_LatexEquation: _xlfn.LAMBDA("E_{CH4}=\sum_{c}(M_{burn,c}\times CC_{c}\times EF_{CH4}\times C_{CH4}\times 10^{-3})")
Name AgResidue_Equations_FieldBurning.VEERG_6_4_1_1__1__MethaneEmissionsFromBurningOfCropResidues_LatexEquation: _xlfn.LAMBDA("E_{CH4}=\sum_{c}(M_{burn,c}\times CC_{c}\times EF_{CH4}\times C_{CH4}\times 10^{-3})")
Name AgResidue_Equations_FieldBurning.VEERG_6_4_1_1__1__MethaneEmissionsFromBurningOfCropResidues_LatexEquation: _xlfn.LAMBDA("E_{CH4}=\sum_{c}(M_{burn,c}\times CC_{c}\times EF_{CH4}\times C_{CH4}\times 10^{-3})")
Name AgResidue_Equations_FieldBurning.VEERG_6_4_1_1__1__MethaneEmissionsFromBurningOfCropResidues_LatexEquation: _xlfn.LAMBDA("E_{CH4}=\sum_{c}(M_{burn,c}\times CC_{c}\times EF_{CH4}\times C_{CH4}\times 10^{-3})")
Name AgResidue_Equations_FieldBurning.VEERG_6_4_1_1__1__MethaneEmissionsFromBurningOfCropResidues_LatexEquation: _xlfn.LAMBDA("E_{CH4}=\sum_{c}(M_{burn,c}\times CC_{c}\times EF_{CH4}\times C_{CH4}\times 10^{-3})")
Name AgResidue_Equations_FieldBurning.VEERG_6_4_1_1__1__MethaneEmissionsFromBurningOfCropResidues_LatexEquation: _xlfn.LAMBDA("E_{CH4}=\sum_{c}(M_{burn,c}\times CC_{c}\times EF_{CH4}\times C_{CH4}\times 10^{-3})")
Name AgResidue_Equations_FieldBurning.VEERG_6_4_1_1__1__MethaneEmissionsFromBurningOfCropResidues_LatexEquation: _xlfn.LAMBDA("E_{CH4}=\sum_{c}(M_{burn,c}\times CC_{c}\times EF_{CH4}\times C_{CH4}\times 10^{-3})")
Name AgResidue_Equations_FieldBurning.VEERG_6_4_1_1__1__MethaneEmissionsFromBurningOfCropResidues_LatexEquation: _xlfn.LAMBDA("E_{CH4}=\sum_{c}(M_{burn,c}\times CC_{c}\times EF_{CH4}\times C_{CH4}\times 10^{-3})")
Name AgResidue_Equations_FieldBurning.VEERG_6_4_1_1__1__MethaneEmissionsFromBurningOfCropResidues_LatexEquation: _xlfn.LAMBDA("E_{CH4}=\sum_{c}(M_{burn,c}\times CC_{c}\times EF_{CH4}\times C_{CH4}\times 10^{-3})")
Name AgResidue_Equations_FieldBurning.VEERG_6_4_1_1__1__MethaneEmissionsFromBurningOfCropResidues_LatexEquation: _xlfn.LAMBDA("E_{CH4}=\sum\nolimits_c(M_{burn,c}\times CC_{c})\times EF_{CH4}\times C_{CH4}\times 10^{-3}")
Name AgResidue_Equations_FieldBurning.VEERG_6_4_1_1__1__MethaneEmissionsFromBurningOfCropResidues_NIRReference: _xlfn.LAMBDA("")
Name AgResidue_Equations_FieldBurning.VEERG_6_4_1_1__1__MethaneEmissionsFromBurningOfCropResidues_Source: _xlfn.LAMBDA("VEERG 2026: 6.4.1.1, Equation (1)")
Name AgResidue_Equations_FieldBurning.VEERG_6_4_1_1__1__MethaneEmissionsFromBurningOfCropResidues_Title: _xlfn.LAMBDA("Methane emissions from the burning of crop residues")
Name AgResidue_Equations_FieldBurning.VEERG_6_4_1_1__1__MethaneEmissionsFromBurningOfCropResidues_Unit: _xlfn.LAMBDA("t CH4")
Name AgResidue_Equations_FieldBurning.VEERG_6_4_1_1__1__MethaneEmissionsFromBurningOfCropResidues_Variable: _xlfn.LAMBDA("ECH4")
Name AgResidue_Equations_FieldBurning.VEERG_6_4_1_1__2__NitrousOxideEmissionsFromBurningOfCropResidues: _xlfn.LAMBDA(_xlpm.Mburnc,_xlpm.NCAGc,_xlpm.EFN2O,_xlpm.CN2O, _xlpm.Mburnc * _xlpm.NCAGc * _xlpm.EFN2O * _xlpm.CN2O * 10 ^ (-3))
Name AgResidue_Equations_FieldBurning.VEERG_6_4_1_1__2__NitrousOxideEmissionsFromBurningOfCropResidues: _xlfn.LAMBDA(_xlpm.Mburnc,_xlpm.NCAGc,_xlpm.EFN2O,_xlpm.CN2O, _xlpm.Mburnc * _xlpm.NCAGc * _xlpm.EFN2O * _xlpm.CN2O * 10 ^ (-3))
Name AgResidue_Equations_FieldBurning.VEERG_6_4_1_1__2__NitrousOxideEmissionsFromBurningOfCropResidues: _xlfn.LAMBDA(_xlpm.Mburnc,_xlpm.NCAGc,_xlpm.EFN2O,_xlpm.CN2O, _xlpm.Mburnc * _xlpm.NCAGc * _xlpm.EFN2O * _xlpm.CN2O * 10 ^ (-3))
Name AgResidue_Equations_FieldBurning.VEERG_6_4_1_1__2__NitrousOxideEmissionsFromBurningOfCropResidues: _xlfn.LAMBDA(_xlpm.Mburnc,_xlpm.NCAGc,_xlpm.EFN2O,_xlpm.CN2O, _xlpm.Mburnc * _xlpm.NCAGc * _xlpm.EFN2O * _xlpm.CN2O * 10 ^ (-3))
Name AgResidue_Equations_FieldBurning.VEERG_6_4_1_1__2__NitrousOxideEmissionsFromBurningOfCropResidues: _xlfn.LAMBDA(_xlpm.Mburnc,_xlpm.NCAGc,_xlpm.EFN2O,_xlpm.CN2O, _xlpm.Mburnc * _xlpm.NCAGc * _xlpm.EFN2O * _xlpm.CN2O * 10 ^ (-3))
Name AgResidue_Equations_FieldBurning.VEERG_6_4_1_1__2__NitrousOxideEmissionsFromBurningOfCropResidues: _xlfn.LAMBDA(_xlpm.Mburnc,_xlpm.NCAGc,_xlpm.EFN2O,_xlpm.CN2O, _xlpm.Mburnc * _xlpm.NCAGc * _xlpm.EFN2O * _xlpm.CN2O * 10 ^ (-3))
Name AgResidue_Equations_FieldBurning.VEERG_6_4_1_1__2__NitrousOxideEmissionsFromBurningOfCropResidues: _xlfn.LAMBDA(_xlpm.Mburnc,_xlpm.NCAGc,_xlpm.EFN2O,_xlpm.CN2O, _xlpm.Mburnc * _xlpm.NCAGc * _xlpm.EFN2O * _xlpm.CN2O * 10 ^ (-3))
Name AgResidue_Equations_FieldBurning.VEERG_6_4_1_1__2__NitrousOxideEmissionsFromBurningOfCropResidues: _xlfn.LAMBDA(_xlpm.Mburnc,_xlpm.NCAGc,_xlpm.EFN2O,_xlpm.CN2O, _xlpm.Mburnc * _xlpm.NCAGc * _xlpm.EFN2O * _xlpm.CN2O * 10 ^ (-3))
Name AgResidue_Equations_FieldBurning.VEERG_6_4_1_1__2__NitrousOxideEmissionsFromBurningOfCropResidues: _xlfn.LAMBDA(_xlpm.Mburnc,_xlpm.NCAGc,_xlpm.EFN2O,_xlpm.CN2O, _xlpm.Mburnc * _xlpm.NCAGc * _xlpm.EFN2O * _xlpm.CN2O * 10 ^ (-3))
Name AgResidue_Equations_FieldBurning.VEERG_6_4_1_1__2__NitrousOxideEmissionsFromBurningOfCropResidues: _xlfn.LAMBDA(_xlpm.M_burnc,_xlpm.NC_AGc,_xlpm.EF_N2O,_xlpm.C_N2O, (_xlpm.M_burnc * _xlpm.NC_AGc) * _xlpm.EF_N2O * _xlpm.C_N2O * 10 ^ (-3))

Sheet Home
A1: #VALUE!
A3: =HYPERLINK("#'Home'!A1", "Home") -> Home
A4: =HYPERLINK("#'Results - Activity period'!A1", "Results - Activity period") -> Results - Activity period
A5: =HYPERLINK("#'Results - Product EI'!A1", "Results - Product Emissions Intensity") -> Results - Product Emissions Intensity
A6: =HYPERLINK("#'Results'!A1", "Results") -> Results
A9: INPUTS
A10: =HYPERLINK("#'Input - Enterprise'!A1", "Enterprise") -> Enterprise
A11: =HYPERLINK("#'Input - Site'!A1", "Site") -> Site
A12: =HYPERLINK("#'Input - Dairy'!A1", "Dairy") -> Dairy
A13: =HYPERLINK("#'Input - Livestock sales'!A1", "Livestock sales") -> Livestock sales
A14: =HYPERLINK("#'Input - Dairy cattle purchases'!A1", "Dairy cattle purchases") -> Dairy cattle purchases
A15: =HYPERLINK("#'Input - Pasture'!A1", "Pasture") -> Pasture
A16: =HYPERLINK("#'Input - Fert Prod System'!A1", "Fert Prod System") -> Fert Prod System
A17: =HYPERLINK("#'Input - Fertiliser'!A1", "Fertiliser") -> Fertiliser
A18: =HYPERLINK("#'Input - Fuel'!A1", "Fuel") -> Fuel
A19: =HYPERLINK("#'Input - Electricity'!A1", "Electricity") -> Electricity
A20: =HYPERLINK("#'Input - Common farm inputs'!A1", "Common farm inputs") -> Common farm inputs
A21: =HYPERLINK("#'Input - Crop pasture farm input'!A1", "Crop pasture farm input") -> Crop pasture farm input
A22: =HYPERLINK("#'Input - Livestock farm Inputs'!A1", "Livestock farm Inputs") -> Livestock farm Inputs
A23: =HYPERLINK("#'Input - Freight'!A1", "Freight") -> Freight
A24: =HYPERLINK("#'Input - Solid waste'!A1", "Solid waste") -> Solid waste
A25: =HYPERLINK("#'Input - Manure sent off-site'!A1", "Manure sent off-site") -> Manure sent off-site
A26: =HYPERLINK("#'Input - Data quality'!A1", "Data quality") -> Data quality
A29: CALCULATIONS
A30: =HYPERLINK("#'3.3.1.1-2 Enteric Methane'!A1", "3.3.1.1-2 Enteric methane") -> 3.3.1.1-2 Enteric methane
A31: =HYPERLINK("#'4.3.1.1-2 Methane'!A1", "4.3.1.1-2 Manure methane") -> 4.3.1.1-2 Manure methane
A32: =HYPERLINK("#'4.3.1.3-4 Direct N20'!A1", "4.3.1.3-4 Direct N20") -> 4.3.1.3-4 Direct N20
A33: =HYPERLINK("#'4.3.1.5 Atmos deposition'!A1", "4.3.1.5 Atmos deposition") -> 4.3.1.5 Atmos deposition
A34: =HYPERLINK("#'4.3.1.6-7 Leaching and runoff'!A1", "4.3.1.6-7 Leaching & runoff") -> 4.3.1.6-7 Leaching & runoff
A35: =HYPERLINK("#'4.3.1.8 Manure applied to soils'!A1", "4.3.1.8 Manure applied to soils") -> 4.3.1.8 Manure applied to soils
A36: =HYPERLINK("#'4.3.1.9 Soil direct N2O'!A1", "4.3.1.9 Soil direct N2O") -> 4.3.1.9 Soil direct N2O
A37: =HYPERLINK("#'4.3.1.10-11 Soil Atmos Dep'!A1", "4.3.1.10-11 Soil Atmos Deposition") -> 4.3.1.10-11 Soil Atmos Deposition
A38: =HYPERLINK("#'4.3.1.12-13 Soil leach runoff'!A1", "4.3.1.12-13 Soil leach & runoff") -> 4.3.1.12-13 Soil leach & runoff
A39: =HYPERLINK("#'5.1.1.1-2 Inorganic fert N2O'!A1", "5.1.1.1-2 Inorganic fert N2O") -> 5.1.1.1-2 Inorganic fert N2O
A40: =HYPERLINK("#'5.1.1.3-4 Inorganic fert CO2'!A1", "5.1.1.3-4 Inorganic fert CO2") -> 5.1.1.3-4 Inorganic fert CO2
A41: =HYPERLINK("#'5.2.1.1-2 Organic Fert N2O'!A1", "5.2.1.1-2 Organic fert N2O") -> 5.2.1.1-2 Organic fert N2O
A42: =HYPERLINK("#'5.3.1.1-2 Lime CO2'!A1", "5.3.1.1-2 Lime CO2") -> 5.3.1.1-2 Lime CO2
A43: =HYPERLINK("#'5.4.1.1-4 Atmos deposition'!A1", "5.4.1.1-4 Atmos. deposition") -> 5.4.1.1-4 Atmos. deposition
A44: =HYPERLINK("#'5.5.1.1-2 Leaching and runoff'!A1", "5.5.1.1-2 Leaching & runoff") -> 5.5.1.1-2 Leaching & runoff
A45: =HYPERLINK("#'6.2.1.1-2 Pasture residue N2O'!A1", "6.2.1.1-2 Pasture residue N2O") -> 6.2.1.1-2 Pasture residue N2O
A46: =HYPERLINK("#'6.3.1.1-2 Leach runoff pasture'!A1", "6.3.1.1-2 Leach & runoff (pasture)") -> 6.3.1.1-2 Leach & runoff (pasture)
A47: =HYPERLINK("#'8.1.1.1-2 Transport fuel'!A1", "8.1.1.1-2 Transport fuel") -> 8.1.1.1-2 Transport fuel
A48: =HYPERLINK("#'8.2.1.1-2 Stationary fuel'!A1", "8.2.1.1-2 Stationary fuel") -> 8.2.1.1-2 Stationary fuel
A49: =HYPERLINK("#'10.1.1-2 Solid waste treatment'!A1", "10.1.1.1-2 Solid waste") -> 10.1.1.1-2 Solid waste
A50: =HYPERLINK("#'14.1.1-2 Purchased electricity'!A1", "14.1.1-2 Purchased electricity") -> 14.1.1-2 Purchased electricity
A51: =HYPERLINK("#'15 Scope 3'!A1", "15 Scope 3") -> 15 Scope 3
A52: =HYPERLINK("#'Calcs - Manure sent off-site'!A1", "Calcs - Manure sent off-site") -> Calcs - Manure sent off-site
A55: APPENDICES
A56: =HYPERLINK("#'Constants - Dairy'!A1", "Constants - Dairy") -> Constants - Dairy
A57: =HYPERLINK("#'Constants - Ag Residue'!A1", "Constants - Ag residue") -> Constants - Ag residue
A58: =HYPERLINK("#'Constants - Common Livestock'!A1", "Constants - Common Livestock") -> Constants - Common Livestock
A59: =HYPERLINK("#'Constants - Electricity'!A1", "Constants - Electricity") -> Constants - Electricity
A60: =HYPERLINK("#'Constants - Fertiliser'!A1", "Constants - Fertiliser") -> Constants - Fertiliser
A61: =HYPERLINK("#'Constants - Fuel'!A1", "Constants - Fuel") -> Constants - Fuel
A62: =HYPERLINK("#'Constants - Scope 3'!A1", "Constants - Scope 3") -> Constants - Scope 3
A63: =HYPERLINK("#'Constants - Common'!A1", "Constants - Common") -> Constants - Common
A64: =HYPERLINK("#'Constants - Solid Waste'!A1", "Constants - Solid Waste") -> Constants - Solid Waste
A65: =HYPERLINK("#'Acknowledgements'!A1", "Acknowledgements") -> Acknowledgements

Sheet Results - Activity period
A1: #VALUE! | C1: Results - Activity period
A3: =HYPERLINK("#'Home'!A1", "Home") -> Home
A4: =HYPERLINK("#'Results - Activity period'!A1", "Results - Activity period") -> Results - Activity period
A5: =HYPERLINK("#'Results - Product EI'!A1", "Results - Product Emissions Intensity") -> Results - Product Emissions Intensity | D5: ="Emissions breakdown for activities running between " & TEXT(X_Cell_Site_StartDate, "dd mmmm yyyy") & " and " & TEXT('Input - Enterprise'!E13, "dd mmmm yyyy") -> Emissions breakdown for activities running between 01 January 2024 and 31 December 2024
A6: =HYPERLINK("#'Results'!A1", "Results") -> Results
D7: Scope 1
A9: INPUTS | D9: Scope 1 source | E9: GHG emissions method 1 | F9: GHG emissions method 2 | G9: GHG Unit | H9: CO2-e emissions method 1 | I9: CO2-e emissions method 2
A10: =HYPERLINK("#'Input - Enterprise'!A1", "Enterprise") -> Enterprise | D10: 3.3.1.1-2 Enteric methane | E10: {=VEERG_3_3_1_1__1_TotalAnnualMethaneFromEntericFermentationVariation_Result_Method1} -> 32.464683 | F10: {=VEERG_3_3_1_1__1_TotalAnnualMethaneFromEntericFermentationVariation_Result_Method2} -> 32.464683 | G10: t CH4 | H10: {=Common_Equations.Common_ConvertCH4ToCO2e(E10,_xlfn.XLOOKUP("CH4", Table_GWPData[Gas],Table_GWPData[CO2-e factor]))} -> 909.01112 | I10: {=Common_Equations.Common_ConvertCH4ToCO2e(F10,_xlfn.XLOOKUP("CH4", Table_GWPData[Gas],Table_GWPData[CO2-e factor]))} -> 909.01112 | J10: t CO2e
A11: =HYPERLINK("#'Input - Site'!A1", "Site") -> Site | D11: 4.3.1.1-2 Manure methane | E11: {=VEERG_4_3_1_1__1_TotalAnnualMethaneFromManureManagement_Result_Method1} -> #N/A | F11: {=VEERG_4_3_1_1__1_TotalAnnualMethaneFromManureManagement_Result_Method2} -> #N/A | G11: t CH4 | H11: {=Common_Equations.Common_ConvertCH4ToCO2e(E11,_xlfn.XLOOKUP("CH4", Table_GWPData[Gas],Table_GWPData[CO2-e factor]))} -> #N/A | I11: {=Common_Equations.Common_ConvertCH4ToCO2e(F11,_xlfn.XLOOKUP("CH4", Table_GWPData[Gas],Table_GWPData[CO2-e factor]))} -> #N/A | J11: t CO2e
A12: =HYPERLINK("#'Input - Dairy'!A1", "Dairy") -> Dairy | D12: 4.3.1.3-4 Manure direct N2O | E12: {=VEERG_4_3_1_3__1_TotalAnnualDirectNitrousOxideEmissionsFromMMS_Result_Method1} -> 0.058975626 | F12: {=VEERG_4_3_1_3__1_TotalAnnualDirectNitrousOxideEmissionsFromMMS_Result_Method2} -> 0.058975626 | G12: t N2O | H12: {=Common_Equations.Common_ConvertN2OToCO2e(E12,_xlfn.XLOOKUP("N2O", Table_GWPData[Gas],Table_GWPData[CO2-e factor]))} -> 15.628541 | I12: {=Common_Equations.Common_ConvertN2OToCO2e(F12,_xlfn.XLOOKUP("N2O", Table_GWPData[Gas],Table_GWPData[CO2-e factor]))} -> 15.628541 | J12: t CO2e
A13: =HYPERLINK("#'Input - Livestock sales'!A1", "Livestock sales") -> Livestock sales | D13: 4.3.1.5 Manure atmospheric deposition | E13: {=VEERG_4_3_1_5__1_AnnualAtmosphericDepositionEmissionsFromMMS_Result_Method1} -> 0.047299753 | F13: {=VEERG_4_3_1_5__1_AnnualAtmosphericDepositionEmissionsFromMMS_Result_Method2} -> 0.047299753 | G13: t N2O | H13: {=Common_Equations.Common_ConvertN2OToCO2e(E13,_xlfn.XLOOKUP("N2O", Table_GWPData[Gas],Table_GWPData[CO2-e factor]))} -> 12.534435 | I13: {=Common_Equations.Common_ConvertN2OToCO2e(F13,_xlfn.XLOOKUP("N2O", Table_GWPData[Gas],Table_GWPData[CO2-e factor]))} -> 12.534435 | J13: t CO2e
A14: =HYPERLINK("#'Input - Dairy cattle purchases'!A1", "Dairy cattle purchases") -> Dairy cattle purchases | D14: 4.3.1.6-7 Manure leaching and runoff | E14: {=VEERG_4_3_1_6__1_AnnualEmissionsFromLeachingAndRunoffFromMMS_Result_Method1} -> 0.0025949275 | F14: {=VEERG_4_3_1_6__1_AnnualEmissionsFromLeachingAndRunoffFromMMS_Result_Method2} -> 0.0025949275 | G14: t N2O | H14: {=Common_Equations.Common_ConvertN2OToCO2e(E14,_xlfn.XLOOKUP("N2O", Table_GWPData[Gas],Table_GWPData[CO2-e factor]))} -> 0.6876558 | I14: {=Common_Equations.Common_ConvertN2OToCO2e(F14,_xlfn.XLOOKUP("N2O", Table_GWPData[Gas],Table_GWPData[CO2-e factor]))} -> 0.6876558 | J14: t CO2e
A15: =HYPERLINK("#'Input - Pasture'!A1", "Pasture") -> Pasture | D15: 4.3.1.9 Soil direct N2O | E15: {=VEERG_4_3_1_9__1_DirectNitrousOxideEmissionsOnPasture_Result_Method1} -> #VALUE! | F15: {=VEERG_4_3_1_9__1_DirectNitrousOxideEmissionsOnPasture_Result_Method2} -> #VALUE! | G15: t N2O | H15: {=Common_Equations.Common_ConvertN2OToCO2e(E15,_xlfn.XLOOKUP("N2O", Table_GWPData[Gas],Table_GWPData[CO2-e factor]))} -> #VALUE! | I15: {=Common_Equations.Common_ConvertN2OToCO2e(F15,_xlfn.XLOOKUP("N2O", Table_GWPData[Gas],Table_GWPData[CO2-e factor]))} -> #VALUE! | J15: t CO2e
A16: =HYPERLINK("#'Input - Fert Prod System'!A1", "Fert Prod System") -> Fert Prod System | D16: 4.3.1.10-11 Soil atmospheric deposition | E16: {=VEERG_4_3_1_10__1_AtmosphericDepositionEmissionsFromUrineAndDungOnPasture_Result_Method1} -> 0.046286842 | F16: {=VEERG_4_3_1_10__1_AtmosphericDepositionEmissionsFromUrineAndDungOnPasture_Result_Method2} -> 0.046286842 | G16: t N2O | H16: {=Common_Equations.Common_ConvertN2OToCO2e(E16,_xlfn.XLOOKUP("N2O", Table_GWPData[Gas],Table_GWPData[CO2-e factor]))} -> 12.266013 | I16: {=Common_Equations.Common_ConvertN2OToCO2e(F16,_xlfn.XLOOKUP("N2O", Table_GWPData[Gas],Table_GWPData[CO2-e factor]))} -> 12.266013 | J16: t CO2e
A17: =HYPERLINK("#'Input - Fertiliser'!A1", "Fertiliser") -> Fertiliser | D17: 4.3.1.12-13 Soil leaching and runoff | E17: {=VEERG_4_3_1_12__1_LeachingAndRunoffEmissionsFromUrineAndDungOnPasture_Result_Method1} -> 0.098625716 | F17: {=VEERG_4_3_1_12__1_LeachingAndRunoffEmissionsFromUrineAndDungOnPasture_Result_Method2} -> 0.098625716 | G17: t N2O | H17: {=Common_Equations.Common_ConvertN2OToCO2e(E17,_xlfn.XLOOKUP("N2O", Table_GWPData[Gas],Table_GWPData[CO2-e factor]))} -> 26.135815 | I17: {=Common_Equations.Common_ConvertN2OToCO2e(F17,_xlfn.XLOOKUP("N2O", Table_GWPData[Gas],Table_GWPData[CO2-e factor]))} -> 26.135815 | J17: t CO2e
A18: =HYPERLINK("#'Input - Fuel'!A1", "Fuel") -> Fuel | D18: 5.1.1.1-2 Inorganic fert N2O | E18: {=VEERG_5_1_1_1__1_InorganicFertiliserApplicationN2OEmissions_Result_Method1} -> #N/A | F18: {=VEERG_5_1_1_1__1_InorganicFertiliserApplicationN2OEmissions_Result_Method2} -> #VALUE! | G18: t N2O | H18: {=Common_Equations.Common_ConvertN2OToCO2e(E18,_xlfn.XLOOKUP("N2O", Table_GWPData[Gas],Table_GWPData[CO2-e factor]))} -> #N/A | I18: {=Common_Equations.Common_ConvertN2OToCO2e(F18,_xlfn.XLOOKUP("N2O", Table_GWPData[Gas],Table_GWPData[CO2-e factor]))} -> #VALUE! | J18: t CO2e
A19: =HYPERLINK("#'Input - Electricity'!A1", "Electricity") -> Electricity | D19: 5.1.1.3-4 Inorganic fert CO2 | E19: {=VEERG_5_1_1_3__1_InorganicFertiliserApplicationCO2Emissions_Result_Method1} -> 0 | F19: =E19 -> 0 | G19: t CO2 | H19: =E19 -> 0 | I19: =F19 -> 0 | J19: t CO2e
A20: =HYPERLINK("#'Input - Common farm inputs'!A1", "Common farm inputs") -> Common farm inputs | D20: 5.2.1.1-2 Organic fert N2O | E20: {=VEERG_5_2_1_1__2_MassOfNitrogenInOrganicFertiliser_Result_Method1} -> #VALUE! | F20: =E20 -> #VALUE! | G20: t N2O | H20: {=Common_Equations.Common_ConvertN2OToCO2e(E20,_xlfn.XLOOKUP("N2O", Table_GWPData[Gas],Table_GWPData[CO2-e factor]))} -> #VALUE! | I20: {=Common_Equations.Common_ConvertN2OToCO2e(F20,_xlfn.XLOOKUP("N2O", Table_GWPData[Gas],Table_GWPData[CO2-e factor]))} -> #VALUE! | J20: t CO2e
A21: =HYPERLINK("#'Input - Crop pasture farm input'!A1", "Crop pasture farm input") -> Crop pasture farm input | D21: 5.3.1.1-2 Lime CO2 | E21: {=VEERG_5_3_1_1__1_LimeApplicationCO2Emissions_Result_Method1} -> 0 | F21: =E21 -> 0 | G21: t CO2 | H21: =E21 -> 0 | I21: =F21 -> 0 | J21: t CO2e
A22: =HYPERLINK("#'Input - Livestock farm Inputs'!A1", "Livestock farm Inputs") -> Livestock farm Inputs | D22: 5.4.1.1-4 Atmos. deposition | E22: {=VEERG_5_4_1_3__1_OrganicFertiliserAtmosphericDepositionN2OEmissions_Result_Method1} -> #VALUE! | F22: =E22 -> #VALUE! | G22: t N2O | H22: {=Common_Equations.Common_ConvertN2OToCO2e(E22,_xlfn.XLOOKUP("N2O", Table_GWPData[Gas],Table_GWPData[CO2-e factor]))} -> #VALUE! | I22: {=Common_Equations.Common_ConvertN2OToCO2e(F22,_xlfn.XLOOKUP("N2O", Table_GWPData[Gas],Table_GWPData[CO2-e factor]))} -> #VALUE! | J22: t CO2e
A23: =HYPERLINK("#'Input - Freight'!A1", "Freight") -> Freight | D23: 5.5.1.1-2 Leaching & runoff | E23: {=VEERG_5_5_1_1__1_FertiliserLeachingAndRunoffN2OEmissions_result_Method1} -> #VALUE! | F23: =E23 -> #VALUE! | G23: t N2O | H23: {=Common_Equations.Common_ConvertN2OToCO2e(E23,_xlfn.XLOOKUP("N2O", Table_GWPData[Gas],Table_GWPData[CO2-e factor]))} -> #VALUE! | I23: {=Common_Equations.Common_ConvertN2OToCO2e(F23,_xlfn.XLOOKUP("N2O", Table_GWPData[Gas],Table_GWPData[CO2-e factor]))} -> #VALUE! | J23: t CO2e
A24: =HYPERLINK("#'Input - Solid waste'!A1", "Solid waste") -> Solid waste | D24: 6.2.1.1-2 Pasture residue N2O | E24: {=VEERG_6_2_1_1__1__NitrousOxideEmissionsFromPastureResidues_Result_Method1} -> 0 | F24: {=VEERG_6_2_1_1__1__NitrousOxideEmissionsFromPastureResidues_Result_Method2} -> 0 | G24: t N2O | H24: {=Common_Equations.Common_ConvertN2OToCO2e(E24,_xlfn.XLOOKUP("N2O", Table_GWPData[Gas],Table_GWPData[CO2-e factor]))} -> 0 | I24: {=Common_Equations.Common_ConvertN2OToCO2e(F24,_xlfn.XLOOKUP("N2O", Table_GWPData[Gas],Table_GWPData[CO2-e factor]))} -> 0 | J24: t CO2e
A25: =HYPERLINK("#'Input - Manure sent off-site'!A1", "Manure sent off-site") -> Manure sent off-site | D25: 6.3.1.1-2 Leach & runoff (pasture) | E25: {=VEERG_6_3_1_1__1__LeachingAndRunoffEmissionsCropAndPastureResidue_PastureOnly_Result_Method1} -> 3.0793186e-07 | F25: {=VEERG_6_3_1_1__1__LeachingAndRunoffEmissionsCropAndPastureResidue_PastureOnly_Result_Method2} -> 3.0793186e-07 | G25: t N2O | H25: {=Common_Equations.Common_ConvertN2OToCO2e(E25,_xlfn.XLOOKUP("N2O", Table_GWPData[Gas],Table_GWPData[CO2-e factor]))} -> 8.1601944e-05 | I25: {=Common_Equations.Common_ConvertN2OToCO2e(F25,_xlfn.XLOOKUP("N2O", Table_GWPData[Gas],Table_GWPData[CO2-e factor]))} -> 8.1601944e-05 | J25: t CO2e
A26: =HYPERLINK("#'Input - Data quality'!A1", "Data quality") -> Data quality | D26: 8.1.1.1-2 Transport fuel CO2 | E26: {=VEERG_8_1_1_1__1_FuelCombustionTransport_Result_CO2} -> 83.182 | F26: =E26 -> 83.182 | G26: t CO2 | H26: =E26 -> 83.182 | I26: =F26 -> 83.182 | J26: t CO2e
D27: 8.1.1.1-2 Transport fuel CH4 | E27: {=VEERG_8_1_1_1__1_FuelCombustionTransport_Result_CH4} -> 0.19906 | F27: =E27 -> 0.19906 | G27: t CH4 | H27: {=Common_Equations.Common_ConvertCH4ToCO2e(E27,_xlfn.XLOOKUP("CH4", Table_GWPData[Gas],Table_GWPData[CO2-e factor]))} -> 5.57368 | I27: {=Common_Equations.Common_ConvertCH4ToCO2e(F27,_xlfn.XLOOKUP("CH4", Table_GWPData[Gas],Table_GWPData[CO2-e factor]))} -> 5.57368 | J27: t CO2e
D28: 8.1.1.1-2 Transport fuel N2O | E28: {=VEERG_8_1_1_1__1_FuelCombustionTransport_Result_N2O} -> 0.5845 | F28: =E28 -> 0.5845 | G28: t N2O | H28: {=Common_Equations.Common_ConvertN2OToCO2e(E28,_xlfn.XLOOKUP("N2O", Table_GWPData[Gas],Table_GWPData[CO2-e factor]))} -> 154.8925 | I28: {=Common_Equations.Common_ConvertN2OToCO2e(F28,_xlfn.XLOOKUP("N2O", Table_GWPData[Gas],Table_GWPData[CO2-e factor]))} -> 154.8925 | J28: t CO2e
A29: CALCULATIONS | D29: 8.2.1.1-2 Stationary fuel CO2 | E29: {=VEERG_8_2_1_1__1_FuelCombustionStationary_Result_CO2} -> 29.0708 | F29: =E29 -> 29.0708 | G29: t CO2 | H29: =E29 -> 29.0708 | I29: =F29 -> 29.0708 | J29: t CO2e
A30: =HYPERLINK("#'3.3.1.1-2 Enteric Methane'!A1", "3.3.1.1-2 Enteric methane") -> 3.3.1.1-2 Enteric methane | D30: 8.2.1.1-2 Stationary fuel CH4 | E30: {=VEERG_8_2_1_1__1_FuelCombustionStationary_Result_CH4} -> 0.0724 | F30: =E30 -> 0.0724 | G30: t CH4 | H30: {=Common_Equations.Common_ConvertCH4ToCO2e(E30,_xlfn.XLOOKUP("CH4", Table_GWPData[Gas],Table_GWPData[CO2-e factor]))} -> 2.0272 | I30: {=Common_Equations.Common_ConvertCH4ToCO2e(F30,_xlfn.XLOOKUP("CH4", Table_GWPData[Gas],Table_GWPData[CO2-e factor]))} -> 2.0272 | J30: t CO2e
A31: =HYPERLINK("#'4.3.1.1-2 Methane'!A1", "4.3.1.1-2 Manure methane") -> 4.3.1.1-2 Manure methane | D31: 8.2.1.1-2 Stationary fuel N2O | E31: {=VEERG_8_2_1_1__1_FuelCombustionStationary_Result_N2O} -> 0.0714 | F31: =E31 -> 0.0714 | G31: t N2O | H31: {=Common_Equations.Common_ConvertN2OToCO2e(E31,_xlfn.XLOOKUP("N2O", Table_GWPData[Gas],Table_GWPData[CO2-e factor]))} -> 18.921 | I31: {=Common_Equations.Common_ConvertN2OToCO2e(F31,_xlfn.XLOOKUP("N2O", Table_GWPData[Gas],Table_GWPData[CO2-e factor]))} -> 18.921 | J31: t CO2e
A32: =HYPERLINK("#'4.3.1.3-4 Direct N20'!A1", "4.3.1.3-4 Direct N20") -> 4.3.1.3-4 Direct N20 | D32: 14.1.1-2 Purchased electricity (Location-based) | E32: {=VEERG_14_1_1__1_LocationBasedScopeElectricityEmissions_Result_Method1} -> 16.8 | F32: =E32 -> 16.8 | G32: t CO2e | H32: =E32 -> 16.8 | I32: =F32 -> 16.8 | J32: t CO2e
A33: =HYPERLINK("#'4.3.1.5 Atmos deposition'!A1", "4.3.1.5 Atmos deposition") -> 4.3.1.5 Atmos deposition | D33: 14.1.1-2 Purchased electricity (Market-based) | E33: {=VEERG_14_1_2__1_MarketBasedScopeElectricityEmissionsVariation_Result_Method1} -> 13.77 | F33: =E33 -> 13.77 | G33: t CO2e | H33: =E33 -> 13.77 | I33: =F33 -> 13.77 | J33: t CO2e
A34: =HYPERLINK("#'4.3.1.6-7 Leaching and runoff'!A1", "4.3.1.6-7 Leaching & runoff") -> 4.3.1.6-7 Leaching & runoff | D34: Total scope 1 | H34: =SUM(H10:H33) -> #N/A | I34: =SUM(I10:I33) -> #N/A | J34: t CO2e
A35: =HYPERLINK("#'4.3.1.8 Manure applied to soils'!A1", "4.3.1.8 Manure applied to soils") -> 4.3.1.8 Manure applied to soils
A36: =HYPERLINK("#'4.3.1.9 Soil direct N2O'!A1", "4.3.1.9 Soil direct N2O") -> 4.3.1.9 Soil direct N2O
A37: =HYPERLINK("#'4.3.1.10-11 Soil Atmos Dep'!A1", "4.3.1.10-11 Soil Atmos Deposition") -> 4.3.1.10-11 Soil Atmos Deposition | D37: Scope 2
A38: =HYPERLINK("#'4.3.1.12-13 Soil leach runoff'!A1", "4.3.1.12-13 Soil leach & runoff") -> 4.3.1.12-13 Soil leach & runoff
A39: =HYPERLINK("#'5.1.1.1-2 Inorganic fert N2O'!A1", "5.1.1.1-2 Inorganic fert N2O") -> 5.1.1.1-2 Inorganic fert N2O | D39: Scope 2 source | E39: GHG emissions method 1 | F39: GHG emissions method 2 | G39: GHG Unit | H39: CO2-e emissions method 1 | I39: CO2-e emissions method 2
A40: =HYPERLINK("#'5.1.1.3-4 Inorganic fert CO2'!A1", "5.1.1.3-4 Inorganic fert CO2") -> 5.1.1.3-4 Inorganic fert CO2 | D40: {="14.1.1-2 Purchased electricity " & IF(X_Cell_Electricity_CalculationMethod="Location-based (simpler)", "(Location-based)", "(Market-based)")} -> 14.1.1-2 Purchased electricity (Location-based) | E40: {=IF(X_Cell_Electricity_CalculationMethod="Location-based (simpler)", VEERG_14_1_1__1_LocationBasedScopeElectricityEmissions_Result_Method1, VEERG_14_1_2__1_MarketBasedScopeElectricityEmissionsVariation_Result_Method1)} -> 16.8 | F40: =E34 -> 0 | G40: t CO2e | H40: =E34 -> 0 | I40: =F34 -> 0 | J40: t CO2e
A41: =HYPERLINK("#'5.2.1.1-2 Organic Fert N2O'!A1", "5.2.1.1-2 Organic fert N2O") -> 5.2.1.1-2 Organic fert N2O | D41: Total scope 2 | H41: =SUM(H34:H34) -> #N/A | I41: =SUM(I34:I34) -> #N/A | J41: t CO2e
A42: =HYPERLINK("#'5.3.1.1-2 Lime CO2'!A1", "5.3.1.1-2 Lime CO2") -> 5.3.1.1-2 Lime CO2
A43: =HYPERLINK("#'5.4.1.1-4 Atmos deposition'!A1", "5.4.1.1-4 Atmos. deposition") -> 5.4.1.1-4 Atmos. deposition
A44: =HYPERLINK("#'5.5.1.1-2 Leaching and runoff'!A1", "5.5.1.1-2 Leaching & runoff") -> 5.5.1.1-2 Leaching & runoff | D44: Scope 3
A45: =HYPERLINK("#'6.2.1.1-2 Pasture residue N2O'!A1", "6.2.1.1-2 Pasture residue N2O") -> 6.2.1.1-2 Pasture residue N2O | D45: Scope 3 source | E45: GHG emissions method 1 | F45: GHG emissions method 2 | G45: GHG Unit | H45: CO2-e emissions method 1 | I45: CO2-e emissions method 2
A46: =HYPERLINK("#'6.3.1.1-2 Leach runoff pasture'!A1", "6.3.1.1-2 Leach & runoff (pasture)") -> 6.3.1.1-2 Leach & runoff (pasture) | D46: 15.1.1.1 Purchased livestock | E46: {=VEERG_15_1_1_1__1_EmissionsFromPurchasedLivestock_Result_Method1} -> 295.47 | F46: {=VEERG_15_1_1_1__1_EmissionsFromPurchasedLivestock_Result_Method2} -> 415.625 | G46: t CO2e | H46: =E46 -> 295.47 | I46: =F46 -> 415.625 | J46: t CO2e
A47: =HYPERLINK("#'8.1.1.1-2 Transport fuel'!A1", "8.1.1.1-2 Transport fuel") -> 8.1.1.1-2 Transport fuel | D47: 15.2.1.1 Purchased feed | E47: {=VEERG_15_2_1_1__1_EmissionsFromPurchasedFeed_Result_Method1} -> 0.785052 | F47: {=VEERG_15_2_1_1__1_EmissionsFromPurchasedFeed_Result_Method2} -> 0.52978 | G47: t CO2e | H47: =E47 -> 0.785052 | I47: =F47 -> 0.52978 | J47: t CO2e
A48: =HYPERLINK("#'8.2.1.1-2 Stationary fuel'!A1", "8.2.1.1-2 Stationary fuel") -> 8.2.1.1-2 Stationary fuel | D48: 15.3.1.1 Mineral supplements | E48: {=VEERG_15_3_1_1__1_EmissionsFromPurchasedMineralSupplements_Result_Method1} -> 0.1789 | F48: {=VEERG_15_3_1_1__1_EmissionsFromPurchasedMineralSupplements_Result_Method2} -> 0.16 | G48: t CO2e | H48: =E48 -> 0.1789 | I48: =F48 -> 0.16 | J48: t CO2e
A49: =HYPERLINK("#'10.1.1-2 Solid waste treatment'!A1", "10.1.1.1-2 Solid waste") -> 10.1.1.1-2 Solid waste | D49: 15.4.1.1 Fertiliser | E49: {=VEERG_15_4_1_1__2_EmissionsFromPurchasedFertiliserComponentsVariation_Result_Method1} -> 0 | F49: {=VEERG_15_4_1_1__2_EmissionsFromPurchasedFertiliserComponentsVariation_Result_Method2} -> 0 | G49: t CO2e | H49: =E49 -> 0 | I49: =F49 -> 0 | J49: t CO2e
A50: =HYPERLINK("#'14.1.1-2 Purchased electricity'!A1", "14.1.1-2 Purchased electricity") -> 14.1.1-2 Purchased electricity | D50: 15.5.1.1 Agrichemicals | E50: {=VEERG_15_5_1_1__1_EmissionsFromPurchasedAgrichemicals_Result_Method1} -> 7.516 | F50: {=VEERG_15_5_1_1__1_EmissionsFromPurchasedAgrichemicals_Result_Method2} -> 7.496 | G50: t CO2e | H50: =E50 -> 7.516 | I50: =F50 -> 7.496 | J50: t CO2e
A51: =HYPERLINK("#'15 Scope 3'!A1", "15 Scope 3") -> 15 Scope 3 | D51: 15.6.1.1 Lime | E51: {=VEERG_15_6_1_1__1_EmissionsFromPurchasedLime_Result_Method1} -> 0 | F51: {=VEERG_15_6_1_1__1_EmissionsFromPurchasedLime_Result_Method2} -> 0 | G51: t CO2e | H51: =E51 -> 0 | I51: =F51 -> 0 | J51: t CO2e
A52: =HYPERLINK("#'Calcs - Manure sent off-site'!A1", "Calcs - Manure sent off-site") -> Calcs - Manure sent off-site | D52: 15.7.1.1 Services and contractor operations | E52: {=VEERG_15_7_1_1__1_EmissionsFromPurchasedServices_Result_Method1} -> No data | F52: {=VEERG_15_7_1_1__1_EmissionsFromPurchasedServices_Result_Method2} -> 42 | G52: t CO2e | H52: =E52 -> No data | I52: =F52 -> 42 | J52: t CO2e
D53: 15.10.1.1 Other: Cleaning chemicals | E53: {=VEERG_15_10_1_1__1_OtherPurchasedGoodsAndServices_CleaningChemicals_Result_Method1} -> 0.5051 | F53: {=VEERG_15_10_1_1__1_OtherPurchasedGoodsAndServices_CleaningChemicals_Result_Method2} -> 2.73 | G53: t CO2e | H53: =E53 -> 0.5051 | I53: =F53 -> 2.73 | J53: t CO2e
D54: 15.10.1.1 Other: Pharmacy chemicals | E54: {=VEERG_15_10_1_1__1_OtherPurchasedGoodsAndServices_PharmacyChemicals_Result_Method1} -> 0.015636 | F54: {=VEERG_15_10_1_1__1_OtherPurchasedGoodsAndServices_PharmacyChemicals_Result_Method2} -> 0.0134 | G54: t CO2e | H54: =E54 -> 0.015636 | I54: =F54 -> 0.0134 | J54: t CO2e
A55: APPENDICES | D55: 15.10.1.1 Other: Miscellaneous | E55: {=VEERG_15_10_1_1__1_OtherPurchasedGoodsAndServices_Misc_Result_Method1} -> 0.0101 | F55: {=VEERG_15_10_1_1__1_OtherPurchasedGoodsAndServices_Misc_Result_Method2} -> 0.02586 | G55: t CO2e | H55: =E55 -> 0.0101 | I55: =F55 -> 0.02586 | J55: t CO2e
A56: =HYPERLINK("#'Constants - Dairy'!A1", "Constants - Dairy") -> Constants - Dairy | D56: 15.10.1.1 Other: Uncategorised | E56: {=VEERG_15_10_1_1__1_OtherPurchasedGoodsAndServices_Uncategorised_Result_Method1} -> No data | F56: {=VEERG_15_10_1_1__1_OtherPurchasedGoodsAndServices_Uncategorised_Result_Method2} -> 4000 | G56: t CO2e | H56: =E56 -> No data | I56: =F56 -> 4000 | J56: t CO2e
A57: =HYPERLINK("#'Constants - Ag Residue'!A1", "Constants - Ag residue") -> Constants - Ag residue | D57: 15.11.1.1 Fuel | E57: {=VEERG_15_11_1_1__1_TotalUpstreamEmissionsFromFuel_Result} -> 26.384 | F57: =E57 -> 26.384 | G57: t CO2e | H57: =E57 -> 26.384 | I57: =F57 -> 26.384 | J57: t CO2e
A58: =HYPERLINK("#'Constants - Common Livestock'!A1", "Constants - Common Livestock") -> Constants - Common Livestock | D58: {="15.12.1.1 Purchased electricity " & IF(X_Cell_Electricity_CalculationMethod="Location-based (simpler)", "(Location-based)", "(Market-based)")} -> 15.12.1.1 Purchased electricity (Location-based) | E58: {=IF(X_Cell_Electricity_CalculationMethod="Location-based (simpler)", VEERG_15_12_1_1__1_UpstreamPurchasedElectricityLocationBased_Result, VEERG_15_12_1_1__1_UpstreamPurchasedElectricityMarketBased_Result)} -> 2.7 | F58: =E58 -> 2.7 | G58: t CO2e | H58: =E58 -> 2.7 | I58: =F58 -> 2.7 | J58: t CO2e
A59: =HYPERLINK("#'Constants - Electricity'!A1", "Constants - Electricity") -> Constants - Electricity | D59: 15.14.1.1 Incoming freight | E59: {=VEERG_15_14_1_1__1_EmbeddedEmissionsFromUpstreamFreight_Incoming_Result_Method1} -> No data | F59: {=VEERG_15_14_1_1__1_EmbeddedEmissionsFromUpstreamFreight_Incoming_Result_Method2} -> 5146700 | G59: t CO2e | H59: =E59 -> No data | I59: =F59 -> 5146700 | J59: t CO2e
A60: =HYPERLINK("#'Constants - Fertiliser'!A1", "Constants - Fertiliser") -> Constants - Fertiliser | D60: 15.13.1.1 Waste sent to treatment facility | E60: {=VEERG_10_1_1_1__1_EmissionsFromWasteManagement_Scope3_Result_Method1} -> 441.15 | F60: =E60 -> 441.15 | G60: t CO2e | H60: =E60 -> 441.15 | I60: =F60 -> 441.15 | J60: t CO2e
A61: =HYPERLINK("#'Constants - Fuel'!A1", "Constants - Fuel") -> Constants - Fuel | D61: 15.14.1.1 Outgoing freight | E61: {=VEERG_15_14_1_1__1_EmbeddedEmissionsFromUpstreamFreight_Outgoing_Result_Method1} -> No data | F61: {=VEERG_15_14_1_1__1_EmbeddedEmissionsFromUpstreamFreight_Outgoing_Result_Method2} -> 432640 | G61: t CO2e | H61: =E61 -> No data | I61: =F61 -> 432640 | J61: t CO2e
A62: =HYPERLINK("#'Constants - Scope 3'!A1", "Constants - Scope 3") -> Constants - Scope 3 | D62: Total scope 3 | H62: =SUM(H46:H61) -> 774.71479 | I62: =SUM(I46:I61) -> 5584278.8 | J62: t CO2e
A63: =HYPERLINK("#'Constants - Common'!A1", "Constants - Common") -> Constants - Common
A64: =HYPERLINK("#'Constants - Solid Waste'!A1", "Constants - Solid Waste") -> Constants - Solid Waste
A65: =HYPERLINK("#'Acknowledgements'!A1", "Acknowledgements") -> Acknowledgements | D65: ="Carbon removals from plantings for the activity period " & TEXT(X_Cell_Site_StartDate, "d mmmm yyyy") & " and " & TEXT(X_Cell_Site_EndDate, "d mmmm yyyy") -> Carbon removals from plantings for the activity period 1 January 2024 and 31 December 2024
D67: Total removals | E67: =SUM(Table_Input_Enterprise_PlantingRemovals[Removal allocated to this enterprise]) -> 0 | F67: t CO2
D70: ="Net emissions for the activity period " & TEXT(X_Cell_Site_StartDate, "d mmmm yyyy") & " and " & TEXT(X_Cell_Site_EndDate, "d mmmm yyyy") -> Net emissions for the activity period 1 January 2024 and 31 December 2024
E72: Method 1 | F72: Method 2
D73: Total emissions excluding removals | E73: =Result_Enterprise_Scope1_Method1+Result_Enterprise_Scope2_Method1+Result_Enterprise_Scope3_Method1 -> #N/A | F73: =Result_Enterprise_Scope1_Method2+Result_Enterprise_Scope2_Method2+Result_Enterprise_Scope3_Method2 -> #N/A | G73: t CO2-e
D74: Total net emissions | E74: =Result_Enterprise_Gross_Method1-Result_Enterprise_Removals -> #N/A | F74: =Result_Enterprise_Gross_Method2-Result_Enterprise_Removals -> #N/A | G74: t CO2-e

Sheet Results - Product EI
A1: #VALUE! | C1: Results - Product emissions intensity
A3: =HYPERLINK("#'Home'!A1", "Home") -> Home
A4: =HYPERLINK("#'Results - Activity period'!A1", "Results - Activity period") -> Results - Activity period
A5: =HYPERLINK("#'Results - Product EI'!A1", "Results - Product Emissions Intensity") -> Results - Product Emissions Intensity
A6: =HYPERLINK("#'Results'!A1", "Results") -> Results
A9: INPUTS
A10: =HYPERLINK("#'Input - Enterprise'!A1", "Enterprise") -> Enterprise
A11: =HYPERLINK("#'Input - Site'!A1", "Site") -> Site
A12: =HYPERLINK("#'Input - Dairy'!A1", "Dairy") -> Dairy
A13: =HYPERLINK("#'Input - Livestock sales'!A1", "Livestock sales") -> Livestock sales
A14: =HYPERLINK("#'Input - Dairy cattle purchases'!A1", "Dairy cattle purchases") -> Dairy cattle purchases
A15: =HYPERLINK("#'Input - Pasture'!A1", "Pasture") -> Pasture
A16: =HYPERLINK("#'Input - Fert Prod System'!A1", "Fert Prod System") -> Fert Prod System
A17: =HYPERLINK("#'Input - Fertiliser'!A1", "Fertiliser") -> Fertiliser
A18: =HYPERLINK("#'Input - Fuel'!A1", "Fuel") -> Fuel
A19: =HYPERLINK("#'Input - Electricity'!A1", "Electricity") -> Electricity
A20: =HYPERLINK("#'Input - Common farm inputs'!A1", "Common farm inputs") -> Common farm inputs
A21: =HYPERLINK("#'Input - Crop pasture farm input'!A1", "Crop pasture farm input") -> Crop pasture farm input
A22: =HYPERLINK("#'Input - Livestock farm Inputs'!A1", "Livestock farm Inputs") -> Livestock farm Inputs
A23: =HYPERLINK("#'Input - Freight'!A1", "Freight") -> Freight
A24: =HYPERLINK("#'Input - Solid waste'!A1", "Solid waste") -> Solid waste
A25: =HYPERLINK("#'Input - Manure sent off-site'!A1", "Manure sent off-site") -> Manure sent off-site
A26: =HYPERLINK("#'Input - Data quality'!A1", "Data quality") -> Data quality
A29: CALCULATIONS
A30: =HYPERLINK("#'3.3.1.1-2 Enteric Methane'!A1", "3.3.1.1-2 Enteric methane") -> 3.3.1.1-2 Enteric methane
A31: =HYPERLINK("#'4.3.1.1-2 Methane'!A1", "4.3.1.1-2 Manure methane") -> 4.3.1.1-2 Manure methane
A32: =HYPERLINK("#'4.3.1.3-4 Direct N20'!A1", "4.3.1.3-4 Direct N20") -> 4.3.1.3-4 Direct N20 | D32: ="Emissions for whole production cycle running between " & TEXT(X_Cell_Enterprise_ProductionTimeframeStart, "d mmmm yyyy") & " and " & TEXT(X_Cell_Enterprise_ProductionTimeframeEnd, "d mmmm yyyy") -> Emissions for whole production cycle running between 1 November 2023 and 31 March 2025
A33: =HYPERLINK("#'4.3.1.5 Atmos deposition'!A1", "4.3.1.5 Atmos deposition") -> 4.3.1.5 Atmos deposition
A34: =HYPERLINK("#'4.3.1.6-7 Leaching and runoff'!A1", "4.3.1.6-7 Leaching & runoff") -> 4.3.1.6-7 Leaching & runoff
A35: =HYPERLINK("#'4.3.1.8 Manure applied to soils'!A1", "4.3.1.8 Manure applied to soils") -> 4.3.1.8 Manure applied to soils | E35: Method 1 | F35: Method 2
A36: =HYPERLINK("#'4.3.1.9 Soil direct N2O'!A1", "4.3.1.9 Soil direct N2O") -> 4.3.1.9 Soil direct N2O | D36: Emissions for production cycle excluding removals | E36: =Result_EmissionsForWholeProductionCycle_Gross_Method1 -> #N/A | F36: =Result_EmissionsForWholeProductionCycle_Gross_Method2 -> #N/A | G36: t CO2e
A37: =HYPERLINK("#'4.3.1.10-11 Soil Atmos Dep'!A1", "4.3.1.10-11 Soil Atmos Deposition") -> 4.3.1.10-11 Soil Atmos Deposition | D37: Net emissions for production cycle | E37: =Result_EmissionsForWholeProductionCycle_Net_Method1 -> #N/A | F37: =Result_EmissionsForWholeProductionCycle_Net_Method2 -> #N/A | G37: t CO2e
A38: =HYPERLINK("#'4.3.1.12-13 Soil leach runoff'!A1", "4.3.1.12-13 Soil leach & runoff") -> 4.3.1.12-13 Soil leach & runoff
A39: =HYPERLINK("#'5.1.1.1-2 Inorganic fert N2O'!A1", "5.1.1.1-2 Inorganic fert N2O") -> 5.1.1.1-2 Inorganic fert N2O | D39: ="Product emissions intensity for whole production cycle running between " & TEXT(X_Cell_Enterprise_ProductionTimeframeStart, "d mmmm yyyy") & " and " & TEXT(X_Cell_Enterprise_ProductionTimeframeEnd, "d mmmm yyyy") -> Product emissions intensity for whole production cycle running between 1 November 2023 and 31 March 2025
A40: =HYPERLINK("#'5.1.1.3-4 Inorganic fert CO2'!A1", "5.1.1.3-4 Inorganic fert CO2") -> 5.1.1.3-4 Inorganic fert CO2
A41: =HYPERLINK("#'5.2.1.1-2 Organic Fert N2O'!A1", "5.2.1.1-2 Organic fert N2O") -> 5.2.1.1-2 Organic fert N2O
A42: =HYPERLINK("#'5.3.1.1-2 Lime CO2'!A1", "5.3.1.1-2 Lime CO2") -> 5.3.1.1-2 Lime CO2 | D42: Product emissions - Mass
A43: =HYPERLINK("#'5.4.1.1-4 Atmos deposition'!A1", "5.4.1.1-4 Atmos. deposition") -> 5.4.1.1-4 Atmos. deposition | D43: Product | E43: Product type | F43: Amount (tonnnes) | G43: Mass emissions assignment | H43: Emissions intensity (Method 1) | I43: Emissions intensity (Method 2) | J43: Unit
A44: =HYPERLINK("#'5.5.1.1-2 Leaching and runoff'!A1", "5.5.1.1-2 Leaching & runoff") -> 5.5.1.1-2 Leaching & runoff | D44: Milk sold - excluding removals | E44: Main product | F44: =X_Cell_Enterprise_MilkProduced*(IF(X_Cell_Enterprise_MilkProducedUnit="Litres of milk", 1.03, 1))*10^-3 -> 7.74457 | G44: =F44/(F44+F46+F48) -> 0.56346397 | H44: =(E36/F44)*G44 -> #N/A | I44: =(F36/F44)*G44 -> #N/A | J44: t co2e/t milk sold
A45: =HYPERLINK("#'6.2.1.1-2 Pasture residue N2O'!A1", "6.2.1.1-2 Pasture residue N2O") -> 6.2.1.1-2 Pasture residue N2O | D45: Milk sold - net emissions | E45: Main product | F45: =F44 -> 7.74457 | G45: =G44 -> 0.56346397 | H45: =(E37/F45)*G45 -> #N/A | I45: =(F37/F45)*G45 -> #N/A | J45: t co2e/t milk sold
A46: =HYPERLINK("#'6.3.1.1-2 Leach runoff pasture'!A1", "6.3.1.1-2 Leach & runoff (pasture)") -> 6.3.1.1-2 Leach & runoff (pasture) | D46: Liveweight sold - excluding removals | E46: Co-product | F46: =X_Cell_Enterprise_LiveweightSold -> 5 | G46: =F46/(F44+F46+F48) -> 0.36378002 | H46: =(E36/F46)*G46 -> #N/A | I46: =(F36/F46)*G46 -> #N/A | J46: t co2e/t liveweight sold
A47: =HYPERLINK("#'8.1.1.1-2 Transport fuel'!A1", "8.1.1.1-2 Transport fuel") -> 8.1.1.1-2 Transport fuel | D47: Liveweight sold - net emissions | E47: Co-product | F47: =F46 -> 5 | G47: =G46 -> 0.36378002 | H47: =(E37/F47)*G47 -> #N/A | I47: =(F37/F47)*G47 -> #N/A | J47: t co2e/t liveweight sold
A48: =HYPERLINK("#'8.2.1.1-2 Stationary fuel'!A1", "8.2.1.1-2 Stationary fuel") -> 8.2.1.1-2 Stationary fuel | D48: Manure sold - excluding removals | E48: Co-product | F48: =X_Cell_Enterprise_ManureSoldTonnes -> 1 | G48: =F48/(F44+F46+F48) -> 0.072756005 | H48: =(E36/F48)*G48 -> #N/A | I48: =(F36/F48)*G48 -> #N/A | J48: t co2e/t manure sold
A49: =HYPERLINK("#'10.1.1-2 Solid waste treatment'!A1", "10.1.1.1-2 Solid waste") -> 10.1.1.1-2 Solid waste | D49: Manure sold - net emissions | E49: Co-product | F49: =F48 -> 1 | G49: =G48 -> 0.072756005 | H49: =(E37/F49)*G49 -> #N/A | I49: =(F37/F49)*G49 -> #N/A | J49: t co2e/t manure sold
A50: =HYPERLINK("#'14.1.1-2 Purchased electricity'!A1", "14.1.1-2 Purchased electricity") -> 14.1.1-2 Purchased electricity | D50: Manure used as fertiliser on own farm | E50: Residual product | F50: =X_Cell_Enterprise_ManureUsedAsFertiliserTonnes -> 1 | G50: N/A | H50: N/A | I50: N/A
A51: =HYPERLINK("#'15 Scope 3'!A1", "15 Scope 3") -> 15 Scope 3
A52: =HYPERLINK("#'Calcs - Manure sent off-site'!A1", "Calcs - Manure sent off-site") -> Calcs - Manure sent off-site | D52: Product emissions - Economic
D53: Product | E53: Product type | F53: Amount (tonnnes) | G53: Economic emissions assignment | H53: Emissions intestity (Method 1) | I53: Emissions intestity (Method 2) | J53: Unit
D54: Milk sold - excluding removals | E54: Main product | F54: =X_Cell_Enterprise_MilkProduced*(IF(X_Cell_Enterprise_MilkProducedUnit="Litres", 1.03, 1))*10^-3 -> 7.519 | G54: =X_Cell_Enterprise_PercentIncomeFromMilk -> 0.8 | H54: =E36*G54/F54 -> #N/A | I54: =F36*G54/F54 -> #N/A | J54: t co2e/t grain sold
A55: APPENDICES | D55: Milk sold - net emissions | E55: Main product | F55: =F54 -> 7.519 | G55: =G54 -> 0.8 | H55: =E37*G55/F55 -> #N/A | I55: =F37*G55/F55 -> #N/A | J55: t co2e/t grain sold
A56: =HYPERLINK("#'Constants - Dairy'!A1", "Constants - Dairy") -> Constants - Dairy | D56: Liveweight sold - excluding removals | E56: Co-product | F56: =X_Cell_Enterprise_LiveweightSold -> 5 | G56: =X_Cell_Enterprise_PercentIncomeFromLiveweight -> 0.15 | H56: =E36*G56/F56 -> #N/A | I56: =F36*G56/F56 -> #N/A
A57: =HYPERLINK("#'Constants - Ag Residue'!A1", "Constants - Ag residue") -> Constants - Ag residue | D57: Liveweight sold - net emissions | E57: Co-product | F57: =F56 -> 5 | G57: =G56 -> 0.15 | H57: =E37*G57/F57 -> #N/A | I57: =F37*G57/F57 -> #N/A | J57: t co2e/t baled hay/silage
A58: =HYPERLINK("#'Constants - Common Livestock'!A1", "Constants - Common Livestock") -> Constants - Common Livestock | D58: Manure sold - excluding removals | E58: Co-product | F58: =X_Cell_Enterprise_ManureSoldTonnes -> 1 | G58: =X_Cell_Enterprise_PercentIncomeFromManure -> 0.05 | H58: =E36*G58/F58 -> #N/A | I58: =F36*G58/F58 -> #N/A | J58: t co2e/t baled hay/silage
A59: =HYPERLINK("#'Constants - Electricity'!A1", "Constants - Electricity") -> Constants - Electricity | D59: Manure sold - net emissions | E59: Co-product | F59: =F58 -> 1 | G59: =G58 -> 0.05 | H59: =E37*G59/F59 -> #N/A | I59: =F37*G59/F59 -> #N/A
A60: =HYPERLINK("#'Constants - Fertiliser'!A1", "Constants - Fertiliser") -> Constants - Fertiliser | D60: Manure used as fertiliser on own farm | E60: Residual product | F60: =X_Cell_Enterprise_ManureUsedAsFertiliserTonnes -> 1 | G60: N/A | H60: N/A | I60: N/A
A61: =HYPERLINK("#'Constants - Fuel'!A1", "Constants - Fuel") -> Constants - Fuel
A62: =HYPERLINK("#'Constants - Scope 3'!A1", "Constants - Scope 3") -> Constants - Scope 3
A63: =HYPERLINK("#'Constants - Common'!A1", "Constants - Common") -> Constants - Common
A64: =HYPERLINK("#'Constants - Solid Waste'!A1", "Constants - Solid Waste") -> Constants - Solid Waste
A65: =HYPERLINK("#'Acknowledgements'!A1", "Acknowledgements") -> Acknowledgements

Sheet Input - Enterprise
A1: #VALUE! | C1: Input - Enterprise
A3: =HYPERLINK("#'Home'!A1", "Home") -> Home
A4: =HYPERLINK("#'Results - Activity period'!A1", "Results - Activity period") -> Results - Activity period
A5: =HYPERLINK("#'Results - Product EI'!A1", "Results - Product Emissions Intensity") -> Results - Product Emissions Intensity | D5: Your business
A6: =HYPERLINK("#'Results'!A1", "Results") -> Results
D7: Farm name | E7: Test Farms
D8: Reporting entity name | E8: Test Farms Pty Ltd
A9: INPUTS
A10: =HYPERLINK("#'Input - Enterprise'!A1", "Enterprise") -> Enterprise | D10: 💡An 'Emissions accounting period' is a 12 month period where the business can report on the emissions, and is typically the same as the business' financial accounting period.
A11: =HYPERLINK("#'Input - Site'!A1", "Site") -> Site
A12: =HYPERLINK("#'Input - Dairy'!A1", "Dairy") -> Dairy | D12: Emissions calculation period start date | E12: 45292 | F12: ← DD/MM/YYYY or DD Month YYYY
A13: =HYPERLINK("#'Input - Livestock sales'!A1", "Livestock sales") -> Livestock sales | D13: Emissions calculation period end date | E13: =DATE(YEAR(E12)+1,MONTH(E12),DAY(E12))-1 -> 45657 | F13: ← Automatically calculated, 12 months after start date
A14: =HYPERLINK("#'Input - Dairy cattle purchases'!A1", "Dairy cattle purchases") -> Dairy cattle purchases
A15: =HYPERLINK("#'Input - Pasture'!A1", "Pasture") -> Pasture
A16: =HYPERLINK("#'Input - Fert Prod System'!A1", "Fert Prod System") -> Fert Prod System | D16: Production
A17: =HYPERLINK("#'Input - Fertiliser'!A1", "Fertiliser") -> Fertiliser
A18: =HYPERLINK("#'Input - Fuel'!A1", "Fuel") -> Fuel | D18: Production timeframe start | E18: 45231 | F18: ← DD/MM/YYYY or DD Month YYYY
A19: =HYPERLINK("#'Input - Electricity'!A1", "Electricity") -> Electricity | D19: Production timeframe end | E19: 45747 | F19: ← DD/MM/YYYY or DD Month YYYY
A20: =HYPERLINK("#'Input - Common farm inputs'!A1", "Common farm inputs") -> Common farm inputs | D20: Production timeframe length | E20: =DATEDIF(E18,E19+1,"m") -> 17 | F20: Months
A21: =HYPERLINK("#'Input - Crop pasture farm input'!A1", "Crop pasture farm input") -> Crop pasture farm input
A22: =HYPERLINK("#'Input - Livestock farm Inputs'!A1", "Livestock farm Inputs") -> Livestock farm Inputs | D22: Liveweight sold | E22: =SUM(Table_Input_LivestockSales[Total liveweight sold])*10^-3 -> 5 | F22: tonnes
A23: =HYPERLINK("#'Input - Freight'!A1", "Freight") -> Freight | D23: Milk produced unit | E23: {=X_Cell_Dairy_MilkProductionUnit} -> Litres of milk
A24: =HYPERLINK("#'Input - Solid waste'!A1", "Solid waste") -> Solid waste | D24: Milk produced | E24: {=X_Cell_Dairy_MilkProductionAmount*365*IF(E23="Milk solds", 1, 1.03)} -> 7519 | F24: =E23 -> Litres of milk
A25: =HYPERLINK("#'Input - Manure sent off-site'!A1", "Manure sent off-site") -> Manure sent off-site | D25: Manure sold | E25: 1 | F25: tonnes
A26: =HYPERLINK("#'Input - Data quality'!A1", "Data quality") -> Data quality | D26: Manure used as fertiliser on own farm | E26: 1 | F26: tonnes
D28: Percentage of income from milk sold | E28: 0.8 | F28: percent
A29: CALCULATIONS | D29: Percentage of income from liveweight sold | E29: 0.15 | F29: percent
A30: =HYPERLINK("#'3.3.1.1-2 Enteric Methane'!A1", "3.3.1.1-2 Enteric methane") -> 3.3.1.1-2 Enteric methane | D30: Percentage of income from manure sold | E30: 0.05 | F30: percent
A31: =HYPERLINK("#'4.3.1.1-2 Methane'!A1", "4.3.1.1-2 Manure methane") -> 4.3.1.1-2 Manure methane
A32: =HYPERLINK("#'4.3.1.3-4 Direct N20'!A1", "4.3.1.3-4 Direct N20") -> 4.3.1.3-4 Direct N20
A33: =HYPERLINK("#'4.3.1.5 Atmos deposition'!A1", "4.3.1.5 Atmos deposition") -> 4.3.1.5 Atmos deposition
A34: =HYPERLINK("#'4.3.1.6-7 Leaching and runoff'!A1", "4.3.1.6-7 Leaching & runoff") -> 4.3.1.6-7 Leaching & runoff | D34: Carbon removals
A35: =HYPERLINK("#'4.3.1.8 Manure applied to soils'!A1", "4.3.1.8 Manure applied to soils") -> 4.3.1.8 Manure applied to soils
A36: =HYPERLINK("#'4.3.1.9 Soil direct N2O'!A1", "4.3.1.9 Soil direct N2O") -> 4.3.1.9 Soil direct N2O
A37: =HYPERLINK("#'4.3.1.10-11 Soil Atmos Dep'!A1", "4.3.1.10-11 Soil Atmos Deposition") -> 4.3.1.10-11 Soil Atmos Deposition | D37: ="Carbon captured from " & TEXT(X_Cell_Site_StartDate, "d mmmm yyyy") & " to " & TEXT(X_Cell_Site_EndDate, "d, mmmm, yyyy") & " from environmental plantings" -> Carbon captured from 1 January 2024 to 31, December, 2024 from environmental plantings
A38: =HYPERLINK("#'4.3.1.12-13 Soil leach runoff'!A1", "4.3.1.12-13 Soil leach & runoff") -> 4.3.1.12-13 Soil leach & runoff
A39: =HYPERLINK("#'5.1.1.1-2 Inorganic fert N2O'!A1", "5.1.1.1-2 Inorganic fert N2O") -> 5.1.1.1-2 Inorganic fert N2O | D39: Planting name | E39: Total removed CO2 | F39: Percent allocated to this enterprise | G39: Removal allocated to this enterprise
A40: =HYPERLINK("#'5.1.1.3-4 Inorganic fert CO2'!A1", "5.1.1.3-4 Inorganic fert CO2") -> 5.1.1.3-4 Inorganic fert CO2 | G40: =Table_Input_Enterprise_PlantingRemovals[[#This Row],[Total removed CO2]]*Table_Input_Enterprise_PlantingRemovals[[#This Row],[Percent allocated to this enterprise]] -> 0
A41: =HYPERLINK("#'5.2.1.1-2 Organic Fert N2O'!A1", "5.2.1.1-2 Organic fert N2O") -> 5.2.1.1-2 Organic fert N2O
A42: =HYPERLINK("#'5.3.1.1-2 Lime CO2'!A1", "5.3.1.1-2 Lime CO2") -> 5.3.1.1-2 Lime CO2
A43: =HYPERLINK("#'5.4.1.1-4 Atmos deposition'!A1", "5.4.1.1-4 Atmos. deposition") -> 5.4.1.1-4 Atmos. deposition
A44: =HYPERLINK("#'5.5.1.1-2 Leaching and runoff'!A1", "5.5.1.1-2 Leaching & runoff") -> 5.5.1.1-2 Leaching & runoff | D44: Production cycle emissions and removals
A45: =HYPERLINK("#'6.2.1.1-2 Pasture residue N2O'!A1", "6.2.1.1-2 Pasture residue N2O") -> 6.2.1.1-2 Pasture residue N2O
A46: =HYPERLINK("#'6.3.1.1-2 Leach runoff pasture'!A1", "6.3.1.1-2 Leach & runoff (pasture)") -> 6.3.1.1-2 Leach & runoff (pasture) | D46: ="Gross emissions from other activity periods in the production timeframe " & TEXT(X_Cell_Enterprise_ProductionTimeframeStart, "d mmmm yyyy") & " to " & TEXT(X_Cell_Enterprise_ProductionTimeframeEnd, "d mmmm yyyy") -> Gross emissions from other activity periods in the production timeframe 1 November 2023 to 31 March 2025
A47: =HYPERLINK("#'8.1.1.1-2 Transport fuel'!A1", "8.1.1.1-2 Transport fuel") -> 8.1.1.1-2 Transport fuel
A48: =HYPERLINK("#'8.2.1.1-2 Stationary fuel'!A1", "8.2.1.1-2 Stationary fuel") -> 8.2.1.1-2 Stationary fuel | D48: {="There are " & Common_InputFunctions.getOverlappingReportingCycles(X_Cell_Enterprise_ProductionTimeframeStart,X_Cell_Enterprise_ProductionTimeframeEnd,X_Cell_Site_StartDate) & " emissions calculation periods that need to be completed before total product emissions can be determined."} -> There are 3 emissions calculation periods that need to be completed before total product emissions can be determined.
A49: =HYPERLINK("#'10.1.1-2 Solid waste treatment'!A1", "10.1.1.1-2 Solid waste") -> 10.1.1.1-2 Solid waste | D49: Enter the method 1 and 2 CO2e emissions (excluding removals) from previous emissions calculation periods if applicable.
A50: =HYPERLINK("#'14.1.1-2 Purchased electricity'!A1", "14.1.1-2 Purchased electricity") -> 14.1.1-2 Purchased electricity
A51: =HYPERLINK("#'15 Scope 3'!A1", "15 Scope 3") -> 15 Scope 3 | D51: Emissions calculation cycle | E51: CO2-e emissions method 1 | F51: CO2-e emissions method 2
A52: =HYPERLINK("#'Calcs - Manure sent off-site'!A1", "Calcs - Manure sent off-site") -> Calcs - Manure sent off-site | D52: {=Common_InputFunctions.getOverlappingReportingPeriods(X_Cell_Enterprise_ProductionTimeframeStart,X_Cell_Enterprise_ProductionTimeframeEnd,X_Cell_Site_StartDate)} -> 01 Jan 2023 to 31 Dec 2023 | E52: =IF(ISBLANK($D52), 0, IF(ISNUMBER(SEARCH("reporting", $D52)), Result_Enterprise_Gross_Method1, "Enter value")) -> Enter value | F52: =IF(ISBLANK($D52), 0, IF(ISNUMBER(SEARCH("reporting", $D52)), Result_Enterprise_Gross_Method2, "Enter value")) -> Enter value | G52: t CO2e
D53: 01 Jan 2024 to 31 Dec 2024 (This reporting cycle) | E53: =IF(ISBLANK($D53), 0, IF(ISNUMBER(SEARCH("reporting", $D53)), Result_Enterprise_Gross_Method1, "Enter value")) -> #N/A | F53: =IF(ISBLANK($D53), 0, IF(ISNUMBER(SEARCH("reporting", $D53)), Result_Enterprise_Gross_Method2, "Enter value")) -> #N/A | G53: t CO2e
D54: 01 Jan 2025 to 31 Dec 2025 | E54: =IF(ISBLANK($D54), 0, IF(ISNUMBER(SEARCH("reporting", $D54)), Result_Enterprise_Gross_Method1, "Enter value")) -> Enter value | F54: =IF(ISBLANK($D54), 0, IF(ISNUMBER(SEARCH("reporting", $D54)), Result_Enterprise_Gross_Method2, "Enter value")) -> Enter value | G54: t CO2e
A55: APPENDICES | E55: =IF(ISBLANK($D55), 0, IF(ISNUMBER(SEARCH("reporting", $D55)), Result_Enterprise_Gross_Method1, "Enter value")) -> 0 | F55: =IF(ISBLANK($D55), 0, IF(ISNUMBER(SEARCH("reporting", $D55)), Result_Enterprise_Gross_Method2, "Enter value")) -> 0 | G55: t CO2e
A56: =HYPERLINK("#'Constants - Dairy'!A1", "Constants - Dairy") -> Constants - Dairy | E56: =IF(ISBLANK($D56), 0, IF(ISNUMBER(SEARCH("reporting", $D56)), Result_Enterprise_Gross_Method1, "Enter value")) -> 0 | F56: =IF(ISBLANK($D56), 0, IF(ISNUMBER(SEARCH("reporting", $D56)), Result_Enterprise_Gross_Method2, "Enter value")) -> 0 | G56: t CO2e
A57: =HYPERLINK("#'Constants - Ag Residue'!A1", "Constants - Ag residue") -> Constants - Ag residue | D57: Total emissions for production cycle | E57: =SUM(E52:E56) -> #N/A | F57: =SUM(F52:F56) -> #N/A | G57: t CO2e
A58: =HYPERLINK("#'Constants - Common Livestock'!A1", "Constants - Common Livestock") -> Constants - Common Livestock
A59: =HYPERLINK("#'Constants - Electricity'!A1", "Constants - Electricity") -> Constants - Electricity
A60: =HYPERLINK("#'Constants - Fertiliser'!A1", "Constants - Fertiliser") -> Constants - Fertiliser
A61: =HYPERLINK("#'Constants - Fuel'!A1", "Constants - Fuel") -> Constants - Fuel
A62: =HYPERLINK("#'Constants - Scope 3'!A1", "Constants - Scope 3") -> Constants - Scope 3 | D62: ="Carbon removals from environmental plantings for whole production cycle running between " & TEXT(X_Cell_Enterprise_ProductionTimeframeStart, "d mmmm yyyy") & " and " & TEXT(X_Cell_Enterprise_ProductionTimeframeEnd, "d mmmm yyyy") -> Carbon removals from environmental plantings for whole production cycle running between 1 November 2023 and 31 March 2025
A63: =HYPERLINK("#'Constants - Common'!A1", "Constants - Common") -> Constants - Common
A64: =HYPERLINK("#'Constants - Solid Waste'!A1", "Constants - Solid Waste") -> Constants - Solid Waste | D64: Emissions calculation cycle | E64: CO2 removed attributed to this enterprise
A65: =HYPERLINK("#'Acknowledgements'!A1", "Acknowledgements") -> Acknowledgements | D65: {=Common_InputFunctions.getOverlappingReportingPeriods(X_Cell_Enterprise_ProductionTimeframeStart,X_Cell_Enterprise_ProductionTimeframeEnd,X_Cell_Site_StartDate)} -> 01 Jan 2023 to 31 Dec 2023 | E65: =IF(ISBLANK($D65), 0, IF(ISNUMBER(SEARCH("reporting", $D65)), SUM(Table_Input_Enterprise_PlantingRemovals[Removal allocated to this enterprise]), "Enter value")) -> Enter value | F65: t CO2
D66: 01 Jan 2024 to 31 Dec 2024 (This reporting cycle) | E66: =IF(ISBLANK($D66), 0, IF(ISNUMBER(SEARCH("reporting", $D66)), SUM(Table_Input_Enterprise_PlantingRemovals[Removal allocated to this enterprise]), "Enter value")) -> 0 | F66: t CO2
D67: 01 Jan 2025 to 31 Dec 2025 | E67: =IF(ISBLANK($D67), 0, IF(ISNUMBER(SEARCH("reporting", $D67)), SUM(Table_Input_Enterprise_PlantingRemovals[Removal allocated to this enterprise]), "Enter value")) -> Enter value | F67: t CO2
E68: =IF(ISBLANK($D68), 0, IF(ISNUMBER(SEARCH("reporting", $D68)), SUM(Table_Input_Enterprise_PlantingRemovals[Removal allocated to this enterprise]), "Enter value")) -> 0 | F68: t CO2
E69: =IF(ISBLANK($D69), 0, IF(ISNUMBER(SEARCH("reporting", $D69)), SUM(Table_Input_Enterprise_PlantingRemovals[Removal allocated to this enterprise]), "Enter value")) -> 0 | F69: t CO2
D70: Total carbon removals for production cycle | E70: =SUM(E65:E69) -> 0 | F70: t CO2
D73: ="Net emissions from other activity periods in the production timeframe " & TEXT(X_Cell_Enterprise_ProductionTimeframeStart, "d mmmm yyyy") & " to " & TEXT(X_Cell_Enterprise_ProductionTimeframeEnd, "d mmmm yyyy") -> Net emissions from other activity periods in the production timeframe 1 November 2023 to 31 March 2025
D75: Emissions calculation cycle | E75: CO2-e emissions method 1 | F75: CO2-e emissions method 2
D76: {=Common_InputFunctions.getOverlappingReportingPeriods(X_Cell_Enterprise_ProductionTimeframeStart,X_Cell_Enterprise_ProductionTimeframeEnd,X_Cell_Site_StartDate)} -> 01 Jan 2023 to 31 Dec 2023 | E76: =IF(ISBLANK($D76), 0, IF(ISNUMBER(SEARCH("reporting", $D76)), E52-$E$67, "Enter value")) -> Enter value | F76: =IF(ISBLANK($D76), 0, IF(ISNUMBER(SEARCH("reporting", $D76)), F52-$E$67, "Enter value")) -> Enter value | G76: t CO2e
D77: 01 Jan 2024 to 31 Dec 2024 (This reporting cycle) | E77: =IF(ISBLANK($D77), 0, IF(ISNUMBER(SEARCH("reporting", $D77)), E53-$E$67, "Enter value")) -> #N/A | F77: =IF(ISBLANK($D77), 0, IF(ISNUMBER(SEARCH("reporting", $D77)), F53-$E$67, "Enter value")) -> #N/A | G77: t CO2e
D78: 01 Jan 2025 to 31 Dec 2025 | E78: =IF(ISBLANK($D78), 0, IF(ISNUMBER(SEARCH("reporting", $D78)), E54-$E$67, "Enter value")) -> Enter value | F78: =IF(ISBLANK($D78), 0, IF(ISNUMBER(SEARCH("reporting", $D78)), F54-$E$67, "Enter value")) -> Enter value | G78: t CO2e
E79: =IF(ISBLANK($D79), 0, IF(ISNUMBER(SEARCH("reporting", $D79)), E55-$E$67, "Enter value")) -> 0 | F79: =IF(ISBLANK($D79), 0, IF(ISNUMBER(SEARCH("reporting", $D79)), F55-$E$67, "Enter value")) -> 0 | G79: t CO2e
E80: =IF(ISBLANK($D80), 0, IF(ISNUMBER(SEARCH("reporting", $D80)), E56-$E$67, "Enter value")) -> 0 | F80: =IF(ISBLANK($D80), 0, IF(ISNUMBER(SEARCH("reporting", $D80)), F56-$E$67, "Enter value")) -> 0 | G80: t CO2e
D81: Total emissions for production cycle | E81: =SUM(E76:E80) -> #N/A | F81: =SUM(F76:F80) -> #N/A | G81: t CO2e

Sheet Input - Site
A1: #VALUE! | C1: Input - Site
A3: =HYPERLINK("#'Home'!A1", "Home") -> Home
A4: =HYPERLINK("#'Results - Activity period'!A1", "Results - Activity period") -> Results - Activity period
A5: =HYPERLINK("#'Results - Product EI'!A1", "Results - Product Emissions Intensity") -> Results - Product Emissions Intensity | D5: Location and climate
A6: =HYPERLINK("#'Results'!A1", "Results") -> Results
D7: Location information is used to reference some region and climate-specific emission factors
D8: Tip: Use the web-based GAF Location Helper tool to easily get region and climate information. You will need an internet connection to use the GAF Location Helper.
A9: INPUTS
A10: =HYPERLINK("#'Input - Enterprise'!A1", "Enterprise") -> Enterprise | D10: State | E10: Western Australia | F10: ← Please select
A11: =HYPERLINK("#'Input - Site'!A1", "Site") -> Site | D11: Region (ABS Statistical area level 4) if state is WA | E11: Western Australia - Outback (South) | F11: ← Please select
A12: =HYPERLINK("#'Input - Dairy'!A1", "Dairy") -> Dairy | D12: Leaching zone | E12: NO - Not in leaching zone | F12: ← Please select
A13: =HYPERLINK("#'Input - Livestock sales'!A1", "Livestock sales") -> Livestock sales | D13: Elevation | E13: 307.7 | F13: Meters
A14: =HYPERLINK("#'Input - Dairy cattle purchases'!A1", "Dairy cattle purchases") -> Dairy cattle purchases | D14: Average temperature for reporting period | E14: 18 | F14: Degrees celsius
A15: =HYPERLINK("#'Input - Pasture'!A1", "Pasture") -> Pasture | D15: Total rainfall for reporting period | E15: 601 | F15: Millimetres
A16: =HYPERLINK("#'Input - Fert Prod System'!A1", "Fert Prod System") -> Fert Prod System | D16: Potential evapotranspiration for reporting period | E16: 1326 | F16: Millimetres
A17: =HYPERLINK("#'Input - Fertiliser'!A1", "Fertiliser") -> Fertiliser | D17: Number of frost days for reporting period | E17: 7 | F17: Days
A18: =HYPERLINK("#'Input - Fuel'!A1", "Fuel") -> Fuel | D18: MAP:PET ratio | E18: =E15/E16 -> 0.45324284
A19: =HYPERLINK("#'Input - Electricity'!A1", "Electricity") -> Electricity | D19: Rainfall zone | E19: =Common_InputFunctions.Utility_LookupItemFromMinMax(E15,Table_SourceData_RainfallZones[Min rainfall],Table_SourceData_RainfallZones[Max rainfall],Table_SourceData_RainfallZones[Rainfall Zone]) -> High rainfall
A20: =HYPERLINK("#'Input - Common farm inputs'!A1", "Common farm inputs") -> Common farm inputs | D20: Climate zone | E20: =Common_InputFunctions.Utility_GetClimateZone(E14,E15,E17,E13,E18,Table_SourceData_ClimateZones[Min temp],Table_SourceData_ClimateZones[Max temp],Table_SourceData_ClimateZones[Min rainfall],Table_SourceData_ClimateZones[Max rainfall],Table_SourceData_ClimateZones[Min frost days],Table_SourceData_ClimateZones[Max frost days],Table_SourceData_ClimateZones[Min elevation],Table_SourceData_ClimateZones[Max elevation],Table_SourceData_ClimateZones[Min MAP:PET],Table_SourceData_ClimateZones[Max MAP:PET],Table_SourceData_ClimateZones[Climate zone]) -> Warm temperate dry
A21: =HYPERLINK("#'Input - Crop pasture farm input'!A1", "Crop pasture farm input") -> Crop pasture farm input | D21: Wet or dry climate zone | E21: =Common_InputFunctions.Utility_LookupValueInTable($E$20,Table_SourceData_WetDryZones[Climate zone],Table_SourceData_WetDryZones[Wet or Dry Zone]) -> Dry climate zone
A22: =HYPERLINK("#'Input - Livestock farm Inputs'!A1", "Livestock farm Inputs") -> Livestock farm Inputs | D22: Temperature zone | E22: =Common_InputFunctions.Utility_LookupItemFromMinMax(E14,Table_SourceData_TemperatureZones[Min MAT],Table_SourceData_TemperatureZones[Max MAT],Table_SourceData_TemperatureZones[Temperature Zone]) -> Temperate
A23: =HYPERLINK("#'Input - Freight'!A1", "Freight") -> Freight
A24: =HYPERLINK("#'Input - Solid waste'!A1", "Solid waste") -> Solid waste
A25: =HYPERLINK("#'Input - Manure sent off-site'!A1", "Manure sent off-site") -> Manure sent off-site
A26: =HYPERLINK("#'Input - Data quality'!A1", "Data quality") -> Data quality
A29: CALCULATIONS
A30: =HYPERLINK("#'3.3.1.1-2 Enteric Methane'!A1", "3.3.1.1-2 Enteric methane") -> 3.3.1.1-2 Enteric methane
A31: =HYPERLINK("#'4.3.1.1-2 Methane'!A1", "4.3.1.1-2 Manure methane") -> 4.3.1.1-2 Manure methane
A32: =HYPERLINK("#'4.3.1.3-4 Direct N20'!A1", "4.3.1.3-4 Direct N20") -> 4.3.1.3-4 Direct N20
A33: =HYPERLINK("#'4.3.1.5 Atmos deposition'!A1", "4.3.1.5 Atmos deposition") -> 4.3.1.5 Atmos deposition
A34: =HYPERLINK("#'4.3.1.6-7 Leaching and runoff'!A1", "4.3.1.6-7 Leaching & runoff") -> 4.3.1.6-7 Leaching & runoff
A35: =HYPERLINK("#'4.3.1.8 Manure applied to soils'!A1", "4.3.1.8 Manure applied to soils") -> 4.3.1.8 Manure applied to soils
A36: =HYPERLINK("#'4.3.1.9 Soil direct N2O'!A1", "4.3.1.9 Soil direct N2O") -> 4.3.1.9 Soil direct N2O
A37: =HYPERLINK("#'4.3.1.10-11 Soil Atmos Dep'!A1", "4.3.1.10-11 Soil Atmos Deposition") -> 4.3.1.10-11 Soil Atmos Deposition
A38: =HYPERLINK("#'4.3.1.12-13 Soil leach runoff'!A1", "4.3.1.12-13 Soil leach & runoff") -> 4.3.1.12-13 Soil leach & runoff
A39: =HYPERLINK("#'5.1.1.1-2 Inorganic fert N2O'!A1", "5.1.1.1-2 Inorganic fert N2O") -> 5.1.1.1-2 Inorganic fert N2O
A40: =HYPERLINK("#'5.1.1.3-4 Inorganic fert CO2'!A1", "5.1.1.3-4 Inorganic fert CO2") -> 5.1.1.3-4 Inorganic fert CO2
A41: =HYPERLINK("#'5.2.1.1-2 Organic Fert N2O'!A1", "5.2.1.1-2 Organic fert N2O") -> 5.2.1.1-2 Organic fert N2O
A42: =HYPERLINK("#'5.3.1.1-2 Lime CO2'!A1", "5.3.1.1-2 Lime CO2") -> 5.3.1.1-2 Lime CO2
A43: =HYPERLINK("#'5.4.1.1-4 Atmos deposition'!A1", "5.4.1.1-4 Atmos. deposition") -> 5.4.1.1-4 Atmos. deposition
A44: =HYPERLINK("#'5.5.1.1-2 Leaching and runoff'!A1", "5.5.1.1-2 Leaching & runoff") -> 5.5.1.1-2 Leaching & runoff
A45: =HYPERLINK("#'6.2.1.1-2 Pasture residue N2O'!A1", "6.2.1.1-2 Pasture residue N2O") -> 6.2.1.1-2 Pasture residue N2O
A46: =HYPERLINK("#'6.3.1.1-2 Leach runoff pasture'!A1", "6.3.1.1-2 Leach & runoff (pasture)") -> 6.3.1.1-2 Leach & runoff (pasture)
A47: =HYPERLINK("#'8.1.1.1-2 Transport fuel'!A1", "8.1.1.1-2 Transport fuel") -> 8.1.1.1-2 Transport fuel
A48: =HYPERLINK("#'8.2.1.1-2 Stationary fuel'!A1", "8.2.1.1-2 Stationary fuel") -> 8.2.1.1-2 Stationary fuel
A49: =HYPERLINK("#'10.1.1-2 Solid waste treatment'!A1", "10.1.1.1-2 Solid waste") -> 10.1.1.1-2 Solid waste
A50: =HYPERLINK("#'14.1.1-2 Purchased electricity'!A1", "14.1.1-2 Purchased electricity") -> 14.1.1-2 Purchased electricity
A51: =HYPERLINK("#'15 Scope 3'!A1", "15 Scope 3") -> 15 Scope 3
A52: =HYPERLINK("#'Calcs - Manure sent off-site'!A1", "Calcs - Manure sent off-site") -> Calcs - Manure sent off-site
A55: APPENDICES
A56: =HYPERLINK("#'Constants - Dairy'!A1", "Constants - Dairy") -> Constants - Dairy
A57: =HYPERLINK("#'Constants - Ag Residue'!A1", "Constants - Ag residue") -> Constants - Ag residue
A58: =HYPERLINK("#'Constants - Common Livestock'!A1", "Constants - Common Livestock") -> Constants - Common Livestock
A59: =HYPERLINK("#'Constants - Electricity'!A1", "Constants - Electricity") -> Constants - Electricity
A60: =HYPERLINK("#'Constants - Fertiliser'!A1", "Constants - Fertiliser") -> Constants - Fertiliser
A61: =HYPERLINK("#'Constants - Fuel'!A1", "Constants - Fuel") -> Constants - Fuel
A62: =HYPERLINK("#'Constants - Scope 3'!A1", "Constants - Scope 3") -> Constants - Scope 3
A63: =HYPERLINK("#'Constants - Common'!A1", "Constants - Common") -> Constants - Common
A64: =HYPERLINK("#'Constants - Solid Waste'!A1", "Constants - Solid Waste") -> Constants - Solid Waste
A65: =HYPERLINK("#'Acknowledgements'!A1", "Acknowledgements") -> Acknowledgements

Sheet Input - Dairy
A1: #VALUE! | C1: Input -Dairy
A3: =HYPERLINK("#'Home'!A1", "Home") -> Home
A4: =HYPERLINK("#'Results - Activity period'!A1", "Results - Activity period") -> Results - Activity period
A5: =HYPERLINK("#'Results - Product EI'!A1", "Results - Product Emissions Intensity") -> Results - Product Emissions Intensity | D5: Herd movement
A6: =HYPERLINK("#'Results'!A1", "Results") -> Results
D7: Breed | E7: Medium Friesian | F7: ← Please select
A9: INPUTS | E9: Milking cows | F9: Heifers > 1 year | G9: Heifers < 1 year | H9: Bulls > 1 year | I9: Bulls < 1 year
A10: =HYPERLINK("#'Input - Enterprise'!A1", "Enterprise") -> Enterprise | D10: ="Average number of head between " & TEXT(X_Cell_Site_StartDate, "dd mmm yy") & " and " & TEXT(X_Cell_Site_EndDate, "dd mmm yy") -> Average number of head between NO - Not in leaching zone and 02 Nov 00 | E10: 100 | F10: 100 | G10: 100 | H10: 100 | I10: 100 | J10: head
A11: =HYPERLINK("#'Input - Site'!A1", "Site") -> Site
A12: =HYPERLINK("#'Input - Dairy'!A1", "Dairy") -> Dairy | D12: Liveweight
A13: =HYPERLINK("#'Input - Livestock sales'!A1", "Livestock sales") -> Livestock sales | D13: Method 1 default values (Do not edit) | E13: Milking cows | F13: Heifers > 1 year | G13: Heifers < 1 year | H13: Bulls > 1 year | I13: Bulls < 1 year
A14: =HYPERLINK("#'Input - Dairy cattle purchases'!A1", "Dairy cattle purchases") -> Dairy cattle purchases | D14: Average liveweight | E14: =Common_InputFunctions.Utility_LookupValueInTableNumber(X_Cell_Dairy_Breed, Table_SourceData_Dairy_WjCowsHeifers[Breed],Table_SourceData_Dairy_WjCowsHeifers[Milking cows]) -> 550 | F14: =Common_InputFunctions.Utility_LookupValueInTableNumber(X_Cell_Dairy_Breed, Table_SourceData_Dairy_WjCowsHeifers[Breed],Table_SourceData_Dairy_WjCowsHeifers[Heifers > 1]) -> 380 | G14: =Common_InputFunctions.Utility_LookupValueInTableNumber(X_Cell_Dairy_Breed, Table_SourceData_Dairy_WjCowsHeifers[Breed],Table_SourceData_Dairy_WjCowsHeifers[Heifers < 1 (weaned)]) -> 155 | H14: {=Table_SourceData_Dairy_WjBulls[Bulls > 1]} -> 600 | I14: {=Table_SourceData_Dairy_WjBulls[Bulls < 1 (weaned)]} -> 225 | J14: kg/head
A15: =HYPERLINK("#'Input - Pasture'!A1", "Pasture") -> Pasture | D15: Average liveweight gain | E15: {=Table_SourceData_Dairy_LWGj[Milking cows]} -> 0.016 | F15: {=Table_SourceData_Dairy_LWGj[Heifers > 1]} -> 0.6 | G15: {=Table_SourceData_Dairy_LWGj[Heifers < 1 (weaned)]} -> 0.57 | H15: {=Table_SourceData_Dairy_LWGj[Bulls > 1]} -> 0.1 | I15: {=Table_SourceData_Dairy_LWGj[Bulls < 1 (weaned)]} -> 0.8 | J15: kg/head/day
A16: =HYPERLINK("#'Input - Fert Prod System'!A1", "Fert Prod System") -> Fert Prod System
A17: =HYPERLINK("#'Input - Fertiliser'!A1", "Fertiliser") -> Fertiliser | D17: Method 2 custom values (Edit if known) | E17: Milking cows | F17: Heifers > 1 year | G17: Heifers < 1 year | H17: Bulls > 1 year | I17: Bulls < 1 year
A18: =HYPERLINK("#'Input - Fuel'!A1", "Fuel") -> Fuel | D18: Average liveweight | E18: =Common_InputFunctions.Utility_LookupValueInTableNumber(X_Cell_Dairy_Breed, Table_SourceData_Dairy_WjCowsHeifers[Breed],Table_SourceData_Dairy_WjCowsHeifers[Milking cows]) -> 550 | F18: =Common_InputFunctions.Utility_LookupValueInTableNumber(X_Cell_Dairy_Breed, Table_SourceData_Dairy_WjCowsHeifers[Breed],Table_SourceData_Dairy_WjCowsHeifers[Heifers > 1]) -> 380 | G18: =Common_InputFunctions.Utility_LookupValueInTableNumber(X_Cell_Dairy_Breed, Table_SourceData_Dairy_WjCowsHeifers[Breed],Table_SourceData_Dairy_WjCowsHeifers[Heifers < 1 (weaned)]) -> 155 | H18: {=Table_SourceData_Dairy_WjBulls[Bulls > 1]} -> 600 | I18: {=Table_SourceData_Dairy_WjBulls[Bulls < 1 (weaned)]} -> 225 | J18: kg/head
A19: =HYPERLINK("#'Input - Electricity'!A1", "Electricity") -> Electricity | D19: Average liveweight gain | E19: {=Table_SourceData_Dairy_LWGj[Milking cows]} -> 0.016 | F19: {=Table_SourceData_Dairy_LWGj[Heifers > 1]} -> 0.6 | G19: {=Table_SourceData_Dairy_LWGj[Heifers < 1 (weaned)]} -> 0.57 | H19: {=Table_SourceData_Dairy_LWGj[Bulls > 1]} -> 0.1 | I19: {=Table_SourceData_Dairy_LWGj[Bulls < 1 (weaned)]} -> 0.8 | J19: kg/head/day
A20: =HYPERLINK("#'Input - Common farm inputs'!A1", "Common farm inputs") -> Common farm inputs
A21: =HYPERLINK("#'Input - Crop pasture farm input'!A1", "Crop pasture farm input") -> Crop pasture farm input | D21: Duration of stay
A22: =HYPERLINK("#'Input - Livestock farm Inputs'!A1", "Livestock farm Inputs") -> Livestock farm Inputs
A23: =HYPERLINK("#'Input - Freight'!A1", "Freight") -> Freight | D23: Method 1 default values (Do not edit) | E23: Milking cows | F23: Heifers > 1 year | G23: Heifers < 1 year | H23: Bulls > 1 year | I23: Bulls < 1 year
A24: =HYPERLINK("#'Input - Solid waste'!A1", "Solid waste") -> Solid waste | D24: ="Average duration of stay between " & TEXT(X_Cell_Site_StartDate, "dd mmm yy") & " and " & TEXT(X_Cell_Site_EndDate, "dd mmm yy") & " weaned livestock" -> Average duration of stay between NO - Not in leaching zone and 02 Nov 00 weaned livestock | E24: {=Common_InputFunctions.Utility_LookupValueInTableNumber(E23,Table_SourceData_Dairy_Duration[Animal class j],Table_SourceData_Dairy_Duration[Duration (weaned)])} -> 365 | F24: {=Common_InputFunctions.Utility_LookupValueInTableNumber(F23,Table_SourceData_Dairy_Duration[Animal class j],Table_SourceData_Dairy_Duration[Duration (weaned)])} -> 365 | G24: {=Common_InputFunctions.Utility_LookupValueInTableNumber(G23,Table_SourceData_Dairy_Duration[Animal class j],Table_SourceData_Dairy_Duration[Duration (weaned)])} -> 281 | H24: {=Common_InputFunctions.Utility_LookupValueInTableNumber(H23,Table_SourceData_Dairy_Duration[Animal class j],Table_SourceData_Dairy_Duration[Duration (weaned)])} -> 365 | I24: {=Common_InputFunctions.Utility_LookupValueInTableNumber(I23,Table_SourceData_Dairy_Duration[Animal class j],Table_SourceData_Dairy_Duration[Duration (weaned)])} -> 281 | J24: Days
A25: =HYPERLINK("#'Input - Manure sent off-site'!A1", "Manure sent off-site") -> Manure sent off-site | D25: ="Average duration of stay between " & TEXT(X_Cell_Site_StartDate, "dd mmm yy") & " and " & TEXT(X_Cell_Site_EndDate, "dd mmm yy") & " pre-weaned livestock" -> Average duration of stay between NO - Not in leaching zone and 02 Nov 00 pre-weaned livestock | E25: {=Common_InputFunctions.Utility_LookupValueInTableNumber(E23,Table_SourceData_Dairy_Duration[Animal class j],Table_SourceData_Dairy_Duration[Duration (pre-weaned)])} -> 0 | F25: {=Common_InputFunctions.Utility_LookupValueInTableNumber(F23,Table_SourceData_Dairy_Duration[Animal class j],Table_SourceData_Dairy_Duration[Duration (pre-weaned)])} -> 0 | G25: {=Common_InputFunctions.Utility_LookupValueInTableNumber(G23,Table_SourceData_Dairy_Duration[Animal class j],Table_SourceData_Dairy_Duration[Duration (pre-weaned)])} -> 84 | H25: {=Common_InputFunctions.Utility_LookupValueInTableNumber(H23,Table_SourceData_Dairy_Duration[Animal class j],Table_SourceData_Dairy_Duration[Duration (pre-weaned)])} -> 0 | I25: {=Common_InputFunctions.Utility_LookupValueInTableNumber(I23,Table_SourceData_Dairy_Duration[Animal class j],Table_SourceData_Dairy_Duration[Duration (pre-weaned)])} -> 84 | J25: Days
A26: =HYPERLINK("#'Input - Data quality'!A1", "Data quality") -> Data quality
D27: Method 2 custom values (Edit if known) | E27: Milking cows | F27: Heifers > 1 year | G27: Heifers < 1 year | H27: Bulls > 1 year | I27: Bulls < 1 year
D28: ="Average duration of stay between " & TEXT(X_Cell_Site_StartDate, "dd mmm yy") & " and " & TEXT(X_Cell_Site_EndDate, "dd mmm yy") & " weaned livestock" -> Average duration of stay between NO - Not in leaching zone and 02 Nov 00 weaned livestock | E28: {=Common_InputFunctions.Utility_LookupValueInTableNumber(E27,Table_SourceData_Dairy_Duration[Animal class j],Table_SourceData_Dairy_Duration[Duration (weaned)])} -> 365 | F28: {=Common_InputFunctions.Utility_LookupValueInTableNumber(F27,Table_SourceData_Dairy_Duration[Animal class j],Table_SourceData_Dairy_Duration[Duration (weaned)])} -> 365 | G28: {=Common_InputFunctions.Utility_LookupValueInTableNumber(G27,Table_SourceData_Dairy_Duration[Animal class j],Table_SourceData_Dairy_Duration[Duration (weaned)])} -> 281 | H28: {=Common_InputFunctions.Utility_LookupValueInTableNumber(H27,Table_SourceData_Dairy_Duration[Animal class j],Table_SourceData_Dairy_Duration[Duration (weaned)])} -> 365 | I28: {=Common_InputFunctions.Utility_LookupValueInTableNumber(I27,Table_SourceData_Dairy_Duration[Animal class j],Table_SourceData_Dairy_Duration[Duration (weaned)])} -> 281 | J28: Days
A29: CALCULATIONS | D29: ="Average duration of stay between " & TEXT(X_Cell_Site_StartDate, "dd mmm yy") & " and " & TEXT(X_Cell_Site_EndDate, "dd mmm yy") & " pre-weaned livestock" -> Average duration of stay between NO - Not in leaching zone and 02 Nov 00 pre-weaned livestock | E29: =365-E28 -> 0 | F29: =365-F28 -> 0 | G29: =365-G28 -> 84 | H29: =365-H28 -> 0 | I29: =365-I28 -> 84 | J29: Days
A30: =HYPERLINK("#'3.3.1.1-2 Enteric Methane'!A1", "3.3.1.1-2 Enteric methane") -> 3.3.1.1-2 Enteric methane
A31: =HYPERLINK("#'4.3.1.1-2 Methane'!A1", "4.3.1.1-2 Manure methane") -> 4.3.1.1-2 Manure methane
A32: =HYPERLINK("#'4.3.1.3-4 Direct N20'!A1", "4.3.1.3-4 Direct N20") -> 4.3.1.3-4 Direct N20
A33: =HYPERLINK("#'4.3.1.5 Atmos deposition'!A1", "4.3.1.5 Atmos deposition") -> 4.3.1.5 Atmos deposition | D33: Diet
A34: =HYPERLINK("#'4.3.1.6-7 Leaching and runoff'!A1", "4.3.1.6-7 Leaching & runoff") -> 4.3.1.6-7 Leaching & runoff
A35: =HYPERLINK("#'4.3.1.8 Manure applied to soils'!A1", "4.3.1.8 Manure applied to soils") -> 4.3.1.8 Manure applied to soils | D35: Method 1 default values (Do not edit) | E35: Milking cows | F35: Heifers > 1 year | G35: Heifers < 1 year | H35: Bulls > 1 year | I35: Bulls < 1 year
A36: =HYPERLINK("#'4.3.1.9 Soil direct N2O'!A1", "4.3.1.9 Soil direct N2O") -> 4.3.1.9 Soil direct N2O | D36: Dry matter digestibility | E36: =SourceData_Dairy_DryMatterDigestibility_Data -> 0.75 | F36: =SourceData_Dairy_DryMatterDigestibility_Data -> 0.75 | G36: =SourceData_Dairy_DryMatterDigestibility_Data -> 0.75 | H36: =SourceData_Dairy_DryMatterDigestibility_Data -> 0.75 | I36: =SourceData_Dairy_DryMatterDigestibility_Data -> 0.75 | J36: Fraction
A37: =HYPERLINK("#'4.3.1.10-11 Soil Atmos Dep'!A1", "4.3.1.10-11 Soil Atmos Deposition") -> 4.3.1.10-11 Soil Atmos Deposition | D37: Crude protein | E37: =SourceData_Dairy_CrudeProtein_Data -> 0.2 | F37: =SourceData_Dairy_CrudeProtein_Data -> 0.2 | G37: =SourceData_Dairy_CrudeProtein_Data -> 0.2 | H37: =SourceData_Dairy_CrudeProtein_Data -> 0.2 | I37: =SourceData_Dairy_CrudeProtein_Data -> 0.2 | J37: Fraction
A38: =HYPERLINK("#'4.3.1.12-13 Soil leach runoff'!A1", "4.3.1.12-13 Soil leach & runoff") -> 4.3.1.12-13 Soil leach & runoff
A39: =HYPERLINK("#'5.1.1.1-2 Inorganic fert N2O'!A1", "5.1.1.1-2 Inorganic fert N2O") -> 5.1.1.1-2 Inorganic fert N2O | D39: Method 2 custom values (Edit if known) | E39: Milking cows | F39: Heifers > 1 year | G39: Heifers < 1 year | H39: Bulls > 1 year | I39: Bulls < 1 year
A40: =HYPERLINK("#'5.1.1.3-4 Inorganic fert CO2'!A1", "5.1.1.3-4 Inorganic fert CO2") -> 5.1.1.3-4 Inorganic fert CO2 | D40: Dry matter digestibility | E40: =SourceData_Dairy_DryMatterDigestibility_Data -> 0.75 | F40: =SourceData_Dairy_DryMatterDigestibility_Data -> 0.75 | G40: =SourceData_Dairy_DryMatterDigestibility_Data -> 0.75 | H40: =SourceData_Dairy_DryMatterDigestibility_Data -> 0.75 | I40: =SourceData_Dairy_DryMatterDigestibility_Data -> 0.75 | J40: Fraction
A41: =HYPERLINK("#'5.2.1.1-2 Organic Fert N2O'!A1", "5.2.1.1-2 Organic fert N2O") -> 5.2.1.1-2 Organic fert N2O | D41: Crude protein | E41: =SourceData_Dairy_CrudeProtein_Data -> 0.2 | F41: =SourceData_Dairy_CrudeProtein_Data -> 0.2 | G41: =SourceData_Dairy_CrudeProtein_Data -> 0.2 | H41: =SourceData_Dairy_CrudeProtein_Data -> 0.2 | I41: =SourceData_Dairy_CrudeProtein_Data -> 0.2 | J41: Fraction
A42: =HYPERLINK("#'5.3.1.1-2 Lime CO2'!A1", "5.3.1.1-2 Lime CO2") -> 5.3.1.1-2 Lime CO2
A43: =HYPERLINK("#'5.4.1.1-4 Atmos deposition'!A1", "5.4.1.1-4 Atmos. deposition") -> 5.4.1.1-4 Atmos. deposition
A44: =HYPERLINK("#'5.5.1.1-2 Leaching and runoff'!A1", "5.5.1.1-2 Leaching & runoff") -> 5.5.1.1-2 Leaching & runoff
A45: =HYPERLINK("#'6.2.1.1-2 Pasture residue N2O'!A1", "6.2.1.1-2 Pasture residue N2O") -> 6.2.1.1-2 Pasture residue N2O | D45: Milk production
A46: =HYPERLINK("#'6.3.1.1-2 Leach runoff pasture'!A1", "6.3.1.1-2 Leach & runoff (pasture)") -> 6.3.1.1-2 Leach & runoff (pasture)
A47: =HYPERLINK("#'8.1.1.1-2 Transport fuel'!A1", "8.1.1.1-2 Transport fuel") -> 8.1.1.1-2 Transport fuel | D47: Milk production unit | E47: Litres of milk | F47: ← Please select
A48: =HYPERLINK("#'8.2.1.1-2 Stationary fuel'!A1", "8.2.1.1-2 Stationary fuel") -> 8.2.1.1-2 Stationary fuel
A49: =HYPERLINK("#'10.1.1-2 Solid waste treatment'!A1", "10.1.1.1-2 Solid waste") -> 10.1.1.1-2 Solid waste | E49: Milking cows
A50: =HYPERLINK("#'14.1.1-2 Purchased electricity'!A1", "14.1.1-2 Purchased electricity") -> 14.1.1-2 Purchased electricity | D50: Average daily milk production | E50: 20 | F50: =IF(X_Cell_Dairy_MilkProductionUnit="Litres of milk", "litres/head/day", "kg milk solids/head/day") -> litres/head/day
A51: =HYPERLINK("#'15 Scope 3'!A1", "15 Scope 3") -> 15 Scope 3
A52: =HYPERLINK("#'Calcs - Manure sent off-site'!A1", "Calcs - Manure sent off-site") -> Calcs - Manure sent off-site | D52: For milk solids only: | E52: Method 1 (don't edit) | F52: Method 2 (edit if known)
D53: Fat content in fat and protein corrected milk | E53: =SourceData_Dairy_FatContentInMilk_Data/100 -> 0.04 | F53: =SourceData_Dairy_FatContentInMilk_Data/100 -> 0.04 | G53: percent
D54: Protein content in fat and protein corrected milk | E54: =SourceData_Dairy_ProteinContentInMilk_Data/100 -> 0.033 | F54: =SourceData_Dairy_ProteinContentInMilk_Data/100 -> 0.033 | G54: percent
A55: APPENDICES
A56: =HYPERLINK("#'Constants - Dairy'!A1", "Constants - Dairy") -> Constants - Dairy
A57: =HYPERLINK("#'Constants - Ag Residue'!A1", "Constants - Ag residue") -> Constants - Ag residue
A58: =HYPERLINK("#'Constants - Common Livestock'!A1", "Constants - Common Livestock") -> Constants - Common Livestock | D58: Production systems
A59: =HYPERLINK("#'Constants - Electricity'!A1", "Constants - Electricity") -> Constants - Electricity | D59: Time spent in production systems
A60: =HYPERLINK("#'Constants - Fertiliser'!A1", "Constants - Fertiliser") -> Constants - Fertiliser | D60: Production system template | E60: System 3: Pasture-grazed 3-9 months/year | F60: ← Please select
A61: =HYPERLINK("#'Constants - Fuel'!A1", "Constants - Fuel") -> Constants - Fuel
A62: =HYPERLINK("#'Constants - Scope 3'!A1", "Constants - Scope 3") -> Constants - Scope 3 | D62: Method 1 default values (Do not edit) | E62: Milking cows | F62: Heifers > 1 year | G62: Heifers < 1 year | H62: Bulls > 1 year | I62: Bulls < 1 year
A63: =HYPERLINK("#'Constants - Common'!A1", "Constants - Common") -> Constants - Common | D63: Pasture | E63: =Common_InputFunctions.Utility_LookupValueInTableNumber(X_Cell_Dairy_ProductionSystemTemplate, Table_SourceData_Dairy_ProductionSystemTemplates[Area],Table_SourceData_Dairy_ProductionSystemTemplates[Pasture]) -> 0.534 | F63: =Common_InputFunctions.Utility_LookupValueInTableNumber(X_Cell_Dairy_ProductionSystemTemplate, Table_SourceData_Dairy_ProductionSystemTemplates[Area],Table_SourceData_Dairy_ProductionSystemTemplates[Pasture]) -> 0.534 | G63: =Common_InputFunctions.Utility_LookupValueInTableNumber(X_Cell_Dairy_ProductionSystemTemplate, Table_SourceData_Dairy_ProductionSystemTemplates[Area],Table_SourceData_Dairy_ProductionSystemTemplates[Pasture]) -> 0.534 | H63: =Common_InputFunctions.Utility_LookupValueInTableNumber(X_Cell_Dairy_ProductionSystemTemplate, Table_SourceData_Dairy_ProductionSystemTemplates[Area],Table_SourceData_Dairy_ProductionSystemTemplates[Pasture]) -> 0.534 | I63: =Common_InputFunctions.Utility_LookupValueInTableNumber(X_Cell_Dairy_ProductionSystemTemplate, Table_SourceData_Dairy_ProductionSystemTemplates[Area],Table_SourceData_Dairy_ProductionSystemTemplates[Pasture]) -> 0.534 | J63: Percent
A64: =HYPERLINK("#'Constants - Solid Waste'!A1", "Constants - Solid Waste") -> Constants - Solid Waste | D64: Milking shed | E64: =Common_InputFunctions.Utility_LookupValueInTableNumber(X_Cell_Dairy_ProductionSystemTemplate, Table_SourceData_Dairy_ProductionSystemTemplates[Area],Table_SourceData_Dairy_ProductionSystemTemplates[Milking shed]) -> 0.11 | F64: =Common_InputFunctions.Utility_LookupValueInTableNumber(X_Cell_Dairy_ProductionSystemTemplate, Table_SourceData_Dairy_ProductionSystemTemplates[Area],Table_SourceData_Dairy_ProductionSystemTemplates[Milking shed]) -> 0.11 | G64: =Common_InputFunctions.Utility_LookupValueInTableNumber(X_Cell_Dairy_ProductionSystemTemplate, Table_SourceData_Dairy_ProductionSystemTemplates[Area],Table_SourceData_Dairy_ProductionSystemTemplates[Milking shed]) -> 0.11 | H64: =Common_InputFunctions.Utility_LookupValueInTableNumber(X_Cell_Dairy_ProductionSystemTemplate, Table_SourceData_Dairy_ProductionSystemTemplates[Area],Table_SourceData_Dairy_ProductionSystemTemplates[Milking shed]) -> 0.11 | I64: =Common_InputFunctions.Utility_LookupValueInTableNumber(X_Cell_Dairy_ProductionSystemTemplate, Table_SourceData_Dairy_ProductionSystemTemplates[Area],Table_SourceData_Dairy_ProductionSystemTemplates[Milking shed]) -> 0.11 | J64: Percent
A65: =HYPERLINK("#'Acknowledgements'!A1", "Acknowledgements") -> Acknowledgements | D65: Feed pad | E65: =Common_InputFunctions.Utility_LookupValueInTableNumber(X_Cell_Dairy_ProductionSystemTemplate, Table_SourceData_Dairy_ProductionSystemTemplates[Area],Table_SourceData_Dairy_ProductionSystemTemplates[Feedpad]) -> 0.356 | F65: =Common_InputFunctions.Utility_LookupValueInTableNumber(X_Cell_Dairy_ProductionSystemTemplate, Table_SourceData_Dairy_ProductionSystemTemplates[Area],Table_SourceData_Dairy_ProductionSystemTemplates[Feedpad]) -> 0.356 | G65: =Common_InputFunctions.Utility_LookupValueInTableNumber(X_Cell_Dairy_ProductionSystemTemplate, Table_SourceData_Dairy_ProductionSystemTemplates[Area],Table_SourceData_Dairy_ProductionSystemTemplates[Feedpad]) -> 0.356 | H65: =Common_InputFunctions.Utility_LookupValueInTableNumber(X_Cell_Dairy_ProductionSystemTemplate, Table_SourceData_Dairy_ProductionSystemTemplates[Area],Table_SourceData_Dairy_ProductionSystemTemplates[Feedpad]) -> 0.356 | I65: =Common_InputFunctions.Utility_LookupValueInTableNumber(X_Cell_Dairy_ProductionSystemTemplate, Table_SourceData_Dairy_ProductionSystemTemplates[Area],Table_SourceData_Dairy_ProductionSystemTemplates[Feedpad]) -> 0.356 | J65: Percent
D67: Method 2 custom values (Edit if known) | E67: Milking cows | F67: Heifers > 1 year | G67: Heifers < 1 year | H67: Bulls > 1 year | I67: Bulls < 1 year
D68: Pasture | E68: =Common_InputFunctions.Utility_LookupValueInTableNumber(X_Cell_Dairy_ProductionSystemTemplate, Table_SourceData_Dairy_ProductionSystemTemplates[Area],Table_SourceData_Dairy_ProductionSystemTemplates[Pasture]) -> 0.534 | F68: =Common_InputFunctions.Utility_LookupValueInTableNumber(X_Cell_Dairy_ProductionSystemTemplate, Table_SourceData_Dairy_ProductionSystemTemplates[Area],Table_SourceData_Dairy_ProductionSystemTemplates[Pasture]) -> 0.534 | G68: =Common_InputFunctions.Utility_LookupValueInTableNumber(X_Cell_Dairy_ProductionSystemTemplate, Table_SourceData_Dairy_ProductionSystemTemplates[Area],Table_SourceData_Dairy_ProductionSystemTemplates[Pasture]) -> 0.534 | H68: =Common_InputFunctions.Utility_LookupValueInTableNumber(X_Cell_Dairy_ProductionSystemTemplate, Table_SourceData_Dairy_ProductionSystemTemplates[Area],Table_SourceData_Dairy_ProductionSystemTemplates[Pasture]) -> 0.534 | I68: =Common_InputFunctions.Utility_LookupValueInTableNumber(X_Cell_Dairy_ProductionSystemTemplate, Table_SourceData_Dairy_ProductionSystemTemplates[Area],Table_SourceData_Dairy_ProductionSystemTemplates[Pasture]) -> 0.534 | J68: Percent
D69: Milking shed | E69: =Common_InputFunctions.Utility_LookupValueInTableNumber(X_Cell_Dairy_ProductionSystemTemplate, Table_SourceData_Dairy_ProductionSystemTemplates[Area],Table_SourceData_Dairy_ProductionSystemTemplates[Milking shed]) -> 0.11 | F69: =Common_InputFunctions.Utility_LookupValueInTableNumber(X_Cell_Dairy_ProductionSystemTemplate, Table_SourceData_Dairy_ProductionSystemTemplates[Area],Table_SourceData_Dairy_ProductionSystemTemplates[Milking shed]) -> 0.11 | G69: =Common_InputFunctions.Utility_LookupValueInTableNumber(X_Cell_Dairy_ProductionSystemTemplate, Table_SourceData_Dairy_ProductionSystemTemplates[Area],Table_SourceData_Dairy_ProductionSystemTemplates[Milking shed]) -> 0.11 | H69: =Common_InputFunctions.Utility_LookupValueInTableNumber(X_Cell_Dairy_ProductionSystemTemplate, Table_SourceData_Dairy_ProductionSystemTemplates[Area],Table_SourceData_Dairy_ProductionSystemTemplates[Milking shed]) -> 0.11 | I69: =Common_InputFunctions.Utility_LookupValueInTableNumber(X_Cell_Dairy_ProductionSystemTemplate, Table_SourceData_Dairy_ProductionSystemTemplates[Area],Table_SourceData_Dairy_ProductionSystemTemplates[Milking shed]) -> 0.11 | J69: Percent
D70: Feed pad | E70: =Common_InputFunctions.Utility_LookupValueInTableNumber(X_Cell_Dairy_ProductionSystemTemplate, Table_SourceData_Dairy_ProductionSystemTemplates[Area],Table_SourceData_Dairy_ProductionSystemTemplates[Feedpad]) -> 0.356 | F70: =Common_InputFunctions.Utility_LookupValueInTableNumber(X_Cell_Dairy_ProductionSystemTemplate, Table_SourceData_Dairy_ProductionSystemTemplates[Area],Table_SourceData_Dairy_ProductionSystemTemplates[Feedpad]) -> 0.356 | G70: =Common_InputFunctions.Utility_LookupValueInTableNumber(X_Cell_Dairy_ProductionSystemTemplate, Table_SourceData_Dairy_ProductionSystemTemplates[Area],Table_SourceData_Dairy_ProductionSystemTemplates[Feedpad]) -> 0.356 | H70: =Common_InputFunctions.Utility_LookupValueInTableNumber(X_Cell_Dairy_ProductionSystemTemplate, Table_SourceData_Dairy_ProductionSystemTemplates[Area],Table_SourceData_Dairy_ProductionSystemTemplates[Feedpad]) -> 0.356 | I70: =Common_InputFunctions.Utility_LookupValueInTableNumber(X_Cell_Dairy_ProductionSystemTemplate, Table_SourceData_Dairy_ProductionSystemTemplates[Area],Table_SourceData_Dairy_ProductionSystemTemplates[Feedpad]) -> 0.356 | J70: Percent
D74: Manure management systems
D75: ="From " & $D$64 -> From Milking shed
D77: Stage 1 MMS | E77: Milking cows | F77: Heifers > 1 year | G77: Heifers < 1 year | H77: Bulls > 1 year | I77: Bulls < 1 year | J77: ► | L77: Destination after stage 2 MMS (Percent)
L78: Sold | M78: Fert for own farm (eg crop) | N78: Direct application to soil
D79: ='Constants - Dairy'!$D$8 -> Anaerobic lagoon | E79: 0.25 | F79: 0.25 | G79: 0.25 | H79: 0.25 | I79: 0.25 | J79: Percent | L79: 0.25 | M79: 0.25 | N79: =1-SUM(L79:M79) -> 0.5
D80: ="Were solids separated from " & D79 & "?" -> Were solids separated from Anaerobic lagoon? | E80: Yes
D81: ="Percent solids separated from " & D79 & " (Method 1)" -> Percent solids separated from Anaerobic lagoon (Method 1) | E81: =IF(X_Cell_Dairy_Stage1MMS_1_AnaerobicLagoon_SolidsSeparated="Yes", 20%, 0) -> 0.2
D82: ="Percent solids separated from " & D79 & " (Method 2)" -> Percent solids separated from Anaerobic lagoon (Method 2) | E82: 0.2
D84: ='Constants - Dairy'!$D$9 -> Sump and dispersal system | E84: 0.25 | F84: 0.25 | G84: 0.25 | H84: 0.25 | I84: 0.25 | J84: Percent | L84: 0.25 | M84: 0.25 | N84: =1-SUM(L84:M84) -> 0.5
D85: ="Were solids separated from " & D84 & "?" -> Were solids separated from Sump and dispersal system? | E85: Yes
D86: ="Percent solids separated from " & D84 & " (Method 1)" -> Percent solids separated from Sump and dispersal system (Method 1) | E86: =IF(X_Cell_Dairy_Stage1MMS_1_SumpAndDispersal_SolidsSeparated="Yes", 20%, 0) -> 0.2
D87: ="Percent solids separated from " & D84 & " (Method 2)" -> Percent solids separated from Sump and dispersal system (Method 2) | E87: 0.2
D89: ='Constants - Dairy'!$D$10 -> Drains to paddock | E89: 0.25 | F89: 0.25 | G89: 0.25 | H89: 0.25 | I89: 0.25 | J89: Percent | L89: 0.25 | M89: 0.25 | N89: =1-SUM(L89:M89) -> 0.5
D90: ="Were solids separated from " & D89 & "?" -> Were solids separated from Drains to paddock? | E90: Yes
D91: ="Percent solids separated from " & D89 & " (Method 1)" -> Percent solids separated from Drains to paddock (Method 1) | E91: =IF(X_Cell_Dairy_Stage1MMS_1_DrainsToPaddock_SolidsSeparated="Yes", 20%, 0) -> 0.2
D92: ="Percent solids separated from " & D89 & " (Method 2)" -> Percent solids separated from Drains to paddock (Method 2) | E92: 0.2
D94: ='Constants - Dairy'!$D$11 & " (before solid separation)" -> Solid storage (before solid separation) | E94: 0.25 | F94: 0.25 | G94: 0.25 | H94: 0.25 | I94: 0.25 | J94: Percent | L94: 0.25 | M94: 0.25 | N94: =1-SUM(L94:M94) -> 0.5
D95: Solid storage (after solid separation) - Method 1 | E95: =E94+(E79*X_Cell_Dairy_Stage1MMS_1_AnaerobicLagoon_AmountSeparated_Method1)+(E84*X_Cell_Dairy_Stage1MMS_1_SumpAndDispersal_AmountSeparated_Method1)+(E89*X_Cell_Dairy_Stage1MMS_1_DrainsToPaddock_AmountSeparated_Method1) -> 0.4 | F95: =F94+(F79*X_Cell_Dairy_Stage1MMS_1_AnaerobicLagoon_AmountSeparated_Method1)+(F84*X_Cell_Dairy_Stage1MMS_1_SumpAndDispersal_AmountSeparated_Method1)+(F89*X_Cell_Dairy_Stage1MMS_1_DrainsToPaddock_AmountSeparated_Method1) -> 0.4 | G95: =G94+(G79*X_Cell_Dairy_Stage1MMS_1_AnaerobicLagoon_AmountSeparated_Method1)+(G84*X_Cell_Dairy_Stage1MMS_1_SumpAndDispersal_AmountSeparated_Method1)+(G89*X_Cell_Dairy_Stage1MMS_1_DrainsToPaddock_AmountSeparated_Method1) -> 0.4 | H95: =H94+(H79*X_Cell_Dairy_Stage1MMS_1_AnaerobicLagoon_AmountSeparated_Method1)+(H84*X_Cell_Dairy_Stage1MMS_1_SumpAndDispersal_AmountSeparated_Method1)+(H89*X_Cell_Dairy_Stage1MMS_1_DrainsToPaddock_AmountSeparated_Method1) -> 0.4 | I95: =I94+(I79*X_Cell_Dairy_Stage1MMS_1_AnaerobicLagoon_AmountSeparated_Method1)+(I84*X_Cell_Dairy_Stage1MMS_1_SumpAndDispersal_AmountSeparated_Method1)+(I89*X_Cell_Dairy_Stage1MMS_1_DrainsToPaddock_AmountSeparated_Method1) -> 0.4 | J95: Percent
D96: Solid storage (after solid separation) - Method 2 | E96: =E94+(E79*X_Cell_Dairy_Stage1MMS_1_AnaerobicLagoon_AmountSeparated_Method2)+(E84*X_Cell_Dairy_Stage1MMS_1_SumpAndDispersal_AmountSeparated_Method2)+(E89*X_Cell_Dairy_Stage1MMS_1_DrainsToPaddock_AmountSeparated_Method2) -> 0.4 | F96: =F94+(F79*X_Cell_Dairy_Stage1MMS_1_AnaerobicLagoon_AmountSeparated_Method2)+(F84*X_Cell_Dairy_Stage1MMS_1_SumpAndDispersal_AmountSeparated_Method2)+(F89*X_Cell_Dairy_Stage1MMS_1_DrainsToPaddock_AmountSeparated_Method2) -> 0.4 | G96: =G94+(G79*X_Cell_Dairy_Stage1MMS_1_AnaerobicLagoon_AmountSeparated_Method2)+(G84*X_Cell_Dairy_Stage1MMS_1_SumpAndDispersal_AmountSeparated_Method2)+(G89*X_Cell_Dairy_Stage1MMS_1_DrainsToPaddock_AmountSeparated_Method2) -> 0.4 | H96: =H94+(H79*X_Cell_Dairy_Stage1MMS_1_AnaerobicLagoon_AmountSeparated_Method2)+(H84*X_Cell_Dairy_Stage1MMS_1_SumpAndDispersal_AmountSeparated_Method2)+(H89*X_Cell_Dairy_Stage1MMS_1_DrainsToPaddock_AmountSeparated_Method2) -> 0.4 | I96: =I94+(I79*X_Cell_Dairy_Stage1MMS_1_AnaerobicLagoon_AmountSeparated_Method2)+(I84*X_Cell_Dairy_Stage1MMS_1_SumpAndDispersal_AmountSeparated_Method2)+(I89*X_Cell_Dairy_Stage1MMS_1_DrainsToPaddock_AmountSeparated_Method2) -> 0.4 | J96: Percent
D99: ="From " & $D$65 -> From Feed pad
D101: Stage 1 MMS | E101: Milking cows | F101: Heifers > 1 year | G101: Heifers < 1 year | H101: Bulls > 1 year | I101: Bulls < 1 year | J101: ► | L101: Destination after stage 2 MMS (Percent)
L102: Sold | M102: Fert for own farm (eg crop) | N102: Direct application to soil
D103: ='Constants - Dairy'!$D$8 -> Anaerobic lagoon | E103: 0.25 | F103: 0.25 | G103: 0.25 | H103: 0.25 | I103: 0.25 | J103: Percent | L103: 0.25 | M103: 0.25 | N103: =1-SUM(L103:M103) -> 0.5
D104: ="Were solids separated from " & D103 & "?" -> Were solids separated from Anaerobic lagoon? | E104: No
D105: ="Percent solids separated from " & D103 & " (Method 1)" -> Percent solids separated from Anaerobic lagoon (Method 1) | E105: =IF(X_Cell_Dairy_Stage1MMS_2_AnaerobicLagoon_SolidsSeparated="Yes", 20%, 0) -> 0
D106: ="Percent solids separated from " & D103 & " (Method 2)" -> Percent solids separated from Anaerobic lagoon (Method 2) | E106: =IF(X_Cell_Dairy_Stage1MMS_2_AnaerobicLagoon_SolidsSeparated="Yes", 20%, 0) -> 0
D108: ='Constants - Dairy'!$D$9 -> Sump and dispersal system | E108: 0.25 | F108: 0.25 | G108: 0.25 | H108: 0.25 | I108: 0.25 | J108: Percent | L108: 0.25 | M108: 0.25 | N108: =1-SUM(L108:M108) -> 0.5
D109: ="Were solids separated from " & D108 & "?" -> Were solids separated from Sump and dispersal system? | E109: Yes
D110: ="Percent solids separated from " & D108 & " (Method 1)" -> Percent solids separated from Sump and dispersal system (Method 1) | E110: =IF(X_Cell_Dairy_Stage1MMS_2_SumpAndDispersal_SolidsSeparated="Yes", 20%, 0) -> 0.2
D111: ="Percent solids separated from " & D108 & " (Method 2)" -> Percent solids separated from Sump and dispersal system (Method 2) | E111: =IF(X_Cell_Dairy_Stage1MMS_2_SumpAndDispersal_SolidsSeparated="Yes", 20%, 0) -> 0.2
D113: ='Constants - Dairy'!$D$10 -> Drains to paddock | E113: 0.25 | F113: 0.25 | G113: 0.25 | H113: 0.25 | I113: 0.25 | J113: Percent | L113: 0.25 | M113: 0.25 | N113: =1-SUM(L113:M113) -> 0.5
D114: ="Were solids separated from " & D113 & "?" -> Were solids separated from Drains to paddock? | E114: Yes
D115: ="Percent solids separated from " & D113 & " (Method 1)" -> Percent solids separated from Drains to paddock (Method 1) | E115: =IF(X_Cell_Dairy_Stage1MMS_2_DrainsToPaddock_SolidsSeparated="Yes", 20%, 0) -> 0.2
...

Sheet Input - Livestock sales
A1: #VALUE! | C1: Input - Livestock sales
A3: =HYPERLINK("#'Home'!A1", "Home") -> Home
A4: =HYPERLINK("#'Results - Activity period'!A1", "Results - Activity period") -> Results - Activity period
A5: =HYPERLINK("#'Results - Product EI'!A1", "Results - Product Emissions Intensity") -> Results - Product Emissions Intensity | D5: ⚠️ Livestock sales are not automatically reflected in the duration and head tables - you will need to manually adjust head count and average liveweight
A6: =HYPERLINK("#'Results'!A1", "Results") -> Results | D6: Transaction name | E6: Class (select) | F6: Sale date | G6: Head sold | H6: Average weight per head (kg) | I6: Total liveweight sold
F7: 45566 | G7: 10 | H7: 500 | I7: =G7*H7 -> 5000
I8: =G8*H8 -> 0
A9: INPUTS | I9: =G9*H9 -> 0
A10: =HYPERLINK("#'Input - Enterprise'!A1", "Enterprise") -> Enterprise | I10: =G10*H10 -> 0
A11: =HYPERLINK("#'Input - Site'!A1", "Site") -> Site | I11: =G11*H11 -> 0
A12: =HYPERLINK("#'Input - Dairy'!A1", "Dairy") -> Dairy | I12: =G12*H12 -> 0
A13: =HYPERLINK("#'Input - Livestock sales'!A1", "Livestock sales") -> Livestock sales | I13: =G13*H13 -> 0
A14: =HYPERLINK("#'Input - Dairy cattle purchases'!A1", "Dairy cattle purchases") -> Dairy cattle purchases | I14: =G14*H14 -> 0
A15: =HYPERLINK("#'Input - Pasture'!A1", "Pasture") -> Pasture | I15: =G15*H15 -> 0
A16: =HYPERLINK("#'Input - Fert Prod System'!A1", "Fert Prod System") -> Fert Prod System | I16: =G16*H16 -> 0
A17: =HYPERLINK("#'Input - Fertiliser'!A1", "Fertiliser") -> Fertiliser
A18: =HYPERLINK("#'Input - Fuel'!A1", "Fuel") -> Fuel
A19: =HYPERLINK("#'Input - Electricity'!A1", "Electricity") -> Electricity
A20: =HYPERLINK("#'Input - Common farm inputs'!A1", "Common farm inputs") -> Common farm inputs
A21: =HYPERLINK("#'Input - Crop pasture farm input'!A1", "Crop pasture farm input") -> Crop pasture farm input
A22: =HYPERLINK("#'Input - Livestock farm Inputs'!A1", "Livestock farm Inputs") -> Livestock farm Inputs
A23: =HYPERLINK("#'Input - Freight'!A1", "Freight") -> Freight
A24: =HYPERLINK("#'Input - Solid waste'!A1", "Solid waste") -> Solid waste
A25: =HYPERLINK("#'Input - Manure sent off-site'!A1", "Manure sent off-site") -> Manure sent off-site
A26: =HYPERLINK("#'Input - Data quality'!A1", "Data quality") -> Data quality
A29: CALCULATIONS
A30: =HYPERLINK("#'3.3.1.1-2 Enteric Methane'!A1", "3.3.1.1-2 Enteric methane") -> 3.3.1.1-2 Enteric methane
A31: =HYPERLINK("#'4.3.1.1-2 Methane'!A1", "4.3.1.1-2 Manure methane") -> 4.3.1.1-2 Manure methane
A32: =HYPERLINK("#'4.3.1.3-4 Direct N20'!A1", "4.3.1.3-4 Direct N20") -> 4.3.1.3-4 Direct N20
A33: =HYPERLINK("#'4.3.1.5 Atmos deposition'!A1", "4.3.1.5 Atmos deposition") -> 4.3.1.5 Atmos deposition
A34: =HYPERLINK("#'4.3.1.6-7 Leaching and runoff'!A1", "4.3.1.6-7 Leaching & runoff") -> 4.3.1.6-7 Leaching & runoff
A35: =HYPERLINK("#'4.3.1.8 Manure applied to soils'!A1", "4.3.1.8 Manure applied to soils") -> 4.3.1.8 Manure applied to soils
A36: =HYPERLINK("#'4.3.1.9 Soil direct N2O'!A1", "4.3.1.9 Soil direct N2O") -> 4.3.1.9 Soil direct N2O
A37: =HYPERLINK("#'4.3.1.10-11 Soil Atmos Dep'!A1", "4.3.1.10-11 Soil Atmos Deposition") -> 4.3.1.10-11 Soil Atmos Deposition
A38: =HYPERLINK("#'4.3.1.12-13 Soil leach runoff'!A1", "4.3.1.12-13 Soil leach & runoff") -> 4.3.1.12-13 Soil leach & runoff
A39: =HYPERLINK("#'5.1.1.1-2 Inorganic fert N2O'!A1", "5.1.1.1-2 Inorganic fert N2O") -> 5.1.1.1-2 Inorganic fert N2O
A40: =HYPERLINK("#'5.1.1.3-4 Inorganic fert CO2'!A1", "5.1.1.3-4 Inorganic fert CO2") -> 5.1.1.3-4 Inorganic fert CO2
A41: =HYPERLINK("#'5.2.1.1-2 Organic Fert N2O'!A1", "5.2.1.1-2 Organic fert N2O") -> 5.2.1.1-2 Organic fert N2O
A42: =HYPERLINK("#'5.3.1.1-2 Lime CO2'!A1", "5.3.1.1-2 Lime CO2") -> 5.3.1.1-2 Lime CO2
A43: =HYPERLINK("#'5.4.1.1-4 Atmos deposition'!A1", "5.4.1.1-4 Atmos. deposition") -> 5.4.1.1-4 Atmos. deposition
A44: =HYPERLINK("#'5.5.1.1-2 Leaching and runoff'!A1", "5.5.1.1-2 Leaching & runoff") -> 5.5.1.1-2 Leaching & runoff
A45: =HYPERLINK("#'6.2.1.1-2 Pasture residue N2O'!A1", "6.2.1.1-2 Pasture residue N2O") -> 6.2.1.1-2 Pasture residue N2O
A46: =HYPERLINK("#'6.3.1.1-2 Leach runoff pasture'!A1", "6.3.1.1-2 Leach & runoff (pasture)") -> 6.3.1.1-2 Leach & runoff (pasture)
A47: =HYPERLINK("#'8.1.1.1-2 Transport fuel'!A1", "8.1.1.1-2 Transport fuel") -> 8.1.1.1-2 Transport fuel
A48: =HYPERLINK("#'8.2.1.1-2 Stationary fuel'!A1", "8.2.1.1-2 Stationary fuel") -> 8.2.1.1-2 Stationary fuel
A49: =HYPERLINK("#'10.1.1-2 Solid waste treatment'!A1", "10.1.1.1-2 Solid waste") -> 10.1.1.1-2 Solid waste
A50: =HYPERLINK("#'14.1.1-2 Purchased electricity'!A1", "14.1.1-2 Purchased electricity") -> 14.1.1-2 Purchased electricity
A51: =HYPERLINK("#'15 Scope 3'!A1", "15 Scope 3") -> 15 Scope 3
A52: =HYPERLINK("#'Calcs - Manure sent off-site'!A1", "Calcs - Manure sent off-site") -> Calcs - Manure sent off-site
A55: APPENDICES
A56: =HYPERLINK("#'Constants - Dairy'!A1", "Constants - Dairy") -> Constants - Dairy
A57: =HYPERLINK("#'Constants - Ag Residue'!A1", "Constants - Ag residue") -> Constants - Ag residue
A58: =HYPERLINK("#'Constants - Common Livestock'!A1", "Constants - Common Livestock") -> Constants - Common Livestock
A59: =HYPERLINK("#'Constants - Electricity'!A1", "Constants - Electricity") -> Constants - Electricity
A60: =HYPERLINK("#'Constants - Fertiliser'!A1", "Constants - Fertiliser") -> Constants - Fertiliser
A61: =HYPERLINK("#'Constants - Fuel'!A1", "Constants - Fuel") -> Constants - Fuel
A62: =HYPERLINK("#'Constants - Scope 3'!A1", "Constants - Scope 3") -> Constants - Scope 3
A63: =HYPERLINK("#'Constants - Common'!A1", "Constants - Common") -> Constants - Common
A64: =HYPERLINK("#'Constants - Solid Waste'!A1", "Constants - Solid Waste") -> Constants - Solid Waste
A65: =HYPERLINK("#'Acknowledgements'!A1", "Acknowledgements") -> Acknowledgements

Sheet Input - Dairy cattle purchases
A1: #VALUE! | C1: Input - Dairy Cattle Purchases
A3: =HYPERLINK("#'Home'!A1", "Home") -> Home
A4: =HYPERLINK("#'Results - Activity period'!A1", "Results - Activity period") -> Results - Activity period
A5: =HYPERLINK("#'Results - Product EI'!A1", "Results - Product Emissions Intensity") -> Results - Product Emissions Intensity | D5: ⚠️ Livestock sales and purchases are not automatically reflected in the duration and head count tables - you will need to manually adjust head count, duration and average liveweight
A6: =HYPERLINK("#'Results'!A1", "Results") -> Results | D6: Transaction name | E6: Class (select) | F6: Breed (select) | G6: Quantity (head) | H6: Liveweight (kg/head) Method 1 | I6: Liveweight (kg/head) Method 2
D7: Dairy cows from Denise | E7: Heifers < 1 (weaned) | F7: Jersey crossbred | G7: 100 | H7: {=Common_InputFunctions.Utility_LookupValueInTableOneColumnAndHeader(Table_Input_LivestockPurchases_Dairy[[#This Row],[Breed (select)]],Table_Input_LivestockPurchases_Dairy[[#This Row],[Class (select)]],Table_SourceData_Dairy_WjCowsHeifers[Breed],Table_SourceData_Dairy_WjCowsHeifers[#Headers],Table_SourceData_Dairy_WjCowsHeifers[#Data], 0)} -> 130 | I7: 350
E8: Milking cows | F8: Ayrshire | G8: 100 | H8: {=Common_InputFunctions.Utility_LookupValueInTableOneColumnAndHeader(Table_Input_LivestockPurchases_Dairy[[#This Row],[Breed (select)]],Table_Input_LivestockPurchases_Dairy[[#This Row],[Class (select)]],Table_SourceData_Dairy_WjCowsHeifers[Breed],Table_SourceData_Dairy_WjCowsHeifers[#Headers],Table_SourceData_Dairy_WjCowsHeifers[#Data], 0)} -> 540 | I8: 625
A9: INPUTS | E9: Heifers > 1 | F9: Jersey crossbred | H9: {=Common_InputFunctions.Utility_LookupValueInTableOneColumnAndHeader(Table_Input_LivestockPurchases_Dairy[[#This Row],[Breed (select)]],Table_Input_LivestockPurchases_Dairy[[#This Row],[Class (select)]],Table_SourceData_Dairy_WjCowsHeifers[Breed],Table_SourceData_Dairy_WjCowsHeifers[#Headers],Table_SourceData_Dairy_WjCowsHeifers[#Data], 0)} -> 315
A10: =HYPERLINK("#'Input - Enterprise'!A1", "Enterprise") -> Enterprise | H10: {=Common_InputFunctions.Utility_LookupValueInTableOneColumnAndHeader(Table_Input_LivestockPurchases_Dairy[[#This Row],[Breed (select)]],Table_Input_LivestockPurchases_Dairy[[#This Row],[Class (select)]],Table_SourceData_Dairy_WjCowsHeifers[Breed],Table_SourceData_Dairy_WjCowsHeifers[#Headers],Table_SourceData_Dairy_WjCowsHeifers[#Data], 0)} -> 0
A11: =HYPERLINK("#'Input - Site'!A1", "Site") -> Site | H11: {=Common_InputFunctions.Utility_LookupValueInTableOneColumnAndHeader(Table_Input_LivestockPurchases_Dairy[[#This Row],[Breed (select)]],Table_Input_LivestockPurchases_Dairy[[#This Row],[Class (select)]],Table_SourceData_Dairy_WjCowsHeifers[Breed],Table_SourceData_Dairy_WjCowsHeifers[#Headers],Table_SourceData_Dairy_WjCowsHeifers[#Data], 0)} -> 0
A12: =HYPERLINK("#'Input - Dairy'!A1", "Dairy") -> Dairy | H12: {=Common_InputFunctions.Utility_LookupValueInTableOneColumnAndHeader(Table_Input_LivestockPurchases_Dairy[[#This Row],[Breed (select)]],Table_Input_LivestockPurchases_Dairy[[#This Row],[Class (select)]],Table_SourceData_Dairy_WjCowsHeifers[Breed],Table_SourceData_Dairy_WjCowsHeifers[#Headers],Table_SourceData_Dairy_WjCowsHeifers[#Data], 0)} -> 0
A13: =HYPERLINK("#'Input - Livestock sales'!A1", "Livestock sales") -> Livestock sales | H13: {=Common_InputFunctions.Utility_LookupValueInTableOneColumnAndHeader(Table_Input_LivestockPurchases_Dairy[[#This Row],[Breed (select)]],Table_Input_LivestockPurchases_Dairy[[#This Row],[Class (select)]],Table_SourceData_Dairy_WjCowsHeifers[Breed],Table_SourceData_Dairy_WjCowsHeifers[#Headers],Table_SourceData_Dairy_WjCowsHeifers[#Data], 0)} -> 0
A14: =HYPERLINK("#'Input - Dairy cattle purchases'!A1", "Dairy cattle purchases") -> Dairy cattle purchases | H14: {=Common_InputFunctions.Utility_LookupValueInTableOneColumnAndHeader(Table_Input_LivestockPurchases_Dairy[[#This Row],[Breed (select)]],Table_Input_LivestockPurchases_Dairy[[#This Row],[Class (select)]],Table_SourceData_Dairy_WjCowsHeifers[Breed],Table_SourceData_Dairy_WjCowsHeifers[#Headers],Table_SourceData_Dairy_WjCowsHeifers[#Data], 0)} -> 0
A15: =HYPERLINK("#'Input - Pasture'!A1", "Pasture") -> Pasture | H15: {=Common_InputFunctions.Utility_LookupValueInTableOneColumnAndHeader(Table_Input_LivestockPurchases_Dairy[[#This Row],[Breed (select)]],Table_Input_LivestockPurchases_Dairy[[#This Row],[Class (select)]],Table_SourceData_Dairy_WjCowsHeifers[Breed],Table_SourceData_Dairy_WjCowsHeifers[#Headers],Table_SourceData_Dairy_WjCowsHeifers[#Data], 0)} -> 0
A16: =HYPERLINK("#'Input - Fert Prod System'!A1", "Fert Prod System") -> Fert Prod System | H16: {=Common_InputFunctions.Utility_LookupValueInTableOneColumnAndHeader(Table_Input_LivestockPurchases_Dairy[[#This Row],[Breed (select)]],Table_Input_LivestockPurchases_Dairy[[#This Row],[Class (select)]],Table_SourceData_Dairy_WjCowsHeifers[Breed],Table_SourceData_Dairy_WjCowsHeifers[#Headers],Table_SourceData_Dairy_WjCowsHeifers[#Data], 0)} -> 0
A17: =HYPERLINK("#'Input - Fertiliser'!A1", "Fertiliser") -> Fertiliser
A18: =HYPERLINK("#'Input - Fuel'!A1", "Fuel") -> Fuel
A19: =HYPERLINK("#'Input - Electricity'!A1", "Electricity") -> Electricity
A20: =HYPERLINK("#'Input - Common farm inputs'!A1", "Common farm inputs") -> Common farm inputs
A21: =HYPERLINK("#'Input - Crop pasture farm input'!A1", "Crop pasture farm input") -> Crop pasture farm input
A22: =HYPERLINK("#'Input - Livestock farm Inputs'!A1", "Livestock farm Inputs") -> Livestock farm Inputs
A23: =HYPERLINK("#'Input - Freight'!A1", "Freight") -> Freight
A24: =HYPERLINK("#'Input - Solid waste'!A1", "Solid waste") -> Solid waste
A25: =HYPERLINK("#'Input - Manure sent off-site'!A1", "Manure sent off-site") -> Manure sent off-site
A26: =HYPERLINK("#'Input - Data quality'!A1", "Data quality") -> Data quality
A29: CALCULATIONS
A30: =HYPERLINK("#'3.3.1.1-2 Enteric Methane'!A1", "3.3.1.1-2 Enteric methane") -> 3.3.1.1-2 Enteric methane
A31: =HYPERLINK("#'4.3.1.1-2 Methane'!A1", "4.3.1.1-2 Manure methane") -> 4.3.1.1-2 Manure methane
A32: =HYPERLINK("#'4.3.1.3-4 Direct N20'!A1", "4.3.1.3-4 Direct N20") -> 4.3.1.3-4 Direct N20
A33: =HYPERLINK("#'4.3.1.5 Atmos deposition'!A1", "4.3.1.5 Atmos deposition") -> 4.3.1.5 Atmos deposition
A34: =HYPERLINK("#'4.3.1.6-7 Leaching and runoff'!A1", "4.3.1.6-7 Leaching & runoff") -> 4.3.1.6-7 Leaching & runoff
A35: =HYPERLINK("#'4.3.1.8 Manure applied to soils'!A1", "4.3.1.8 Manure applied to soils") -> 4.3.1.8 Manure applied to soils
A36: =HYPERLINK("#'4.3.1.9 Soil direct N2O'!A1", "4.3.1.9 Soil direct N2O") -> 4.3.1.9 Soil direct N2O
A37: =HYPERLINK("#'4.3.1.10-11 Soil Atmos Dep'!A1", "4.3.1.10-11 Soil Atmos Deposition") -> 4.3.1.10-11 Soil Atmos Deposition
A38: =HYPERLINK("#'4.3.1.12-13 Soil leach runoff'!A1", "4.3.1.12-13 Soil leach & runoff") -> 4.3.1.12-13 Soil leach & runoff
A39: =HYPERLINK("#'5.1.1.1-2 Inorganic fert N2O'!A1", "5.1.1.1-2 Inorganic fert N2O") -> 5.1.1.1-2 Inorganic fert N2O
A40: =HYPERLINK("#'5.1.1.3-4 Inorganic fert CO2'!A1", "5.1.1.3-4 Inorganic fert CO2") -> 5.1.1.3-4 Inorganic fert CO2
A41: =HYPERLINK("#'5.2.1.1-2 Organic Fert N2O'!A1", "5.2.1.1-2 Organic fert N2O") -> 5.2.1.1-2 Organic fert N2O
A42: =HYPERLINK("#'5.3.1.1-2 Lime CO2'!A1", "5.3.1.1-2 Lime CO2") -> 5.3.1.1-2 Lime CO2
A43: =HYPERLINK("#'5.4.1.1-4 Atmos deposition'!A1", "5.4.1.1-4 Atmos. deposition") -> 5.4.1.1-4 Atmos. deposition
A44: =HYPERLINK("#'5.5.1.1-2 Leaching and runoff'!A1", "5.5.1.1-2 Leaching & runoff") -> 5.5.1.1-2 Leaching & runoff
A45: =HYPERLINK("#'6.2.1.1-2 Pasture residue N2O'!A1", "6.2.1.1-2 Pasture residue N2O") -> 6.2.1.1-2 Pasture residue N2O
A46: =HYPERLINK("#'6.3.1.1-2 Leach runoff pasture'!A1", "6.3.1.1-2 Leach & runoff (pasture)") -> 6.3.1.1-2 Leach & runoff (pasture)
A47: =HYPERLINK("#'8.1.1.1-2 Transport fuel'!A1", "8.1.1.1-2 Transport fuel") -> 8.1.1.1-2 Transport fuel
A48: =HYPERLINK("#'8.2.1.1-2 Stationary fuel'!A1", "8.2.1.1-2 Stationary fuel") -> 8.2.1.1-2 Stationary fuel
A49: =HYPERLINK("#'10.1.1-2 Solid waste treatment'!A1", "10.1.1.1-2 Solid waste") -> 10.1.1.1-2 Solid waste
A50: =HYPERLINK("#'14.1.1-2 Purchased electricity'!A1", "14.1.1-2 Purchased electricity") -> 14.1.1-2 Purchased electricity
A51: =HYPERLINK("#'15 Scope 3'!A1", "15 Scope 3") -> 15 Scope 3
A52: =HYPERLINK("#'Calcs - Manure sent off-site'!A1", "Calcs - Manure sent off-site") -> Calcs - Manure sent off-site
A55: APPENDICES
A56: =HYPERLINK("#'Constants - Dairy'!A1", "Constants - Dairy") -> Constants - Dairy
A57: =HYPERLINK("#'Constants - Ag Residue'!A1", "Constants - Ag residue") -> Constants - Ag residue
A58: =HYPERLINK("#'Constants - Common Livestock'!A1", "Constants - Common Livestock") -> Constants - Common Livestock
A59: =HYPERLINK("#'Constants - Electricity'!A1", "Constants - Electricity") -> Constants - Electricity
A60: =HYPERLINK("#'Constants - Fertiliser'!A1", "Constants - Fertiliser") -> Constants - Fertiliser
A61: =HYPERLINK("#'Constants - Fuel'!A1", "Constants - Fuel") -> Constants - Fuel
A62: =HYPERLINK("#'Constants - Scope 3'!A1", "Constants - Scope 3") -> Constants - Scope 3
A63: =HYPERLINK("#'Constants - Common'!A1", "Constants - Common") -> Constants - Common
A64: =HYPERLINK("#'Constants - Solid Waste'!A1", "Constants - Solid Waste") -> Constants - Solid Waste
A65: =HYPERLINK("#'Acknowledgements'!A1", "Acknowledgements") -> Acknowledgements

Sheet Input - Pasture
A1: #VALUE! | C1: Input - Pasture
A3: =HYPERLINK("#'Home'!A1", "Home") -> Home
A4: =HYPERLINK("#'Results - Activity period'!A1", "Results - Activity period") -> Results - Activity period
A5: =HYPERLINK("#'Results - Product EI'!A1", "Results - Product Emissions Intensity") -> Results - Product Emissions Intensity | D5: Area
A6: =HYPERLINK("#'Results'!A1", "Results") -> Results
D7: If multiple paddocks were managed in the same way at the same time, you can enter information for them all together.
A9: INPUTS | D9: Pasture type | E9: Grass clover mixture | F9: ← Please select
A10: =HYPERLINK("#'Input - Enterprise'!A1", "Enterprise") -> Enterprise | D10: Irrigation method | E10: Surface irrigation | F10: ← Please select
A11: =HYPERLINK("#'Input - Site'!A1", "Site") -> Site
A12: =HYPERLINK("#'Input - Dairy'!A1", "Dairy") -> Dairy | D12: Area under pasture | E12: 1000 | F12: Hectares
A13: =HYPERLINK("#'Input - Livestock sales'!A1", "Livestock sales") -> Livestock sales
A14: =HYPERLINK("#'Input - Dairy cattle purchases'!A1", "Dairy cattle purchases") -> Dairy cattle purchases | D14: Yield
A15: =HYPERLINK("#'Input - Pasture'!A1", "Pasture") -> Pasture
A16: =HYPERLINK("#'Input - Fert Prod System'!A1", "Fert Prod System") -> Fert Prod System | D16: 💡 'Pasture yield' is the average amount of dry matter that is grazed.
A17: =HYPERLINK("#'Input - Fertiliser'!A1", "Fertiliser") -> Fertiliser | D17: A default value is provided based on pasture type. You can edit this if known.
A18: =HYPERLINK("#'Input - Fuel'!A1", "Fuel") -> Fuel
A19: =HYPERLINK("#'Input - Electricity'!A1", "Electricity") -> Electricity | D19: Pasture yield | E19: =_xlfn.XLOOKUP(X_Cell_Pasture_PastureType, Table_SourceData_PastureAttributes[Pasture type],Table_SourceData_PastureAttributes[Average Yield (t DM ha) Yp]) -> 8.34 | F19: Tonnes dry matter / hectare
A20: =HYPERLINK("#'Input - Common farm inputs'!A1", "Common farm inputs") -> Common farm inputs | D20: Total pasture yield | E20: =X_Cell_Pasture_AreaUnderPasture*X_Cell_Pasture_YieldPerHectare -> 8340 | F20: Tonnes
A21: =HYPERLINK("#'Input - Crop pasture farm input'!A1", "Crop pasture farm input") -> Crop pasture farm input
A22: =HYPERLINK("#'Input - Livestock farm Inputs'!A1", "Livestock farm Inputs") -> Livestock farm Inputs
A23: =HYPERLINK("#'Input - Freight'!A1", "Freight") -> Freight | D23: Residue management
A24: =HYPERLINK("#'Input - Solid waste'!A1", "Solid waste") -> Solid waste
A25: =HYPERLINK("#'Input - Manure sent off-site'!A1", "Manure sent off-site") -> Manure sent off-site | D25: Area of pasture renewed or removed | E25: 500 | F25: Hectares
A26: =HYPERLINK("#'Input - Data quality'!A1", "Data quality") -> Data quality
A29: CALCULATIONS
A30: =HYPERLINK("#'3.3.1.1-2 Enteric Methane'!A1", "3.3.1.1-2 Enteric methane") -> 3.3.1.1-2 Enteric methane
A31: =HYPERLINK("#'4.3.1.1-2 Methane'!A1", "4.3.1.1-2 Manure methane") -> 4.3.1.1-2 Manure methane
A32: =HYPERLINK("#'4.3.1.3-4 Direct N20'!A1", "4.3.1.3-4 Direct N20") -> 4.3.1.3-4 Direct N20
A33: =HYPERLINK("#'4.3.1.5 Atmos deposition'!A1", "4.3.1.5 Atmos deposition") -> 4.3.1.5 Atmos deposition
A34: =HYPERLINK("#'4.3.1.6-7 Leaching and runoff'!A1", "4.3.1.6-7 Leaching & runoff") -> 4.3.1.6-7 Leaching & runoff
A35: =HYPERLINK("#'4.3.1.8 Manure applied to soils'!A1", "4.3.1.8 Manure applied to soils") -> 4.3.1.8 Manure applied to soils
A36: =HYPERLINK("#'4.3.1.9 Soil direct N2O'!A1", "4.3.1.9 Soil direct N2O") -> 4.3.1.9 Soil direct N2O
A37: =HYPERLINK("#'4.3.1.10-11 Soil Atmos Dep'!A1", "4.3.1.10-11 Soil Atmos Deposition") -> 4.3.1.10-11 Soil Atmos Deposition
A38: =HYPERLINK("#'4.3.1.12-13 Soil leach runoff'!A1", "4.3.1.12-13 Soil leach & runoff") -> 4.3.1.12-13 Soil leach & runoff
A39: =HYPERLINK("#'5.1.1.1-2 Inorganic fert N2O'!A1", "5.1.1.1-2 Inorganic fert N2O") -> 5.1.1.1-2 Inorganic fert N2O
A40: =HYPERLINK("#'5.1.1.3-4 Inorganic fert CO2'!A1", "5.1.1.3-4 Inorganic fert CO2") -> 5.1.1.3-4 Inorganic fert CO2
A41: =HYPERLINK("#'5.2.1.1-2 Organic Fert N2O'!A1", "5.2.1.1-2 Organic fert N2O") -> 5.2.1.1-2 Organic fert N2O
A42: =HYPERLINK("#'5.3.1.1-2 Lime CO2'!A1", "5.3.1.1-2 Lime CO2") -> 5.3.1.1-2 Lime CO2
A43: =HYPERLINK("#'5.4.1.1-4 Atmos deposition'!A1", "5.4.1.1-4 Atmos. deposition") -> 5.4.1.1-4 Atmos. deposition
A44: =HYPERLINK("#'5.5.1.1-2 Leaching and runoff'!A1", "5.5.1.1-2 Leaching & runoff") -> 5.5.1.1-2 Leaching & runoff
A45: =HYPERLINK("#'6.2.1.1-2 Pasture residue N2O'!A1", "6.2.1.1-2 Pasture residue N2O") -> 6.2.1.1-2 Pasture residue N2O
A46: =HYPERLINK("#'6.3.1.1-2 Leach runoff pasture'!A1", "6.3.1.1-2 Leach & runoff (pasture)") -> 6.3.1.1-2 Leach & runoff (pasture)
A47: =HYPERLINK("#'8.1.1.1-2 Transport fuel'!A1", "8.1.1.1-2 Transport fuel") -> 8.1.1.1-2 Transport fuel
A48: =HYPERLINK("#'8.2.1.1-2 Stationary fuel'!A1", "8.2.1.1-2 Stationary fuel") -> 8.2.1.1-2 Stationary fuel
A49: =HYPERLINK("#'10.1.1-2 Solid waste treatment'!A1", "10.1.1.1-2 Solid waste") -> 10.1.1.1-2 Solid waste
A50: =HYPERLINK("#'14.1.1-2 Purchased electricity'!A1", "14.1.1-2 Purchased electricity") -> 14.1.1-2 Purchased electricity
A51: =HYPERLINK("#'15 Scope 3'!A1", "15 Scope 3") -> 15 Scope 3
A52: =HYPERLINK("#'Calcs - Manure sent off-site'!A1", "Calcs - Manure sent off-site") -> Calcs - Manure sent off-site
A55: APPENDICES
A56: =HYPERLINK("#'Constants - Dairy'!A1", "Constants - Dairy") -> Constants - Dairy
A57: =HYPERLINK("#'Constants - Ag Residue'!A1", "Constants - Ag residue") -> Constants - Ag residue
A58: =HYPERLINK("#'Constants - Common Livestock'!A1", "Constants - Common Livestock") -> Constants - Common Livestock
A59: =HYPERLINK("#'Constants - Electricity'!A1", "Constants - Electricity") -> Constants - Electricity
A60: =HYPERLINK("#'Constants - Fertiliser'!A1", "Constants - Fertiliser") -> Constants - Fertiliser
A61: =HYPERLINK("#'Constants - Fuel'!A1", "Constants - Fuel") -> Constants - Fuel
A62: =HYPERLINK("#'Constants - Scope 3'!A1", "Constants - Scope 3") -> Constants - Scope 3
A63: =HYPERLINK("#'Constants - Common'!A1", "Constants - Common") -> Constants - Common
A64: =HYPERLINK("#'Constants - Solid Waste'!A1", "Constants - Solid Waste") -> Constants - Solid Waste
A65: =HYPERLINK("#'Acknowledgements'!A1", "Acknowledgements") -> Acknowledgements

Sheet Input - Fert Prod System
A1: #VALUE! | C1: Input - Fertiliser Production System
A3: =HYPERLINK("#'Home'!A1", "Home") -> Home
A4: =HYPERLINK("#'Results - Activity period'!A1", "Results - Activity period") -> Results - Activity period
A5: =HYPERLINK("#'Results - Product EI'!A1", "Results - Product Emissions Intensity") -> Results - Product Emissions Intensity | D5: These inputs are used for fertiliser calculations, and they take their values from the "Input - Pasture" sheet. Do not edit these cells.
A6: =HYPERLINK("#'Results'!A1", "Results") -> Results
D7: Production system | E7: Pasture
D8: Crop type | E8: Pasture
A9: INPUTS | D9: Irrigation method | E9: {=X_Cell_Pasture_IrrigationMethod} -> Surface irrigation
A10: =HYPERLINK("#'Input - Enterprise'!A1", "Enterprise") -> Enterprise | D10: Area under cropping | E10: {=X_Cell_Pasture_AreaUnderPasture} -> 1000
A11: =HYPERLINK("#'Input - Site'!A1", "Site") -> Site
A12: =HYPERLINK("#'Input - Dairy'!A1", "Dairy") -> Dairy
A13: =HYPERLINK("#'Input - Livestock sales'!A1", "Livestock sales") -> Livestock sales
A14: =HYPERLINK("#'Input - Dairy cattle purchases'!A1", "Dairy cattle purchases") -> Dairy cattle purchases
A15: =HYPERLINK("#'Input - Pasture'!A1", "Pasture") -> Pasture
A16: =HYPERLINK("#'Input - Fert Prod System'!A1", "Fert Prod System") -> Fert Prod System
A17: =HYPERLINK("#'Input - Fertiliser'!A1", "Fertiliser") -> Fertiliser
A18: =HYPERLINK("#'Input - Fuel'!A1", "Fuel") -> Fuel
A19: =HYPERLINK("#'Input - Electricity'!A1", "Electricity") -> Electricity
A20: =HYPERLINK("#'Input - Common farm inputs'!A1", "Common farm inputs") -> Common farm inputs
A21: =HYPERLINK("#'Input - Crop pasture farm input'!A1", "Crop pasture farm input") -> Crop pasture farm input
A22: =HYPERLINK("#'Input - Livestock farm Inputs'!A1", "Livestock farm Inputs") -> Livestock farm Inputs
A23: =HYPERLINK("#'Input - Freight'!A1", "Freight") -> Freight
A24: =HYPERLINK("#'Input - Solid waste'!A1", "Solid waste") -> Solid waste
A25: =HYPERLINK("#'Input - Manure sent off-site'!A1", "Manure sent off-site") -> Manure sent off-site
A26: =HYPERLINK("#'Input - Data quality'!A1", "Data quality") -> Data quality
A29: CALCULATIONS
A30: =HYPERLINK("#'3.3.1.1-2 Enteric Methane'!A1", "3.3.1.1-2 Enteric methane") -> 3.3.1.1-2 Enteric methane
A31: =HYPERLINK("#'4.3.1.1-2 Methane'!A1", "4.3.1.1-2 Manure methane") -> 4.3.1.1-2 Manure methane
A32: =HYPERLINK("#'4.3.1.3-4 Direct N20'!A1", "4.3.1.3-4 Direct N20") -> 4.3.1.3-4 Direct N20
A33: =HYPERLINK("#'4.3.1.5 Atmos deposition'!A1", "4.3.1.5 Atmos deposition") -> 4.3.1.5 Atmos deposition
A34: =HYPERLINK("#'4.3.1.6-7 Leaching and runoff'!A1", "4.3.1.6-7 Leaching & runoff") -> 4.3.1.6-7 Leaching & runoff
A35: =HYPERLINK("#'4.3.1.8 Manure applied to soils'!A1", "4.3.1.8 Manure applied to soils") -> 4.3.1.8 Manure applied to soils
A36: =HYPERLINK("#'4.3.1.9 Soil direct N2O'!A1", "4.3.1.9 Soil direct N2O") -> 4.3.1.9 Soil direct N2O
A37: =HYPERLINK("#'4.3.1.10-11 Soil Atmos Dep'!A1", "4.3.1.10-11 Soil Atmos Deposition") -> 4.3.1.10-11 Soil Atmos Deposition
A38: =HYPERLINK("#'4.3.1.12-13 Soil leach runoff'!A1", "4.3.1.12-13 Soil leach & runoff") -> 4.3.1.12-13 Soil leach & runoff
A39: =HYPERLINK("#'5.1.1.1-2 Inorganic fert N2O'!A1", "5.1.1.1-2 Inorganic fert N2O") -> 5.1.1.1-2 Inorganic fert N2O
A40: =HYPERLINK("#'5.1.1.3-4 Inorganic fert CO2'!A1", "5.1.1.3-4 Inorganic fert CO2") -> 5.1.1.3-4 Inorganic fert CO2
A41: =HYPERLINK("#'5.2.1.1-2 Organic Fert N2O'!A1", "5.2.1.1-2 Organic fert N2O") -> 5.2.1.1-2 Organic fert N2O
A42: =HYPERLINK("#'5.3.1.1-2 Lime CO2'!A1", "5.3.1.1-2 Lime CO2") -> 5.3.1.1-2 Lime CO2
A43: =HYPERLINK("#'5.4.1.1-4 Atmos deposition'!A1", "5.4.1.1-4 Atmos. deposition") -> 5.4.1.1-4 Atmos. deposition
A44: =HYPERLINK("#'5.5.1.1-2 Leaching and runoff'!A1", "5.5.1.1-2 Leaching & runoff") -> 5.5.1.1-2 Leaching & runoff
A45: =HYPERLINK("#'6.2.1.1-2 Pasture residue N2O'!A1", "6.2.1.1-2 Pasture residue N2O") -> 6.2.1.1-2 Pasture residue N2O
A46: =HYPERLINK("#'6.3.1.1-2 Leach runoff pasture'!A1", "6.3.1.1-2 Leach & runoff (pasture)") -> 6.3.1.1-2 Leach & runoff (pasture)
A47: =HYPERLINK("#'8.1.1.1-2 Transport fuel'!A1", "8.1.1.1-2 Transport fuel") -> 8.1.1.1-2 Transport fuel
A48: =HYPERLINK("#'8.2.1.1-2 Stationary fuel'!A1", "8.2.1.1-2 Stationary fuel") -> 8.2.1.1-2 Stationary fuel
A49: =HYPERLINK("#'10.1.1-2 Solid waste treatment'!A1", "10.1.1.1-2 Solid waste") -> 10.1.1.1-2 Solid waste
A50: =HYPERLINK("#'14.1.1-2 Purchased electricity'!A1", "14.1.1-2 Purchased electricity") -> 14.1.1-2 Purchased electricity
A51: =HYPERLINK("#'15 Scope 3'!A1", "15 Scope 3") -> 15 Scope 3
A52: =HYPERLINK("#'Calcs - Manure sent off-site'!A1", "Calcs - Manure sent off-site") -> Calcs - Manure sent off-site
A55: APPENDICES
A56: =HYPERLINK("#'Constants - Dairy'!A1", "Constants - Dairy") -> Constants - Dairy
A57: =HYPERLINK("#'Constants - Ag Residue'!A1", "Constants - Ag residue") -> Constants - Ag residue
A58: =HYPERLINK("#'Constants - Common Livestock'!A1", "Constants - Common Livestock") -> Constants - Common Livestock
A59: =HYPERLINK("#'Constants - Electricity'!A1", "Constants - Electricity") -> Constants - Electricity
A60: =HYPERLINK("#'Constants - Fertiliser'!A1", "Constants - Fertiliser") -> Constants - Fertiliser
A61: =HYPERLINK("#'Constants - Fuel'!A1", "Constants - Fuel") -> Constants - Fuel
A62: =HYPERLINK("#'Constants - Scope 3'!A1", "Constants - Scope 3") -> Constants - Scope 3
A63: =HYPERLINK("#'Constants - Common'!A1", "Constants - Common") -> Constants - Common
A64: =HYPERLINK("#'Constants - Solid Waste'!A1", "Constants - Solid Waste") -> Constants - Solid Waste
A65: =HYPERLINK("#'Acknowledgements'!A1", "Acknowledgements") -> Acknowledgements

Sheet Input - Fertiliser
A1: #VALUE! | C1: Input - Fertiliser
A3: =HYPERLINK("#'Home'!A1", "Home") -> Home
A4: =HYPERLINK("#'Results - Activity period'!A1", "Results - Activity period") -> Results - Activity period
A5: =HYPERLINK("#'Results - Product EI'!A1", "Results - Product Emissions Intensity") -> Results - Product Emissions Intensity | D5: Inorganic fertiliser applied
A6: =HYPERLINK("#'Results'!A1", "Results") -> Results
D7: 💡You can add more rows to tables by right-clicking on the table and selecting "Insert > Table rows above/below".
D8: 💡The application area is the same as the area under pasture / cropping by default. You can edit it if the application area is different.
A9: INPUTS
A10: =HYPERLINK("#'Input - Enterprise'!A1", "Enterprise") -> Enterprise | D10: Branded fertiliser products
A11: =HYPERLINK("#'Input - Site'!A1", "Site") -> Site | D11: Product (select) | E11: Amount applied per hectare | F11: Application unit | G11: Application area (ha) | H11: Density | I11: Total applied (kg) | J11: Ingredient 1 | K11: Ingredient 1 percent | L11: Ingredient 2 | M11: Ingredient 2 percent | N11: Ingredient 3 | O11: Ingredient 3 percent | P11: Ingredient 4 | Q11: Ingredient 4 percent | R11: Ingredient 5 | S11: Ingredient 5 percent | T11: Ingredient 6 | U11: Ingredient 6 percent | V11: % N (Ingredients) | W11: % N (declared) | X11: N application rate (kg/ha) | Y11: Urea source | Z11: Ammonia source
A12: =HYPERLINK("#'Input - Dairy'!A1", "Dairy") -> Dairy | D12: Urea | E12: 100 | F12: =IFERROR(_xlfn.XLOOKUP(Table_Input_InorganicFertiliser_Brands[[#This Row],[Product (select)]],FertiliserProducts[Product],FertiliserProducts[Unit]), "kg") -> kg | G12: =X_Cell_Fertiliser_AreaUnderCropping -> Pasture | H12: =IFERROR(_xlfn.XLOOKUP(Table_Input_InorganicFertiliser_Brands[[#This Row],[Product (select)]],FertiliserProducts[Product],FertiliserProducts[Density]), 1) -> 1 | I12: =(Table_Input_InorganicFertiliser_Brands[[#This Row],[Amount applied per hectare]]*Table_Input_InorganicFertiliser_Brands[[#This Row],[Density]])*Table_Input_InorganicFertiliser_Brands[[#This Row],[Application area (ha)]] -> #VALUE! | J12: {=Fertiliser_InputFunctions.Fertiliser_FertiliserProductLookup(Table_Input_InorganicFertiliser_Brands[[#This Row],[Product (select)]], Table_Input_InorganicFertiliser_Brands[[#Headers],[Ingredient 1]], FertiliserProducts[#Data], FertiliserProducts[Product], FertiliserProducts[#Headers])} -> Urea | K12: {=Fertiliser_InputFunctions.Fertiliser_FertiliserProductLookup(Table_Input_InorganicFertiliser_Brands[[#This Row],[Product (select)]], Table_Input_InorganicFertiliser_Brands[[#Headers],[Ingredient 1 percent]], FertiliserProducts[#Data], FertiliserProducts[Product], FertiliserProducts[#Headers])} -> 1 | L12: {=Fertiliser_InputFunctions.Fertiliser_FertiliserProductLookup(Table_Input_InorganicFertiliser_Brands[[#This Row],[Product (select)]], Table_Input_InorganicFertiliser_Brands[[#Headers],[Ingredient 2]], FertiliserProducts[#Data], FertiliserProducts[Product], FertiliserProducts[#Headers])} | M12: {=Fertiliser_InputFunctions.Fertiliser_FertiliserProductLookup(Table_Input_InorganicFertiliser_Brands[[#This Row],[Product (select)]], Table_Input_InorganicFertiliser_Brands[[#Headers],[Ingredient 2 percent]], FertiliserProducts[#Data], FertiliserProducts[Product], FertiliserProducts[#Headers])} | N12: {=Fertiliser_InputFunctions.Fertiliser_FertiliserProductLookup(Table_Input_InorganicFertiliser_Brands[[#This Row],[Product (select)]], Table_Input_InorganicFertiliser_Brands[[#Headers],[Ingredient 3]], FertiliserProducts[#Data], FertiliserProducts[Product], FertiliserProducts[#Headers])} | O12: {=Fertiliser_InputFunctions.Fertiliser_FertiliserProductLookup(Table_Input_InorganicFertiliser_Brands[[#This Row],[Product (select)]], Table_Input_InorganicFertiliser_Brands[[#Headers],[Ingredient 3 percent]], FertiliserProducts[#Data], FertiliserProducts[Product], FertiliserProducts[#Headers])} | P12: {=Fertiliser_InputFunctions.Fertiliser_FertiliserProductLookup(Table_Input_InorganicFertiliser_Brands[[#This Row],[Product (select)]], Table_Input_InorganicFertiliser_Brands[[#Headers],[Ingredient 4]], FertiliserProducts[#Data], FertiliserProducts[Product], FertiliserProducts[#Headers])} | Q12: {=Fertiliser_InputFunctions.Fertiliser_FertiliserProductLookup(Table_Input_InorganicFertiliser_Brands[[#This Row],[Product (select)]], Table_Input_InorganicFertiliser_Brands[[#Headers],[Ingredient 4 percent]], FertiliserProducts[#Data], FertiliserProducts[Product], FertiliserProducts[#Headers])} | R12: {=Fertiliser_InputFunctions.Fertiliser_FertiliserProductLookup(Table_Input_InorganicFertiliser_Brands[[#This Row],[Product (select)]], Table_Input_InorganicFertiliser_Brands[[#Headers],[Ingredient 5]], FertiliserProducts[#Data], FertiliserProducts[Product], FertiliserProducts[#Headers])} | S12: {=Fertiliser_InputFunctions.Fertiliser_FertiliserProductLookup(Table_Input_InorganicFertiliser_Brands[[#This Row],[Product (select)]], Table_Input_InorganicFertiliser_Brands[[#Headers],[Ingredient 5 percent]], FertiliserProducts[#Data], FertiliserProducts[Product], FertiliserProducts[#Headers])} | T12: {=Fertiliser_InputFunctions.Fertiliser_FertiliserProductLookup(Table_Input_InorganicFertiliser_Brands[[#This Row],[Product (select)]], Table_Input_InorganicFertiliser_Brands[[#Headers],[Ingredient 6]], FertiliserProducts[#Data], FertiliserProducts[Product], FertiliserProducts[#Headers])} | U12: {=Fertiliser_InputFunctions.Fertiliser_FertiliserProductLookup(Table_Input_InorganicFertiliser_Brands[[#This Row],[Product (select)]], Table_Input_InorganicFertiliser_Brands[[#Headers],[Ingredient 6 percent]], FertiliserProducts[#Data], FertiliserProducts[Product], FertiliserProducts[#Headers])} | V12: =IFERROR((_xlfn.XLOOKUP(Table_Input_InorganicFertiliser_Brands[[#This Row],[Ingredient 1]], Table_Fertiliser_ChemicalCompounds[Fertiliser type f],Table_Fertiliser_ChemicalCompounds[FNinorganic f])*Table_Input_InorganicFertiliser_Brands[[#This Row],[Ingredient 1 percent]]), 0)+ IFERROR((_xlfn.XLOOKUP(Table_Input_InorganicFertiliser_Brands[[#This Row],[Ingredient 2]],Table_Fertiliser_ChemicalCompounds[Fertiliser type f],Table_Fertiliser_ChemicalCompounds[FNinorganic f])*Table_Input_InorganicFertiliser_Brands[[#This Row],[Ingredient 2 percent]]), 0)+ IFERROR((_xlfn.XLOOKUP(Table_Input_InorganicFertiliser_Brands[[#This Row],[Ingredient 3]],Table_Fertiliser_ChemicalCompounds[Fertiliser type f],Table_Fertiliser_ChemicalCompounds[FNinorganic f])*Table_Input_InorganicFertiliser_Brands[[#This Row],[Ingredient 3 percent]]), 0)+ IFERROR((_xlfn.XLOOKUP(Table_Input_InorganicFertiliser_Brands[[#This Row],[Ingredient 4]],Table_Fertiliser_ChemicalCompounds[Fertiliser type f],Table_Fertiliser_ChemicalCompounds[FNinorganic f])*Table_Input_InorganicFertiliser_Brands[[#This Row],[Ingredient 4 percent]]), 0)+ IFERROR((_xlfn.XLOOKUP(Table_Input_InorganicFertiliser_Brands[[#This Row],[Ingredient 5]],Table_Fertiliser_ChemicalCompounds[Fertiliser type f],Table_Fertiliser_ChemicalCompounds[FNinorganic f])*Table_Input_InorganicFertiliser_Brands[[#This Row],[Ingredient 5 percent]]), 0)+ IFERROR((_xlfn.XLOOKUP(Table_Input_InorganicFertiliser_Brands[[#This Row],[Ingredient 6]],Table_Fertiliser_ChemicalCompounds[Fertiliser type f],Table_Fertiliser_ChemicalCompounds[FNinorganic f])*Table_Input_InorganicFertiliser_Brands[[#This Row],[Ingredient 6 percent]]), 0) -> 0.46 | W12: {=IFERROR(Fertiliser_InputFunctions.Fertiliser_FertiliserProductLookup(Table_Input_InorganicFertiliser_Brands[[#This Row],[Product (select)]], "N declared", FertiliserProducts[#Data], FertiliserProducts[Product], FertiliserProducts[#Headers])*0.01, 0)} -> 0.46 | X12: =(Table_Input_InorganicFertiliser_Brands[[#This Row],[Amount applied per hectare]]*Table_Input_InorganicFertiliser_Brands[[#This Row],[Density]])*(IF(Table_Input_InorganicFertiliser_Brands[[#This Row],[% N (declared)]], Table_Input_InorganicFertiliser_Brands[[#This Row],[% N (declared)]], Table_Input_InorganicFertiliser_Brands[[#This Row],[% N (Ingredients)]])) -> 46 | Y12: =IFERROR(_xlfn.XLOOKUP(Table_Input_InorganicFertiliser_Brands[[#This Row],[Product (select)]],FertiliserProducts[Product],FertiliserProducts[Urea source]), "") | Z12: =IFERROR(_xlfn.XLOOKUP(Table_Input_InorganicFertiliser_Brands[[#This Row],[Product (select)]],FertiliserProducts[Product],FertiliserProducts[Ammonia source]), "")
A13: =HYPERLINK("#'Input - Livestock sales'!A1", "Livestock sales") -> Livestock sales | D13: Boost-It | E13: 100 | F13: =IFERROR(_xlfn.XLOOKUP(Table_Input_InorganicFertiliser_Brands[[#This Row],[Product (select)]],FertiliserProducts[Product],FertiliserProducts[Unit]), "kg") -> kg | G13: =X_Cell_Fertiliser_AreaUnderCropping -> Pasture | H13: =IFERROR(_xlfn.XLOOKUP(Table_Input_InorganicFertiliser_Brands[[#This Row],[Product (select)]],FertiliserProducts[Product],FertiliserProducts[Density]), 1) -> 1 | I13: =(Table_Input_InorganicFertiliser_Brands[[#This Row],[Amount applied per hectare]]*Table_Input_InorganicFertiliser_Brands[[#This Row],[Density]])*Table_Input_InorganicFertiliser_Brands[[#This Row],[Application area (ha)]] -> #VALUE! | J13: {=Fertiliser_InputFunctions.Fertiliser_FertiliserProductLookup(Table_Input_InorganicFertiliser_Brands[[#This Row],[Product (select)]], Table_Input_InorganicFertiliser_Brands[[#Headers],[Ingredient 1]], FertiliserProducts[#Data], FertiliserProducts[Product], FertiliserProducts[#Headers])} -> Urea | K13: {=Fertiliser_InputFunctions.Fertiliser_FertiliserProductLookup(Table_Input_InorganicFertiliser_Brands[[#This Row],[Product (select)]], Table_Input_InorganicFertiliser_Brands[[#Headers],[Ingredient 1 percent]], FertiliserProducts[#Data], FertiliserProducts[Product], FertiliserProducts[#Headers])} -> 0.521739 | L13: {=Fertiliser_InputFunctions.Fertiliser_FertiliserProductLookup(Table_Input_InorganicFertiliser_Brands[[#This Row],[Product (select)]], Table_Input_InorganicFertiliser_Brands[[#Headers],[Ingredient 2]], FertiliserProducts[#Data], FertiliserProducts[Product], FertiliserProducts[#Headers])} -> Potassium - Generic | M13: {=Fertiliser_InputFunctions.Fertiliser_FertiliserProductLookup(Table_Input_InorganicFertiliser_Brands[[#This Row],[Product (select)]], Table_Input_InorganicFertiliser_Brands[[#Headers],[Ingredient 2 percent]], FertiliserProducts[#Data], FertiliserProducts[Product], FertiliserProducts[#Headers])} -> 0.08 | N13: {=Fertiliser_InputFunctions.Fertiliser_FertiliserProductLookup(Table_Input_InorganicFertiliser_Brands[[#This Row],[Product (select)]], Table_Input_InorganicFertiliser_Brands[[#Headers],[Ingredient 3]], FertiliserProducts[#Data], FertiliserProducts[Product], FertiliserProducts[#Headers])} -> Sulfur - Generic | O13: {=Fertiliser_InputFunctions.Fertiliser_FertiliserProductLookup(Table_Input_InorganicFertiliser_Brands[[#This Row],[Product (select)]], Table_Input_InorganicFertiliser_Brands[[#Headers],[Ingredient 3 percent]], FertiliserProducts[#Data], FertiliserProducts[Product], FertiliserProducts[#Headers])} -> 0.053 | P13: {=Fertiliser_InputFunctions.Fertiliser_FertiliserProductLookup(Table_Input_InorganicFertiliser_Brands[[#This Row],[Product (select)]], Table_Input_InorganicFertiliser_Brands[[#Headers],[Ingredient 4]], FertiliserProducts[#Data], FertiliserProducts[Product], FertiliserProducts[#Headers])} -> Phosphorus - Generic | Q13: {=Fertiliser_InputFunctions.Fertiliser_FertiliserProductLookup(Table_Input_InorganicFertiliser_Brands[[#This Row],[Product (select)]], Table_Input_InorganicFertiliser_Brands[[#Headers],[Ingredient 4 percent]], FertiliserProducts[#Data], FertiliserProducts[Product], FertiliserProducts[#Headers])} -> 0.052 | R13: {=Fertiliser_InputFunctions.Fertiliser_FertiliserProductLookup(Table_Input_InorganicFertiliser_Brands[[#This Row],[Product (select)]], Table_Input_InorganicFertiliser_Brands[[#Headers],[Ingredient 5]], FertiliserProducts[#Data], FertiliserProducts[Product], FertiliserProducts[#Headers])} -> Magnesium | S13: {=Fertiliser_InputFunctions.Fertiliser_FertiliserProductLookup(Table_Input_InorganicFertiliser_Brands[[#This Row],[Product (select)]], Table_Input_InorganicFertiliser_Brands[[#Headers],[Ingredient 5 percent]], FertiliserProducts[#Data], FertiliserProducts[Product], FertiliserProducts[#Headers])} -> 0.013 | T13: {=Fertiliser_InputFunctions.Fertiliser_FertiliserProductLookup(Table_Input_InorganicFertiliser_Brands[[#This Row],[Product (select)]], Table_Input_InorganicFertiliser_Brands[[#Headers],[Ingredient 6]], FertiliserProducts[#Data], FertiliserProducts[Product], FertiliserProducts[#Headers])} -> Zinc | U13: {=Fertiliser_InputFunctions.Fertiliser_FertiliserProductLookup(Table_Input_InorganicFertiliser_Brands[[#This Row],[Product (select)]], Table_Input_InorganicFertiliser_Brands[[#Headers],[Ingredient 6 percent]], FertiliserProducts[#Data], FertiliserProducts[Product], FertiliserProducts[#Headers])} -> 0.002 | V13: =IFERROR((_xlfn.XLOOKUP(Table_Input_InorganicFertiliser_Brands[[#This Row],[Ingredient 1]], Table_Fertiliser_ChemicalCompounds[Fertiliser type f],Table_Fertiliser_ChemicalCompounds[FNinorganic f])*Table_Input_InorganicFertiliser_Brands[[#This Row],[Ingredient 1 percent]]), 0)+ IFERROR((_xlfn.XLOOKUP(Table_Input_InorganicFertiliser_Brands[[#This Row],[Ingredient 2]],Table_Fertiliser_ChemicalCompounds[Fertiliser type f],Table_Fertiliser_ChemicalCompounds[FNinorganic f])*Table_Input_InorganicFertiliser_Brands[[#This Row],[Ingredient 2 percent]]), 0)+ IFERROR((_xlfn.XLOOKUP(Table_Input_InorganicFertiliser_Brands[[#This Row],[Ingredient 3]],Table_Fertiliser_ChemicalCompounds[Fertiliser type f],Table_Fertiliser_ChemicalCompounds[FNinorganic f])*Table_Input_InorganicFertiliser_Brands[[#This Row],[Ingredient 3 percent]]), 0)+ IFERROR((_xlfn.XLOOKUP(Table_Input_InorganicFertiliser_Brands[[#This Row],[Ingredient 4]],Table_Fertiliser_ChemicalCompounds[Fertiliser type f],Table_Fertiliser_ChemicalCompounds[FNinorganic f])*Table_Input_InorganicFertiliser_Brands[[#This Row],[Ingredient 4 percent]]), 0)+ IFERROR((_xlfn.XLOOKUP(Table_Input_InorganicFertiliser_Brands[[#This Row],[Ingredient 5]],Table_Fertiliser_ChemicalCompounds[Fertiliser type f],Table_Fertiliser_ChemicalCompounds[FNinorganic f])*Table_Input_InorganicFertiliser_Brands[[#This Row],[Ingredient 5 percent]]), 0)+ IFERROR((_xlfn.XLOOKUP(Table_Input_InorganicFertiliser_Brands[[#This Row],[Ingredient 6]],Table_Fertiliser_ChemicalCompounds[Fertiliser type f],Table_Fertiliser_ChemicalCompounds[FNinorganic f])*Table_Input_InorganicFertiliser_Brands[[#This Row],[Ingredient 6 percent]]), 0) -> 0.23999994 | W13: {=IFERROR(Fertiliser_InputFunctions.Fertiliser_FertiliserProductLookup(Table_Input_InorganicFertiliser_Brands[[#This Row],[Product (select)]], "N declared", FertiliserProducts[#Data], FertiliserProducts[Product], FertiliserProducts[#Headers])*0.01, 0)} -> 0.24 | X13: =(Table_Input_InorganicFertiliser_Brands[[#This Row],[Amount applied per hectare]]*Table_Input_InorganicFertiliser_Brands[[#This Row],[Density]])*(IF(Table_Input_InorganicFertiliser_Brands[[#This Row],[% N (declared)]], Table_Input_InorganicFertiliser_Brands[[#This Row],[% N (declared)]], Table_Input_InorganicFertiliser_Brands[[#This Row],[% N (Ingredients)]])) -> 24 | Y13: =IFERROR(_xlfn.XLOOKUP(Table_Input_InorganicFertiliser_Brands[[#This Row],[Product (select)]],FertiliserProducts[Product],FertiliserProducts[Urea source]), "") | Z13: =IFERROR(_xlfn.XLOOKUP(Table_Input_InorganicFertiliser_Brands[[#This Row],[Product (select)]],FertiliserProducts[Product],FertiliserProducts[Ammonia source]), "")
A14: =HYPERLINK("#'Input - Dairy cattle purchases'!A1", "Dairy cattle purchases") -> Dairy cattle purchases | D14: Cal-Gran 50/50 | E14: 100 | F14: =IFERROR(_xlfn.XLOOKUP(Table_Input_InorganicFertiliser_Brands[[#This Row],[Product (select)]],FertiliserProducts[Product],FertiliserProducts[Unit]), "kg") -> kg | G14: =X_Cell_Fertiliser_AreaUnderCropping -> Pasture | H14: =IFERROR(_xlfn.XLOOKUP(Table_Input_InorganicFertiliser_Brands[[#This Row],[Product (select)]],FertiliserProducts[Product],FertiliserProducts[Density]), 1) -> 1 | I14: =(Table_Input_InorganicFertiliser_Brands[[#This Row],[Amount applied per hectare]]*Table_Input_InorganicFertiliser_Brands[[#This Row],[Density]])*Table_Input_InorganicFertiliser_Brands[[#This Row],[Application area (ha)]] -> #VALUE! | J14: {=Fertiliser_InputFunctions.Fertiliser_FertiliserProductLookup(Table_Input_InorganicFertiliser_Brands[[#This Row],[Product (select)]], Table_Input_InorganicFertiliser_Brands[[#Headers],[Ingredient 1]], FertiliserProducts[#Data], FertiliserProducts[Product], FertiliserProducts[#Headers])} -> Nitrogen - Nitrate | K14: {=Fertiliser_InputFunctions.Fertiliser_FertiliserProductLookup(Table_Input_InorganicFertiliser_Brands[[#This Row],[Product (select)]], Table_Input_InorganicFertiliser_Brands[[#Headers],[Ingredient 1 percent]], FertiliserProducts[#Data], FertiliserProducts[Product], FertiliserProducts[#Headers])} -> 0.055 | L14: {=Fertiliser_InputFunctions.Fertiliser_FertiliserProductLookup(Table_Input_InorganicFertiliser_Brands[[#This Row],[Product (select)]], Table_Input_InorganicFertiliser_Brands[[#Headers],[Ingredient 2]], FertiliserProducts[#Data], FertiliserProducts[Product], FertiliserProducts[#Headers])} -> Nitrogen - Ammoniacal | M14: {=Fertiliser_InputFunctions.Fertiliser_FertiliserProductLookup(Table_Input_InorganicFertiliser_Brands[[#This Row],[Product (select)]], Table_Input_InorganicFertiliser_Brands[[#Headers],[Ingredient 2 percent]], FertiliserProducts[#Data], FertiliserProducts[Product], FertiliserProducts[#Headers])} -> 0.124 | N14: {=Fertiliser_InputFunctions.Fertiliser_FertiliserProductLookup(Table_Input_InorganicFertiliser_Brands[[#This Row],[Product (select)]], Table_Input_InorganicFertiliser_Brands[[#Headers],[Ingredient 3]], FertiliserProducts[#Data], FertiliserProducts[Product], FertiliserProducts[#Headers])} -> Potassium - Generic | O14: {=Fertiliser_InputFunctions.Fertiliser_FertiliserProductLookup(Table_Input_InorganicFertiliser_Brands[[#This Row],[Product (select)]], Table_Input_InorganicFertiliser_Brands[[#Headers],[Ingredient 3 percent]], FertiliserProducts[#Data], FertiliserProducts[Product], FertiliserProducts[#Headers])} -> 0.15 | P14: {=Fertiliser_InputFunctions.Fertiliser_FertiliserProductLookup(Table_Input_InorganicFertiliser_Brands[[#This Row],[Product (select)]], Table_Input_InorganicFertiliser_Brands[[#Headers],[Ingredient 4]], FertiliserProducts[#Data], FertiliserProducts[Product], FertiliserProducts[#Headers])} -> Sulfur - Generic | Q14: {=Fertiliser_InputFunctions.Fertiliser_FertiliserProductLookup(Table_Input_InorganicFertiliser_Brands[[#This Row],[Product (select)]], Table_Input_InorganicFertiliser_Brands[[#Headers],[Ingredient 4 percent]], FertiliserProducts[#Data], FertiliserProducts[Product], FertiliserProducts[#Headers])} -> 0.036 | R14: {=Fertiliser_InputFunctions.Fertiliser_FertiliserProductLookup(Table_Input_InorganicFertiliser_Brands[[#This Row],[Product (select)]], Table_Input_InorganicFertiliser_Brands[[#Headers],[Ingredient 5]], FertiliserProducts[#Data], FertiliserProducts[Product], FertiliserProducts[#Headers])} -> Calcium | S14: {=Fertiliser_InputFunctions.Fertiliser_FertiliserProductLookup(Table_Input_InorganicFertiliser_Brands[[#This Row],[Product (select)]], Table_Input_InorganicFertiliser_Brands[[#Headers],[Ingredient 5 percent]], FertiliserProducts[#Data], FertiliserProducts[Product], FertiliserProducts[#Headers])} -> 0.044 | T14: {=Fertiliser_InputFunctions.Fertiliser_FertiliserProductLookup(Table_Input_InorganicFertiliser_Brands[[#This Row],[Product (select)]], Table_Input_InorganicFertiliser_Brands[[#Headers],[Ingredient 6]], FertiliserProducts[#Data], FertiliserProducts[Product], FertiliserProducts[#Headers])} | U14: {=Fertiliser_InputFunctions.Fertiliser_FertiliserProductLookup(Table_Input_InorganicFertiliser_Brands[[#This Row],[Product (select)]], Table_Input_InorganicFertiliser_Brands[[#Headers],[Ingredient 6 percent]], FertiliserProducts[#Data], FertiliserProducts[Product], FertiliserProducts[#Headers])} | V14: =IFERROR((_xlfn.XLOOKUP(Table_Input_InorganicFertiliser_Brands[[#This Row],[Ingredient 1]], Table_Fertiliser_ChemicalCompounds[Fertiliser type f],Table_Fertiliser_ChemicalCompounds[FNinorganic f])*Table_Input_InorganicFertiliser_Brands[[#This Row],[Ingredient 1 percent]]), 0)+ IFERROR((_xlfn.XLOOKUP(Table_Input_InorganicFertiliser_Brands[[#This Row],[Ingredient 2]],Table_Fertiliser_ChemicalCompounds[Fertiliser type f],Table_Fertiliser_ChemicalCompounds[FNinorganic f])*Table_Input_InorganicFertiliser_Brands[[#This Row],[Ingredient 2 percent]]), 0)+ IFERROR((_xlfn.XLOOKUP(Table_Input_InorganicFertiliser_Brands[[#This Row],[Ingredient 3]],Table_Fertiliser_ChemicalCompounds[Fertiliser type f],Table_Fertiliser_ChemicalCompounds[FNinorganic f])*Table_Input_InorganicFertiliser_Brands[[#This Row],[Ingredient 3 percent]]), 0)+ IFERROR((_xlfn.XLOOKUP(Table_Input_InorganicFertiliser_Brands[[#This Row],[Ingredient 4]],Table_Fertiliser_ChemicalCompounds[Fertiliser type f],Table_Fertiliser_ChemicalCompounds[FNinorganic f])*Table_Input_InorganicFertiliser_Brands[[#This Row],[Ingredient 4 percent]]), 0)+ IFERROR((_xlfn.XLOOKUP(Table_Input_InorganicFertiliser_Brands[[#This Row],[Ingredient 5]],Table_Fertiliser_ChemicalCompounds[Fertiliser type f],Table_Fertiliser_ChemicalCompounds[FNinorganic f])*Table_Input_InorganicFertiliser_Brands[[#This Row],[Ingredient 5 percent]]), 0)+ IFERROR((_xlfn.XLOOKUP(Table_Input_InorganicFertiliser_Brands[[#This Row],[Ingredient 6]],Table_Fertiliser_ChemicalCompounds[Fertiliser type f],Table_Fertiliser_ChemicalCompounds[FNinorganic f])*Table_Input_InorganicFertiliser_Brands[[#This Row],[Ingredient 6 percent]]), 0) -> 0.179 | W14: {=IFERROR(Fertiliser_InputFunctions.Fertiliser_FertiliserProductLookup(Table_Input_InorganicFertiliser_Brands[[#This Row],[Product (select)]], "N declared", FertiliserProducts[#Data], FertiliserProducts[Product], FertiliserProducts[#Headers])*0.01, 0)} -> 0.179 | X14: =(Table_Input_InorganicFertiliser_Brands[[#This Row],[Amount applied per hectare]]*Table_Input_InorganicFertiliser_Brands[[#This Row],[Density]])*(IF(Table_Input_InorganicFertiliser_Brands[[#This Row],[% N (declared)]], Table_Input_InorganicFertiliser_Brands[[#This Row],[% N (declared)]], Table_Input_InorganicFertiliser_Brands[[#This Row],[% N (Ingredients)]])) -> 17.9 | Y14: =IFERROR(_xlfn.XLOOKUP(Table_Input_InorganicFertiliser_Brands[[#This Row],[Product (select)]],FertiliserProducts[Product],FertiliserProducts[Urea source]), "") | Z14: =IFERROR(_xlfn.XLOOKUP(Table_Input_InorganicFertiliser_Brands[[#This Row],[Product (select)]],FertiliserProducts[Product],FertiliserProducts[Ammonia source]), "")
A15: =HYPERLINK("#'Input - Pasture'!A1", "Pasture") -> Pasture | F15: =IFERROR(_xlfn.XLOOKUP(Table_Input_InorganicFertiliser_Brands[[#This Row],[Product (select)]],FertiliserProducts[Product],FertiliserProducts[Unit]), "kg") -> kg | G15: =X_Cell_Fertiliser_AreaUnderCropping -> Pasture | H15: =IFERROR(_xlfn.XLOOKUP(Table_Input_InorganicFertiliser_Brands[[#This Row],[Product (select)]],FertiliserProducts[Product],FertiliserProducts[Density]), 1) -> 1 | I15: =(Table_Input_InorganicFertiliser_Brands[[#This Row],[Amount applied per hectare]]*Table_Input_InorganicFertiliser_Brands[[#This Row],[Density]])*Table_Input_InorganicFertiliser_Brands[[#This Row],[Application area (ha)]] -> #VALUE! | J15: {=Fertiliser_InputFunctions.Fertiliser_FertiliserProductLookup(Table_Input_InorganicFertiliser_Brands[[#This Row],[Product (select)]], Table_Input_InorganicFertiliser_Brands[[#Headers],[Ingredient 1]], FertiliserProducts[#Data], FertiliserProducts[Product], FertiliserProducts[#Headers])} | K15: {=Fertiliser_InputFunctions.Fertiliser_FertiliserProductLookup(Table_Input_InorganicFertiliser_Brands[[#This Row],[Product (select)]], Table_Input_InorganicFertiliser_Brands[[#Headers],[Ingredient 1 percent]], FertiliserProducts[#Data], FertiliserProducts[Product], FertiliserProducts[#Headers])} | L15: {=Fertiliser_InputFunctions.Fertiliser_FertiliserProductLookup(Table_Input_InorganicFertiliser_Brands[[#This Row],[Product (select)]], Table_Input_InorganicFertiliser_Brands[[#Headers],[Ingredient 2]], FertiliserProducts[#Data], FertiliserProducts[Product], FertiliserProducts[#Headers])} | M15: {=Fertiliser_InputFunctions.Fertiliser_FertiliserProductLookup(Table_Input_InorganicFertiliser_Brands[[#This Row],[Product (select)]], Table_Input_InorganicFertiliser_Brands[[#Headers],[Ingredient 2 percent]], FertiliserProducts[#Data], FertiliserProducts[Product], FertiliserProducts[#Headers])} | N15: {=Fertiliser_InputFunctions.Fertiliser_FertiliserProductLookup(Table_Input_InorganicFertiliser_Brands[[#This Row],[Product (select)]], Table_Input_InorganicFertiliser_Brands[[#Headers],[Ingredient 3]], FertiliserProducts[#Data], FertiliserProducts[Product], FertiliserProducts[#Headers])} | O15: {=Fertiliser_InputFunctions.Fertiliser_FertiliserProductLookup(Table_Input_InorganicFertiliser_Brands[[#This Row],[Product (select)]], Table_Input_InorganicFertiliser_Brands[[#Headers],[Ingredient 3 percent]], FertiliserProducts[#Data], FertiliserProducts[Product], FertiliserProducts[#Headers])} | P15: {=Fertiliser_InputFunctions.Fertiliser_FertiliserProductLookup(Table_Input_InorganicFertiliser_Brands[[#This Row],[Product (select)]], Table_Input_InorganicFertiliser_Brands[[#Headers],[Ingredient 4]], FertiliserProducts[#Data], FertiliserProducts[Product], FertiliserProducts[#Headers])} | Q15: {=Fertiliser_InputFunctions.Fertiliser_FertiliserProductLookup(Table_Input_InorganicFertiliser_Brands[[#This Row],[Product (select)]], Table_Input_InorganicFertiliser_Brands[[#Headers],[Ingredient 4 percent]], FertiliserProducts[#Data], FertiliserProducts[Product], FertiliserProducts[#Headers])} | R15: {=Fertiliser_InputFunctions.Fertiliser_FertiliserProductLookup(Table_Input_InorganicFertiliser_Brands[[#This Row],[Product (select)]], Table_Input_InorganicFertiliser_Brands[[#Headers],[Ingredient 5]], FertiliserProducts[#Data], FertiliserProducts[Product], FertiliserProducts[#Headers])} | S15: {=Fertiliser_InputFunctions.Fertiliser_FertiliserProductLookup(Table_Input_InorganicFertiliser_Brands[[#This Row],[Product (select)]], Table_Input_InorganicFertiliser_Brands[[#Headers],[Ingredient 5 percent]], FertiliserProducts[#Data], FertiliserProducts[Product], FertiliserProducts[#Headers])} | T15: {=Fertiliser_InputFunctions.Fertiliser_FertiliserProductLookup(Table_Input_InorganicFertiliser_Brands[[#This Row],[Product (select)]], Table_Input_InorganicFertiliser_Brands[[#Headers],[Ingredient 6]], FertiliserProducts[#Data], FertiliserProducts[Product], FertiliserProducts[#Headers])} | U15: {=Fertiliser_InputFunctions.Fertiliser_FertiliserProductLookup(Table_Input_InorganicFertiliser_Brands[[#This Row],[Product (select)]], Table_Input_InorganicFertiliser_Brands[[#Headers],[Ingredient 6 percent]], FertiliserProducts[#Data], FertiliserProducts[Product], FertiliserProducts[#Headers])} | V15: =IFERROR((_xlfn.XLOOKUP(Table_Input_InorganicFertiliser_Brands[[#This Row],[Ingredient 1]], Table_Fertiliser_ChemicalCompounds[Fertiliser type f],Table_Fertiliser_ChemicalCompounds[FNinorganic f])*Table_Input_InorganicFertiliser_Brands[[#This Row],[Ingredient 1 percent]]), 0)+ IFERROR((_xlfn.XLOOKUP(Table_Input_InorganicFertiliser_Brands[[#This Row],[Ingredient 2]],Table_Fertiliser_ChemicalCompounds[Fertiliser type f],Table_Fertiliser_ChemicalCompounds[FNinorganic f])*Table_Input_InorganicFertiliser_Brands[[#This Row],[Ingredient 2 percent]]), 0)+ IFERROR((_xlfn.XLOOKUP(Table_Input_InorganicFertiliser_Brands[[#This Row],[Ingredient 3]],Table_Fertiliser_ChemicalCompounds[Fertiliser type f],Table_Fertiliser_ChemicalCompounds[FNinorganic f])*Table_Input_InorganicFertiliser_Brands[[#This Row],[Ingredient 3 percent]]), 0)+ IFERROR((_xlfn.XLOOKUP(Table_Input_InorganicFertiliser_Brands[[#This Row],[Ingredient 4]],Table_Fertiliser_ChemicalCompounds[Fertiliser type f],Table_Fertiliser_ChemicalCompounds[FNinorganic f])*Table_Input_InorganicFertiliser_Brands[[#This Row],[Ingredient 4 percent]]), 0)+ IFERROR((_xlfn.XLOOKUP(Table_Input_InorganicFertiliser_Brands[[#This Row],[Ingredient 5]],Table_Fertiliser_ChemicalCompounds[Fertiliser type f],Table_Fertiliser_ChemicalCompounds[FNinorganic f])*Table_Input_InorganicFertiliser_Brands[[#This Row],[Ingredient 5 percent]]), 0)+ IFERROR((_xlfn.XLOOKUP(Table_Input_InorganicFertiliser_Brands[[#This Row],[Ingredient 6]],Table_Fertiliser_ChemicalCompounds[Fertiliser type f],Table_Fertiliser_ChemicalCompounds[FNinorganic f])*Table_Input_InorganicFertiliser_Brands[[#This Row],[Ingredient 6 percent]]), 0) -> 0 | W15: {=IFERROR(Fertiliser_InputFunctions.Fertiliser_FertiliserProductLookup(Table_Input_InorganicFertiliser_Brands[[#This Row],[Product (select)]], "N declared", FertiliserProducts[#Data], FertiliserProducts[Product], FertiliserProducts[#Headers])*0.01, 0)} -> 0 | X15: =(Table_Input_InorganicFertiliser_Brands[[#This Row],[Amount applied per hectare]]*Table_Input_InorganicFertiliser_Brands[[#This Row],[Density]])*(IF(Table_Input_InorganicFertiliser_Brands[[#This Row],[% N (declared)]], Table_Input_InorganicFertiliser_Brands[[#This Row],[% N (declared)]], Table_Input_InorganicFertiliser_Brands[[#This Row],[% N (Ingredients)]])) -> 0 | Y15: =IFERROR(_xlfn.XLOOKUP(Table_Input_InorganicFertiliser_Brands[[#This Row],[Product (select)]],FertiliserProducts[Product],FertiliserProducts[Urea source]), "") | Z15: =IFERROR(_xlfn.XLOOKUP(Table_Input_InorganicFertiliser_Brands[[#This Row],[Product (select)]],FertiliserProducts[Product],FertiliserProducts[Ammonia source]), "")
A16: =HYPERLINK("#'Input - Fert Prod System'!A1", "Fert Prod System") -> Fert Prod System | F16: =IFERROR(_xlfn.XLOOKUP(Table_Input_InorganicFertiliser_Brands[[#This Row],[Product (select)]],FertiliserProducts[Product],FertiliserProducts[Unit]), "kg") -> kg | G16: =X_Cell_Fertiliser_AreaUnderCropping -> Pasture | H16: =IFERROR(_xlfn.XLOOKUP(Table_Input_InorganicFertiliser_Brands[[#This Row],[Product (select)]],FertiliserProducts[Product],FertiliserProducts[Density]), 1) -> 1 | I16: =(Table_Input_InorganicFertiliser_Brands[[#This Row],[Amount applied per hectare]]*Table_Input_InorganicFertiliser_Brands[[#This Row],[Density]])*Table_Input_InorganicFertiliser_Brands[[#This Row],[Application area (ha)]] -> #VALUE! | J16: {=Fertiliser_InputFunctions.Fertiliser_FertiliserProductLookup(Table_Input_InorganicFertiliser_Brands[[#This Row],[Product (select)]], Table_Input_InorganicFertiliser_Brands[[#Headers],[Ingredient 1]], FertiliserProducts[#Data], FertiliserProducts[Product], FertiliserProducts[#Headers])} | K16: {=Fertiliser_InputFunctions.Fertiliser_FertiliserProductLookup(Table_Input_InorganicFertiliser_Brands[[#This Row],[Product (select)]], Table_Input_InorganicFertiliser_Brands[[#Headers],[Ingredient 1 percent]], FertiliserProducts[#Data], FertiliserProducts[Product], FertiliserProducts[#Headers])} | L16: {=Fertiliser_InputFunctions.Fertiliser_FertiliserProductLookup(Table_Input_InorganicFertiliser_Brands[[#This Row],[Product (select)]], Table_Input_InorganicFertiliser_Brands[[#Headers],[Ingredient 2]], FertiliserProducts[#Data], FertiliserProducts[Product], FertiliserProducts[#Headers])} | M16: {=Fertiliser_InputFunctions.Fertiliser_FertiliserProductLookup(Table_Input_InorganicFertiliser_Brands[[#This Row],[Product (select)]], Table_Input_InorganicFertiliser_Brands[[#Headers],[Ingredient 2 percent]], FertiliserProducts[#Data], FertiliserProducts[Product], FertiliserProducts[#Headers])} | N16: {=Fertiliser_InputFunctions.Fertiliser_FertiliserProductLookup(Table_Input_InorganicFertiliser_Brands[[#This Row],[Product (select)]], Table_Input_InorganicFertiliser_Brands[[#Headers],[Ingredient 3]], FertiliserProducts[#Data], FertiliserProducts[Product], FertiliserProducts[#Headers])} | O16: {=Fertiliser_InputFunctions.Fertiliser_FertiliserProductLookup(Table_Input_InorganicFertiliser_Brands[[#This Row],[Product (select)]], Table_Input_InorganicFertiliser_Brands[[#Headers],[Ingredient 3 percent]], FertiliserProducts[#Data], FertiliserProducts[Product], FertiliserProducts[#Headers])} | P16: {=Fertiliser_InputFunctions.Fertiliser_FertiliserProductLookup(Table_Input_InorganicFertiliser_Brands[[#This Row],[Product (select)]], Table_Input_InorganicFertiliser_Brands[[#Headers],[Ingredient 4]], FertiliserProducts[#Data], FertiliserProducts[Product], FertiliserProducts[#Headers])} | Q16: {=Fertiliser_InputFunctions.Fertiliser_FertiliserProductLookup(Table_Input_InorganicFertiliser_Brands[[#This Row],[Product (select)]], Table_Input_InorganicFertiliser_Brands[[#Headers],[Ingredient 4 percent]], FertiliserProducts[#Data], FertiliserProducts[Product], FertiliserProducts[#Headers])} | R16: {=Fertiliser_InputFunctions.Fertiliser_FertiliserProductLookup(Table_Input_InorganicFertiliser_Brands[[#This Row],[Product (select)]], Table_Input_InorganicFertiliser_Brands[[#Headers],[Ingredient 5]], FertiliserProducts[#Data], FertiliserProducts[Product], FertiliserProducts[#Headers])} | S16: {=Fertiliser_InputFunctions.Fertiliser_FertiliserProductLookup(Table_Input_InorganicFertiliser_Brands[[#This Row],[Product (select)]], Table_Input_InorganicFertiliser_Brands[[#Headers],[Ingredient 5 percent]], FertiliserProducts[#Data], FertiliserProducts[Product], FertiliserProducts[#Headers])} | T16: {=Fertiliser_InputFunctions.Fertiliser_FertiliserProductLookup(Table_Input_InorganicFertiliser_Brands[[#This Row],[Product (select)]], Table_Input_InorganicFertiliser_Brands[[#Headers],[Ingredient 6]], FertiliserProducts[#Data], FertiliserProducts[Product], FertiliserProducts[#Headers])} | U16: {=Fertiliser_InputFunctions.Fertiliser_FertiliserProductLookup(Table_Input_InorganicFertiliser_Brands[[#This Row],[Product (select)]], Table_Input_InorganicFertiliser_Brands[[#Headers],[Ingredient 6 percent]], FertiliserProducts[#Data], FertiliserProducts[Product], FertiliserProducts[#Headers])} | V16: =IFERROR((_xlfn.XLOOKUP(Table_Input_InorganicFertiliser_Brands[[#This Row],[Ingredient 1]], Table_Fertiliser_ChemicalCompounds[Fertiliser type f],Table_Fertiliser_ChemicalCompounds[FNinorganic f])*Table_Input_InorganicFertiliser_Brands[[#This Row],[Ingredient 1 percent]]), 0)+ IFERROR((_xlfn.XLOOKUP(Table_Input_InorganicFertiliser_Brands[[#This Row],[Ingredient 2]],Table_Fertiliser_ChemicalCompounds[Fertiliser type f],Table_Fertiliser_ChemicalCompounds[FNinorganic f])*Table_Input_InorganicFertiliser_Brands[[#This Row],[Ingredient 2 percent]]), 0)+ IFERROR((_xlfn.XLOOKUP(Table_Input_InorganicFertiliser_Brands[[#This Row],[Ingredient 3]],Table_Fertiliser_ChemicalCompounds[Fertiliser type f],Table_Fertiliser_ChemicalCompounds[FNinorganic f])*Table_Input_InorganicFertiliser_Brands[[#This Row],[Ingredient 3 percent]]), 0)+ IFERROR((_xlfn.XLOOKUP(Table_Input_InorganicFertiliser_Brands[[#This Row],[Ingredient 4]],Table_Fertiliser_ChemicalCompounds[Fertiliser type f],Table_Fertiliser_ChemicalCompounds[FNinorganic f])*Table_Input_InorganicFertiliser_Brands[[#This Row],[Ingredient 4 percent]]), 0)+ IFERROR((_xlfn.XLOOKUP(Table_Input_InorganicFertiliser_Brands[[#This Row],[Ingredient 5]],Table_Fertiliser_ChemicalCompounds[Fertiliser type f],Table_Fertiliser_ChemicalCompounds[FNinorganic f])*Table_Input_InorganicFertiliser_Brands[[#This Row],[Ingredient 5 percent]]), 0)+ IFERROR((_xlfn.XLOOKUP(Table_Input_InorganicFertiliser_Brands[[#This Row],[Ingredient 6]],Table_Fertiliser_ChemicalCompounds[Fertiliser type f],Table_Fertiliser_ChemicalCompounds[FNinorganic f])*Table_Input_InorganicFertiliser_Brands[[#This Row],[Ingredient 6 percent]]), 0) -> 0 | W16: {=IFERROR(Fertiliser_InputFunctions.Fertiliser_FertiliserProductLookup(Table_Input_InorganicFertiliser_Brands[[#This Row],[Product (select)]], "N declared", FertiliserProducts[#Data], FertiliserProducts[Product], FertiliserProducts[#Headers])*0.01, 0)} -> 0 | X16: =(Table_Input_InorganicFertiliser_Brands[[#This Row],[Amount applied per hectare]]*Table_Input_InorganicFertiliser_Brands[[#This Row],[Density]])*(IF(Table_Input_InorganicFertiliser_Brands[[#This Row],[% N (declared)]], Table_Input_InorganicFertiliser_Brands[[#This Row],[% N (declared)]], Table_Input_InorganicFertiliser_Brands[[#This Row],[% N (Ingredients)]])) -> 0 | Y16: =IFERROR(_xlfn.XLOOKUP(Table_Input_InorganicFertiliser_Brands[[#This Row],[Product (select)]],FertiliserProducts[Product],FertiliserProducts[Urea source]), "") | Z16: =IFERROR(_xlfn.XLOOKUP(Table_Input_InorganicFertiliser_Brands[[#This Row],[Product (select)]],FertiliserProducts[Product],FertiliserProducts[Ammonia source]), "")
A17: =HYPERLINK("#'Input - Fertiliser'!A1", "Fertiliser") -> Fertiliser | F17: =IFERROR(_xlfn.XLOOKUP(Table_Input_InorganicFertiliser_Brands[[#This Row],[Product (select)]],FertiliserProducts[Product],FertiliserProducts[Unit]), "kg") -> kg | G17: =X_Cell_Fertiliser_AreaUnderCropping -> Pasture | H17: =IFERROR(_xlfn.XLOOKUP(Table_Input_InorganicFertiliser_Brands[[#This Row],[Product (select)]],FertiliserProducts[Product],FertiliserProducts[Density]), 1) -> 1 | I17: =(Table_Input_InorganicFertiliser_Brands[[#This Row],[Amount applied per hectare]]*Table_Input_InorganicFertiliser_Brands[[#This Row],[Density]])*Table_Input_InorganicFertiliser_Brands[[#This Row],[Application area (ha)]] -> #VALUE! | J17: {=Fertiliser_InputFunctions.Fertiliser_FertiliserProductLookup(Table_Input_InorganicFertiliser_Brands[[#This Row],[Product (select)]], Table_Input_InorganicFertiliser_Brands[[#Headers],[Ingredient 1]], FertiliserProducts[#Data], FertiliserProducts[Product], FertiliserProducts[#Headers])} | K17: {=Fertiliser_InputFunctions.Fertiliser_FertiliserProductLookup(Table_Input_InorganicFertiliser_Brands[[#This Row],[Product (select)]], Table_Input_InorganicFertiliser_Brands[[#Headers],[Ingredient 1 percent]], FertiliserProducts[#Data], FertiliserProducts[Product], FertiliserProducts[#Headers])} | L17: {=Fertiliser_InputFunctions.Fertiliser_FertiliserProductLookup(Table_Input_InorganicFertiliser_Brands[[#This Row],[Product (select)]], Table_Input_InorganicFertiliser_Brands[[#Headers],[Ingredient 2]], FertiliserProducts[#Data], FertiliserProducts[Product], FertiliserProducts[#Headers])} | M17: {=Fertiliser_InputFunctions.Fertiliser_FertiliserProductLookup(Table_Input_InorganicFertiliser_Brands[[#This Row],[Product (select)]], Table_Input_InorganicFertiliser_Brands[[#Headers],[Ingredient 2 percent]], FertiliserProducts[#Data], FertiliserProducts[Product], FertiliserProducts[#Headers])} | N17: {=Fertiliser_InputFunctions.Fertiliser_FertiliserProductLookup(Table_Input_InorganicFertiliser_Brands[[#This Row],[Product (select)]], Table_Input_InorganicFertiliser_Brands[[#Headers],[Ingredient 3]], FertiliserProducts[#Data], FertiliserProducts[Product], FertiliserProducts[#Headers])} | O17: {=Fertiliser_InputFunctions.Fertiliser_FertiliserProductLookup(Table_Input_InorganicFertiliser_Brands[[#This Row],[Product (select)]], Table_Input_InorganicFertiliser_Brands[[#Headers],[Ingredient 3 percent]], FertiliserProducts[#Data], FertiliserProducts[Product], FertiliserProducts[#Headers])} | P17: {=Fertiliser_InputFunctions.Fertiliser_FertiliserProductLookup(Table_Input_InorganicFertiliser_Brands[[#This Row],[Product (select)]], Table_Input_InorganicFertiliser_Brands[[#Headers],[Ingredient 4]], FertiliserProducts[#Data], FertiliserProducts[Product], FertiliserProducts[#Headers])} | Q17: {=Fertiliser_InputFunctions.Fertiliser_FertiliserProductLookup(Table_Input_InorganicFertiliser_Brands[[#This Row],[Product (select)]], Table_Input_InorganicFertiliser_Brands[[#Headers],[Ingredient 4 percent]], FertiliserProducts[#Data], FertiliserProducts[Product], FertiliserProducts[#Headers])} | R17: {=Fertiliser_InputFunctions.Fertiliser_FertiliserProductLookup(Table_Input_InorganicFertiliser_Brands[[#This Row],[Product (select)]], Table_Input_InorganicFertiliser_Brands[[#Headers],[Ingredient 5]], FertiliserProducts[#Data], FertiliserProducts[Product], FertiliserProducts[#Headers])} | S17: {=Fertiliser_InputFunctions.Fertiliser_FertiliserProductLookup(Table_Input_InorganicFertiliser_Brands[[#This Row],[Product (select)]], Table_Input_InorganicFertiliser_Brands[[#Headers],[Ingredient 5 percent]], FertiliserProducts[#Data], FertiliserProducts[Product], FertiliserProducts[#Headers])} | T17: {=Fertiliser_InputFunctions.Fertiliser_FertiliserProductLookup(Table_Input_InorganicFertiliser_Brands[[#This Row],[Product (select)]], Table_Input_InorganicFertiliser_Brands[[#Headers],[Ingredient 6]], FertiliserProducts[#Data], FertiliserProducts[Product], FertiliserProducts[#Headers])} | U17: {=Fertiliser_InputFunctions.Fertiliser_FertiliserProductLookup(Table_Input_InorganicFertiliser_Brands[[#This Row],[Product (select)]], Table_Input_InorganicFertiliser_Brands[[#Headers],[Ingredient 6 percent]], FertiliserProducts[#Data], FertiliserProducts[Product], FertiliserProducts[#Headers])} | V17: =IFERROR((_xlfn.XLOOKUP(Table_Input_InorganicFertiliser_Brands[[#This Row],[Ingredient 1]], Table_Fertiliser_ChemicalCompounds[Fertiliser type f],Table_Fertiliser_ChemicalCompounds[FNinorganic f])*Table_Input_InorganicFertiliser_Brands[[#This Row],[Ingredient 1 percent]]), 0)+ IFERROR((_xlfn.XLOOKUP(Table_Input_InorganicFertiliser_Brands[[#This Row],[Ingredient 2]],Table_Fertiliser_ChemicalCompounds[Fertiliser type f],Table_Fertiliser_ChemicalCompounds[FNinorganic f])*Table_Input_InorganicFertiliser_Brands[[#This Row],[Ingredient 2 percent]]), 0)+ IFERROR((_xlfn.XLOOKUP(Table_Input_InorganicFertiliser_Brands[[#This Row],[Ingredient 3]],Table_Fertiliser_ChemicalCompounds[Fertiliser type f],Table_Fertiliser_ChemicalCompounds[FNinorganic f])*Table_Input_InorganicFertiliser_Brands[[#This Row],[Ingredient 3 percent]]), 0)+ IFERROR((_xlfn.XLOOKUP(Table_Input_InorganicFertiliser_Brands[[#This Row],[Ingredient 4]],Table_Fertiliser_ChemicalCompounds[Fertiliser type f],Table_Fertiliser_ChemicalCompounds[FNinorganic f])*Table_Input_InorganicFertiliser_Brands[[#This Row],[Ingredient 4 percent]]), 0)+ IFERROR((_xlfn.XLOOKUP(Table_Input_InorganicFertiliser_Brands[[#This Row],[Ingredient 5]],Table_Fertiliser_ChemicalCompounds[Fertiliser type f],Table_Fertiliser_ChemicalCompounds[FNinorganic f])*Table_Input_InorganicFertiliser_Brands[[#This Row],[Ingredient 5 percent]]), 0)+ IFERROR((_xlfn.XLOOKUP(Table_Input_InorganicFertiliser_Brands[[#This Row],[Ingredient 6]],Table_Fertiliser_ChemicalCompounds[Fertiliser type f],Table_Fertiliser_ChemicalCompounds[FNinorganic f])*Table_Input_InorganicFertiliser_Brands[[#This Row],[Ingredient 6 percent]]), 0) -> 0 | W17: {=IFERROR(Fertiliser_InputFunctions.Fertiliser_FertiliserProductLookup(Table_Input_InorganicFertiliser_Brands[[#This Row],[Product (select)]], "N declared", FertiliserProducts[#Data], FertiliserProducts[Product], FertiliserProducts[#Headers])*0.01, 0)} -> 0 | X17: =(Table_Input_InorganicFertiliser_Brands[[#This Row],[Amount applied per hectare]]*Table_Input_InorganicFertiliser_Brands[[#This Row],[Density]])*(IF(Table_Input_InorganicFertiliser_Brands[[#This Row],[% N (declared)]], Table_Input_InorganicFertiliser_Brands[[#This Row],[% N (declared)]], Table_Input_InorganicFertiliser_Brands[[#This Row],[% N (Ingredients)]])) -> 0 | Y17: =IFERROR(_xlfn.XLOOKUP(Table_Input_InorganicFertiliser_Brands[[#This Row],[Product (select)]],FertiliserProducts[Product],FertiliserProducts[Urea source]), "") | Z17: =IFERROR(_xlfn.XLOOKUP(Table_Input_InorganicFertiliser_Brands[[#This Row],[Product (select)]],FertiliserProducts[Product],FertiliserProducts[Ammonia source]), "")
A18: =HYPERLINK("#'Input - Fuel'!A1", "Fuel") -> Fuel | F18: =IFERROR(_xlfn.XLOOKUP(Table_Input_InorganicFertiliser_Brands[[#This Row],[Product (select)]],FertiliserProducts[Product],FertiliserProducts[Unit]), "kg") -> kg | G18: =X_Cell_Fertiliser_AreaUnderCropping -> Pasture | H18: =IFERROR(_xlfn.XLOOKUP(Table_Input_InorganicFertiliser_Brands[[#This Row],[Product (select)]],FertiliserProducts[Product],FertiliserProducts[Density]), 1) -> 1 | I18: =(Table_Input_InorganicFertiliser_Brands[[#This Row],[Amount applied per hectare]]*Table_Input_InorganicFertiliser_Brands[[#This Row],[Density]])*Table_Input_InorganicFertiliser_Brands[[#This Row],[Application area (ha)]] -> #VALUE! | J18: {=Fertiliser_InputFunctions.Fertiliser_FertiliserProductLookup(Table_Input_InorganicFertiliser_Brands[[#This Row],[Product (select)]], Table_Input_InorganicFertiliser_Brands[[#Headers],[Ingredient 1]], FertiliserProducts[#Data], FertiliserProducts[Product], FertiliserProducts[#Headers])} | K18: {=Fertiliser_InputFunctions.Fertiliser_FertiliserProductLookup(Table_Input_InorganicFertiliser_Brands[[#This Row],[Product (select)]], Table_Input_InorganicFertiliser_Brands[[#Headers],[Ingredient 1 percent]], FertiliserProducts[#Data], FertiliserProducts[Product], FertiliserProducts[#Headers])} | L18: {=Fertiliser_InputFunctions.Fertiliser_FertiliserProductLookup(Table_Input_InorganicFertiliser_Brands[[#This Row],[Product (select)]], Table_Input_InorganicFertiliser_Brands[[#Headers],[Ingredient 2]], FertiliserProducts[#Data], FertiliserProducts[Product], FertiliserProducts[#Headers])} | M18: {=Fertiliser_InputFunctions.Fertiliser_FertiliserProductLookup(Table_Input_InorganicFertiliser_Brands[[#This Row],[Product (select)]], Table_Input_InorganicFertiliser_Brands[[#Headers],[Ingredient 2 percent]], FertiliserProducts[#Data], FertiliserProducts[Product], FertiliserProducts[#Headers])} | N18: {=Fertiliser_InputFunctions.Fertiliser_FertiliserProductLookup(Table_Input_InorganicFertiliser_Brands[[#This Row],[Product (select)]], Table_Input_InorganicFertiliser_Brands[[#Headers],[Ingredient 3]], FertiliserProducts[#Data], FertiliserProducts[Product], FertiliserProducts[#Headers])} | O18: {=Fertiliser_InputFunctions.Fertiliser_FertiliserProductLookup(Table_Input_InorganicFertiliser_Brands[[#This Row],[Product (select)]], Table_Input_InorganicFertiliser_Brands[[#Headers],[Ingredient 3 percent]], FertiliserProducts[#Data], FertiliserProducts[Product], FertiliserProducts[#Headers])} | P18: {=Fertiliser_InputFunctions.Fertiliser_FertiliserProductLookup(Table_Input_InorganicFertiliser_Brands[[#This Row],[Product (select)]], Table_Input_InorganicFertiliser_Brands[[#Headers],[Ingredient 4]], FertiliserProducts[#Data], FertiliserProducts[Product], FertiliserProducts[#Headers])} | Q18: {=Fertiliser_InputFunctions.Fertiliser_FertiliserProductLookup(Table_Input_InorganicFertiliser_Brands[[#This Row],[Product (select)]], Table_Input_InorganicFertiliser_Brands[[#Headers],[Ingredient 4 percent]], FertiliserProducts[#Data], FertiliserProducts[Product], FertiliserProducts[#Headers])} | R18: {=Fertiliser_InputFunctions.Fertiliser_FertiliserProductLookup(Table_Input_InorganicFertiliser_Brands[[#This Row],[Product (select)]], Table_Input_InorganicFertiliser_Brands[[#Headers],[Ingredient 5]], FertiliserProducts[#Data], FertiliserProducts[Product], FertiliserProducts[#Headers])} | S18: {=Fertiliser_InputFunctions.Fertiliser_FertiliserProductLookup(Table_Input_InorganicFertiliser_Brands[[#This Row],[Product (select)]], Table_Input_InorganicFertiliser_Brands[[#Headers],[Ingredient 5 percent]], FertiliserProducts[#Data], FertiliserProducts[Product], FertiliserProducts[#Headers])} | T18: {=Fertiliser_InputFunctions.Fertiliser_FertiliserProductLookup(Table_Input_InorganicFertiliser_Brands[[#This Row],[Product (select)]], Table_Input_InorganicFertiliser_Brands[[#Headers],[Ingredient 6]], FertiliserProducts[#Data], FertiliserProducts[Product], FertiliserProducts[#Headers])} | U18: {=Fertiliser_InputFunctions.Fertiliser_FertiliserProductLookup(Table_Input_InorganicFertiliser_Brands[[#This Row],[Product (select)]], Table_Input_InorganicFertiliser_Brands[[#Headers],[Ingredient 6 percent]], FertiliserProducts[#Data], FertiliserProducts[Product], FertiliserProducts[#Headers])} | V18: =IFERROR((_xlfn.XLOOKUP(Table_Input_InorganicFertiliser_Brands[[#This Row],[Ingredient 1]], Table_Fertiliser_ChemicalCompounds[Fertiliser type f],Table_Fertiliser_ChemicalCompounds[FNinorganic f])*Table_Input_InorganicFertiliser_Brands[[#This Row],[Ingredient 1 percent]]), 0)+ IFERROR((_xlfn.XLOOKUP(Table_Input_InorganicFertiliser_Brands[[#This Row],[Ingredient 2]],Table_Fertiliser_ChemicalCompounds[Fertiliser type f],Table_Fertiliser_ChemicalCompounds[FNinorganic f])*Table_Input_InorganicFertiliser_Brands[[#This Row],[Ingredient 2 percent]]), 0)+ IFERROR((_xlfn.XLOOKUP(Table_Input_InorganicFertiliser_Brands[[#This Row],[Ingredient 3]],Table_Fertiliser_ChemicalCompounds[Fertiliser type f],Table_Fertiliser_ChemicalCompounds[FNinorganic f])*Table_Input_InorganicFertiliser_Brands[[#This Row],[Ingredient 3 percent]]), 0)+ IFERROR((_xlfn.XLOOKUP(Table_Input_InorganicFertiliser_Brands[[#This Row],[Ingredient 4]],Table_Fertiliser_ChemicalCompounds[Fertiliser type f],Table_Fertiliser_ChemicalCompounds[FNinorganic f])*Table_Input_InorganicFertiliser_Brands[[#This Row],[Ingredient 4 percent]]), 0)+ IFERROR((_xlfn.XLOOKUP(Table_Input_InorganicFertiliser_Brands[[#This Row],[Ingredient 5]],Table_Fertiliser_ChemicalCompounds[Fertiliser type f],Table_Fertiliser_ChemicalCompounds[FNinorganic f])*Table_Input_InorganicFertiliser_Brands[[#This Row],[Ingredient 5 percent]]), 0)+ IFERROR((_xlfn.XLOOKUP(Table_Input_InorganicFertiliser_Brands[[#This Row],[Ingredient 6]],Table_Fertiliser_ChemicalCompounds[Fertiliser type f],Table_Fertiliser_ChemicalCompounds[FNinorganic f])*Table_Input_InorganicFertiliser_Brands[[#This Row],[Ingredient 6 percent]]), 0) -> 0 | W18: {=IFERROR(Fertiliser_InputFunctions.Fertiliser_FertiliserProductLookup(Table_Input_InorganicFertiliser_Brands[[#This Row],[Product (select)]], "N declared", FertiliserProducts[#Data], FertiliserProducts[Product], FertiliserProducts[#Headers])*0.01, 0)} -> 0 | X18: =(Table_Input_InorganicFertiliser_Brands[[#This Row],[Amount applied per hectare]]*Table_Input_InorganicFertiliser_Brands[[#This Row],[Density]])*(IF(Table_Input_InorganicFertiliser_Brands[[#This Row],[% N (declared)]], Table_Input_InorganicFertiliser_Brands[[#This Row],[% N (declared)]], Table_Input_InorganicFertiliser_Brands[[#This Row],[% N (Ingredients)]])) -> 0 | Y18: =IFERROR(_xlfn.XLOOKUP(Table_Input_InorganicFertiliser_Brands[[#This Row],[Product (select)]],FertiliserProducts[Product],FertiliserProducts[Urea source]), "") | Z18: =IFERROR(_xlfn.XLOOKUP(Table_Input_InorganicFertiliser_Brands[[#This Row],[Product (select)]],FertiliserProducts[Product],FertiliserProducts[Ammonia source]), "")
A19: =HYPERLINK("#'Input - Electricity'!A1", "Electricity") -> Electricity | F19: =IFERROR(_xlfn.XLOOKUP(Table_Input_InorganicFertiliser_Brands[[#This Row],[Product (select)]],FertiliserProducts[Product],FertiliserProducts[Unit]), "kg") -> kg | G19: =X_Cell_Fertiliser_AreaUnderCropping -> Pasture | H19: =IFERROR(_xlfn.XLOOKUP(Table_Input_InorganicFertiliser_Brands[[#This Row],[Product (select)]],FertiliserProducts[Product],FertiliserProducts[Density]), 1) -> 1 | I19: =(Table_Input_InorganicFertiliser_Brands[[#This Row],[Amount applied per hectare]]*Table_Input_InorganicFertiliser_Brands[[#This Row],[Density]])*Table_Input_InorganicFertiliser_Brands[[#This Row],[Application area (ha)]] -> #VALUE! | J19: {=Fertiliser_InputFunctions.Fertiliser_FertiliserProductLookup(Table_Input_InorganicFertiliser_Brands[[#This Row],[Product (select)]], Table_Input_InorganicFertiliser_Brands[[#Headers],[Ingredient 1]], FertiliserProducts[#Data], FertiliserProducts[Product], FertiliserProducts[#Headers])} | K19: {=Fertiliser_InputFunctions.Fertiliser_FertiliserProductLookup(Table_Input_InorganicFertiliser_Brands[[#This Row],[Product (select)]], Table_Input_InorganicFertiliser_Brands[[#Headers],[Ingredient 1 percent]], FertiliserProducts[#Data], FertiliserProducts[Product], FertiliserProducts[#Headers])} | L19: {=Fertiliser_InputFunctions.Fertiliser_FertiliserProductLookup(Table_Input_InorganicFertiliser_Brands[[#This Row],[Product (select)]], Table_Input_InorganicFertiliser_Brands[[#Headers],[Ingredient 2]], FertiliserProducts[#Data], FertiliserProducts[Product], FertiliserProducts[#Headers])} | M19: {=Fertiliser_InputFunctions.Fertiliser_FertiliserProductLookup(Table_Input_InorganicFertiliser_Brands[[#This Row],[Product (select)]], Table_Input_InorganicFertiliser_Brands[[#Headers],[Ingredient 2 percent]], FertiliserProducts[#Data], FertiliserProducts[Product], FertiliserProducts[#Headers])} | N19: {=Fertiliser_InputFunctions.Fertiliser_FertiliserProductLookup(Table_Input_InorganicFertiliser_Brands[[#This Row],[Product (select)]], Table_Input_InorganicFertiliser_Brands[[#Headers],[Ingredient 3]], FertiliserProducts[#Data], FertiliserProducts[Product], FertiliserProducts[#Headers])} | O19: {=Fertiliser_InputFunctions.Fertiliser_FertiliserProductLookup(Table_Input_InorganicFertiliser_Brands[[#This Row],[Product (select)]], Table_Input_InorganicFertiliser_Brands[[#Headers],[Ingredient 3 percent]], FertiliserProducts[#Data], FertiliserProducts[Product], FertiliserProducts[#Headers])} | P19: {=Fertiliser_InputFunctions.Fertiliser_FertiliserProductLookup(Table_Input_InorganicFertiliser_Brands[[#This Row],[Product (select)]], Table_Input_InorganicFertiliser_Brands[[#Headers],[Ingredient 4]], FertiliserProducts[#Data], FertiliserProducts[Product], FertiliserProducts[#Headers])} | Q19: {=Fertiliser_InputFunctions.Fertiliser_FertiliserProductLookup(Table_Input_InorganicFertiliser_Brands[[#This Row],[Product (select)]], Table_Input_InorganicFertiliser_Brands[[#Headers],[Ingredient 4 percent]], FertiliserProducts[#Data], FertiliserProducts[Product], FertiliserProducts[#Headers])} | R19: {=Fertiliser_InputFunctions.Fertiliser_FertiliserProductLookup(Table_Input_InorganicFertiliser_Brands[[#This Row],[Product (select)]], Table_Input_InorganicFertiliser_Brands[[#Headers],[Ingredient 5]], FertiliserProducts[#Data], FertiliserProducts[Product], FertiliserProducts[#Headers])} | S19: {=Fertiliser_InputFunctions.Fertiliser_FertiliserProductLookup(Table_Input_InorganicFertiliser_Brands[[#This Row],[Product (select)]], Table_Input_InorganicFertiliser_Brands[[#Headers],[Ingredient 5 percent]], FertiliserProducts[#Data], FertiliserProducts[Product], FertiliserProducts[#Headers])} | T19: {=Fertiliser_InputFunctions.Fertiliser_FertiliserProductLookup(Table_Input_InorganicFertiliser_Brands[[#This Row],[Product (select)]], Table_Input_InorganicFertiliser_Brands[[#Headers],[Ingredient 6]], FertiliserProducts[#Data], FertiliserProducts[Product], FertiliserProducts[#Headers])} | U19: {=Fertiliser_InputFunctions.Fertiliser_FertiliserProductLookup(Table_Input_InorganicFertiliser_Brands[[#This Row],[Product (select)]], Table_Input_InorganicFertiliser_Brands[[#Headers],[Ingredient 6 percent]], FertiliserProducts[#Data], FertiliserProducts[Product], FertiliserProducts[#Headers])} | V19: =IFERROR((_xlfn.XLOOKUP(Table_Input_InorganicFertiliser_Brands[[#This Row],[Ingredient 1]], Table_Fertiliser_ChemicalCompounds[Fertiliser type f],Table_Fertiliser_ChemicalCompounds[FNinorganic f])*Table_Input_InorganicFertiliser_Brands[[#This Row],[Ingredient 1 percent]]), 0)+ IFERROR((_xlfn.XLOOKUP(Table_Input_InorganicFertiliser_Brands[[#This Row],[Ingredient 2]],Table_Fertiliser_ChemicalCompounds[Fertiliser type f],Table_Fertiliser_ChemicalCompounds[FNinorganic f])*Table_Input_InorganicFertiliser_Brands[[#This Row],[Ingredient 2 percent]]), 0)+ IFERROR((_xlfn.XLOOKUP(Table_Input_InorganicFertiliser_Brands[[#This Row],[Ingredient 3]],Table_Fertiliser_ChemicalCompounds[Fertiliser type f],Table_Fertiliser_ChemicalCompounds[FNinorganic f])*Table_Input_InorganicFertiliser_Brands[[#This Row],[Ingredient 3 percent]]), 0)+ IFERROR((_xlfn.XLOOKUP(Table_Input_InorganicFertiliser_Brands[[#This Row],[Ingredient 4]],Table_Fertiliser_ChemicalCompounds[Fertiliser type f],Table_Fertiliser_ChemicalCompounds[FNinorganic f])*Table_Input_InorganicFertiliser_Brands[[#This Row],[Ingredient 4 percent]]), 0)+ IFERROR((_xlfn.XLOOKUP(Table_Input_InorganicFertiliser_Brands[[#This Row],[Ingredient 5]],Table_Fertiliser_ChemicalCompounds[Fertiliser type f],Table_Fertiliser_ChemicalCompounds[FNinorganic f])*Table_Input_InorganicFertiliser_Brands[[#This Row],[Ingredient 5 percent]]), 0)+ IFERROR((_xlfn.XLOOKUP(Table_Input_InorganicFertiliser_Brands[[#This Row],[Ingredient 6]],Table_Fertiliser_ChemicalCompounds[Fertiliser type f],Table_Fertiliser_ChemicalCompounds[FNinorganic f])*Table_Input_InorganicFertiliser_Brands[[#This Row],[Ingredient 6 percent]]), 0) -> 0 | W19: {=IFERROR(Fertiliser_InputFunctions.Fertiliser_FertiliserProductLookup(Table_Input_InorganicFertiliser_Brands[[#This Row],[Product (select)]], "N declared", FertiliserProducts[#Data], FertiliserProducts[Product], FertiliserProducts[#Headers])*0.01, 0)} -> 0 | X19: =(Table_Input_InorganicFertiliser_Brands[[#This Row],[Amount applied per hectare]]*Table_Input_InorganicFertiliser_Brands[[#This Row],[Density]])*(IF(Table_Input_InorganicFertiliser_Brands[[#This Row],[% N (declared)]], Table_Input_InorganicFertiliser_Brands[[#This Row],[% N (declared)]], Table_Input_InorganicFertiliser_Brands[[#This Row],[% N (Ingredients)]])) -> 0 | Y19: =IFERROR(_xlfn.XLOOKUP(Table_Input_InorganicFertiliser_Brands[[#This Row],[Product (select)]],FertiliserProducts[Product],FertiliserProducts[Urea source]), "") | Z19: =IFERROR(_xlfn.XLOOKUP(Table_Input_InorganicFertiliser_Brands[[#This Row],[Product (select)]],FertiliserProducts[Product],FertiliserProducts[Ammonia source]), "")
A20: =HYPERLINK("#'Input - Common farm inputs'!A1", "Common farm inputs") -> Common farm inputs | F20: =IFERROR(_xlfn.XLOOKUP(Table_Input_InorganicFertiliser_Brands[[#This Row],[Product (select)]],FertiliserProducts[Product],FertiliserProducts[Unit]), "kg") -> kg | G20: =X_Cell_Fertiliser_AreaUnderCropping -> Pasture | H20: =IFERROR(_xlfn.XLOOKUP(Table_Input_InorganicFertiliser_Brands[[#This Row],[Product (select)]],FertiliserProducts[Product],FertiliserProducts[Density]), 1) -> 1 | I20: =(Table_Input_InorganicFertiliser_Brands[[#This Row],[Amount applied per hectare]]*Table_Input_InorganicFertiliser_Brands[[#This Row],[Density]])*Table_Input_InorganicFertiliser_Brands[[#This Row],[Application area (ha)]] -> #VALUE! | J20: {=Fertiliser_InputFunctions.Fertiliser_FertiliserProductLookup(Table_Input_InorganicFertiliser_Brands[[#This Row],[Product (select)]], Table_Input_InorganicFertiliser_Brands[[#Headers],[Ingredient 1]], FertiliserProducts[#Data], FertiliserProducts[Product], FertiliserProducts[#Headers])} | K20: {=Fertiliser_InputFunctions.Fertiliser_FertiliserProductLookup(Table_Input_InorganicFertiliser_Brands[[#This Row],[Product (select)]], Table_Input_InorganicFertiliser_Brands[[#Headers],[Ingredient 1 percent]], FertiliserProducts[#Data], FertiliserProducts[Product], FertiliserProducts[#Headers])} | L20: {=Fertiliser_InputFunctions.Fertiliser_FertiliserProductLookup(Table_Input_InorganicFertiliser_Brands[[#This Row],[Product (select)]], Table_Input_InorganicFertiliser_Brands[[#Headers],[Ingredient 2]], FertiliserProducts[#Data], FertiliserProducts[Product], FertiliserProducts[#Headers])} | M20: {=Fertiliser_InputFunctions.Fertiliser_FertiliserProductLookup(Table_Input_InorganicFertiliser_Brands[[#This Row],[Product (select)]], Table_Input_InorganicFertiliser_Brands[[#Headers],[Ingredient 2 percent]], FertiliserProducts[#Data], FertiliserProducts[Product], FertiliserProducts[#Headers])} | N20: {=Fertiliser_InputFunctions.Fertiliser_FertiliserProductLookup(Table_Input_InorganicFertiliser_Brands[[#This Row],[Product (select)]], Table_Input_InorganicFertiliser_Brands[[#Headers],[Ingredient 3]], FertiliserProducts[#Data], FertiliserProducts[Product], FertiliserProducts[#Headers])} | O20: {=Fertiliser_InputFunctions.Fertiliser_FertiliserProductLookup(Table_Input_InorganicFertiliser_Brands[[#This Row],[Product (select)]], Table_Input_InorganicFertiliser_Brands[[#Headers],[Ingredient 3 percent]], FertiliserProducts[#Data], FertiliserProducts[Product], FertiliserProducts[#Headers])} | P20: {=Fertiliser_InputFunctions.Fertiliser_FertiliserProductLookup(Table_Input_InorganicFertiliser_Brands[[#This Row],[Product (select)]], Table_Input_InorganicFertiliser_Brands[[#Headers],[Ingredient 4]], FertiliserProducts[#Data], FertiliserProducts[Product], FertiliserProducts[#Headers])} | Q20: {=Fertiliser_InputFunctions.Fertiliser_FertiliserProductLookup(Table_Input_InorganicFertiliser_Brands[[#This Row],[Product (select)]], Table_Input_InorganicFertiliser_Brands[[#Headers],[Ingredient 4 percent]], FertiliserProducts[#Data], FertiliserProducts[Product], FertiliserProducts[#Headers])} | R20: {=Fertiliser_InputFunctions.Fertiliser_FertiliserProductLookup(Table_Input_InorganicFertiliser_Brands[[#This Row],[Product (select)]], Table_Input_InorganicFertiliser_Brands[[#Headers],[Ingredient 5]], FertiliserProducts[#Data], FertiliserProducts[Product], FertiliserProducts[#Headers])} | S20: {=Fertiliser_InputFunctions.Fertiliser_FertiliserProductLookup(Table_Input_InorganicFertiliser_Brands[[#This Row],[Product (select)]], Table_Input_InorganicFertiliser_Brands[[#Headers],[Ingredient 5 percent]], FertiliserProducts[#Data], FertiliserProducts[Product], FertiliserProducts[#Headers])} | T20: {=Fertiliser_InputFunctions.Fertiliser_FertiliserProductLookup(Table_Input_InorganicFertiliser_Brands[[#This Row],[Product (select)]], Table_Input_InorganicFertiliser_Brands[[#Headers],[Ingredient 6]], FertiliserProducts[#Data], FertiliserProducts[Product], FertiliserProducts[#Headers])} | U20: {=Fertiliser_InputFunctions.Fertiliser_FertiliserProductLookup(Table_Input_InorganicFertiliser_Brands[[#This Row],[Product (select)]], Table_Input_InorganicFertiliser_Brands[[#Headers],[Ingredient 6 percent]], FertiliserProducts[#Data], FertiliserProducts[Product], FertiliserProducts[#Headers])} | V20: =IFERROR((_xlfn.XLOOKUP(Table_Input_InorganicFertiliser_Brands[[#This Row],[Ingredient 1]], Table_Fertiliser_ChemicalCompounds[Fertiliser type f],Table_Fertiliser_ChemicalCompounds[FNinorganic f])*Table_Input_InorganicFertiliser_Brands[[#This Row],[Ingredient 1 percent]]), 0)+ IFERROR((_xlfn.XLOOKUP(Table_Input_InorganicFertiliser_Brands[[#This Row],[Ingredient 2]],Table_Fertiliser_ChemicalCompounds[Fertiliser type f],Table_Fertiliser_ChemicalCompounds[FNinorganic f])*Table_Input_InorganicFertiliser_Brands[[#This Row],[Ingredient 2 percent]]), 0)+ IFERROR((_xlfn.XLOOKUP(Table_Input_InorganicFertiliser_Brands[[#This Row],[Ingredient 3]],Table_Fertiliser_ChemicalCompounds[Fertiliser type f],Table_Fertiliser_ChemicalCompounds[FNinorganic f])*Table_Input_InorganicFertiliser_Brands[[#This Row],[Ingredient 3 percent]]), 0)+ IFERROR((_xlfn.XLOOKUP(Table_Input_InorganicFertiliser_Brands[[#This Row],[Ingredient 4]],Table_Fertiliser_ChemicalCompounds[Fertiliser type f],Table_Fertiliser_ChemicalCompounds[FNinorganic f])*Table_Input_InorganicFertiliser_Brands[[#This Row],[Ingredient 4 percent]]), 0)+ IFERROR((_xlfn.XLOOKUP(Table_Input_InorganicFertiliser_Brands[[#This Row],[Ingredient 5]],Table_Fertiliser_ChemicalCompounds[Fertiliser type f],Table_Fertiliser_ChemicalCompounds[FNinorganic f])*Table_Input_InorganicFertiliser_Brands[[#This Row],[Ingredient 5 percent]]), 0)+ IFERROR((_xlfn.XLOOKUP(Table_Input_InorganicFertiliser_Brands[[#This Row],[Ingredient 6]],Table_Fertiliser_ChemicalCompounds[Fertiliser type f],Table_Fertiliser_ChemicalCompounds[FNinorganic f])*Table_Input_InorganicFertiliser_Brands[[#This Row],[Ingredient 6 percent]]), 0) -> 0 | W20: {=IFERROR(Fertiliser_InputFunctions.Fertiliser_FertiliserProductLookup(Table_Input_InorganicFertiliser_Brands[[#This Row],[Product (select)]], "N declared", FertiliserProducts[#Data], FertiliserProducts[Product], FertiliserProducts[#Headers])*0.01, 0)} -> 0 | X20: =(Table_Input_InorganicFertiliser_Brands[[#This Row],[Amount applied per hectare]]*Table_Input_InorganicFertiliser_Brands[[#This Row],[Density]])*(IF(Table_Input_InorganicFertiliser_Brands[[#This Row],[% N (declared)]], Table_Input_InorganicFertiliser_Brands[[#This Row],[% N (declared)]], Table_Input_InorganicFertiliser_Brands[[#This Row],[% N (Ingredients)]])) -> 0 | Y20: =IFERROR(_xlfn.XLOOKUP(Table_Input_InorganicFertiliser_Brands[[#This Row],[Product (select)]],FertiliserProducts[Product],FertiliserProducts[Urea source]), "") | Z20: =IFERROR(_xlfn.XLOOKUP(Table_Input_InorganicFertiliser_Brands[[#This Row],[Product (select)]],FertiliserProducts[Product],FertiliserProducts[Ammonia source]), "")
A21: =HYPERLINK("#'Input - Crop pasture farm input'!A1", "Crop pasture farm input") -> Crop pasture farm input | F21: =IFERROR(_xlfn.XLOOKUP(Table_Input_InorganicFertiliser_Brands[[#This Row],[Product (select)]],FertiliserProducts[Product],FertiliserProducts[Unit]), "kg") -> kg | G21: =X_Cell_Fertiliser_AreaUnderCropping -> Pasture | H21: =IFERROR(_xlfn.XLOOKUP(Table_Input_InorganicFertiliser_Brands[[#This Row],[Product (select)]],FertiliserProducts[Product],FertiliserProducts[Density]), 1) -> 1 | I21: =(Table_Input_InorganicFertiliser_Brands[[#This Row],[Amount applied per hectare]]*Table_Input_InorganicFertiliser_Brands[[#This Row],[Density]])*Table_Input_InorganicFertiliser_Brands[[#This Row],[Application area (ha)]] -> #VALUE! | J21: {=Fertiliser_InputFunctions.Fertiliser_FertiliserProductLookup(Table_Input_InorganicFertiliser_Brands[[#This Row],[Product (select)]], Table_Input_InorganicFertiliser_Brands[[#Headers],[Ingredient 1]], FertiliserProducts[#Data], FertiliserProducts[Product], FertiliserProducts[#Headers])} | K21: {=Fertiliser_InputFunctions.Fertiliser_FertiliserProductLookup(Table_Input_InorganicFertiliser_Brands[[#This Row],[Product (select)]], Table_Input_InorganicFertiliser_Brands[[#Headers],[Ingredient 1 percent]], FertiliserProducts[#Data], FertiliserProducts[Product], FertiliserProducts[#Headers])} | L21: {=Fertiliser_InputFunctions.Fertiliser_FertiliserProductLookup(Table_Input_InorganicFertiliser_Brands[[#This Row],[Product (select)]], Table_Input_InorganicFertiliser_Brands[[#Headers],[Ingredient 2]], FertiliserProducts[#Data], FertiliserProducts[Product], FertiliserProducts[#Headers])} | M21: {=Fertiliser_InputFunctions.Fertiliser_FertiliserProductLookup(Table_Input_InorganicFertiliser_Brands[[#This Row],[Product (select)]], Table_Input_InorganicFertiliser_Brands[[#Headers],[Ingredient 2 percent]], FertiliserProducts[#Data], FertiliserProducts[Product], FertiliserProducts[#Headers])} | N21: {=Fertiliser_InputFunctions.Fertiliser_FertiliserProductLookup(Table_Input_InorganicFertiliser_Brands[[#This Row],[Product (select)]], Table_Input_InorganicFertiliser_Brands[[#Headers],[Ingredient 3]], FertiliserProducts[#Data], FertiliserProducts[Product], FertiliserProducts[#Headers])} | O21: {=Fertiliser_InputFunctions.Fertiliser_FertiliserProductLookup(Table_Input_InorganicFertiliser_Brands[[#This Row],[Product (select)]], Table_Input_InorganicFertiliser_Brands[[#Headers],[Ingredient 3 percent]], FertiliserProducts[#Data], FertiliserProducts[Product], FertiliserProducts[#Headers])} | P21: {=Fertiliser_InputFunctions.Fertiliser_FertiliserProductLookup(Table_Input_InorganicFertiliser_Brands[[#This Row],[Product (select)]], Table_Input_InorganicFertiliser_Brands[[#Headers],[Ingredient 4]], FertiliserProducts[#Data], FertiliserProducts[Product], FertiliserProducts[#Headers])} | Q21: {=Fertiliser_InputFunctions.Fertiliser_FertiliserProductLookup(Table_Input_InorganicFertiliser_Brands[[#This Row],[Product (select)]], Table_Input_InorganicFertiliser_Brands[[#Headers],[Ingredient 4 percent]], FertiliserProducts[#Data], FertiliserProducts[Product], FertiliserProducts[#Headers])} | R21: {=Fertiliser_InputFunctions.Fertiliser_FertiliserProductLookup(Table_Input_InorganicFertiliser_Brands[[#This Row],[Product (select)]], Table_Input_InorganicFertiliser_Brands[[#Headers],[Ingredient 5]], FertiliserProducts[#Data], FertiliserProducts[Product], FertiliserProducts[#Headers])} | S21: {=Fertiliser_InputFunctions.Fertiliser_FertiliserProductLookup(Table_Input_InorganicFertiliser_Brands[[#This Row],[Product (select)]], Table_Input_InorganicFertiliser_Brands[[#Headers],[Ingredient 5 percent]], FertiliserProducts[#Data], FertiliserProducts[Product], FertiliserProducts[#Headers])} | T21: {=Fertiliser_InputFunctions.Fertiliser_FertiliserProductLookup(Table_Input_InorganicFertiliser_Brands[[#This Row],[Product (select)]], Table_Input_InorganicFertiliser_Brands[[#Headers],[Ingredient 6]], FertiliserProducts[#Data], FertiliserProducts[Product], FertiliserProducts[#Headers])} | U21: {=Fertiliser_InputFunctions.Fertiliser_FertiliserProductLookup(Table_Input_InorganicFertiliser_Brands[[#This Row],[Product (select)]], Table_Input_InorganicFertiliser_Brands[[#Headers],[Ingredient 6 percent]], FertiliserProducts[#Data], FertiliserProducts[Product], FertiliserProducts[#Headers])} | V21: =IFERROR((_xlfn.XLOOKUP(Table_Input_InorganicFertiliser_Brands[[#This Row],[Ingredient 1]], Table_Fertiliser_ChemicalCompounds[Fertiliser type f],Table_Fertiliser_ChemicalCompounds[FNinorganic f])*Table_Input_InorganicFertiliser_Brands[[#This Row],[Ingredient 1 percent]]), 0)+ IFERROR((_xlfn.XLOOKUP(Table_Input_InorganicFertiliser_Brands[[#This Row],[Ingredient 2]],Table_Fertiliser_ChemicalCompounds[Fertiliser type f],Table_Fertiliser_ChemicalCompounds[FNinorganic f])*Table_Input_InorganicFertiliser_Brands[[#This Row],[Ingredient 2 percent]]), 0)+ IFERROR((_xlfn.XLOOKUP(Table_Input_InorganicFertiliser_Brands[[#This Row],[Ingredient 3]],Table_Fertiliser_ChemicalCompounds[Fertiliser type f],Table_Fertiliser_ChemicalCompounds[FNinorganic f])*Table_Input_InorganicFertiliser_Brands[[#This Row],[Ingredient 3 percent]]), 0)+ IFERROR((_xlfn.XLOOKUP(Table_Input_InorganicFertiliser_Brands[[#This Row],[Ingredient 4]],Table_Fertiliser_ChemicalCompounds[Fertiliser type f],Table_Fertiliser_ChemicalCompounds[FNinorganic f])*Table_Input_InorganicFertiliser_Brands[[#This Row],[Ingredient 4 percent]]), 0)+ IFERROR((_xlfn.XLOOKUP(Table_Input_InorganicFertiliser_Brands[[#This Row],[Ingredient 5]],Table_Fertiliser_ChemicalCompounds[Fertiliser type f],Table_Fertiliser_ChemicalCompounds[FNinorganic f])*Table_Input_InorganicFertiliser_Brands[[#This Row],[Ingredient 5 percent]]), 0)+ IFERROR((_xlfn.XLOOKUP(Table_Input_InorganicFertiliser_Brands[[#This Row],[Ingredient 6]],Table_Fertiliser_ChemicalCompounds[Fertiliser type f],Table_Fertiliser_ChemicalCompounds[FNinorganic f])*Table_Input_InorganicFertiliser_Brands[[#This Row],[Ingredient 6 percent]]), 0) -> 0 | W21: {=IFERROR(Fertiliser_InputFunctions.Fertiliser_FertiliserProductLookup(Table_Input_InorganicFertiliser_Brands[[#This Row],[Product (select)]], "N declared", FertiliserProducts[#Data], FertiliserProducts[Product], FertiliserProducts[#Headers])*0.01, 0)} -> 0 | X21: =(Table_Input_InorganicFertiliser_Brands[[#This Row],[Amount applied per hectare]]*Table_Input_InorganicFertiliser_Brands[[#This Row],[Density]])*(IF(Table_Input_InorganicFertiliser_Brands[[#This Row],[% N (declared)]], Table_Input_InorganicFertiliser_Brands[[#This Row],[% N (declared)]], Table_Input_InorganicFertiliser_Brands[[#This Row],[% N (Ingredients)]])) -> 0 | Y21: =IFERROR(_xlfn.XLOOKUP(Table_Input_InorganicFertiliser_Brands[[#This Row],[Product (select)]],FertiliserProducts[Product],FertiliserProducts[Urea source]), "") | Z21: =IFERROR(_xlfn.XLOOKUP(Table_Input_InorganicFertiliser_Brands[[#This Row],[Product (select)]],FertiliserProducts[Product],FertiliserProducts[Ammonia source]), "")
A22: =HYPERLINK("#'Input - Livestock farm Inputs'!A1", "Livestock farm Inputs") -> Livestock farm Inputs
A23: =HYPERLINK("#'Input - Freight'!A1", "Freight") -> Freight | D23: Custom fertiliser blends
A24: =HYPERLINK("#'Input - Solid waste'!A1", "Solid waste") -> Solid waste | D24: Custom blend name | E24: Amount applied (kg / ha) | F24: Application area (ha) | G24: Total applied (kg) | H24: Ingredient 1 (select) | I24: Ingredient 1 percent | J24: Ingredient 2 | K24: Ingredient 2 percent | L24: Ingredient 3 | M24: Ingredient 3 percent | N24: Ingredient 4 | O24: Ingredient 4 percent | P24: N application rate (kg/ha) | Q24: Urea source (Select) | R24: Ammonia source (select)
